Workbook

Sheet QA Dashboard
A1: FinanceOS RC1 QA — Linked Regression (Excel Web 3-tab)
A3: FinanceOS Version Tested | B3: v1.0 RC1
A4: QA Workbook Version | B4: RC1 QA Master 2026-09-19
A5: Testing environment | B5: Excel Web — three tabs, one browser session
A6: Tab 1 Baseline (frozen) | B6: FinanceOS_QA_Baseline.xlsx
A7: Tab 2 Under test | B7: FinanceOS_v1.0-QA-RC1.xlsx
A8: Active Scenario | B8: SCN-BASE
A9: Timestamp | B9: =NOW()
A10: PASS Count | B10: =COUNTIF('Difference Engine'!F:F,"PASS")
A11: FAIL Count | B11: =COUNTIF('Difference Engine'!F:F,"FAIL")
A12: WAIT Count | B12: =COUNTIF('Difference Engine'!F:F,"WAIT")
A13: MAXIFS Gate | B13: ='Formula Inventory'!G16
A14: Compatibility Status | B14: ='Compatibility Gate'!B13
A15: Regression Status | B15: =IF(OR(B11>0,B12>0,ISNUMBER(SEARCH("MAXIFS PRESENT",B13)),B14<>"PASS"),"DO NOT PROMOTE","READY FOR PROMOTION")
A17: Open FinanceOS_QA_Baseline.xlsx, FinanceOS_v1.0-QA-RC1.xlsx, and this file as three tabs in the SAME Excel Web window (same Microsoft account, same folder). Click Trust workbook links once. Edit only the QA-RC1 tab. Difference Engine compares Baseline vs QA-RC1 automatically. No paste-values.

Sheet Test Scenarios
A1: Scenario ID | B1: Test Name | C1: Preconditions | D1: Test Data | E1: Step 1 | F1: Step 2 | G1: Expected outputs | H1: Rollback | I1: Amount | J1: From Account | K1: To Account | L1: Txn Type | M1: Status | N1: Date Mode | O1: Executed? | P1: Result
A2: SCN-BASE | B2: Baseline identical | C2: Baseline and QA-RC1 start identical. | D2: Do not edit either engine. | E2: Open all three Excel Web tabs. Trust workbook links. | F2: Confirm Difference Engine is all ~0 / PASS. | G2: All differences 0. | H2: None. | I2: 0 | M2: Completed | N2: ASOF | P2: =IF(O2<>"Yes","",IF('QA Dashboard'!$B$8<>A2,"OTHER",IF('QA Dashboard'!$B$11>0,"FAIL",IF('QA Dashboard'!$B$12>0,"WAIT","PASS"))))
A3: SCN-A | B3: Add income | C3: Baseline frozen. Edit QA-RC1 only. | D3: Completed Income 3000 HDFC Salary, Acme Payroll, date=As-Of. | E3: Add the income row on QA-RC1 Transactions. | F3: Wait for links to refresh. | G3: Monthly/annual income +3000. B23 unchanged. | H3: Delete the new row. | I3: 3000 | J3: HDFC Salary | L3: Income | M3: Completed | N3: ASOF | P3: =IF(O3<>"Yes","",IF('QA Dashboard'!$B$8<>A3,"OTHER",IF('QA Dashboard'!$B$11>0,"FAIL",IF('QA Dashboard'!$B$12>0,"WAIT","PASS"))))
A4: SCN-B | B4: Add expense | C4: Baseline frozen. | D4: Completed Expense 2500 HDFC Salary Groceries, As-Of. | E4: Add expense on QA-RC1. | F4: Refresh. | G4: CM expenses +2500. Savings -2500. B23 unchanged. | H4: Delete the row. | I4: 2500 | J4: HDFC Salary | L4: Expense | M4: Completed | N4: ASOF | P4: =IF(O4<>"Yes","",IF('QA Dashboard'!$B$8<>A4,"OTHER",IF('QA Dashboard'!$B$11>0,"FAIL",IF('QA Dashboard'!$B$12>0,"WAIT","PASS"))))
A5: SCN-C | B5: Add transfer | C5: Baseline frozen. | D5: Completed Transfer 1000 HDFC Salary → SBI Savings, As-Of. | E5: Add transfer on QA-RC1. | F5: Refresh. | G5: Income/expense 0 change. Account-summary B4 stays 0 on this RC1 freeze. | H5: Delete the row. | I5: 1000 | J5: HDFC Salary | K5: SBI Savings | L5: Transfer | M5: Completed | N5: ASOF | P5: =IF(O5<>"Yes","",IF('QA Dashboard'!$B$8<>A5,"OTHER",IF('QA Dashboard'!$B$11>0,"FAIL",IF('QA Dashboard'!$B$12>0,"WAIT","PASS"))))
A6: SCN-D | B6: Pending ignored | C6: Baseline frozen. | D6: Pending Expense 2500 HDFC, As-Of. | E6: Add pending expense. | F6: Refresh. | G6: RC1 SUMIFS does not filter status — record actual vs expected. Desired: no change. | H6: Delete the row. | I6: 2500 | J6: HDFC Salary | L6: Expense | M6: Pending | N6: ASOF | P6: =IF(O6<>"Yes","",IF('QA Dashboard'!$B$8<>A6,"OTHER",IF('QA Dashboard'!$B$11>0,"FAIL",IF('QA Dashboard'!$B$12>0,"WAIT","PASS"))))
A7: SCN-E | B7: Cancelled ignored | C7: Baseline frozen. | D7: Cancelled Expense 2500 HDFC, As-Of. | E7: Add cancelled expense. | F7: Refresh. | G7: Desired: no change. RC1 SUMIFS may still include it. | H7: Delete the row. | I7: 2500 | J7: HDFC Salary | L7: Expense | M7: Cancelled | N7: ASOF | P7: =IF(O7<>"Yes","",IF('QA Dashboard'!$B$8<>A7,"OTHER",IF('QA Dashboard'!$B$11>0,"FAIL",IF('QA Dashboard'!$B$12>0,"WAIT","PASS"))))
A8: SCN-F | B8: Reconciled counted | C8: Baseline frozen. | D8: Reconciled Income 1000 HDFC, As-Of. | E8: Add reconciled income. | F8: Refresh. | G8: Income totals +1000. | H8: Delete the row. | I8: 1000 | J8: HDFC Salary | L8: Income | M8: Reconciled | N8: ASOF | P8: =IF(O8<>"Yes","",IF('QA Dashboard'!$B$8<>A8,"OTHER",IF('QA Dashboard'!$B$11>0,"FAIL",IF('QA Dashboard'!$B$12>0,"WAIT","PASS"))))
A9: SCN-G | B9: Goal contribution | C9: Baseline frozen. | D9: Expense 5000 Destination Type=Goal Destination=Emergency Fund. | E9: Add goal contribution. | F9: Refresh. | G9: CM expenses +5000. Goal table saved amount is not auto-updated on this RC1 freeze. | H9: Delete the row. | I9: 5000 | J9: HDFC Salary | K9: Emergency Fund | L9: Expense | M9: Completed | N9: ASOF | P9: =IF(O9<>"Yes","",IF('QA Dashboard'!$B$8<>A9,"OTHER",IF('QA Dashboard'!$B$11>0,"FAIL",IF('QA Dashboard'!$B$12>0,"WAIT","PASS"))))
A10: SCN-H | B10: Credit card spend | C10: Baseline frozen. | D10: Expense 2000 from ICICI Credit Card, Shopping, Completed, As-Of. | E10: Add CC spend. | F10: Refresh. | G10: CM expenses +2000. | H10: Delete the row. | I10: 2000 | J10: ICICI Credit Card | L10: Expense | M10: Completed | N10: ASOF | P10: =IF(O10<>"Yes","",IF('QA Dashboard'!$B$8<>A10,"OTHER",IF('QA Dashboard'!$B$11>0,"FAIL",IF('QA Dashboard'!$B$12>0,"WAIT","PASS"))))
A11: SCN-I | B11: Credit card payment | C11: Baseline frozen. | D11: Transfer 2000 HDFC Salary → ICICI Credit Card. | E11: Add CC payment transfer. | F11: Refresh. | G11: Income/expense 0 change. | H11: Delete the row. | I11: 2000 | J11: HDFC Salary | K11: ICICI Credit Card | L11: Transfer | M11: Completed | N11: ASOF | P11: =IF(O11<>"Yes","",IF('QA Dashboard'!$B$8<>A11,"OTHER",IF('QA Dashboard'!$B$11>0,"FAIL",IF('QA Dashboard'!$B$12>0,"WAIT","PASS"))))
A12: SCN-J | B12: Asset purchase | C12: Baseline frozen. | D12: Expense 15000 Destination Type=Asset Destination=Gold. | E12: Add asset purchase expense. | F12: Refresh. | G12: CM expenses +15000. Asset current value is not auto-updated. | H12: Delete the row. | I12: 15000 | J12: HDFC Salary | K12: Gold | L12: Expense | M12: Completed | N12: ASOF | P12: =IF(O12<>"Yes","",IF('QA Dashboard'!$B$8<>A12,"OTHER",IF('QA Dashboard'!$B$11>0,"FAIL",IF('QA Dashboard'!$B$12>0,"WAIT","PASS"))))
A13: SCN-K | B13: BUG-003 latest date vs row order | C13: Baseline already has TXN-000090 30-Sep above TXN-000010 01-Jan. | D13: Do not add rows. Inspect order. | E13: Confirm row 2 date is 30-Sep-2026 and row 3 is 01-Jan-2026. | F13: Refresh. | G13: RC1 has no Last Transaction Date engine cell. Record N/A unless Account Engine is added later. | H13: None. | I13: 0 | J13: HDFC Salary | L13: Income | M13: Completed | N13: BUG003 | P13: =IF(O13<>"Yes","",IF('QA Dashboard'!$B$8<>A13,"OTHER",IF('QA Dashboard'!$B$11>0,"FAIL",IF('QA Dashboard'!$B$12>0,"WAIT","PASS"))))
A14: SCN-L | B14: Pending latest ignored | C14: Pending 25-Sep already in fixture. | D14: Optional: add another pending dated after last completed. | E14: Inspect pending row. | F14: Refresh. | G14: Desired: pending does not become last completed date. No LAST cell on this RC1 freeze. | H14: Delete extra pending if added. | I14: 0 | J14: HDFC Salary | L14: Expense | M14: Pending | N14: ASOF | P14: =IF(O14<>"Yes","",IF('QA Dashboard'!$B$8<>A14,"OTHER",IF('QA Dashboard'!$B$11>0,"FAIL",IF('QA Dashboard'!$B$12>0,"WAIT","PASS"))))
A15: SCN-M | B15: Cancelled latest ignored | C15: Cancelled 22-Sep already in fixture. | D15: Optional extra cancelled after as-of. | E15: Inspect cancelled row. | F15: Refresh. | G15: Desired: cancelled ignored for last date. No LAST cell on this RC1 freeze. | H15: Delete extra row. | I15: 0 | J15: HDFC Salary | L15: Expense | M15: Cancelled | N15: ASOF | P15: =IF(O15<>"Yes","",IF('QA Dashboard'!$B$8<>A15,"OTHER",IF('QA Dashboard'!$B$11>0,"FAIL",IF('QA Dashboard'!$B$12>0,"WAIT","PASS"))))
A16: SCN-N | B16: Inbound transfer dest account | C16: Baseline frozen. | D16: Completed Transfer 2500 SBI Savings → HDFC Salary. | E16: Add inbound transfer. | F16: Refresh. | G16: Income/expense 0. Dest account should increase when Account Engine exists. | H16: Delete the row. | I16: 2500 | J16: SBI Savings | K16: HDFC Salary | L16: Transfer | M16: Completed | N16: ASOF | P16: =IF(O16<>"Yes","",IF('QA Dashboard'!$B$8<>A16,"OTHER",IF('QA Dashboard'!$B$11>0,"FAIL",IF('QA Dashboard'!$B$12>0,"WAIT","PASS"))))
A17: SCN-O | B17: Outbound transfer source account | C17: Baseline frozen. | D17: Completed Transfer 2500 HDFC Salary → SBI Savings. | E17: Add outbound transfer. | F17: Refresh. | G17: Income/expense 0. Source account should decrease when Account Engine exists. | H17: Delete the row. | I17: 2500 | J17: HDFC Salary | K17: SBI Savings | L17: Transfer | M17: Completed | N17: ASOF | P17: =IF(O17<>"Yes","",IF('QA Dashboard'!$B$8<>A17,"OTHER",IF('QA Dashboard'!$B$11>0,"FAIL",IF('QA Dashboard'!$B$12>0,"WAIT","PASS"))))
A18: SCN-P | B18: Mixed statuses + row order | C18: Use existing fixture plus one completed, one pending, one cancelled. | D18: Mix dates and row positions. | E18: Add three rows then inspect. | F18: Refresh. | G18: Completed affects income/expense; pending/cancelled desired ignored; row order must not change last date. | H18: Delete the three rows. | I18: 100 | J18: HDFC Salary | L18: Income | M18: Completed | N18: ASOF | P18: =IF(O18<>"Yes","",IF('QA Dashboard'!$B$8<>A18,"OTHER",IF('QA Dashboard'!$B$11>0,"FAIL",IF('QA Dashboard'!$B$12>0,"WAIT","PASS"))))

Sheet Difference Engine
A1: Metric ID | B1: Baseline | C1: QA-RC1 | D1: Difference | E1: Expected Difference | F1: PASS / FAIL | G1: Metric | H1: Section | I1: Cell | J1: Sheet
A2: ACC_TOTAL_BAL | B2: ='[FinanceOS_QA_Baseline.xlsx]Business Engine'!B4 | C2: ='[FinanceOS_v1.0-QA-RC1.xlsx]Business Engine'!B4 | D2: =IF(OR(B2="",C2=""),"",IF(AND(ISNUMBER(B2),ISNUMBER(C2)),C2-B2,IF(B2=C2,0,"≠"))) | E2: =0 | F2: =IF(OR(B2="",C2=""),"WAIT",IF(AND(ISNUMBER(D2),ISNUMBER(E2)),IF(ABS(D2-E2)<0.005,"PASS","FAIL"),IF(D2=E2,"PASS","FAIL"))) | G2: Total Active Account Balance | H2: Accounts Summary | I2: B4 | J2: Business Engine
A3: ACC_ACTIVE_N | B3: ='[FinanceOS_QA_Baseline.xlsx]Business Engine'!B5 | C3: ='[FinanceOS_v1.0-QA-RC1.xlsx]Business Engine'!B5 | D3: =IF(OR(B3="",C3=""),"",IF(AND(ISNUMBER(B3),ISNUMBER(C3)),C3-B3,IF(B3=C3,0,"≠"))) | E3: =0 | F3: =IF(OR(B3="",C3=""),"WAIT",IF(AND(ISNUMBER(D3),ISNUMBER(E3)),IF(ABS(D3-E3)<0.005,"PASS","FAIL"),IF(D3=E3,"PASS","FAIL"))) | G3: Number of Active Accounts | H3: Accounts Summary | I3: B5 | J3: Business Engine
A4: ACC_CASH | B4: ='[FinanceOS_QA_Baseline.xlsx]Business Engine'!B6 | C4: ='[FinanceOS_v1.0-QA-RC1.xlsx]Business Engine'!B6 | D4: =IF(OR(B4="",C4=""),"",IF(AND(ISNUMBER(B4),ISNUMBER(C4)),C4-B4,IF(B4=C4,0,"≠"))) | E4: =0 | F4: =IF(OR(B4="",C4=""),"WAIT",IF(AND(ISNUMBER(D4),ISNUMBER(E4)),IF(ABS(D4-E4)<0.005,"PASS","FAIL"),IF(D4=E4,"PASS","FAIL"))) | G4: Cash Accounts Total | H4: Accounts Summary | I4: B6 | J4: Business Engine
A5: ACC_SAVINGS | B5: ='[FinanceOS_QA_Baseline.xlsx]Business Engine'!B7 | C5: ='[FinanceOS_v1.0-QA-RC1.xlsx]Business Engine'!B7 | D5: =IF(OR(B5="",C5=""),"",IF(AND(ISNUMBER(B5),ISNUMBER(C5)),C5-B5,IF(B5=C5,0,"≠"))) | E5: =0 | F5: =IF(OR(B5="",C5=""),"WAIT",IF(AND(ISNUMBER(D5),ISNUMBER(E5)),IF(ABS(D5-E5)<0.005,"PASS","FAIL"),IF(D5=E5,"PASS","FAIL"))) | G5: Savings Accounts Total | H5: Accounts Summary | I5: B7 | J5: Business Engine
A6: ACC_INVEST | B6: ='[FinanceOS_QA_Baseline.xlsx]Business Engine'!B8 | C6: ='[FinanceOS_v1.0-QA-RC1.xlsx]Business Engine'!B8 | D6: =IF(OR(B6="",C6=""),"",IF(AND(ISNUMBER(B6),ISNUMBER(C6)),C6-B6,IF(B6=C6,0,"≠"))) | E6: =0 | F6: =IF(OR(B6="",C6=""),"WAIT",IF(AND(ISNUMBER(D6),ISNUMBER(E6)),IF(ABS(D6-E6)<0.005,"PASS","FAIL"),IF(D6=E6,"PASS","FAIL"))) | G6: Investment Accounts Total | H6: Accounts Summary | I6: B8 | J6: Business Engine
A7: ACC_CREDIT | B7: ='[FinanceOS_QA_Baseline.xlsx]Business Engine'!B9 | C7: ='[FinanceOS_v1.0-QA-RC1.xlsx]Business Engine'!B9 | D7: =IF(OR(B7="",C7=""),"",IF(AND(ISNUMBER(B7),ISNUMBER(C7)),C7-B7,IF(B7=C7,0,"≠"))) | E7: =0 | F7: =IF(OR(B7="",C7=""),"WAIT",IF(AND(ISNUMBER(D7),ISNUMBER(E7)),IF(ABS(D7-E7)<0.005,"PASS","FAIL"),IF(D7=E7,"PASS","FAIL"))) | G7: Credit Accounts Total | H7: Accounts Summary | I7: B9 | J7: Business Engine
A8: INC_SALARY | B8: ='[FinanceOS_QA_Baseline.xlsx]Business Engine'!B12 | C8: ='[FinanceOS_v1.0-QA-RC1.xlsx]Business Engine'!B12 | D8: =IF(OR(B8="",C8=""),"",IF(AND(ISNUMBER(B8),ISNUMBER(C8)),C8-B8,IF(B8=C8,0,"≠"))) | E8: =IF(AND(OR($J$7="Completed",$J$7="Reconciled"),$J$6="Income",$J$9),$J$3,0) | F8: =IF(OR(B8="",C8=""),"WAIT",IF(AND(ISNUMBER(D8),ISNUMBER(E8)),IF(ABS(D8-E8)<0.005,"PASS","FAIL"),IF(D8=E8,"PASS","FAIL"))) | G8: Monthly Salary Income | H8: Income Summary | I8: B12 | J8: Business Engine
A9: INC_BIZ | B9: ='[FinanceOS_QA_Baseline.xlsx]Business Engine'!B13 | C9: ='[FinanceOS_v1.0-QA-RC1.xlsx]Business Engine'!B13 | D9: =IF(OR(B9="",C9=""),"",IF(AND(ISNUMBER(B9),ISNUMBER(C9)),C9-B9,IF(B9=C9,0,"≠"))) | E9: =0 | F9: =IF(OR(B9="",C9=""),"WAIT",IF(AND(ISNUMBER(D9),ISNUMBER(E9)),IF(ABS(D9-E9)<0.005,"PASS","FAIL"),IF(D9=E9,"PASS","FAIL"))) | G9: Monthly Business Income | H9: Income Summary | I9: B13 | J9: Business Engine
A10: INC_FREE | B10: ='[FinanceOS_QA_Baseline.xlsx]Business Engine'!B14 | C10: ='[FinanceOS_v1.0-QA-RC1.xlsx]Business Engine'!B14 | D10: =IF(OR(B10="",C10=""),"",IF(AND(ISNUMBER(B10),ISNUMBER(C10)),C10-B10,IF(B10=C10,0,"≠"))) | E10: =IF(AND(OR($J$7="Completed",$J$7="Reconciled"),$J$6="Income",$J$5="Freelance Gigs",$J$9),$J$3,0) | F10: =IF(OR(B10="",C10=""),"WAIT",IF(AND(ISNUMBER(D10),ISNUMBER(E10)),IF(ABS(D10-E10)<0.005,"PASS","FAIL"),IF(D10=E10,"PASS","FAIL"))) | G10: Monthly Freelance Income | H10: Income Summary | I10: B14 | J10: Business Engine
A11: INC_INV | B11: ='[FinanceOS_QA_Baseline.xlsx]Business Engine'!B15 | C11: ='[FinanceOS_v1.0-QA-RC1.xlsx]Business Engine'!B15 | D11: =IF(OR(B11="",C11=""),"",IF(AND(ISNUMBER(B11),ISNUMBER(C11)),C11-B11,IF(B11=C11,0,"≠"))) | E11: =0 | F11: =IF(OR(B11="",C11=""),"WAIT",IF(AND(ISNUMBER(D11),ISNUMBER(E11)),IF(ABS(D11-E11)<0.005,"PASS","FAIL"),IF(D11=E11,"PASS","FAIL"))) | G11: Monthly Investment Income | H11: Income Summary | I11: B15 | J11: Business Engine
A12: INC_MONTH | B12: ='[FinanceOS_QA_Baseline.xlsx]Business Engine'!B16 | C12: ='[FinanceOS_v1.0-QA-RC1.xlsx]Business Engine'!B16 | D12: =IF(OR(B12="",C12=""),"",IF(AND(ISNUMBER(B12),ISNUMBER(C12)),C12-B12,IF(B12=C12,0,"≠"))) | E12: =IF(AND(OR($J$7="Completed",$J$7="Reconciled"),$J$6="Income",$J$9),$J$3,0) | F12: =IF(OR(B12="",C12=""),"WAIT",IF(AND(ISNUMBER(D12),ISNUMBER(E12)),IF(ABS(D12-E12)<0.005,"PASS","FAIL"),IF(D12=E12,"PASS","FAIL"))) | G12: Total Monthly Income | H12: Income Summary | I12: B16 | J12: Business Engine
A13: INC_OTHER | B13: ='[FinanceOS_QA_Baseline.xlsx]Business Engine'!B17 | C13: ='[FinanceOS_v1.0-QA-RC1.xlsx]Business Engine'!B17 | D13: =IF(OR(B13="",C13=""),"",IF(AND(ISNUMBER(B13),ISNUMBER(C13)),C13-B13,IF(B13=C13,0,"≠"))) | E13: =0 | F13: =IF(OR(B13="",C13=""),"WAIT",IF(AND(ISNUMBER(D13),ISNUMBER(E13)),IF(ABS(D13-E13)<0.005,"PASS","FAIL"),IF(D13=E13,"PASS","FAIL"))) | G13: Monthly Other Income | H13: Income Summary | I13: B17 | J13: Business Engine
A14: INC_ANNUAL | B14: ='[FinanceOS_QA_Baseline.xlsx]Business Engine'!B18 | C14: ='[FinanceOS_v1.0-QA-RC1.xlsx]Business Engine'!B18 | D14: =IF(OR(B14="",C14=""),"",IF(AND(ISNUMBER(B14),ISNUMBER(C14)),C14-B14,IF(B14=C14,0,"≠"))) | E14: =IF(AND(OR($J$7="Completed",$J$7="Reconciled"),$J$6="Income"),$J$3,0) | F14: =IF(OR(B14="",C14=""),"WAIT",IF(AND(ISNUMBER(D14),ISNUMBER(E14)),IF(ABS(D14-E14)<0.005,"PASS","FAIL"),IF(D14=E14,"PASS","FAIL"))) | G14: Total Annual Income | H14: Income Summary | I14: B18 | J14: Business Engine
A15: INC_SRC_N | B15: ='[FinanceOS_QA_Baseline.xlsx]Business Engine'!B19 | C15: ='[FinanceOS_v1.0-QA-RC1.xlsx]Business Engine'!B19 | D15: =IF(OR(B15="",C15=""),"",IF(AND(ISNUMBER(B15),ISNUMBER(C15)),C15-B15,IF(B15=C15,0,"≠"))) | E15: =0 | F15: =IF(OR(B15="",C15=""),"WAIT",IF(AND(ISNUMBER(D15),ISNUMBER(E15)),IF(ABS(D15-E15)<0.005,"PASS","FAIL"),IF(D15=E15,"PASS","FAIL"))) | G15: Active Income Source Count | H15: Income Summary | I15: B19 | J15: Business Engine
A16: EXP_CM | B16: ='[FinanceOS_QA_Baseline.xlsx]Business Engine'!B22 | C16: ='[FinanceOS_v1.0-QA-RC1.xlsx]Business Engine'!B22 | D16: =IF(OR(B16="",C16=""),"",IF(AND(ISNUMBER(B16),ISNUMBER(C16)),C16-B16,IF(B16=C16,0,"≠"))) | E16: =IF(AND(OR($J$7="Completed",$J$7="Reconciled"),$J$6="Expense",$J$9),$J$3,0) | F16: =IF(OR(B16="",C16=""),"WAIT",IF(AND(ISNUMBER(D16),ISNUMBER(E16)),IF(ABS(D16-E16)<0.005,"PASS","FAIL"),IF(D16=E16,"PASS","FAIL"))) | G16: Current Month Expenses | H16: Expense Summary | I16: B22 | J16: Business Engine
A17: EXP_PM | B17: ='[FinanceOS_QA_Baseline.xlsx]Business Engine'!B23 | C17: ='[FinanceOS_v1.0-QA-RC1.xlsx]Business Engine'!B23 | D17: =IF(OR(B17="",C17=""),"",IF(AND(ISNUMBER(B17),ISNUMBER(C17)),C17-B17,IF(B17=C17,0,"≠"))) | E17: =0 | F17: =IF(OR(B17="",C17=""),"WAIT",IF(AND(ISNUMBER(D17),ISNUMBER(E17)),IF(ABS(D17-E17)<0.005,"PASS","FAIL"),IF(D17=E17,"PASS","FAIL"))) | G17: Previous Month Expenses | H17: Expense Summary | I17: B23 | J17: Business Engine
A18: EXP_YTD | B18: ='[FinanceOS_QA_Baseline.xlsx]Business Engine'!B24 | C18: ='[FinanceOS_v1.0-QA-RC1.xlsx]Business Engine'!B24 | D18: =IF(OR(B18="",C18=""),"",IF(AND(ISNUMBER(B18),ISNUMBER(C18)),C18-B18,IF(B18=C18,0,"≠"))) | E18: =IF(AND(OR($J$7="Completed",$J$7="Reconciled"),$J$6="Expense"),$J$3,0) | F18: =IF(OR(B18="",C18=""),"WAIT",IF(AND(ISNUMBER(D18),ISNUMBER(E18)),IF(ABS(D18-E18)<0.005,"PASS","FAIL"),IF(D18=E18,"PASS","FAIL"))) | G18: Year-to-Date Expenses | H18: Expense Summary | I18: B24 | J18: Business Engine
A19: EXP_N | B19: ='[FinanceOS_QA_Baseline.xlsx]Business Engine'!B25 | C19: ='[FinanceOS_v1.0-QA-RC1.xlsx]Business Engine'!B25 | D19: =IF(OR(B19="",C19=""),"",IF(AND(ISNUMBER(B19),ISNUMBER(C19)),C19-B19,IF(B19=C19,0,"≠"))) | E19: =IF(AND(OR($J$7="Completed",$J$7="Reconciled"),$J$6="Expense",$J$9),1,0) | F19: =IF(OR(B19="",C19=""),"WAIT",IF(AND(ISNUMBER(D19),ISNUMBER(E19)),IF(ABS(D19-E19)<0.005,"PASS","FAIL"),IF(D19=E19,"PASS","FAIL"))) | G19: Expense Transaction Count | H19: Expense Summary | I19: B25 | J19: Business Engine
A20: SAV_INC | B20: ='[FinanceOS_QA_Baseline.xlsx]Business Engine'!B28 | C20: ='[FinanceOS_v1.0-QA-RC1.xlsx]Business Engine'!B28 | D20: =IF(OR(B20="",C20=""),"",IF(AND(ISNUMBER(B20),ISNUMBER(C20)),C20-B20,IF(B20=C20,0,"≠"))) | E20: =IF(AND(OR($J$7="Completed",$J$7="Reconciled"),$J$6="Income",$J$9),$J$3,0) | F20: =IF(OR(B20="",C20=""),"WAIT",IF(AND(ISNUMBER(D20),ISNUMBER(E20)),IF(ABS(D20-E20)<0.005,"PASS","FAIL"),IF(D20=E20,"PASS","FAIL"))) | G20: Current Month Income | H20: Savings Summary | I20: B28 | J20: Business Engine
A21: SAV_AMT | B21: ='[FinanceOS_QA_Baseline.xlsx]Business Engine'!B29 | C21: ='[FinanceOS_v1.0-QA-RC1.xlsx]Business Engine'!B29 | D21: =IF(OR(B21="",C21=""),"",IF(AND(ISNUMBER(B21),ISNUMBER(C21)),C21-B21,IF(B21=C21,0,"≠"))) | E21: =IF(AND(OR($J$7="Completed",$J$7="Reconciled"),$J$9),IF($J$6="Income",$J$3,IF($J$6="Expense",-$J$3,0)),0) | F21: =IF(OR(B21="",C21=""),"WAIT",IF(AND(ISNUMBER(D21),ISNUMBER(E21)),IF(ABS(D21-E21)<0.005,"PASS","FAIL"),IF(D21=E21,"PASS","FAIL"))) | G21: Current Month Savings | H21: Savings Summary | I21: B29 | J21: Business Engine
A22: SAV_RATE | B22: ='[FinanceOS_QA_Baseline.xlsx]Business Engine'!B30 | C22: ='[FinanceOS_v1.0-QA-RC1.xlsx]Business Engine'!B30 | D22: =IF(OR(B22="",C22=""),"",IF(AND(ISNUMBER(B22),ISNUMBER(C22)),C22-B22,IF(B22=C22,0,"≠"))) | E22: =0 | F22: =IF(OR(B22="",C22=""),"WAIT",IF(AND(ISNUMBER(D22),ISNUMBER(E22)),IF(ABS(D22-E22)<0.005,"PASS","FAIL"),IF(D22=E22,"PASS","FAIL"))) | G22: Savings Rate (%) | H22: Savings Summary | I22: B30 | J22: Business Engine
A23: SAV_AVG | B23: ='[FinanceOS_QA_Baseline.xlsx]Business Engine'!B31 | C23: ='[FinanceOS_v1.0-QA-RC1.xlsx]Business Engine'!B31 | D23: =IF(OR(B23="",C23=""),"",IF(AND(ISNUMBER(B23),ISNUMBER(C23)),C23-B23,IF(B23=C23,0,"≠"))) | E23: =0 | F23: =IF(OR(B23="",C23=""),"WAIT",IF(AND(ISNUMBER(D23),ISNUMBER(E23)),IF(ABS(D23-E23)<0.005,"PASS","FAIL"),IF(D23=E23,"PASS","FAIL"))) | G23: Average Monthly Savings | H23: Savings Summary | I23: B31 | J23: Business Engine
A24: AST_PUR | B24: ='[FinanceOS_QA_Baseline.xlsx]Business Engine'!B34 | C24: ='[FinanceOS_v1.0-QA-RC1.xlsx]Business Engine'!B34 | D24: =IF(OR(B24="",C24=""),"",IF(AND(ISNUMBER(B24),ISNUMBER(C24)),C24-B24,IF(B24=C24,0,"≠"))) | E24: =0 | F24: =IF(OR(B24="",C24=""),"WAIT",IF(AND(ISNUMBER(D24),ISNUMBER(E24)),IF(ABS(D24-E24)<0.005,"PASS","FAIL"),IF(D24=E24,"PASS","FAIL"))) | G24: Total Purchase Value | H24: Asset Summary | I24: B34 | J24: Business Engine
A25: AST_CUR | B25: ='[FinanceOS_QA_Baseline.xlsx]Business Engine'!B35 | C25: ='[FinanceOS_v1.0-QA-RC1.xlsx]Business Engine'!B35 | D25: =IF(OR(B25="",C25=""),"",IF(AND(ISNUMBER(B25),ISNUMBER(C25)),C25-B25,IF(B25=C25,0,"≠"))) | E25: =0 | F25: =IF(OR(B25="",C25=""),"WAIT",IF(AND(ISNUMBER(D25),ISNUMBER(E25)),IF(ABS(D25-E25)<0.005,"PASS","FAIL"),IF(D25=E25,"PASS","FAIL"))) | G25: Total Current Value | H25: Asset Summary | I25: B35 | J25: Business Engine
A26: AST_APP | B26: ='[FinanceOS_QA_Baseline.xlsx]Business Engine'!B36 | C26: ='[FinanceOS_v1.0-QA-RC1.xlsx]Business Engine'!B36 | D26: =IF(OR(B26="",C26=""),"",IF(AND(ISNUMBER(B26),ISNUMBER(C26)),C26-B26,IF(B26=C26,0,"≠"))) | E26: =0 | F26: =IF(OR(B26="",C26=""),"WAIT",IF(AND(ISNUMBER(D26),ISNUMBER(E26)),IF(ABS(D26-E26)<0.005,"PASS","FAIL"),IF(D26=E26,"PASS","FAIL"))) | G26: Total Appreciation Amount | H26: Asset Summary | I26: B36 | J26: Business Engine
A27: AST_PCT | B27: ='[FinanceOS_QA_Baseline.xlsx]Business Engine'!B37 | C27: ='[FinanceOS_v1.0-QA-RC1.xlsx]Business Engine'!B37 | D27: =IF(OR(B27="",C27=""),"",IF(AND(ISNUMBER(B27),ISNUMBER(C27)),C27-B27,IF(B27=C27,0,"≠"))) | E27: =0 | F27: =IF(OR(B27="",C27=""),"WAIT",IF(AND(ISNUMBER(D27),ISNUMBER(E27)),IF(ABS(D27-E27)<0.005,"PASS","FAIL"),IF(D27=E27,"PASS","FAIL"))) | G27: Weighted Appreciation % | H27: Asset Summary | I27: B37 | J27: Business Engine
A28: AST_N | B28: ='[FinanceOS_QA_Baseline.xlsx]Business Engine'!B38 | C28: ='[FinanceOS_v1.0-QA-RC1.xlsx]Business Engine'!B38 | D28: =IF(OR(B28="",C28=""),"",IF(AND(ISNUMBER(B28),ISNUMBER(C28)),C28-B28,IF(B28=C28,0,"≠"))) | E28: =0 | F28: =IF(OR(B28="",C28=""),"WAIT",IF(AND(ISNUMBER(D28),ISNUMBER(E28)),IF(ABS(D28-E28)<0.005,"PASS","FAIL"),IF(D28=E28,"PASS","FAIL"))) | G28: Active Asset Count | H28: Asset Summary | I28: B38 | J28: Business Engine
A29: LIA_ORIG | B29: ='[FinanceOS_QA_Baseline.xlsx]Business Engine'!B41 | C29: ='[FinanceOS_v1.0-QA-RC1.xlsx]Business Engine'!B41 | D29: =IF(OR(B29="",C29=""),"",IF(AND(ISNUMBER(B29),ISNUMBER(C29)),C29-B29,IF(B29=C29,0,"≠"))) | E29: =0 | F29: =IF(OR(B29="",C29=""),"WAIT",IF(AND(ISNUMBER(D29),ISNUMBER(E29)),IF(ABS(D29-E29)<0.005,"PASS","FAIL"),IF(D29=E29,"PASS","FAIL"))) | G29: Total Original Liability | H29: Liability Summary | I29: B41 | J29: Business Engine
A30: LIA_OUT | B30: ='[FinanceOS_QA_Baseline.xlsx]Business Engine'!B42 | C30: ='[FinanceOS_v1.0-QA-RC1.xlsx]Business Engine'!B42 | D30: =IF(OR(B30="",C30=""),"",IF(AND(ISNUMBER(B30),ISNUMBER(C30)),C30-B30,IF(B30=C30,0,"≠"))) | E30: =0 | F30: =IF(OR(B30="",C30=""),"WAIT",IF(AND(ISNUMBER(D30),ISNUMBER(E30)),IF(ABS(D30-E30)<0.005,"PASS","FAIL"),IF(D30=E30,"PASS","FAIL"))) | G30: Total Outstanding Balance | H30: Liability Summary | I30: B42 | J30: Business Engine
A31: LIA_EMI | B31: ='[FinanceOS_QA_Baseline.xlsx]Business Engine'!B43 | C31: ='[FinanceOS_v1.0-QA-RC1.xlsx]Business Engine'!B43 | D31: =IF(OR(B31="",C31=""),"",IF(AND(ISNUMBER(B31),ISNUMBER(C31)),C31-B31,IF(B31=C31,0,"≠"))) | E31: =0 | F31: =IF(OR(B31="",C31=""),"WAIT",IF(AND(ISNUMBER(D31),ISNUMBER(E31)),IF(ABS(D31-E31)<0.005,"PASS","FAIL"),IF(D31=E31,"PASS","FAIL"))) | G31: Total Monthly EMI | H31: Liability Summary | I31: B43 | J31: Business Engine
A32: LIA_INT | B32: ='[FinanceOS_QA_Baseline.xlsx]Business Engine'!B44 | C32: ='[FinanceOS_v1.0-QA-RC1.xlsx]Business Engine'!B44 | D32: =IF(OR(B32="",C32=""),"",IF(AND(ISNUMBER(B32),ISNUMBER(C32)),C32-B32,IF(B32=C32,0,"≠"))) | E32: =0 | F32: =IF(OR(B32="",C32=""),"WAIT",IF(AND(ISNUMBER(D32),ISNUMBER(E32)),IF(ABS(D32-E32)<0.005,"PASS","FAIL"),IF(D32=E32,"PASS","FAIL"))) | G32: Weighted Interest Rate | H32: Liability Summary | I32: B44 | J32: Business Engine
A33: LIA_N | B33: ='[FinanceOS_QA_Baseline.xlsx]Business Engine'!B45 | C33: ='[FinanceOS_v1.0-QA-RC1.xlsx]Business Engine'!B45 | D33: =IF(OR(B33="",C33=""),"",IF(AND(ISNUMBER(B33),ISNUMBER(C33)),C33-B33,IF(B33=C33,0,"≠"))) | E33: =0 | F33: =IF(OR(B33="",C33=""),"WAIT",IF(AND(ISNUMBER(D33),ISNUMBER(E33)),IF(ABS(D33-E33)<0.005,"PASS","FAIL"),IF(D33=E33,"PASS","FAIL"))) | G33: Active Liability Count | H33: Liability Summary | I33: B45 | J33: Business Engine
A34: NW_TOTAL | B34: ='[FinanceOS_QA_Baseline.xlsx]Business Engine'!B48 | C34: ='[FinanceOS_v1.0-QA-RC1.xlsx]Business Engine'!B48 | D34: =IF(OR(B34="",C34=""),"",IF(AND(ISNUMBER(B34),ISNUMBER(C34)),C34-B34,IF(B34=C34,0,"≠"))) | E34: =0 | F34: =IF(OR(B34="",C34=""),"WAIT",IF(AND(ISNUMBER(D34),ISNUMBER(E34)),IF(ABS(D34-E34)<0.005,"PASS","FAIL"),IF(D34=E34,"PASS","FAIL"))) | G34: Net Worth | H34: Net Worth | I34: B48 | J34: Business Engine
A35: NW_LIQ | B35: ='[FinanceOS_QA_Baseline.xlsx]Business Engine'!B49 | C35: ='[FinanceOS_v1.0-QA-RC1.xlsx]Business Engine'!B49 | D35: =IF(OR(B35="",C35=""),"",IF(AND(ISNUMBER(B35),ISNUMBER(C35)),C35-B35,IF(B35=C35,0,"≠"))) | E35: =0 | F35: =IF(OR(B35="",C35=""),"WAIT",IF(AND(ISNUMBER(D35),ISNUMBER(E35)),IF(ABS(D35-E35)<0.005,"PASS","FAIL"),IF(D35=E35,"PASS","FAIL"))) | G35: Liquid Net Worth | H35: Net Worth | I35: B49 | J35: Business Engine
A36: NW_INV | B36: ='[FinanceOS_QA_Baseline.xlsx]Business Engine'!B50 | C36: ='[FinanceOS_v1.0-QA-RC1.xlsx]Business Engine'!B50 | D36: =IF(OR(B36="",C36=""),"",IF(AND(ISNUMBER(B36),ISNUMBER(C36)),C36-B36,IF(B36=C36,0,"≠"))) | E36: =0 | F36: =IF(OR(B36="",C36=""),"WAIT",IF(AND(ISNUMBER(D36),ISNUMBER(E36)),IF(ABS(D36-E36)<0.005,"PASS","FAIL"),IF(D36=E36,"PASS","FAIL"))) | G36: Invested Net Worth | H36: Net Worth | I36: B50 | J36: Business Engine
A37: GOAL_TGT | B37: ='[FinanceOS_QA_Baseline.xlsx]Business Engine'!B53 | C37: ='[FinanceOS_v1.0-QA-RC1.xlsx]Business Engine'!B53 | D37: =IF(OR(B37="",C37=""),"",IF(AND(ISNUMBER(B37),ISNUMBER(C37)),C37-B37,IF(B37=C37,0,"≠"))) | E37: =0 | F37: =IF(OR(B37="",C37=""),"WAIT",IF(AND(ISNUMBER(D37),ISNUMBER(E37)),IF(ABS(D37-E37)<0.005,"PASS","FAIL"),IF(D37=E37,"PASS","FAIL"))) | G37: Total Goal Target Amount | H37: Goal Summary | I37: B53 | J37: Business Engine
A38: GOAL_SAV | B38: ='[FinanceOS_QA_Baseline.xlsx]Business Engine'!B54 | C38: ='[FinanceOS_v1.0-QA-RC1.xlsx]Business Engine'!B54 | D38: =IF(OR(B38="",C38=""),"",IF(AND(ISNUMBER(B38),ISNUMBER(C38)),C38-B38,IF(B38=C38,0,"≠"))) | E38: =0 | F38: =IF(OR(B38="",C38=""),"WAIT",IF(AND(ISNUMBER(D38),ISNUMBER(E38)),IF(ABS(D38-E38)<0.005,"PASS","FAIL"),IF(D38=E38,"PASS","FAIL"))) | G38: Total Saved Toward Goals | H38: Goal Summary | I38: B54 | J38: Business Engine
A39: GOAL_REM | B39: ='[FinanceOS_QA_Baseline.xlsx]Business Engine'!B55 | C39: ='[FinanceOS_v1.0-QA-RC1.xlsx]Business Engine'!B55 | D39: =IF(OR(B39="",C39=""),"",IF(AND(ISNUMBER(B39),ISNUMBER(C39)),C39-B39,IF(B39=C39,0,"≠"))) | E39: =0 | F39: =IF(OR(B39="",C39=""),"WAIT",IF(AND(ISNUMBER(D39),ISNUMBER(E39)),IF(ABS(D39-E39)<0.005,"PASS","FAIL"),IF(D39=E39,"PASS","FAIL"))) | G39: Remaining Goal Amount | H39: Goal Summary | I39: B55 | J39: Business Engine
A40: GOAL_ACT | B40: ='[FinanceOS_QA_Baseline.xlsx]Business Engine'!B56 | C40: ='[FinanceOS_v1.0-QA-RC1.xlsx]Business Engine'!B56 | D40: =IF(OR(B40="",C40=""),"",IF(AND(ISNUMBER(B40),ISNUMBER(C40)),C40-B40,IF(B40=C40,0,"≠"))) | E40: =0 | F40: =IF(OR(B40="",C40=""),"WAIT",IF(AND(ISNUMBER(D40),ISNUMBER(E40)),IF(ABS(D40-E40)<0.005,"PASS","FAIL"),IF(D40=E40,"PASS","FAIL"))) | G40: Active Goal Count | H40: Goal Summary | I40: B56 | J40: Business Engine
A41: GOAL_DONE | B41: ='[FinanceOS_QA_Baseline.xlsx]Business Engine'!B57 | C41: ='[FinanceOS_v1.0-QA-RC1.xlsx]Business Engine'!B57 | D41: =IF(OR(B41="",C41=""),"",IF(AND(ISNUMBER(B41),ISNUMBER(C41)),C41-B41,IF(B41=C41,0,"≠"))) | E41: =0 | F41: =IF(OR(B41="",C41=""),"WAIT",IF(AND(ISNUMBER(D41),ISNUMBER(E41)),IF(ABS(D41-E41)<0.005,"PASS","FAIL"),IF(D41=E41,"PASS","FAIL"))) | G41: Completed Goal Count | H41: Goal Summary | I41: B57 | J41: Business Engine
A42: GOAL_PCT | B42: ='[FinanceOS_QA_Baseline.xlsx]Business Engine'!B58 | C42: ='[FinanceOS_v1.0-QA-RC1.xlsx]Business Engine'!B58 | D42: =IF(OR(B42="",C42=""),"",IF(AND(ISNUMBER(B42),ISNUMBER(C42)),C42-B42,IF(B42=C42,0,"≠"))) | E42: =0 | F42: =IF(OR(B42="",C42=""),"WAIT",IF(AND(ISNUMBER(D42),ISNUMBER(E42)),IF(ABS(D42-E42)<0.005,"PASS","FAIL"),IF(D42=E42,"PASS","FAIL"))) | G42: Goal Completion % | H42: Goal Summary | I42: B58 | J42: Business Engine
A43: HLTH_INC | B43: ='[FinanceOS_QA_Baseline.xlsx]Business Engine'!B61 | C43: ='[FinanceOS_v1.0-QA-RC1.xlsx]Business Engine'!B61 | D43: =IF(OR(B43="",C43=""),"",IF(AND(ISNUMBER(B43),ISNUMBER(C43)),C43-B43,IF(B43=C43,0,"≠"))) | E43: =IF(AND(OR($J$7="Completed",$J$7="Reconciled"),$J$6="Income",$J$9),$J$3,0) | F43: =IF(OR(B43="",C43=""),"WAIT",IF(AND(ISNUMBER(D43),ISNUMBER(E43)),IF(ABS(D43-E43)<0.005,"PASS","FAIL"),IF(D43=E43,"PASS","FAIL"))) | G43: Income | H43: Financial Health | I43: B61 | J43: Business Engine
A44: HLTH_EXP | B44: ='[FinanceOS_QA_Baseline.xlsx]Business Engine'!B62 | C44: ='[FinanceOS_v1.0-QA-RC1.xlsx]Business Engine'!B62 | D44: =IF(OR(B44="",C44=""),"",IF(AND(ISNUMBER(B44),ISNUMBER(C44)),C44-B44,IF(B44=C44,0,"≠"))) | E44: =IF(AND(OR($J$7="Completed",$J$7="Reconciled"),$J$6="Expense",$J$9),$J$3,0) | F44: =IF(OR(B44="",C44=""),"WAIT",IF(AND(ISNUMBER(D44),ISNUMBER(E44)),IF(ABS(D44-E44)<0.005,"PASS","FAIL"),IF(D44=E44,"PASS","FAIL"))) | G44: Expenses | H44: Financial Health | I44: B62 | J44: Business Engine
A45: HLTH_SAV | B45: ='[FinanceOS_QA_Baseline.xlsx]Business Engine'!B63 | C45: ='[FinanceOS_v1.0-QA-RC1.xlsx]Business Engine'!B63 | D45: =IF(OR(B45="",C45=""),"",IF(AND(ISNUMBER(B45),ISNUMBER(C45)),C45-B45,IF(B45=C45,0,"≠"))) | E45: =IF(AND(OR($J$7="Completed",$J$7="Reconciled"),$J$9),IF($J$6="Income",$J$3,IF($J$6="Expense",-$J$3,0)),0) | F45: =IF(OR(B45="",C45=""),"WAIT",IF(AND(ISNUMBER(D45),ISNUMBER(E45)),IF(ABS(D45-E45)<0.005,"PASS","FAIL"),IF(D45=E45,"PASS","FAIL"))) | G45: Savings | H45: Financial Health | I45: B63 | J45: Business Engine
A46: HLTH_RATE | B46: ='[FinanceOS_QA_Baseline.xlsx]Business Engine'!B64 | C46: ='[FinanceOS_v1.0-QA-RC1.xlsx]Business Engine'!B64 | D46: =IF(OR(B46="",C46=""),"",IF(AND(ISNUMBER(B46),ISNUMBER(C46)),C46-B46,IF(B46=C46,0,"≠"))) | E46: =0 | F46: =IF(OR(B46="",C46=""),"WAIT",IF(AND(ISNUMBER(D46),ISNUMBER(E46)),IF(ABS(D46-E46)<0.005,"PASS","FAIL"),IF(D46=E46,"PASS","FAIL"))) | G46: Savings Rate | H46: Financial Health | I46: B64 | J46: Business Engine
A47: HLTH_NW | B47: ='[FinanceOS_QA_Baseline.xlsx]Business Engine'!B65 | C47: ='[FinanceOS_v1.0-QA-RC1.xlsx]Business Engine'!B65 | D47: =IF(OR(B47="",C47=""),"",IF(AND(ISNUMBER(B47),ISNUMBER(C47)),C47-B47,IF(B47=C47,0,"≠"))) | E47: =0 | F47: =IF(OR(B47="",C47=""),"WAIT",IF(AND(ISNUMBER(D47),ISNUMBER(E47)),IF(ABS(D47-E47)<0.005,"PASS","FAIL"),IF(D47=E47,"PASS","FAIL"))) | G47: Net Worth | H47: Financial Health | I47: B65 | J47: Business Engine
A48: HLTH_EMI | B48: ='[FinanceOS_QA_Baseline.xlsx]Business Engine'!B66 | C48: ='[FinanceOS_v1.0-QA-RC1.xlsx]Business Engine'!B66 | D48: =IF(OR(B48="",C48=""),"",IF(AND(ISNUMBER(B48),ISNUMBER(C48)),C48-B48,IF(B48=C48,0,"≠"))) | E48: =0 | F48: =IF(OR(B48="",C48=""),"WAIT",IF(AND(ISNUMBER(D48),ISNUMBER(E48)),IF(ABS(D48-E48)<0.005,"PASS","FAIL"),IF(D48=E48,"PASS","FAIL"))) | G48: EMI Ratio | H48: Financial Health | I48: B66 | J48: Business Engine
A49: HLTH_ALLOC | B49: ='[FinanceOS_QA_Baseline.xlsx]Business Engine'!B67 | C49: ='[FinanceOS_v1.0-QA-RC1.xlsx]Business Engine'!B67 | D49: =IF(OR(B49="",C49=""),"",IF(AND(ISNUMBER(B49),ISNUMBER(C49)),C49-B49,IF(B49=C49,0,"≠"))) | E49: =0 | F49: =IF(OR(B49="",C49=""),"WAIT",IF(AND(ISNUMBER(D49),ISNUMBER(E49)),IF(ABS(D49-E49)<0.005,"PASS","FAIL"),IF(D49=E49,"PASS","FAIL"))) | G49: Asset Allocation | H49: Financial Health | I49: B67 | J49: Business Engine
A50: HLTH_DEBT | B50: ='[FinanceOS_QA_Baseline.xlsx]Business Engine'!B68 | C50: ='[FinanceOS_v1.0-QA-RC1.xlsx]Business Engine'!B68 | D50: =IF(OR(B50="",C50=""),"",IF(AND(ISNUMBER(B50),ISNUMBER(C50)),C50-B50,IF(B50=C50,0,"≠"))) | E50: =0 | F50: =IF(OR(B50="",C50=""),"WAIT",IF(AND(ISNUMBER(D50),ISNUMBER(E50)),IF(ABS(D50-E50)<0.005,"PASS","FAIL"),IF(D50=E50,"PASS","FAIL"))) | G50: Debt Ratio | H50: Financial Health | I50: B68 | J50: Business Engine
A51: ASOF | B51: ='[FinanceOS_QA_Baseline.xlsx]Business Engine'!B1 | C51: ='[FinanceOS_v1.0-QA-RC1.xlsx]Business Engine'!B1 | D51: =IF(OR(B51="",C51=""),"",IF(AND(ISNUMBER(B51),ISNUMBER(C51)),C51-B51,IF(B51=C51,0,"≠"))) | E51: =0 | F51: =IF(OR(B51="",C51=""),"WAIT",IF(AND(ISNUMBER(D51),ISNUMBER(E51)),IF(ABS(D51-E51)<0.005,"PASS","FAIL"),IF(D51=E51,"PASS","FAIL"))) | G51: As-Of Date | H51: Formula Integrity | I51: B1 | J51: Business Engine
A52: AE_ASOF | B52: ='[FinanceOS_QA_Baseline.xlsx]Analysis Engine'!B2 | C52: ='[FinanceOS_v1.0-QA-RC1.xlsx]Analysis Engine'!B2 | D52: =IF(OR(B52="",C52=""),"",IF(AND(ISNUMBER(B52),ISNUMBER(C52)),C52-B52,IF(B52=C52,0,"≠"))) | E52: =0 | F52: =IF(OR(B52="",C52=""),"WAIT",IF(AND(ISNUMBER(D52),ISNUMBER(E52)),IF(ABS(D52-E52)<0.005,"PASS","FAIL"),IF(D52=E52,"PASS","FAIL"))) | G52: As-Of Date | H52: Analysis Engine | I52: B2 | J52: Analysis Engine
A53: AE_INC_CM | B53: ='[FinanceOS_QA_Baseline.xlsx]Analysis Engine'!B6 | C53: ='[FinanceOS_v1.0-QA-RC1.xlsx]Analysis Engine'!B6 | D53: =IF(OR(B53="",C53=""),"",IF(AND(ISNUMBER(B53),ISNUMBER(C53)),C53-B53,IF(B53=C53,0,"≠"))) | E53: =0 | F53: =IF(OR(B53="",C53=""),"WAIT",IF(AND(ISNUMBER(D53),ISNUMBER(E53)),IF(ABS(D53-E53)<0.005,"PASS","FAIL"),IF(D53=E53,"PASS","FAIL"))) | G53: Total Income CM | H53: Analysis Engine | I53: B6 | J53: Analysis Engine
A54: AE_SAL_CM | B54: ='[FinanceOS_QA_Baseline.xlsx]Analysis Engine'!B7 | C54: ='[FinanceOS_v1.0-QA-RC1.xlsx]Analysis Engine'!B7 | D54: =IF(OR(B54="",C54=""),"",IF(AND(ISNUMBER(B54),ISNUMBER(C54)),C54-B54,IF(B54=C54,0,"≠"))) | E54: =0 | F54: =IF(OR(B54="",C54=""),"WAIT",IF(AND(ISNUMBER(D54),ISNUMBER(E54)),IF(ABS(D54-E54)<0.005,"PASS","FAIL"),IF(D54=E54,"PASS","FAIL"))) | G54: Salary CM | H54: Analysis Engine | I54: B7 | J54: Analysis Engine
A55: AE_BIZ_CM | B55: ='[FinanceOS_QA_Baseline.xlsx]Analysis Engine'!B8 | C55: ='[FinanceOS_v1.0-QA-RC1.xlsx]Analysis Engine'!B8 | D55: =IF(OR(B55="",C55=""),"",IF(AND(ISNUMBER(B55),ISNUMBER(C55)),C55-B55,IF(B55=C55,0,"≠"))) | E55: =0 | F55: =IF(OR(B55="",C55=""),"WAIT",IF(AND(ISNUMBER(D55),ISNUMBER(E55)),IF(ABS(D55-E55)<0.005,"PASS","FAIL"),IF(D55=E55,"PASS","FAIL"))) | G55: Business Income CM | H55: Analysis Engine | I55: B8 | J55: Analysis Engine
A56: AE_FREE_CM | B56: ='[FinanceOS_QA_Baseline.xlsx]Analysis Engine'!B9 | C56: ='[FinanceOS_v1.0-QA-RC1.xlsx]Analysis Engine'!B9 | D56: =IF(OR(B56="",C56=""),"",IF(AND(ISNUMBER(B56),ISNUMBER(C56)),C56-B56,IF(B56=C56,0,"≠"))) | E56: =0 | F56: =IF(OR(B56="",C56=""),"WAIT",IF(AND(ISNUMBER(D56),ISNUMBER(E56)),IF(ABS(D56-E56)<0.005,"PASS","FAIL"),IF(D56=E56,"PASS","FAIL"))) | G56: Freelance CM | H56: Analysis Engine | I56: B9 | J56: Analysis Engine
A57: AE_INV_CM | B57: ='[FinanceOS_QA_Baseline.xlsx]Analysis Engine'!B10 | C57: ='[FinanceOS_v1.0-QA-RC1.xlsx]Analysis Engine'!B10 | D57: =IF(OR(B57="",C57=""),"",IF(AND(ISNUMBER(B57),ISNUMBER(C57)),C57-B57,IF(B57=C57,0,"≠"))) | E57: =0 | F57: =IF(OR(B57="",C57=""),"WAIT",IF(AND(ISNUMBER(D57),ISNUMBER(E57)),IF(ABS(D57-E57)<0.005,"PASS","FAIL"),IF(D57=E57,"PASS","FAIL"))) | G57: Investment CM | H57: Analysis Engine | I57: B10 | J57: Analysis Engine
A58: AE_OTH_CM | B58: ='[FinanceOS_QA_Baseline.xlsx]Analysis Engine'!B11 | C58: ='[FinanceOS_v1.0-QA-RC1.xlsx]Analysis Engine'!B11 | D58: =IF(OR(B58="",C58=""),"",IF(AND(ISNUMBER(B58),ISNUMBER(C58)),C58-B58,IF(B58=C58,0,"≠"))) | E58: =0 | F58: =IF(OR(B58="",C58=""),"WAIT",IF(AND(ISNUMBER(D58),ISNUMBER(E58)),IF(ABS(D58-E58)<0.005,"PASS","FAIL"),IF(D58=E58,"PASS","FAIL"))) | G58: Other Income CM | H58: Analysis Engine | I58: B11 | J58: Analysis Engine
A59: AE_INC_PM | B59: ='[FinanceOS_QA_Baseline.xlsx]Analysis Engine'!C6 | C59: ='[FinanceOS_v1.0-QA-RC1.xlsx]Analysis Engine'!C6 | D59: =IF(OR(B59="",C59=""),"",IF(AND(ISNUMBER(B59),ISNUMBER(C59)),C59-B59,IF(B59=C59,0,"≠"))) | E59: =0 | F59: =IF(OR(B59="",C59=""),"WAIT",IF(AND(ISNUMBER(D59),ISNUMBER(E59)),IF(ABS(D59-E59)<0.005,"PASS","FAIL"),IF(D59=E59,"PASS","FAIL"))) | G59: Total Income PM | H59: Analysis Engine | I59: C6 | J59: Analysis Engine
A60: AE_INC_YTD | B60: ='[FinanceOS_QA_Baseline.xlsx]Analysis Engine'!D6 | C60: ='[FinanceOS_v1.0-QA-RC1.xlsx]Analysis Engine'!D6 | D60: =IF(OR(B60="",C60=""),"",IF(AND(ISNUMBER(B60),ISNUMBER(C60)),C60-B60,IF(B60=C60,0,"≠"))) | E60: =0 | F60: =IF(OR(B60="",C60=""),"WAIT",IF(AND(ISNUMBER(D60),ISNUMBER(E60)),IF(ABS(D60-E60)<0.005,"PASS","FAIL"),IF(D60=E60,"PASS","FAIL"))) | G60: Total Income YTD | H60: Analysis Engine | I60: D6 | J60: Analysis Engine
A61: AE_EXP_CM | B61: ='[FinanceOS_QA_Baseline.xlsx]Analysis Engine'!B14 | C61: ='[FinanceOS_v1.0-QA-RC1.xlsx]Analysis Engine'!B14 | D61: =IF(OR(B61="",C61=""),"",IF(AND(ISNUMBER(B61),ISNUMBER(C61)),C61-B61,IF(B61=C61,0,"≠"))) | E61: =0 | F61: =IF(OR(B61="",C61=""),"WAIT",IF(AND(ISNUMBER(D61),ISNUMBER(E61)),IF(ABS(D61-E61)<0.005,"PASS","FAIL"),IF(D61=E61,"PASS","FAIL"))) | G61: Total Expenses CM | H61: Analysis Engine | I61: B14 | J61: Analysis Engine
A62: AE_EXP_PM | B62: ='[FinanceOS_QA_Baseline.xlsx]Analysis Engine'!C14 | C62: ='[FinanceOS_v1.0-QA-RC1.xlsx]Analysis Engine'!C14 | D62: =IF(OR(B62="",C62=""),"",IF(AND(ISNUMBER(B62),ISNUMBER(C62)),C62-B62,IF(B62=C62,0,"≠"))) | E62: =0 | F62: =IF(OR(B62="",C62=""),"WAIT",IF(AND(ISNUMBER(D62),ISNUMBER(E62)),IF(ABS(D62-E62)<0.005,"PASS","FAIL"),IF(D62=E62,"PASS","FAIL"))) | G62: Total Expenses PM | H62: Analysis Engine | I62: C14 | J62: Analysis Engine
A63: AE_EXP_YTD | B63: ='[FinanceOS_QA_Baseline.xlsx]Analysis Engine'!D14 | C63: ='[FinanceOS_v1.0-QA-RC1.xlsx]Analysis Engine'!D14 | D63: =IF(OR(B63="",C63=""),"",IF(AND(ISNUMBER(B63),ISNUMBER(C63)),C63-B63,IF(B63=C63,0,"≠"))) | E63: =0 | F63: =IF(OR(B63="",C63=""),"WAIT",IF(AND(ISNUMBER(D63),ISNUMBER(E63)),IF(ABS(D63-E63)<0.005,"PASS","FAIL"),IF(D63=E63,"PASS","FAIL"))) | G63: Total Expenses YTD | H63: Analysis Engine | I63: D14 | J63: Analysis Engine
A64: AE_CF_INC | B64: ='[FinanceOS_QA_Baseline.xlsx]Analysis Engine'!B44 | C64: ='[FinanceOS_v1.0-QA-RC1.xlsx]Analysis Engine'!B44 | D64: =IF(OR(B64="",C64=""),"",IF(AND(ISNUMBER(B64),ISNUMBER(C64)),C64-B64,IF(B64=C64,0,"≠"))) | E64: =0 | F64: =IF(OR(B64="",C64=""),"WAIT",IF(AND(ISNUMBER(D64),ISNUMBER(E64)),IF(ABS(D64-E64)<0.005,"PASS","FAIL"),IF(D64=E64,"PASS","FAIL"))) | G64: Cash Flow Income | H64: Analysis Engine | I64: B44 | J64: Analysis Engine
A65: AE_CF_EXP | B65: ='[FinanceOS_QA_Baseline.xlsx]Analysis Engine'!B45 | C65: ='[FinanceOS_v1.0-QA-RC1.xlsx]Analysis Engine'!B45 | D65: =IF(OR(B65="",C65=""),"",IF(AND(ISNUMBER(B65),ISNUMBER(C65)),C65-B65,IF(B65=C65,0,"≠"))) | E65: =0 | F65: =IF(OR(B65="",C65=""),"WAIT",IF(AND(ISNUMBER(D65),ISNUMBER(E65)),IF(ABS(D65-E65)<0.005,"PASS","FAIL"),IF(D65=E65,"PASS","FAIL"))) | G65: Cash Flow Expenses | H65: Analysis Engine | I65: B45 | J65: Analysis Engine
A66: AE_CF_SAV | B66: ='[FinanceOS_QA_Baseline.xlsx]Analysis Engine'!B46 | C66: ='[FinanceOS_v1.0-QA-RC1.xlsx]Analysis Engine'!B46 | D66: =IF(OR(B66="",C66=""),"",IF(AND(ISNUMBER(B66),ISNUMBER(C66)),C66-B66,IF(B66=C66,0,"≠"))) | E66: =0 | F66: =IF(OR(B66="",C66=""),"WAIT",IF(AND(ISNUMBER(D66),ISNUMBER(E66)),IF(ABS(D66-E66)<0.005,"PASS","FAIL"),IF(D66=E66,"PASS","FAIL"))) | G66: Cash Flow Savings | H66: Analysis Engine | I66: B46 | J66: Analysis Engine
A67: AE_CF_RATE | B67: ='[FinanceOS_QA_Baseline.xlsx]Analysis Engine'!B47 | C67: ='[FinanceOS_v1.0-QA-RC1.xlsx]Analysis Engine'!B47 | D67: =IF(OR(B67="",C67=""),"",IF(AND(ISNUMBER(B67),ISNUMBER(C67)),C67-B67,IF(B67=C67,0,"≠"))) | E67: =0 | F67: =IF(OR(B67="",C67=""),"WAIT",IF(AND(ISNUMBER(D67),ISNUMBER(E67)),IF(ABS(D67-E67)<0.005,"PASS","FAIL"),IF(D67=E67,"PASS","FAIL"))) | G67: Cash Flow Savings Rate | H67: Analysis Engine | I67: B47 | J67: Analysis Engine
A68: AE_CF_PMEXP | B68: ='[FinanceOS_QA_Baseline.xlsx]Analysis Engine'!B48 | C68: ='[FinanceOS_v1.0-QA-RC1.xlsx]Analysis Engine'!B48 | D68: =IF(OR(B68="",C68=""),"",IF(AND(ISNUMBER(B68),ISNUMBER(C68)),C68-B68,IF(B68=C68,0,"≠"))) | E68: =0 | F68: =IF(OR(B68="",C68=""),"WAIT",IF(AND(ISNUMBER(D68),ISNUMBER(E68)),IF(ABS(D68-E68)<0.005,"PASS","FAIL"),IF(D68=E68,"PASS","FAIL"))) | G68: Previous Month Expenses | H68: Analysis Engine | I68: B48 | J68: Analysis Engine
A69: AE_CF_MOM | B69: ='[FinanceOS_QA_Baseline.xlsx]Analysis Engine'!B49 | C69: ='[FinanceOS_v1.0-QA-RC1.xlsx]Analysis Engine'!B49 | D69: =IF(OR(B69="",C69=""),"",IF(AND(ISNUMBER(B69),ISNUMBER(C69)),C69-B69,IF(B69=C69,0,"≠"))) | E69: =0 | F69: =IF(OR(B69="",C69=""),"WAIT",IF(AND(ISNUMBER(D69),ISNUMBER(E69)),IF(ABS(D69-E69)<0.005,"PASS","FAIL"),IF(D69=E69,"PASS","FAIL"))) | G69: MoM Expense Change | H69: Analysis Engine | I69: B49 | J69: Analysis Engine
A70: AE_AST_PUR | B70: ='[FinanceOS_QA_Baseline.xlsx]Analysis Engine'!B54 | C70: ='[FinanceOS_v1.0-QA-RC1.xlsx]Analysis Engine'!B54 | D70: =IF(OR(B70="",C70=""),"",IF(AND(ISNUMBER(B70),ISNUMBER(C70)),C70-B70,IF(B70=C70,0,"≠"))) | E70: =0 | F70: =IF(OR(B70="",C70=""),"WAIT",IF(AND(ISNUMBER(D70),ISNUMBER(E70)),IF(ABS(D70-E70)<0.005,"PASS","FAIL"),IF(D70=E70,"PASS","FAIL"))) | G70: Asset Purchase Value | H70: Analysis Engine | I70: B54 | J70: Analysis Engine
A71: AE_AST_CUR | B71: ='[FinanceOS_QA_Baseline.xlsx]Analysis Engine'!B55 | C71: ='[FinanceOS_v1.0-QA-RC1.xlsx]Analysis Engine'!B55 | D71: =IF(OR(B71="",C71=""),"",IF(AND(ISNUMBER(B71),ISNUMBER(C71)),C71-B71,IF(B71=C71,0,"≠"))) | E71: =0 | F71: =IF(OR(B71="",C71=""),"WAIT",IF(AND(ISNUMBER(D71),ISNUMBER(E71)),IF(ABS(D71-E71)<0.005,"PASS","FAIL"),IF(D71=E71,"PASS","FAIL"))) | G71: Asset Current Value | H71: Analysis Engine | I71: B55 | J71: Analysis Engine
A72: AE_AST_APP | B72: ='[FinanceOS_QA_Baseline.xlsx]Analysis Engine'!B56 | C72: ='[FinanceOS_v1.0-QA-RC1.xlsx]Analysis Engine'!B56 | D72: =IF(OR(B72="",C72=""),"",IF(AND(ISNUMBER(B72),ISNUMBER(C72)),C72-B72,IF(B72=C72,0,"≠"))) | E72: =0 | F72: =IF(OR(B72="",C72=""),"WAIT",IF(AND(ISNUMBER(D72),ISNUMBER(E72)),IF(ABS(D72-E72)<0.005,"PASS","FAIL"),IF(D72=E72,"PASS","FAIL"))) | G72: Asset Appreciation | H72: Analysis Engine | I72: B56 | J72: Analysis Engine
A73: AE_AST_PCT | B73: ='[FinanceOS_QA_Baseline.xlsx]Analysis Engine'!B57 | C73: ='[FinanceOS_v1.0-QA-RC1.xlsx]Analysis Engine'!B57 | D73: =IF(OR(B73="",C73=""),"",IF(AND(ISNUMBER(B73),ISNUMBER(C73)),C73-B73,IF(B73=C73,0,"≠"))) | E73: =0 | F73: =IF(OR(B73="",C73=""),"WAIT",IF(AND(ISNUMBER(D73),ISNUMBER(E73)),IF(ABS(D73-E73)<0.005,"PASS","FAIL"),IF(D73=E73,"PASS","FAIL"))) | G73: Asset Appreciation % | H73: Analysis Engine | I73: B57 | J73: Analysis Engine
A74: AE_AST_N | B74: ='[FinanceOS_QA_Baseline.xlsx]Analysis Engine'!B58 | C74: ='[FinanceOS_v1.0-QA-RC1.xlsx]Analysis Engine'!B58 | D74: =IF(OR(B74="",C74=""),"",IF(AND(ISNUMBER(B74),ISNUMBER(C74)),C74-B74,IF(B74=C74,0,"≠"))) | E74: =0 | F74: =IF(OR(B74="",C74=""),"WAIT",IF(AND(ISNUMBER(D74),ISNUMBER(E74)),IF(ABS(D74-E74)<0.005,"PASS","FAIL"),IF(D74=E74,"PASS","FAIL"))) | G74: Active Asset Count | H74: Analysis Engine | I74: B58 | J74: Analysis Engine
A75: AE_LIA_ORIG | B75: ='[FinanceOS_QA_Baseline.xlsx]Analysis Engine'!B74 | C75: ='[FinanceOS_v1.0-QA-RC1.xlsx]Analysis Engine'!B74 | D75: =IF(OR(B75="",C75=""),"",IF(AND(ISNUMBER(B75),ISNUMBER(C75)),C75-B75,IF(B75=C75,0,"≠"))) | E75: =0 | F75: =IF(OR(B75="",C75=""),"WAIT",IF(AND(ISNUMBER(D75),ISNUMBER(E75)),IF(ABS(D75-E75)<0.005,"PASS","FAIL"),IF(D75=E75,"PASS","FAIL"))) | G75: Total Original Liability | H75: Analysis Engine | I75: B74 | J75: Analysis Engine
A76: AE_LIA_OUT | B76: ='[FinanceOS_QA_Baseline.xlsx]Analysis Engine'!B75 | C76: ='[FinanceOS_v1.0-QA-RC1.xlsx]Analysis Engine'!B75 | D76: =IF(OR(B76="",C76=""),"",IF(AND(ISNUMBER(B76),ISNUMBER(C76)),C76-B76,IF(B76=C76,0,"≠"))) | E76: =0 | F76: =IF(OR(B76="",C76=""),"WAIT",IF(AND(ISNUMBER(D76),ISNUMBER(E76)),IF(ABS(D76-E76)<0.005,"PASS","FAIL"),IF(D76=E76,"PASS","FAIL"))) | G76: Outstanding Balance | H76: Analysis Engine | I76: B75 | J76: Analysis Engine
A77: AE_LIA_EMI | B77: ='[FinanceOS_QA_Baseline.xlsx]Analysis Engine'!B76 | C77: ='[FinanceOS_v1.0-QA-RC1.xlsx]Analysis Engine'!B76 | D77: =IF(OR(B77="",C77=""),"",IF(AND(ISNUMBER(B77),ISNUMBER(C77)),C77-B77,IF(B77=C77,0,"≠"))) | E77: =0 | F77: =IF(OR(B77="",C77=""),"WAIT",IF(AND(ISNUMBER(D77),ISNUMBER(E77)),IF(ABS(D77-E77)<0.005,"PASS","FAIL"),IF(D77=E77,"PASS","FAIL"))) | G77: Total Monthly EMI | H77: Analysis Engine | I77: B76 | J77: Analysis Engine
A78: AE_LIA_INT | B78: ='[FinanceOS_QA_Baseline.xlsx]Analysis Engine'!B77 | C78: ='[FinanceOS_v1.0-QA-RC1.xlsx]Analysis Engine'!B77 | D78: =IF(OR(B78="",C78=""),"",IF(AND(ISNUMBER(B78),ISNUMBER(C78)),C78-B78,IF(B78=C78,0,"≠"))) | E78: =0 | F78: =IF(OR(B78="",C78=""),"WAIT",IF(AND(ISNUMBER(D78),ISNUMBER(E78)),IF(ABS(D78-E78)<0.005,"PASS","FAIL"),IF(D78=E78,"PASS","FAIL"))) | G78: Weighted Interest Rate | H78: Analysis Engine | I78: B77 | J78: Analysis Engine
A79: AE_LIA_N | B79: ='[FinanceOS_QA_Baseline.xlsx]Analysis Engine'!B79 | C79: ='[FinanceOS_v1.0-QA-RC1.xlsx]Analysis Engine'!B79 | D79: =IF(OR(B79="",C79=""),"",IF(AND(ISNUMBER(B79),ISNUMBER(C79)),C79-B79,IF(B79=C79,0,"≠"))) | E79: =0 | F79: =IF(OR(B79="",C79=""),"WAIT",IF(AND(ISNUMBER(D79),ISNUMBER(E79)),IF(ABS(D79-E79)<0.005,"PASS","FAIL"),IF(D79=E79,"PASS","FAIL"))) | G79: Active Liability Count | H79: Analysis Engine | I79: B79 | J79: Analysis Engine
A80: AE_EMI_RATIO | B80: ='[FinanceOS_QA_Baseline.xlsx]Analysis Engine'!B80 | C80: ='[FinanceOS_v1.0-QA-RC1.xlsx]Analysis Engine'!B80 | D80: =IF(OR(B80="",C80=""),"",IF(AND(ISNUMBER(B80),ISNUMBER(C80)),C80-B80,IF(B80=C80,0,"≠"))) | E80: =0 | F80: =IF(OR(B80="",C80=""),"WAIT",IF(AND(ISNUMBER(D80),ISNUMBER(E80)),IF(ABS(D80-E80)<0.005,"PASS","FAIL"),IF(D80=E80,"PASS","FAIL"))) | G80: EMI Ratio | H80: Analysis Engine | I80: B80 | J80: Analysis Engine
A81: AE_DEBT | B81: ='[FinanceOS_QA_Baseline.xlsx]Analysis Engine'!B81 | C81: ='[FinanceOS_v1.0-QA-RC1.xlsx]Analysis Engine'!B81 | D81: =IF(OR(B81="",C81=""),"",IF(AND(ISNUMBER(B81),ISNUMBER(C81)),C81-B81,IF(B81=C81,0,"≠"))) | E81: =0 | F81: =IF(OR(B81="",C81=""),"WAIT",IF(AND(ISNUMBER(D81),ISNUMBER(E81)),IF(ABS(D81-E81)<0.005,"PASS","FAIL"),IF(D81=E81,"PASS","FAIL"))) | G81: Debt Ratio | H81: Analysis Engine | I81: B81 | J81: Analysis Engine
A82: AE_GOAL_OVER | B82: ='[FinanceOS_QA_Baseline.xlsx]Analysis Engine'!B107 | C82: ='[FinanceOS_v1.0-QA-RC1.xlsx]Analysis Engine'!B107 | D82: =IF(OR(B82="",C82=""),"",IF(AND(ISNUMBER(B82),ISNUMBER(C82)),C82-B82,IF(B82=C82,0,"≠"))) | E82: =0 | F82: =IF(OR(B82="",C82=""),"WAIT",IF(AND(ISNUMBER(D82),ISNUMBER(E82)),IF(ABS(D82-E82)<0.005,"PASS","FAIL"),IF(D82=E82,"PASS","FAIL"))) | G82: Overdue Goal Count | H82: Analysis Engine | I82: B107 | J82: Analysis Engine
A83: AE_GOAL_PCT | B83: ='[FinanceOS_QA_Baseline.xlsx]Analysis Engine'!B108 | C83: ='[FinanceOS_v1.0-QA-RC1.xlsx]Analysis Engine'!B108 | D83: =IF(OR(B83="",C83=""),"",IF(AND(ISNUMBER(B83),ISNUMBER(C83)),C83-B83,IF(B83=C83,0,"≠"))) | E83: =0 | F83: =IF(OR(B83="",C83=""),"WAIT",IF(AND(ISNUMBER(D83),ISNUMBER(E83)),IF(ABS(D83-E83)<0.005,"PASS","FAIL"),IF(D83=E83,"PASS","FAIL"))) | G83: Goal Completion % | H83: Analysis Engine | I83: B108 | J83: Analysis Engine
A84: AE_GOAL_N | B84: ='[FinanceOS_QA_Baseline.xlsx]Analysis Engine'!B109 | C84: ='[FinanceOS_v1.0-QA-RC1.xlsx]Analysis Engine'!B109 | D84: =IF(OR(B84="",C84=""),"",IF(AND(ISNUMBER(B84),ISNUMBER(C84)),C84-B84,IF(B84=C84,0,"≠"))) | E84: =0 | F84: =IF(OR(B84="",C84=""),"WAIT",IF(AND(ISNUMBER(D84),ISNUMBER(E84)),IF(ABS(D84-E84)<0.005,"PASS","FAIL"),IF(D84=E84,"PASS","FAIL"))) | G84: Active Goal Count | H84: Analysis Engine | I84: B109 | J84: Analysis Engine
A85: AE_JAN_INC | B85: ='[FinanceOS_QA_Baseline.xlsx]Analysis Engine'!B30 | C85: ='[FinanceOS_v1.0-QA-RC1.xlsx]Analysis Engine'!B30 | D85: =IF(OR(B85="",C85=""),"",IF(AND(ISNUMBER(B85),ISNUMBER(C85)),C85-B85,IF(B85=C85,0,"≠"))) | E85: =0 | F85: =IF(OR(B85="",C85=""),"WAIT",IF(AND(ISNUMBER(D85),ISNUMBER(E85)),IF(ABS(D85-E85)<0.005,"PASS","FAIL"),IF(D85=E85,"PASS","FAIL"))) | G85: Jan Income | H85: Analysis Engine | I85: B30 | J85: Analysis Engine
A86: AE_AUG_INC | B86: ='[FinanceOS_QA_Baseline.xlsx]Analysis Engine'!B37 | C86: ='[FinanceOS_v1.0-QA-RC1.xlsx]Analysis Engine'!B37 | D86: =IF(OR(B86="",C86=""),"",IF(AND(ISNUMBER(B86),ISNUMBER(C86)),C86-B86,IF(B86=C86,0,"≠"))) | E86: =0 | F86: =IF(OR(B86="",C86=""),"WAIT",IF(AND(ISNUMBER(D86),ISNUMBER(E86)),IF(ABS(D86-E86)<0.005,"PASS","FAIL"),IF(D86=E86,"PASS","FAIL"))) | G86: Aug Income | H86: Analysis Engine | I86: B37 | J86: Analysis Engine
A87: AE_SEP_INC | B87: ='[FinanceOS_QA_Baseline.xlsx]Analysis Engine'!B38 | C87: ='[FinanceOS_v1.0-QA-RC1.xlsx]Analysis Engine'!B38 | D87: =IF(OR(B87="",C87=""),"",IF(AND(ISNUMBER(B87),ISNUMBER(C87)),C87-B87,IF(B87=C87,0,"≠"))) | E87: =0 | F87: =IF(OR(B87="",C87=""),"WAIT",IF(AND(ISNUMBER(D87),ISNUMBER(E87)),IF(ABS(D87-E87)<0.005,"PASS","FAIL"),IF(D87=E87,"PASS","FAIL"))) | G87: Sep Income | H87: Analysis Engine | I87: B38 | J87: Analysis Engine
A88: AE_AUG_EXP | B88: ='[FinanceOS_QA_Baseline.xlsx]Analysis Engine'!C37 | C88: ='[FinanceOS_v1.0-QA-RC1.xlsx]Analysis Engine'!C37 | D88: =IF(OR(B88="",C88=""),"",IF(AND(ISNUMBER(B88),ISNUMBER(C88)),C88-B88,IF(B88=C88,0,"≠"))) | E88: =0 | F88: =IF(OR(B88="",C88=""),"WAIT",IF(AND(ISNUMBER(D88),ISNUMBER(E88)),IF(ABS(D88-E88)<0.005,"PASS","FAIL"),IF(D88=E88,"PASS","FAIL"))) | G88: Aug Expenses | H88: Analysis Engine | I88: C37 | J88: Analysis Engine
A89: AE_SEP_EXP | B89: ='[FinanceOS_QA_Baseline.xlsx]Analysis Engine'!C38 | C89: ='[FinanceOS_v1.0-QA-RC1.xlsx]Analysis Engine'!C38 | D89: =IF(OR(B89="",C89=""),"",IF(AND(ISNUMBER(B89),ISNUMBER(C89)),C89-B89,IF(B89=C89,0,"≠"))) | E89: =0 | F89: =IF(OR(B89="",C89=""),"WAIT",IF(AND(ISNUMBER(D89),ISNUMBER(E89)),IF(ABS(D89-E89)<0.005,"PASS","FAIL"),IF(D89=E89,"PASS","FAIL"))) | G89: Sep Expenses | H89: Analysis Engine | I89: C38 | J89: Analysis Engine
A90: AE_SEP_SAV | B90: ='[FinanceOS_QA_Baseline.xlsx]Analysis Engine'!D38 | C90: ='[FinanceOS_v1.0-QA-RC1.xlsx]Analysis Engine'!D38 | D90: =IF(OR(B90="",C90=""),"",IF(AND(ISNUMBER(B90),ISNUMBER(C90)),C90-B90,IF(B90=C90,0,"≠"))) | E90: =0 | F90: =IF(OR(B90="",C90=""),"WAIT",IF(AND(ISNUMBER(D90),ISNUMBER(E90)),IF(ABS(D90-E90)<0.005,"PASS","FAIL"),IF(D90=E90,"PASS","FAIL"))) | G90: Sep Savings | H90: Analysis Engine | I90: D38 | J90: Analysis Engine
A91: AE_CAT1 | B91: ='[FinanceOS_QA_Baseline.xlsx]Analysis Engine'!B17 | C91: ='[FinanceOS_v1.0-QA-RC1.xlsx]Analysis Engine'!B17 | D91: =IF(OR(B91="",C91=""),"",IF(AND(ISNUMBER(B91),ISNUMBER(C91)),C91-B91,IF(B91=C91,0,"≠"))) | E91: =0 | F91: =IF(OR(B91="",C91=""),"WAIT",IF(AND(ISNUMBER(D91),ISNUMBER(E91)),IF(ABS(D91-E91)<0.005,"PASS","FAIL"),IF(D91=E91,"PASS","FAIL"))) | G91: Category 1 CM | H91: Analysis Engine | I91: B17 | J91: Analysis Engine
A92: AE_CAT2 | B92: ='[FinanceOS_QA_Baseline.xlsx]Analysis Engine'!B18 | C92: ='[FinanceOS_v1.0-QA-RC1.xlsx]Analysis Engine'!B18 | D92: =IF(OR(B92="",C92=""),"",IF(AND(ISNUMBER(B92),ISNUMBER(C92)),C92-B92,IF(B92=C92,0,"≠"))) | E92: =0 | F92: =IF(OR(B92="",C92=""),"WAIT",IF(AND(ISNUMBER(D92),ISNUMBER(E92)),IF(ABS(D92-E92)<0.005,"PASS","FAIL"),IF(D92=E92,"PASS","FAIL"))) | G92: Category 2 CM | H92: Analysis Engine | I92: B18 | J92: Analysis Engine
A93: AE_CAT3 | B93: ='[FinanceOS_QA_Baseline.xlsx]Analysis Engine'!B19 | C93: ='[FinanceOS_v1.0-QA-RC1.xlsx]Analysis Engine'!B19 | D93: =IF(OR(B93="",C93=""),"",IF(AND(ISNUMBER(B93),ISNUMBER(C93)),C93-B93,IF(B93=C93,0,"≠"))) | E93: =0 | F93: =IF(OR(B93="",C93=""),"WAIT",IF(AND(ISNUMBER(D93),ISNUMBER(E93)),IF(ABS(D93-E93)<0.005,"PASS","FAIL"),IF(D93=E93,"PASS","FAIL"))) | G93: Category 3 CM | H93: Analysis Engine | I93: B19 | J93: Analysis Engine
A94: AE_SAL_YTD | B94: ='[FinanceOS_QA_Baseline.xlsx]Analysis Engine'!D7 | C94: ='[FinanceOS_v1.0-QA-RC1.xlsx]Analysis Engine'!D7 | D94: =IF(OR(B94="",C94=""),"",IF(AND(ISNUMBER(B94),ISNUMBER(C94)),C94-B94,IF(B94=C94,0,"≠"))) | E94: =0 | F94: =IF(OR(B94="",C94=""),"WAIT",IF(AND(ISNUMBER(D94),ISNUMBER(E94)),IF(ABS(D94-E94)<0.005,"PASS","FAIL"),IF(D94=E94,"PASS","FAIL"))) | G94: Salary YTD | H94: Analysis Engine | I94: D7 | J94: Analysis Engine
A95: AE_FREE_YTD | B95: ='[FinanceOS_QA_Baseline.xlsx]Analysis Engine'!D9 | C95: ='[FinanceOS_v1.0-QA-RC1.xlsx]Analysis Engine'!D9 | D95: =IF(OR(B95="",C95=""),"",IF(AND(ISNUMBER(B95),ISNUMBER(C95)),C95-B95,IF(B95=C95,0,"≠"))) | E95: =0 | F95: =IF(OR(B95="",C95=""),"WAIT",IF(AND(ISNUMBER(D95),ISNUMBER(E95)),IF(ABS(D95-E95)<0.005,"PASS","FAIL"),IF(D95=E95,"PASS","FAIL"))) | G95: Freelance YTD | H95: Analysis Engine | I95: D9 | J95: Analysis Engine
A96: AE_MOM_PCT | B96: ='[FinanceOS_QA_Baseline.xlsx]Analysis Engine'!B50 | C96: ='[FinanceOS_v1.0-QA-RC1.xlsx]Analysis Engine'!B50 | D96: =IF(OR(B96="",C96=""),"",IF(AND(ISNUMBER(B96),ISNUMBER(C96)),C96-B96,IF(B96=C96,0,"≠"))) | E96: =0 | F96: =IF(OR(B96="",C96=""),"WAIT",IF(AND(ISNUMBER(D96),ISNUMBER(E96)),IF(ABS(D96-E96)<0.005,"PASS","FAIL"),IF(D96=E96,"PASS","FAIL"))) | G96: MoM Expense Change % | H96: Analysis Engine | I96: B50 | J96: Analysis Engine

Sheet Cell Regression
A1: Cell | B1: Sheet | C1: Formula (QA-RC1 FORMULATEXT) | D1: Value Baseline | E1: Value QA-RC1 | F1: Changed? | G1: Expected to change? | H1: PASS / FAIL
A2: B4 | B2: Business Engine | C2: =IFERROR(FORMULATEXT('[FinanceOS_v1.0-QA-RC1.xlsx]Business Engine'!B4),"(value/no formula)") | D2: ='Difference Engine'!B2 | E2: ='Difference Engine'!C2 | F2: =IF(OR(D2="",E2=""),"WAIT",IF(AND(ISNUMBER(D2),ISNUMBER(E2)),IF(ABS(E2-D2)>0.005,"YES","NO"),IF(D2=E2,"NO","YES"))) | G2: =IF(AND(ISNUMBER('Difference Engine'!E2),ABS('Difference Engine'!E2)>0.005),"YES","NO") | H2: =IF(OR(F2="WAIT",D2=""),"WAIT",IF(F2=G2,"PASS","FAIL"))
A3: B5 | B3: Business Engine | C3: =IFERROR(FORMULATEXT('[FinanceOS_v1.0-QA-RC1.xlsx]Business Engine'!B5),"(value/no formula)") | D3: ='Difference Engine'!B3 | E3: ='Difference Engine'!C3 | F3: =IF(OR(D3="",E3=""),"WAIT",IF(AND(ISNUMBER(D3),ISNUMBER(E3)),IF(ABS(E3-D3)>0.005,"YES","NO"),IF(D3=E3,"NO","YES"))) | G3: =IF(AND(ISNUMBER('Difference Engine'!E3),ABS('Difference Engine'!E3)>0.005),"YES","NO") | H3: =IF(OR(F3="WAIT",D3=""),"WAIT",IF(F3=G3,"PASS","FAIL"))
A4: B6 | B4: Business Engine | C4: =IFERROR(FORMULATEXT('[FinanceOS_v1.0-QA-RC1.xlsx]Business Engine'!B6),"(value/no formula)") | D4: ='Difference Engine'!B4 | E4: ='Difference Engine'!C4 | F4: =IF(OR(D4="",E4=""),"WAIT",IF(AND(ISNUMBER(D4),ISNUMBER(E4)),IF(ABS(E4-D4)>0.005,"YES","NO"),IF(D4=E4,"NO","YES"))) | G4: =IF(AND(ISNUMBER('Difference Engine'!E4),ABS('Difference Engine'!E4)>0.005),"YES","NO") | H4: =IF(OR(F4="WAIT",D4=""),"WAIT",IF(F4=G4,"PASS","FAIL"))
A5: B7 | B5: Business Engine | C5: =IFERROR(FORMULATEXT('[FinanceOS_v1.0-QA-RC1.xlsx]Business Engine'!B7),"(value/no formula)") | D5: ='Difference Engine'!B5 | E5: ='Difference Engine'!C5 | F5: =IF(OR(D5="",E5=""),"WAIT",IF(AND(ISNUMBER(D5),ISNUMBER(E5)),IF(ABS(E5-D5)>0.005,"YES","NO"),IF(D5=E5,"NO","YES"))) | G5: =IF(AND(ISNUMBER('Difference Engine'!E5),ABS('Difference Engine'!E5)>0.005),"YES","NO") | H5: =IF(OR(F5="WAIT",D5=""),"WAIT",IF(F5=G5,"PASS","FAIL"))
A6: B8 | B6: Business Engine | C6: =IFERROR(FORMULATEXT('[FinanceOS_v1.0-QA-RC1.xlsx]Business Engine'!B8),"(value/no formula)") | D6: ='Difference Engine'!B6 | E6: ='Difference Engine'!C6 | F6: =IF(OR(D6="",E6=""),"WAIT",IF(AND(ISNUMBER(D6),ISNUMBER(E6)),IF(ABS(E6-D6)>0.005,"YES","NO"),IF(D6=E6,"NO","YES"))) | G6: =IF(AND(ISNUMBER('Difference Engine'!E6),ABS('Difference Engine'!E6)>0.005),"YES","NO") | H6: =IF(OR(F6="WAIT",D6=""),"WAIT",IF(F6=G6,"PASS","FAIL"))
A7: B9 | B7: Business Engine | C7: =IFERROR(FORMULATEXT('[FinanceOS_v1.0-QA-RC1.xlsx]Business Engine'!B9),"(value/no formula)") | D7: ='Difference Engine'!B7 | E7: ='Difference Engine'!C7 | F7: =IF(OR(D7="",E7=""),"WAIT",IF(AND(ISNUMBER(D7),ISNUMBER(E7)),IF(ABS(E7-D7)>0.005,"YES","NO"),IF(D7=E7,"NO","YES"))) | G7: =IF(AND(ISNUMBER('Difference Engine'!E7),ABS('Difference Engine'!E7)>0.005),"YES","NO") | H7: =IF(OR(F7="WAIT",D7=""),"WAIT",IF(F7=G7,"PASS","FAIL"))
A8: B12 | B8: Business Engine | C8: =IFERROR(FORMULATEXT('[FinanceOS_v1.0-QA-RC1.xlsx]Business Engine'!B12),"(value/no formula)") | D8: ='Difference Engine'!B8 | E8: ='Difference Engine'!C8 | F8: =IF(OR(D8="",E8=""),"WAIT",IF(AND(ISNUMBER(D8),ISNUMBER(E8)),IF(ABS(E8-D8)>0.005,"YES","NO"),IF(D8=E8,"NO","YES"))) | G8: =IF(AND(ISNUMBER('Difference Engine'!E8),ABS('Difference Engine'!E8)>0.005),"YES","NO") | H8: =IF(OR(F8="WAIT",D8=""),"WAIT",IF(F8=G8,"PASS","FAIL"))
A9: B13 | B9: Business Engine | C9: =IFERROR(FORMULATEXT('[FinanceOS_v1.0-QA-RC1.xlsx]Business Engine'!B13),"(value/no formula)") | D9: ='Difference Engine'!B9 | E9: ='Difference Engine'!C9 | F9: =IF(OR(D9="",E9=""),"WAIT",IF(AND(ISNUMBER(D9),ISNUMBER(E9)),IF(ABS(E9-D9)>0.005,"YES","NO"),IF(D9=E9,"NO","YES"))) | G9: =IF(AND(ISNUMBER('Difference Engine'!E9),ABS('Difference Engine'!E9)>0.005),"YES","NO") | H9: =IF(OR(F9="WAIT",D9=""),"WAIT",IF(F9=G9,"PASS","FAIL"))
A10: B14 | B10: Business Engine | C10: =IFERROR(FORMULATEXT('[FinanceOS_v1.0-QA-RC1.xlsx]Business Engine'!B14),"(value/no formula)") | D10: ='Difference Engine'!B10 | E10: ='Difference Engine'!C10 | F10: =IF(OR(D10="",E10=""),"WAIT",IF(AND(ISNUMBER(D10),ISNUMBER(E10)),IF(ABS(E10-D10)>0.005,"YES","NO"),IF(D10=E10,"NO","YES"))) | G10: =IF(AND(ISNUMBER('Difference Engine'!E10),ABS('Difference Engine'!E10)>0.005),"YES","NO") | H10: =IF(OR(F10="WAIT",D10=""),"WAIT",IF(F10=G10,"PASS","FAIL"))
A11: B15 | B11: Business Engine | C11: =IFERROR(FORMULATEXT('[FinanceOS_v1.0-QA-RC1.xlsx]Business Engine'!B15),"(value/no formula)") | D11: ='Difference Engine'!B11 | E11: ='Difference Engine'!C11 | F11: =IF(OR(D11="",E11=""),"WAIT",IF(AND(ISNUMBER(D11),ISNUMBER(E11)),IF(ABS(E11-D11)>0.005,"YES","NO"),IF(D11=E11,"NO","YES"))) | G11: =IF(AND(ISNUMBER('Difference Engine'!E11),ABS('Difference Engine'!E11)>0.005),"YES","NO") | H11: =IF(OR(F11="WAIT",D11=""),"WAIT",IF(F11=G11,"PASS","FAIL"))
A12: B16 | B12: Business Engine | C12: =IFERROR(FORMULATEXT('[FinanceOS_v1.0-QA-RC1.xlsx]Business Engine'!B16),"(value/no formula)") | D12: ='Difference Engine'!B12 | E12: ='Difference Engine'!C12 | F12: =IF(OR(D12="",E12=""),"WAIT",IF(AND(ISNUMBER(D12),ISNUMBER(E12)),IF(ABS(E12-D12)>0.005,"YES","NO"),IF(D12=E12,"NO","YES"))) | G12: =IF(AND(ISNUMBER('Difference Engine'!E12),ABS('Difference Engine'!E12)>0.005),"YES","NO") | H12: =IF(OR(F12="WAIT",D12=""),"WAIT",IF(F12=G12,"PASS","FAIL"))
A13: B17 | B13: Business Engine | C13: =IFERROR(FORMULATEXT('[FinanceOS_v1.0-QA-RC1.xlsx]Business Engine'!B17),"(value/no formula)") | D13: ='Difference Engine'!B13 | E13: ='Difference Engine'!C13 | F13: =IF(OR(D13="",E13=""),"WAIT",IF(AND(ISNUMBER(D13),ISNUMBER(E13)),IF(ABS(E13-D13)>0.005,"YES","NO"),IF(D13=E13,"NO","YES"))) | G13: =IF(AND(ISNUMBER('Difference Engine'!E13),ABS('Difference Engine'!E13)>0.005),"YES","NO") | H13: =IF(OR(F13="WAIT",D13=""),"WAIT",IF(F13=G13,"PASS","FAIL"))
A14: B18 | B14: Business Engine | C14: =IFERROR(FORMULATEXT('[FinanceOS_v1.0-QA-RC1.xlsx]Business Engine'!B18),"(value/no formula)") | D14: ='Difference Engine'!B14 | E14: ='Difference Engine'!C14 | F14: =IF(OR(D14="",E14=""),"WAIT",IF(AND(ISNUMBER(D14),ISNUMBER(E14)),IF(ABS(E14-D14)>0.005,"YES","NO"),IF(D14=E14,"NO","YES"))) | G14: =IF(AND(ISNUMBER('Difference Engine'!E14),ABS('Difference Engine'!E14)>0.005),"YES","NO") | H14: =IF(OR(F14="WAIT",D14=""),"WAIT",IF(F14=G14,"PASS","FAIL"))
A15: B19 | B15: Business Engine | C15: =IFERROR(FORMULATEXT('[FinanceOS_v1.0-QA-RC1.xlsx]Business Engine'!B19),"(value/no formula)") | D15: ='Difference Engine'!B15 | E15: ='Difference Engine'!C15 | F15: =IF(OR(D15="",E15=""),"WAIT",IF(AND(ISNUMBER(D15),ISNUMBER(E15)),IF(ABS(E15-D15)>0.005,"YES","NO"),IF(D15=E15,"NO","YES"))) | G15: =IF(AND(ISNUMBER('Difference Engine'!E15),ABS('Difference Engine'!E15)>0.005),"YES","NO") | H15: =IF(OR(F15="WAIT",D15=""),"WAIT",IF(F15=G15,"PASS","FAIL"))
A16: B22 | B16: Business Engine | C16: =IFERROR(FORMULATEXT('[FinanceOS_v1.0-QA-RC1.xlsx]Business Engine'!B22),"(value/no formula)") | D16: ='Difference Engine'!B16 | E16: ='Difference Engine'!C16 | F16: =IF(OR(D16="",E16=""),"WAIT",IF(AND(ISNUMBER(D16),ISNUMBER(E16)),IF(ABS(E16-D16)>0.005,"YES","NO"),IF(D16=E16,"NO","YES"))) | G16: =IF(AND(ISNUMBER('Difference Engine'!E16),ABS('Difference Engine'!E16)>0.005),"YES","NO") | H16: =IF(OR(F16="WAIT",D16=""),"WAIT",IF(F16=G16,"PASS","FAIL"))
A17: B23 | B17: Business Engine | C17: =IFERROR(FORMULATEXT('[FinanceOS_v1.0-QA-RC1.xlsx]Business Engine'!B23),"(value/no formula)") | D17: ='Difference Engine'!B17 | E17: ='Difference Engine'!C17 | F17: =IF(OR(D17="",E17=""),"WAIT",IF(AND(ISNUMBER(D17),ISNUMBER(E17)),IF(ABS(E17-D17)>0.005,"YES","NO"),IF(D17=E17,"NO","YES"))) | G17: =IF(AND(ISNUMBER('Difference Engine'!E17),ABS('Difference Engine'!E17)>0.005),"YES","NO") | H17: =IF(OR(F17="WAIT",D17=""),"WAIT",IF(F17=G17,"PASS","FAIL"))
A18: B24 | B18: Business Engine | C18: =IFERROR(FORMULATEXT('[FinanceOS_v1.0-QA-RC1.xlsx]Business Engine'!B24),"(value/no formula)") | D18: ='Difference Engine'!B18 | E18: ='Difference Engine'!C18 | F18: =IF(OR(D18="",E18=""),"WAIT",IF(AND(ISNUMBER(D18),ISNUMBER(E18)),IF(ABS(E18-D18)>0.005,"YES","NO"),IF(D18=E18,"NO","YES"))) | G18: =IF(AND(ISNUMBER('Difference Engine'!E18),ABS('Difference Engine'!E18)>0.005),"YES","NO") | H18: =IF(OR(F18="WAIT",D18=""),"WAIT",IF(F18=G18,"PASS","FAIL"))
A19: B25 | B19: Business Engine | C19: =IFERROR(FORMULATEXT('[FinanceOS_v1.0-QA-RC1.xlsx]Business Engine'!B25),"(value/no formula)") | D19: ='Difference Engine'!B19 | E19: ='Difference Engine'!C19 | F19: =IF(OR(D19="",E19=""),"WAIT",IF(AND(ISNUMBER(D19),ISNUMBER(E19)),IF(ABS(E19-D19)>0.005,"YES","NO"),IF(D19=E19,"NO","YES"))) | G19: =IF(AND(ISNUMBER('Difference Engine'!E19),ABS('Difference Engine'!E19)>0.005),"YES","NO") | H19: =IF(OR(F19="WAIT",D19=""),"WAIT",IF(F19=G19,"PASS","FAIL"))
A20: B28 | B20: Business Engine | C20: =IFERROR(FORMULATEXT('[FinanceOS_v1.0-QA-RC1.xlsx]Business Engine'!B28),"(value/no formula)") | D20: ='Difference Engine'!B20 | E20: ='Difference Engine'!C20 | F20: =IF(OR(D20="",E20=""),"WAIT",IF(AND(ISNUMBER(D20),ISNUMBER(E20)),IF(ABS(E20-D20)>0.005,"YES","NO"),IF(D20=E20,"NO","YES"))) | G20: =IF(AND(ISNUMBER('Difference Engine'!E20),ABS('Difference Engine'!E20)>0.005),"YES","NO") | H20: =IF(OR(F20="WAIT",D20=""),"WAIT",IF(F20=G20,"PASS","FAIL"))
A21: B29 | B21: Business Engine | C21: =IFERROR(FORMULATEXT('[FinanceOS_v1.0-QA-RC1.xlsx]Business Engine'!B29),"(value/no formula)") | D21: ='Difference Engine'!B21 | E21: ='Difference Engine'!C21 | F21: =IF(OR(D21="",E21=""),"WAIT",IF(AND(ISNUMBER(D21),ISNUMBER(E21)),IF(ABS(E21-D21)>0.005,"YES","NO"),IF(D21=E21,"NO","YES"))) | G21: =IF(AND(ISNUMBER('Difference Engine'!E21),ABS('Difference Engine'!E21)>0.005),"YES","NO") | H21: =IF(OR(F21="WAIT",D21=""),"WAIT",IF(F21=G21,"PASS","FAIL"))
A22: B30 | B22: Business Engine | C22: =IFERROR(FORMULATEXT('[FinanceOS_v1.0-QA-RC1.xlsx]Business Engine'!B30),"(value/no formula)") | D22: ='Difference Engine'!B22 | E22: ='Difference Engine'!C22 | F22: =IF(OR(D22="",E22=""),"WAIT",IF(AND(ISNUMBER(D22),ISNUMBER(E22)),IF(ABS(E22-D22)>0.005,"YES","NO"),IF(D22=E22,"NO","YES"))) | G22: =IF(AND(ISNUMBER('Difference Engine'!E22),ABS('Difference Engine'!E22)>0.005),"YES","NO") | H22: =IF(OR(F22="WAIT",D22=""),"WAIT",IF(F22=G22,"PASS","FAIL"))
A23: B31 | B23: Business Engine | C23: =IFERROR(FORMULATEXT('[FinanceOS_v1.0-QA-RC1.xlsx]Business Engine'!B31),"(value/no formula)") | D23: ='Difference Engine'!B23 | E23: ='Difference Engine'!C23 | F23: =IF(OR(D23="",E23=""),"WAIT",IF(AND(ISNUMBER(D23),ISNUMBER(E23)),IF(ABS(E23-D23)>0.005,"YES","NO"),IF(D23=E23,"NO","YES"))) | G23: =IF(AND(ISNUMBER('Difference Engine'!E23),ABS('Difference Engine'!E23)>0.005),"YES","NO") | H23: =IF(OR(F23="WAIT",D23=""),"WAIT",IF(F23=G23,"PASS","FAIL"))
A24: B34 | B24: Business Engine | C24: =IFERROR(FORMULATEXT('[FinanceOS_v1.0-QA-RC1.xlsx]Business Engine'!B34),"(value/no formula)") | D24: ='Difference Engine'!B24 | E24: ='Difference Engine'!C24 | F24: =IF(OR(D24="",E24=""),"WAIT",IF(AND(ISNUMBER(D24),ISNUMBER(E24)),IF(ABS(E24-D24)>0.005,"YES","NO"),IF(D24=E24,"NO","YES"))) | G24: =IF(AND(ISNUMBER('Difference Engine'!E24),ABS('Difference Engine'!E24)>0.005),"YES","NO") | H24: =IF(OR(F24="WAIT",D24=""),"WAIT",IF(F24=G24,"PASS","FAIL"))
A25: B35 | B25: Business Engine | C25: =IFERROR(FORMULATEXT('[FinanceOS_v1.0-QA-RC1.xlsx]Business Engine'!B35),"(value/no formula)") | D25: ='Difference Engine'!B25 | E25: ='Difference Engine'!C25 | F25: =IF(OR(D25="",E25=""),"WAIT",IF(AND(ISNUMBER(D25),ISNUMBER(E25)),IF(ABS(E25-D25)>0.005,"YES","NO"),IF(D25=E25,"NO","YES"))) | G25: =IF(AND(ISNUMBER('Difference Engine'!E25),ABS('Difference Engine'!E25)>0.005),"YES","NO") | H25: =IF(OR(F25="WAIT",D25=""),"WAIT",IF(F25=G25,"PASS","FAIL"))
A26: B36 | B26: Business Engine | C26: =IFERROR(FORMULATEXT('[FinanceOS_v1.0-QA-RC1.xlsx]Business Engine'!B36),"(value/no formula)") | D26: ='Difference Engine'!B26 | E26: ='Difference Engine'!C26 | F26: =IF(OR(D26="",E26=""),"WAIT",IF(AND(ISNUMBER(D26),ISNUMBER(E26)),IF(ABS(E26-D26)>0.005,"YES","NO"),IF(D26=E26,"NO","YES"))) | G26: =IF(AND(ISNUMBER('Difference Engine'!E26),ABS('Difference Engine'!E26)>0.005),"YES","NO") | H26: =IF(OR(F26="WAIT",D26=""),"WAIT",IF(F26=G26,"PASS","FAIL"))
A27: B37 | B27: Business Engine | C27: =IFERROR(FORMULATEXT('[FinanceOS_v1.0-QA-RC1.xlsx]Business Engine'!B37),"(value/no formula)") | D27: ='Difference Engine'!B27 | E27: ='Difference Engine'!C27 | F27: =IF(OR(D27="",E27=""),"WAIT",IF(AND(ISNUMBER(D27),ISNUMBER(E27)),IF(ABS(E27-D27)>0.005,"YES","NO"),IF(D27=E27,"NO","YES"))) | G27: =IF(AND(ISNUMBER('Difference Engine'!E27),ABS('Difference Engine'!E27)>0.005),"YES","NO") | H27: =IF(OR(F27="WAIT",D27=""),"WAIT",IF(F27=G27,"PASS","FAIL"))
A28: B38 | B28: Business Engine | C28: =IFERROR(FORMULATEXT('[FinanceOS_v1.0-QA-RC1.xlsx]Business Engine'!B38),"(value/no formula)") | D28: ='Difference Engine'!B28 | E28: ='Difference Engine'!C28 | F28: =IF(OR(D28="",E28=""),"WAIT",IF(AND(ISNUMBER(D28),ISNUMBER(E28)),IF(ABS(E28-D28)>0.005,"YES","NO"),IF(D28=E28,"NO","YES"))) | G28: =IF(AND(ISNUMBER('Difference Engine'!E28),ABS('Difference Engine'!E28)>0.005),"YES","NO") | H28: =IF(OR(F28="WAIT",D28=""),"WAIT",IF(F28=G28,"PASS","FAIL"))
A29: B41 | B29: Business Engine | C29: =IFERROR(FORMULATEXT('[FinanceOS_v1.0-QA-RC1.xlsx]Business Engine'!B41),"(value/no formula)") | D29: ='Difference Engine'!B29 | E29: ='Difference Engine'!C29 | F29: =IF(OR(D29="",E29=""),"WAIT",IF(AND(ISNUMBER(D29),ISNUMBER(E29)),IF(ABS(E29-D29)>0.005,"YES","NO"),IF(D29=E29,"NO","YES"))) | G29: =IF(AND(ISNUMBER('Difference Engine'!E29),ABS('Difference Engine'!E29)>0.005),"YES","NO") | H29: =IF(OR(F29="WAIT",D29=""),"WAIT",IF(F29=G29,"PASS","FAIL"))
A30: B42 | B30: Business Engine | C30: =IFERROR(FORMULATEXT('[FinanceOS_v1.0-QA-RC1.xlsx]Business Engine'!B42),"(value/no formula)") | D30: ='Difference Engine'!B30 | E30: ='Difference Engine'!C30 | F30: =IF(OR(D30="",E30=""),"WAIT",IF(AND(ISNUMBER(D30),ISNUMBER(E30)),IF(ABS(E30-D30)>0.005,"YES","NO"),IF(D30=E30,"NO","YES"))) | G30: =IF(AND(ISNUMBER('Difference Engine'!E30),ABS('Difference Engine'!E30)>0.005),"YES","NO") | H30: =IF(OR(F30="WAIT",D30=""),"WAIT",IF(F30=G30,"PASS","FAIL"))
A31: B43 | B31: Business Engine | C31: =IFERROR(FORMULATEXT('[FinanceOS_v1.0-QA-RC1.xlsx]Business Engine'!B43),"(value/no formula)") | D31: ='Difference Engine'!B31 | E31: ='Difference Engine'!C31 | F31: =IF(OR(D31="",E31=""),"WAIT",IF(AND(ISNUMBER(D31),ISNUMBER(E31)),IF(ABS(E31-D31)>0.005,"YES","NO"),IF(D31=E31,"NO","YES"))) | G31: =IF(AND(ISNUMBER('Difference Engine'!E31),ABS('Difference Engine'!E31)>0.005),"YES","NO") | H31: =IF(OR(F31="WAIT",D31=""),"WAIT",IF(F31=G31,"PASS","FAIL"))
A32: B44 | B32: Business Engine | C32: =IFERROR(FORMULATEXT('[FinanceOS_v1.0-QA-RC1.xlsx]Business Engine'!B44),"(value/no formula)") | D32: ='Difference Engine'!B32 | E32: ='Difference Engine'!C32 | F32: =IF(OR(D32="",E32=""),"WAIT",IF(AND(ISNUMBER(D32),ISNUMBER(E32)),IF(ABS(E32-D32)>0.005,"YES","NO"),IF(D32=E32,"NO","YES"))) | G32: =IF(AND(ISNUMBER('Difference Engine'!E32),ABS('Difference Engine'!E32)>0.005),"YES","NO") | H32: =IF(OR(F32="WAIT",D32=""),"WAIT",IF(F32=G32,"PASS","FAIL"))
A33: B45 | B33: Business Engine | C33: =IFERROR(FORMULATEXT('[FinanceOS_v1.0-QA-RC1.xlsx]Business Engine'!B45),"(value/no formula)") | D33: ='Difference Engine'!B33 | E33: ='Difference Engine'!C33 | F33: =IF(OR(D33="",E33=""),"WAIT",IF(AND(ISNUMBER(D33),ISNUMBER(E33)),IF(ABS(E33-D33)>0.005,"YES","NO"),IF(D33=E33,"NO","YES"))) | G33: =IF(AND(ISNUMBER('Difference Engine'!E33),ABS('Difference Engine'!E33)>0.005),"YES","NO") | H33: =IF(OR(F33="WAIT",D33=""),"WAIT",IF(F33=G33,"PASS","FAIL"))
A34: B48 | B34: Business Engine | C34: =IFERROR(FORMULATEXT('[FinanceOS_v1.0-QA-RC1.xlsx]Business Engine'!B48),"(value/no formula)") | D34: ='Difference Engine'!B34 | E34: ='Difference Engine'!C34 | F34: =IF(OR(D34="",E34=""),"WAIT",IF(AND(ISNUMBER(D34),ISNUMBER(E34)),IF(ABS(E34-D34)>0.005,"YES","NO"),IF(D34=E34,"NO","YES"))) | G34: =IF(AND(ISNUMBER('Difference Engine'!E34),ABS('Difference Engine'!E34)>0.005),"YES","NO") | H34: =IF(OR(F34="WAIT",D34=""),"WAIT",IF(F34=G34,"PASS","FAIL"))
A35: B49 | B35: Business Engine | C35: =IFERROR(FORMULATEXT('[FinanceOS_v1.0-QA-RC1.xlsx]Business Engine'!B49),"(value/no formula)") | D35: ='Difference Engine'!B35 | E35: ='Difference Engine'!C35 | F35: =IF(OR(D35="",E35=""),"WAIT",IF(AND(ISNUMBER(D35),ISNUMBER(E35)),IF(ABS(E35-D35)>0.005,"YES","NO"),IF(D35=E35,"NO","YES"))) | G35: =IF(AND(ISNUMBER('Difference Engine'!E35),ABS('Difference Engine'!E35)>0.005),"YES","NO") | H35: =IF(OR(F35="WAIT",D35=""),"WAIT",IF(F35=G35,"PASS","FAIL"))
A36: B50 | B36: Business Engine | C36: =IFERROR(FORMULATEXT('[FinanceOS_v1.0-QA-RC1.xlsx]Business Engine'!B50),"(value/no formula)") | D36: ='Difference Engine'!B36 | E36: ='Difference Engine'!C36 | F36: =IF(OR(D36="",E36=""),"WAIT",IF(AND(ISNUMBER(D36),ISNUMBER(E36)),IF(ABS(E36-D36)>0.005,"YES","NO"),IF(D36=E36,"NO","YES"))) | G36: =IF(AND(ISNUMBER('Difference Engine'!E36),ABS('Difference Engine'!E36)>0.005),"YES","NO") | H36: =IF(OR(F36="WAIT",D36=""),"WAIT",IF(F36=G36,"PASS","FAIL"))
A37: B53 | B37: Business Engine | C37: =IFERROR(FORMULATEXT('[FinanceOS_v1.0-QA-RC1.xlsx]Business Engine'!B53),"(value/no formula)") | D37: ='Difference Engine'!B37 | E37: ='Difference Engine'!C37 | F37: =IF(OR(D37="",E37=""),"WAIT",IF(AND(ISNUMBER(D37),ISNUMBER(E37)),IF(ABS(E37-D37)>0.005,"YES","NO"),IF(D37=E37,"NO","YES"))) | G37: =IF(AND(ISNUMBER('Difference Engine'!E37),ABS('Difference Engine'!E37)>0.005),"YES","NO") | H37: =IF(OR(F37="WAIT",D37=""),"WAIT",IF(F37=G37,"PASS","FAIL"))
A38: B54 | B38: Business Engine | C38: =IFERROR(FORMULATEXT('[FinanceOS_v1.0-QA-RC1.xlsx]Business Engine'!B54),"(value/no formula)") | D38: ='Difference Engine'!B38 | E38: ='Difference Engine'!C38 | F38: =IF(OR(D38="",E38=""),"WAIT",IF(AND(ISNUMBER(D38),ISNUMBER(E38)),IF(ABS(E38-D38)>0.005,"YES","NO"),IF(D38=E38,"NO","YES"))) | G38: =IF(AND(ISNUMBER('Difference Engine'!E38),ABS('Difference Engine'!E38)>0.005),"YES","NO") | H38: =IF(OR(F38="WAIT",D38=""),"WAIT",IF(F38=G38,"PASS","FAIL"))
A39: B55 | B39: Business Engine | C39: =IFERROR(FORMULATEXT('[FinanceOS_v1.0-QA-RC1.xlsx]Business Engine'!B55),"(value/no formula)") | D39: ='Difference Engine'!B39 | E39: ='Difference Engine'!C39 | F39: =IF(OR(D39="",E39=""),"WAIT",IF(AND(ISNUMBER(D39),ISNUMBER(E39)),IF(ABS(E39-D39)>0.005,"YES","NO"),IF(D39=E39,"NO","YES"))) | G39: =IF(AND(ISNUMBER('Difference Engine'!E39),ABS('Difference Engine'!E39)>0.005),"YES","NO") | H39: =IF(OR(F39="WAIT",D39=""),"WAIT",IF(F39=G39,"PASS","FAIL"))
A40: B56 | B40: Business Engine | C40: =IFERROR(FORMULATEXT('[FinanceOS_v1.0-QA-RC1.xlsx]Business Engine'!B56),"(value/no formula)") | D40: ='Difference Engine'!B40 | E40: ='Difference Engine'!C40 | F40: =IF(OR(D40="",E40=""),"WAIT",IF(AND(ISNUMBER(D40),ISNUMBER(E40)),IF(ABS(E40-D40)>0.005,"YES","NO"),IF(D40=E40,"NO","YES"))) | G40: =IF(AND(ISNUMBER('Difference Engine'!E40),ABS('Difference Engine'!E40)>0.005),"YES","NO") | H40: =IF(OR(F40="WAIT",D40=""),"WAIT",IF(F40=G40,"PASS","FAIL"))
A41: B57 | B41: Business Engine | C41: =IFERROR(FORMULATEXT('[FinanceOS_v1.0-QA-RC1.xlsx]Business Engine'!B57),"(value/no formula)") | D41: ='Difference Engine'!B41 | E41: ='Difference Engine'!C41 | F41: =IF(OR(D41="",E41=""),"WAIT",IF(AND(ISNUMBER(D41),ISNUMBER(E41)),IF(ABS(E41-D41)>0.005,"YES","NO"),IF(D41=E41,"NO","YES"))) | G41: =IF(AND(ISNUMBER('Difference Engine'!E41),ABS('Difference Engine'!E41)>0.005),"YES","NO") | H41: =IF(OR(F41="WAIT",D41=""),"WAIT",IF(F41=G41,"PASS","FAIL"))
A42: B58 | B42: Business Engine | C42: =IFERROR(FORMULATEXT('[FinanceOS_v1.0-QA-RC1.xlsx]Business Engine'!B58),"(value/no formula)") | D42: ='Difference Engine'!B42 | E42: ='Difference Engine'!C42 | F42: =IF(OR(D42="",E42=""),"WAIT",IF(AND(ISNUMBER(D42),ISNUMBER(E42)),IF(ABS(E42-D42)>0.005,"YES","NO"),IF(D42=E42,"NO","YES"))) | G42: =IF(AND(ISNUMBER('Difference Engine'!E42),ABS('Difference Engine'!E42)>0.005),"YES","NO") | H42: =IF(OR(F42="WAIT",D42=""),"WAIT",IF(F42=G42,"PASS","FAIL"))
A43: B61 | B43: Business Engine | C43: =IFERROR(FORMULATEXT('[FinanceOS_v1.0-QA-RC1.xlsx]Business Engine'!B61),"(value/no formula)") | D43: ='Difference Engine'!B43 | E43: ='Difference Engine'!C43 | F43: =IF(OR(D43="",E43=""),"WAIT",IF(AND(ISNUMBER(D43),ISNUMBER(E43)),IF(ABS(E43-D43)>0.005,"YES","NO"),IF(D43=E43,"NO","YES"))) | G43: =IF(AND(ISNUMBER('Difference Engine'!E43),ABS('Difference Engine'!E43)>0.005),"YES","NO") | H43: =IF(OR(F43="WAIT",D43=""),"WAIT",IF(F43=G43,"PASS","FAIL"))
A44: B62 | B44: Business Engine | C44: =IFERROR(FORMULATEXT('[FinanceOS_v1.0-QA-RC1.xlsx]Business Engine'!B62),"(value/no formula)") | D44: ='Difference Engine'!B44 | E44: ='Difference Engine'!C44 | F44: =IF(OR(D44="",E44=""),"WAIT",IF(AND(ISNUMBER(D44),ISNUMBER(E44)),IF(ABS(E44-D44)>0.005,"YES","NO"),IF(D44=E44,"NO","YES"))) | G44: =IF(AND(ISNUMBER('Difference Engine'!E44),ABS('Difference Engine'!E44)>0.005),"YES","NO") | H44: =IF(OR(F44="WAIT",D44=""),"WAIT",IF(F44=G44,"PASS","FAIL"))
A45: B63 | B45: Business Engine | C45: =IFERROR(FORMULATEXT('[FinanceOS_v1.0-QA-RC1.xlsx]Business Engine'!B63),"(value/no formula)") | D45: ='Difference Engine'!B45 | E45: ='Difference Engine'!C45 | F45: =IF(OR(D45="",E45=""),"WAIT",IF(AND(ISNUMBER(D45),ISNUMBER(E45)),IF(ABS(E45-D45)>0.005,"YES","NO"),IF(D45=E45,"NO","YES"))) | G45: =IF(AND(ISNUMBER('Difference Engine'!E45),ABS('Difference Engine'!E45)>0.005),"YES","NO") | H45: =IF(OR(F45="WAIT",D45=""),"WAIT",IF(F45=G45,"PASS","FAIL"))
A46: B64 | B46: Business Engine | C46: =IFERROR(FORMULATEXT('[FinanceOS_v1.0-QA-RC1.xlsx]Business Engine'!B64),"(value/no formula)") | D46: ='Difference Engine'!B46 | E46: ='Difference Engine'!C46 | F46: =IF(OR(D46="",E46=""),"WAIT",IF(AND(ISNUMBER(D46),ISNUMBER(E46)),IF(ABS(E46-D46)>0.005,"YES","NO"),IF(D46=E46,"NO","YES"))) | G46: =IF(AND(ISNUMBER('Difference Engine'!E46),ABS('Difference Engine'!E46)>0.005),"YES","NO") | H46: =IF(OR(F46="WAIT",D46=""),"WAIT",IF(F46=G46,"PASS","FAIL"))
A47: B65 | B47: Business Engine | C47: =IFERROR(FORMULATEXT('[FinanceOS_v1.0-QA-RC1.xlsx]Business Engine'!B65),"(value/no formula)") | D47: ='Difference Engine'!B47 | E47: ='Difference Engine'!C47 | F47: =IF(OR(D47="",E47=""),"WAIT",IF(AND(ISNUMBER(D47),ISNUMBER(E47)),IF(ABS(E47-D47)>0.005,"YES","NO"),IF(D47=E47,"NO","YES"))) | G47: =IF(AND(ISNUMBER('Difference Engine'!E47),ABS('Difference Engine'!E47)>0.005),"YES","NO") | H47: =IF(OR(F47="WAIT",D47=""),"WAIT",IF(F47=G47,"PASS","FAIL"))
A48: B66 | B48: Business Engine | C48: =IFERROR(FORMULATEXT('[FinanceOS_v1.0-QA-RC1.xlsx]Business Engine'!B66),"(value/no formula)") | D48: ='Difference Engine'!B48 | E48: ='Difference Engine'!C48 | F48: =IF(OR(D48="",E48=""),"WAIT",IF(AND(ISNUMBER(D48),ISNUMBER(E48)),IF(ABS(E48-D48)>0.005,"YES","NO"),IF(D48=E48,"NO","YES"))) | G48: =IF(AND(ISNUMBER('Difference Engine'!E48),ABS('Difference Engine'!E48)>0.005),"YES","NO") | H48: =IF(OR(F48="WAIT",D48=""),"WAIT",IF(F48=G48,"PASS","FAIL"))
A49: B67 | B49: Business Engine | C49: =IFERROR(FORMULATEXT('[FinanceOS_v1.0-QA-RC1.xlsx]Business Engine'!B67),"(value/no formula)") | D49: ='Difference Engine'!B49 | E49: ='Difference Engine'!C49 | F49: =IF(OR(D49="",E49=""),"WAIT",IF(AND(ISNUMBER(D49),ISNUMBER(E49)),IF(ABS(E49-D49)>0.005,"YES","NO"),IF(D49=E49,"NO","YES"))) | G49: =IF(AND(ISNUMBER('Difference Engine'!E49),ABS('Difference Engine'!E49)>0.005),"YES","NO") | H49: =IF(OR(F49="WAIT",D49=""),"WAIT",IF(F49=G49,"PASS","FAIL"))
A50: B68 | B50: Business Engine | C50: =IFERROR(FORMULATEXT('[FinanceOS_v1.0-QA-RC1.xlsx]Business Engine'!B68),"(value/no formula)") | D50: ='Difference Engine'!B50 | E50: ='Difference Engine'!C50 | F50: =IF(OR(D50="",E50=""),"WAIT",IF(AND(ISNUMBER(D50),ISNUMBER(E50)),IF(ABS(E50-D50)>0.005,"YES","NO"),IF(D50=E50,"NO","YES"))) | G50: =IF(AND(ISNUMBER('Difference Engine'!E50),ABS('Difference Engine'!E50)>0.005),"YES","NO") | H50: =IF(OR(F50="WAIT",D50=""),"WAIT",IF(F50=G50,"PASS","FAIL"))
A51: B1 | B51: Business Engine | C51: =IFERROR(FORMULATEXT('[FinanceOS_v1.0-QA-RC1.xlsx]Business Engine'!B1),"(value/no formula)") | D51: ='Difference Engine'!B51 | E51: ='Difference Engine'!C51 | F51: =IF(OR(D51="",E51=""),"WAIT",IF(AND(ISNUMBER(D51),ISNUMBER(E51)),IF(ABS(E51-D51)>0.005,"YES","NO"),IF(D51=E51,"NO","YES"))) | G51: =IF(AND(ISNUMBER('Difference Engine'!E51),ABS('Difference Engine'!E51)>0.005),"YES","NO") | H51: =IF(OR(F51="WAIT",D51=""),"WAIT",IF(F51=G51,"PASS","FAIL"))
A52: B2 | B52: Analysis Engine | C52: =IFERROR(FORMULATEXT('[FinanceOS_v1.0-QA-RC1.xlsx]Analysis Engine'!B2),"(value/no formula)") | D52: ='Difference Engine'!B52 | E52: ='Difference Engine'!C52 | F52: =IF(OR(D52="",E52=""),"WAIT",IF(AND(ISNUMBER(D52),ISNUMBER(E52)),IF(ABS(E52-D52)>0.005,"YES","NO"),IF(D52=E52,"NO","YES"))) | G52: =IF(AND(ISNUMBER('Difference Engine'!E52),ABS('Difference Engine'!E52)>0.005),"YES","NO") | H52: =IF(OR(F52="WAIT",D52=""),"WAIT",IF(F52=G52,"PASS","FAIL"))
A53: B6 | B53: Analysis Engine | C53: =IFERROR(FORMULATEXT('[FinanceOS_v1.0-QA-RC1.xlsx]Analysis Engine'!B6),"(value/no formula)") | D53: ='Difference Engine'!B53 | E53: ='Difference Engine'!C53 | F53: =IF(OR(D53="",E53=""),"WAIT",IF(AND(ISNUMBER(D53),ISNUMBER(E53)),IF(ABS(E53-D53)>0.005,"YES","NO"),IF(D53=E53,"NO","YES"))) | G53: =IF(AND(ISNUMBER('Difference Engine'!E53),ABS('Difference Engine'!E53)>0.005),"YES","NO") | H53: =IF(OR(F53="WAIT",D53=""),"WAIT",IF(F53=G53,"PASS","FAIL"))
A54: B7 | B54: Analysis Engine | C54: =IFERROR(FORMULATEXT('[FinanceOS_v1.0-QA-RC1.xlsx]Analysis Engine'!B7),"(value/no formula)") | D54: ='Difference Engine'!B54 | E54: ='Difference Engine'!C54 | F54: =IF(OR(D54="",E54=""),"WAIT",IF(AND(ISNUMBER(D54),ISNUMBER(E54)),IF(ABS(E54-D54)>0.005,"YES","NO"),IF(D54=E54,"NO","YES"))) | G54: =IF(AND(ISNUMBER('Difference Engine'!E54),ABS('Difference Engine'!E54)>0.005),"YES","NO") | H54: =IF(OR(F54="WAIT",D54=""),"WAIT",IF(F54=G54,"PASS","FAIL"))
A55: B8 | B55: Analysis Engine | C55: =IFERROR(FORMULATEXT('[FinanceOS_v1.0-QA-RC1.xlsx]Analysis Engine'!B8),"(value/no formula)") | D55: ='Difference Engine'!B55 | E55: ='Difference Engine'!C55 | F55: =IF(OR(D55="",E55=""),"WAIT",IF(AND(ISNUMBER(D55),ISNUMBER(E55)),IF(ABS(E55-D55)>0.005,"YES","NO"),IF(D55=E55,"NO","YES"))) | G55: =IF(AND(ISNUMBER('Difference Engine'!E55),ABS('Difference Engine'!E55)>0.005),"YES","NO") | H55: =IF(OR(F55="WAIT",D55=""),"WAIT",IF(F55=G55,"PASS","FAIL"))
A56: B9 | B56: Analysis Engine | C56: =IFERROR(FORMULATEXT('[FinanceOS_v1.0-QA-RC1.xlsx]Analysis Engine'!B9),"(value/no formula)") | D56: ='Difference Engine'!B56 | E56: ='Difference Engine'!C56 | F56: =IF(OR(D56="",E56=""),"WAIT",IF(AND(ISNUMBER(D56),ISNUMBER(E56)),IF(ABS(E56-D56)>0.005,"YES","NO"),IF(D56=E56,"NO","YES"))) | G56: =IF(AND(ISNUMBER('Difference Engine'!E56),ABS('Difference Engine'!E56)>0.005),"YES","NO") | H56: =IF(OR(F56="WAIT",D56=""),"WAIT",IF(F56=G56,"PASS","FAIL"))
A57: B10 | B57: Analysis Engine | C57: =IFERROR(FORMULATEXT('[FinanceOS_v1.0-QA-RC1.xlsx]Analysis Engine'!B10),"(value/no formula)") | D57: ='Difference Engine'!B57 | E57: ='Difference Engine'!C57 | F57: =IF(OR(D57="",E57=""),"WAIT",IF(AND(ISNUMBER(D57),ISNUMBER(E57)),IF(ABS(E57-D57)>0.005,"YES","NO"),IF(D57=E57,"NO","YES"))) | G57: =IF(AND(ISNUMBER('Difference Engine'!E57),ABS('Difference Engine'!E57)>0.005),"YES","NO") | H57: =IF(OR(F57="WAIT",D57=""),"WAIT",IF(F57=G57,"PASS","FAIL"))
A58: B11 | B58: Analysis Engine | C58: =IFERROR(FORMULATEXT('[FinanceOS_v1.0-QA-RC1.xlsx]Analysis Engine'!B11),"(value/no formula)") | D58: ='Difference Engine'!B58 | E58: ='Difference Engine'!C58 | F58: =IF(OR(D58="",E58=""),"WAIT",IF(AND(ISNUMBER(D58),ISNUMBER(E58)),IF(ABS(E58-D58)>0.005,"YES","NO"),IF(D58=E58,"NO","YES"))) | G58: =IF(AND(ISNUMBER('Difference Engine'!E58),ABS('Difference Engine'!E58)>0.005),"YES","NO") | H58: =IF(OR(F58="WAIT",D58=""),"WAIT",IF(F58=G58,"PASS","FAIL"))
A59: C6 | B59: Analysis Engine | C59: =IFERROR(FORMULATEXT('[FinanceOS_v1.0-QA-RC1.xlsx]Analysis Engine'!C6),"(value/no formula)") | D59: ='Difference Engine'!B59 | E59: ='Difference Engine'!C59 | F59: =IF(OR(D59="",E59=""),"WAIT",IF(AND(ISNUMBER(D59),ISNUMBER(E59)),IF(ABS(E59-D59)>0.005,"YES","NO"),IF(D59=E59,"NO","YES"))) | G59: =IF(AND(ISNUMBER('Difference Engine'!E59),ABS('Difference Engine'!E59)>0.005),"YES","NO") | H59: =IF(OR(F59="WAIT",D59=""),"WAIT",IF(F59=G59,"PASS","FAIL"))
A60: D6 | B60: Analysis Engine | C60: =IFERROR(FORMULATEXT('[FinanceOS_v1.0-QA-RC1.xlsx]Analysis Engine'!D6),"(value/no formula)") | D60: ='Difference Engine'!B60 | E60: ='Difference Engine'!C60 | F60: =IF(OR(D60="",E60=""),"WAIT",IF(AND(ISNUMBER(D60),ISNUMBER(E60)),IF(ABS(E60-D60)>0.005,"YES","NO"),IF(D60=E60,"NO","YES"))) | G60: =IF(AND(ISNUMBER('Difference Engine'!E60),ABS('Difference Engine'!E60)>0.005),"YES","NO") | H60: =IF(OR(F60="WAIT",D60=""),"WAIT",IF(F60=G60,"PASS","FAIL"))
A61: B14 | B61: Analysis Engine | C61: =IFERROR(FORMULATEXT('[FinanceOS_v1.0-QA-RC1.xlsx]Analysis Engine'!B14),"(value/no formula)") | D61: ='Difference Engine'!B61 | E61: ='Difference Engine'!C61 | F61: =IF(OR(D61="",E61=""),"WAIT",IF(AND(ISNUMBER(D61),ISNUMBER(E61)),IF(ABS(E61-D61)>0.005,"YES","NO"),IF(D61=E61,"NO","YES"))) | G61: =IF(AND(ISNUMBER('Difference Engine'!E61),ABS('Difference Engine'!E61)>0.005),"YES","NO") | H61: =IF(OR(F61="WAIT",D61=""),"WAIT",IF(F61=G61,"PASS","FAIL"))
A62: C14 | B62: Analysis Engine | C62: =IFERROR(FORMULATEXT('[FinanceOS_v1.0-QA-RC1.xlsx]Analysis Engine'!C14),"(value/no formula)") | D62: ='Difference Engine'!B62 | E62: ='Difference Engine'!C62 | F62: =IF(OR(D62="",E62=""),"WAIT",IF(AND(ISNUMBER(D62),ISNUMBER(E62)),IF(ABS(E62-D62)>0.005,"YES","NO"),IF(D62=E62,"NO","YES"))) | G62: =IF(AND(ISNUMBER('Difference Engine'!E62),ABS('Difference Engine'!E62)>0.005),"YES","NO") | H62: =IF(OR(F62="WAIT",D62=""),"WAIT",IF(F62=G62,"PASS","FAIL"))
A63: D14 | B63: Analysis Engine | C63: =IFERROR(FORMULATEXT('[FinanceOS_v1.0-QA-RC1.xlsx]Analysis Engine'!D14),"(value/no formula)") | D63: ='Difference Engine'!B63 | E63: ='Difference Engine'!C63 | F63: =IF(OR(D63="",E63=""),"WAIT",IF(AND(ISNUMBER(D63),ISNUMBER(E63)),IF(ABS(E63-D63)>0.005,"YES","NO"),IF(D63=E63,"NO","YES"))) | G63: =IF(AND(ISNUMBER('Difference Engine'!E63),ABS('Difference Engine'!E63)>0.005),"YES","NO") | H63: =IF(OR(F63="WAIT",D63=""),"WAIT",IF(F63=G63,"PASS","FAIL"))
A64: B44 | B64: Analysis Engine | C64: =IFERROR(FORMULATEXT('[FinanceOS_v1.0-QA-RC1.xlsx]Analysis Engine'!B44),"(value/no formula)") | D64: ='Difference Engine'!B64 | E64: ='Difference Engine'!C64 | F64: =IF(OR(D64="",E64=""),"WAIT",IF(AND(ISNUMBER(D64),ISNUMBER(E64)),IF(ABS(E64-D64)>0.005,"YES","NO"),IF(D64=E64,"NO","YES"))) | G64: =IF(AND(ISNUMBER('Difference Engine'!E64),ABS('Difference Engine'!E64)>0.005),"YES","NO") | H64: =IF(OR(F64="WAIT",D64=""),"WAIT",IF(F64=G64,"PASS","FAIL"))
A65: B45 | B65: Analysis Engine | C65: =IFERROR(FORMULATEXT('[FinanceOS_v1.0-QA-RC1.xlsx]Analysis Engine'!B45),"(value/no formula)") | D65: ='Difference Engine'!B65 | E65: ='Difference Engine'!C65 | F65: =IF(OR(D65="",E65=""),"WAIT",IF(AND(ISNUMBER(D65),ISNUMBER(E65)),IF(ABS(E65-D65)>0.005,"YES","NO"),IF(D65=E65,"NO","YES"))) | G65: =IF(AND(ISNUMBER('Difference Engine'!E65),ABS('Difference Engine'!E65)>0.005),"YES","NO") | H65: =IF(OR(F65="WAIT",D65=""),"WAIT",IF(F65=G65,"PASS","FAIL"))
A66: B46 | B66: Analysis Engine | C66: =IFERROR(FORMULATEXT('[FinanceOS_v1.0-QA-RC1.xlsx]Analysis Engine'!B46),"(value/no formula)") | D66: ='Difference Engine'!B66 | E66: ='Difference Engine'!C66 | F66: =IF(OR(D66="",E66=""),"WAIT",IF(AND(ISNUMBER(D66),ISNUMBER(E66)),IF(ABS(E66-D66)>0.005,"YES","NO"),IF(D66=E66,"NO","YES"))) | G66: =IF(AND(ISNUMBER('Difference Engine'!E66),ABS('Difference Engine'!E66)>0.005),"YES","NO") | H66: =IF(OR(F66="WAIT",D66=""),"WAIT",IF(F66=G66,"PASS","FAIL"))
A67: B47 | B67: Analysis Engine | C67: =IFERROR(FORMULATEXT('[FinanceOS_v1.0-QA-RC1.xlsx]Analysis Engine'!B47),"(value/no formula)") | D67: ='Difference Engine'!B67 | E67: ='Difference Engine'!C67 | F67: =IF(OR(D67="",E67=""),"WAIT",IF(AND(ISNUMBER(D67),ISNUMBER(E67)),IF(ABS(E67-D67)>0.005,"YES","NO"),IF(D67=E67,"NO","YES"))) | G67: =IF(AND(ISNUMBER('Difference Engine'!E67),ABS('Difference Engine'!E67)>0.005),"YES","NO") | H67: =IF(OR(F67="WAIT",D67=""),"WAIT",IF(F67=G67,"PASS","FAIL"))
A68: B48 | B68: Analysis Engine | C68: =IFERROR(FORMULATEXT('[FinanceOS_v1.0-QA-RC1.xlsx]Analysis Engine'!B48),"(value/no formula)") | D68: ='Difference Engine'!B68 | E68: ='Difference Engine'!C68 | F68: =IF(OR(D68="",E68=""),"WAIT",IF(AND(ISNUMBER(D68),ISNUMBER(E68)),IF(ABS(E68-D68)>0.005,"YES","NO"),IF(D68=E68,"NO","YES"))) | G68: =IF(AND(ISNUMBER('Difference Engine'!E68),ABS('Difference Engine'!E68)>0.005),"YES","NO") | H68: =IF(OR(F68="WAIT",D68=""),"WAIT",IF(F68=G68,"PASS","FAIL"))
A69: B49 | B69: Analysis Engine | C69: =IFERROR(FORMULATEXT('[FinanceOS_v1.0-QA-RC1.xlsx]Analysis Engine'!B49),"(value/no formula)") | D69: ='Difference Engine'!B69 | E69: ='Difference Engine'!C69 | F69: =IF(OR(D69="",E69=""),"WAIT",IF(AND(ISNUMBER(D69),ISNUMBER(E69)),IF(ABS(E69-D69)>0.005,"YES","NO"),IF(D69=E69,"NO","YES"))) | G69: =IF(AND(ISNUMBER('Difference Engine'!E69),ABS('Difference Engine'!E69)>0.005),"YES","NO") | H69: =IF(OR(F69="WAIT",D69=""),"WAIT",IF(F69=G69,"PASS","FAIL"))
A70: B54 | B70: Analysis Engine | C70: =IFERROR(FORMULATEXT('[FinanceOS_v1.0-QA-RC1.xlsx]Analysis Engine'!B54),"(value/no formula)") | D70: ='Difference Engine'!B70 | E70: ='Difference Engine'!C70 | F70: =IF(OR(D70="",E70=""),"WAIT",IF(AND(ISNUMBER(D70),ISNUMBER(E70)),IF(ABS(E70-D70)>0.005,"YES","NO"),IF(D70=E70,"NO","YES"))) | G70: =IF(AND(ISNUMBER('Difference Engine'!E70),ABS('Difference Engine'!E70)>0.005),"YES","NO") | H70: =IF(OR(F70="WAIT",D70=""),"WAIT",IF(F70=G70,"PASS","FAIL"))
A71: B55 | B71: Analysis Engine | C71: =IFERROR(FORMULATEXT('[FinanceOS_v1.0-QA-RC1.xlsx]Analysis Engine'!B55),"(value/no formula)") | D71: ='Difference Engine'!B71 | E71: ='Difference Engine'!C71 | F71: =IF(OR(D71="",E71=""),"WAIT",IF(AND(ISNUMBER(D71),ISNUMBER(E71)),IF(ABS(E71-D71)>0.005,"YES","NO"),IF(D71=E71,"NO","YES"))) | G71: =IF(AND(ISNUMBER('Difference Engine'!E71),ABS('Difference Engine'!E71)>0.005),"YES","NO") | H71: =IF(OR(F71="WAIT",D71=""),"WAIT",IF(F71=G71,"PASS","FAIL"))
A72: B56 | B72: Analysis Engine | C72: =IFERROR(FORMULATEXT('[FinanceOS_v1.0-QA-RC1.xlsx]Analysis Engine'!B56),"(value/no formula)") | D72: ='Difference Engine'!B72 | E72: ='Difference Engine'!C72 | F72: =IF(OR(D72="",E72=""),"WAIT",IF(AND(ISNUMBER(D72),ISNUMBER(E72)),IF(ABS(E72-D72)>0.005,"YES","NO"),IF(D72=E72,"NO","YES"))) | G72: =IF(AND(ISNUMBER('Difference Engine'!E72),ABS('Difference Engine'!E72)>0.005),"YES","NO") | H72: =IF(OR(F72="WAIT",D72=""),"WAIT",IF(F72=G72,"PASS","FAIL"))
A73: B57 | B73: Analysis Engine | C73: =IFERROR(FORMULATEXT('[FinanceOS_v1.0-QA-RC1.xlsx]Analysis Engine'!B57),"(value/no formula)") | D73: ='Difference Engine'!B73 | E73: ='Difference Engine'!C73 | F73: =IF(OR(D73="",E73=""),"WAIT",IF(AND(ISNUMBER(D73),ISNUMBER(E73)),IF(ABS(E73-D73)>0.005,"YES","NO"),IF(D73=E73,"NO","YES"))) | G73: =IF(AND(ISNUMBER('Difference Engine'!E73),ABS('Difference Engine'!E73)>0.005),"YES","NO") | H73: =IF(OR(F73="WAIT",D73=""),"WAIT",IF(F73=G73,"PASS","FAIL"))
A74: B58 | B74: Analysis Engine | C74: =IFERROR(FORMULATEXT('[FinanceOS_v1.0-QA-RC1.xlsx]Analysis Engine'!B58),"(value/no formula)") | D74: ='Difference Engine'!B74 | E74: ='Difference Engine'!C74 | F74: =IF(OR(D74="",E74=""),"WAIT",IF(AND(ISNUMBER(D74),ISNUMBER(E74)),IF(ABS(E74-D74)>0.005,"YES","NO"),IF(D74=E74,"NO","YES"))) | G74: =IF(AND(ISNUMBER('Difference Engine'!E74),ABS('Difference Engine'!E74)>0.005),"YES","NO") | H74: =IF(OR(F74="WAIT",D74=""),"WAIT",IF(F74=G74,"PASS","FAIL"))
A75: B74 | B75: Analysis Engine | C75: =IFERROR(FORMULATEXT('[FinanceOS_v1.0-QA-RC1.xlsx]Analysis Engine'!B74),"(value/no formula)") | D75: ='Difference Engine'!B75 | E75: ='Difference Engine'!C75 | F75: =IF(OR(D75="",E75=""),"WAIT",IF(AND(ISNUMBER(D75),ISNUMBER(E75)),IF(ABS(E75-D75)>0.005,"YES","NO"),IF(D75=E75,"NO","YES"))) | G75: =IF(AND(ISNUMBER('Difference Engine'!E75),ABS('Difference Engine'!E75)>0.005),"YES","NO") | H75: =IF(OR(F75="WAIT",D75=""),"WAIT",IF(F75=G75,"PASS","FAIL"))
A76: B75 | B76: Analysis Engine | C76: =IFERROR(FORMULATEXT('[FinanceOS_v1.0-QA-RC1.xlsx]Analysis Engine'!B75),"(value/no formula)") | D76: ='Difference Engine'!B76 | E76: ='Difference Engine'!C76 | F76: =IF(OR(D76="",E76=""),"WAIT",IF(AND(ISNUMBER(D76),ISNUMBER(E76)),IF(ABS(E76-D76)>0.005,"YES","NO"),IF(D76=E76,"NO","YES"))) | G76: =IF(AND(ISNUMBER('Difference Engine'!E76),ABS('Difference Engine'!E76)>0.005),"YES","NO") | H76: =IF(OR(F76="WAIT",D76=""),"WAIT",IF(F76=G76,"PASS","FAIL"))
A77: B76 | B77: Analysis Engine | C77: =IFERROR(FORMULATEXT('[FinanceOS_v1.0-QA-RC1.xlsx]Analysis Engine'!B76),"(value/no formula)") | D77: ='Difference Engine'!B77 | E77: ='Difference Engine'!C77 | F77: =IF(OR(D77="",E77=""),"WAIT",IF(AND(ISNUMBER(D77),ISNUMBER(E77)),IF(ABS(E77-D77)>0.005,"YES","NO"),IF(D77=E77,"NO","YES"))) | G77: =IF(AND(ISNUMBER('Difference Engine'!E77),ABS('Difference Engine'!E77)>0.005),"YES","NO") | H77: =IF(OR(F77="WAIT",D77=""),"WAIT",IF(F77=G77,"PASS","FAIL"))
A78: B77 | B78: Analysis Engine | C78: =IFERROR(FORMULATEXT('[FinanceOS_v1.0-QA-RC1.xlsx]Analysis Engine'!B77),"(value/no formula)") | D78: ='Difference Engine'!B78 | E78: ='Difference Engine'!C78 | F78: =IF(OR(D78="",E78=""),"WAIT",IF(AND(ISNUMBER(D78),ISNUMBER(E78)),IF(ABS(E78-D78)>0.005,"YES","NO"),IF(D78=E78,"NO","YES"))) | G78: =IF(AND(ISNUMBER('Difference Engine'!E78),ABS('Difference Engine'!E78)>0.005),"YES","NO") | H78: =IF(OR(F78="WAIT",D78=""),"WAIT",IF(F78=G78,"PASS","FAIL"))
A79: B79 | B79: Analysis Engine | C79: =IFERROR(FORMULATEXT('[FinanceOS_v1.0-QA-RC1.xlsx]Analysis Engine'!B79),"(value/no formula)") | D79: ='Difference Engine'!B79 | E79: ='Difference Engine'!C79 | F79: =IF(OR(D79="",E79=""),"WAIT",IF(AND(ISNUMBER(D79),ISNUMBER(E79)),IF(ABS(E79-D79)>0.005,"YES","NO"),IF(D79=E79,"NO","YES"))) | G79: =IF(AND(ISNUMBER('Difference Engine'!E79),ABS('Difference Engine'!E79)>0.005),"YES","NO") | H79: =IF(OR(F79="WAIT",D79=""),"WAIT",IF(F79=G79,"PASS","FAIL"))
A80: B80 | B80: Analysis Engine | C80: =IFERROR(FORMULATEXT('[FinanceOS_v1.0-QA-RC1.xlsx]Analysis Engine'!B80),"(value/no formula)") | D80: ='Difference Engine'!B80 | E80: ='Difference Engine'!C80 | F80: =IF(OR(D80="",E80=""),"WAIT",IF(AND(ISNUMBER(D80),ISNUMBER(E80)),IF(ABS(E80-D80)>0.005,"YES","NO"),IF(D80=E80,"NO","YES"))) | G80: =IF(AND(ISNUMBER('Difference Engine'!E80),ABS('Difference Engine'!E80)>0.005),"YES","NO") | H80: =IF(OR(F80="WAIT",D80=""),"WAIT",IF(F80=G80,"PASS","FAIL"))
A81: B81 | B81: Analysis Engine | C81: =IFERROR(FORMULATEXT('[FinanceOS_v1.0-QA-RC1.xlsx]Analysis Engine'!B81),"(value/no formula)") | D81: ='Difference Engine'!B81 | E81: ='Difference Engine'!C81 | F81: =IF(OR(D81="",E81=""),"WAIT",IF(AND(ISNUMBER(D81),ISNUMBER(E81)),IF(ABS(E81-D81)>0.005,"YES","NO"),IF(D81=E81,"NO","YES"))) | G81: =IF(AND(ISNUMBER('Difference Engine'!E81),ABS('Difference Engine'!E81)>0.005),"YES","NO") | H81: =IF(OR(F81="WAIT",D81=""),"WAIT",IF(F81=G81,"PASS","FAIL"))
A82: B107 | B82: Analysis Engine | C82: =IFERROR(FORMULATEXT('[FinanceOS_v1.0-QA-RC1.xlsx]Analysis Engine'!B107),"(value/no formula)") | D82: ='Difference Engine'!B82 | E82: ='Difference Engine'!C82 | F82: =IF(OR(D82="",E82=""),"WAIT",IF(AND(ISNUMBER(D82),ISNUMBER(E82)),IF(ABS(E82-D82)>0.005,"YES","NO"),IF(D82=E82,"NO","YES"))) | G82: =IF(AND(ISNUMBER('Difference Engine'!E82),ABS('Difference Engine'!E82)>0.005),"YES","NO") | H82: =IF(OR(F82="WAIT",D82=""),"WAIT",IF(F82=G82,"PASS","FAIL"))
A83: B108 | B83: Analysis Engine | C83: =IFERROR(FORMULATEXT('[FinanceOS_v1.0-QA-RC1.xlsx]Analysis Engine'!B108),"(value/no formula)") | D83: ='Difference Engine'!B83 | E83: ='Difference Engine'!C83 | F83: =IF(OR(D83="",E83=""),"WAIT",IF(AND(ISNUMBER(D83),ISNUMBER(E83)),IF(ABS(E83-D83)>0.005,"YES","NO"),IF(D83=E83,"NO","YES"))) | G83: =IF(AND(ISNUMBER('Difference Engine'!E83),ABS('Difference Engine'!E83)>0.005),"YES","NO") | H83: =IF(OR(F83="WAIT",D83=""),"WAIT",IF(F83=G83,"PASS","FAIL"))
A84: B109 | B84: Analysis Engine | C84: =IFERROR(FORMULATEXT('[FinanceOS_v1.0-QA-RC1.xlsx]Analysis Engine'!B109),"(value/no formula)") | D84: ='Difference Engine'!B84 | E84: ='Difference Engine'!C84 | F84: =IF(OR(D84="",E84=""),"WAIT",IF(AND(ISNUMBER(D84),ISNUMBER(E84)),IF(ABS(E84-D84)>0.005,"YES","NO"),IF(D84=E84,"NO","YES"))) | G84: =IF(AND(ISNUMBER('Difference Engine'!E84),ABS('Difference Engine'!E84)>0.005),"YES","NO") | H84: =IF(OR(F84="WAIT",D84=""),"WAIT",IF(F84=G84,"PASS","FAIL"))
A85: B30 | B85: Analysis Engine | C85: =IFERROR(FORMULATEXT('[FinanceOS_v1.0-QA-RC1.xlsx]Analysis Engine'!B30),"(value/no formula)") | D85: ='Difference Engine'!B85 | E85: ='Difference Engine'!C85 | F85: =IF(OR(D85="",E85=""),"WAIT",IF(AND(ISNUMBER(D85),ISNUMBER(E85)),IF(ABS(E85-D85)>0.005,"YES","NO"),IF(D85=E85,"NO","YES"))) | G85: =IF(AND(ISNUMBER('Difference Engine'!E85),ABS('Difference Engine'!E85)>0.005),"YES","NO") | H85: =IF(OR(F85="WAIT",D85=""),"WAIT",IF(F85=G85,"PASS","FAIL"))
A86: B37 | B86: Analysis Engine | C86: =IFERROR(FORMULATEXT('[FinanceOS_v1.0-QA-RC1.xlsx]Analysis Engine'!B37),"(value/no formula)") | D86: ='Difference Engine'!B86 | E86: ='Difference Engine'!C86 | F86: =IF(OR(D86="",E86=""),"WAIT",IF(AND(ISNUMBER(D86),ISNUMBER(E86)),IF(ABS(E86-D86)>0.005,"YES","NO"),IF(D86=E86,"NO","YES"))) | G86: =IF(AND(ISNUMBER('Difference Engine'!E86),ABS('Difference Engine'!E86)>0.005),"YES","NO") | H86: =IF(OR(F86="WAIT",D86=""),"WAIT",IF(F86=G86,"PASS","FAIL"))
A87: B38 | B87: Analysis Engine | C87: =IFERROR(FORMULATEXT('[FinanceOS_v1.0-QA-RC1.xlsx]Analysis Engine'!B38),"(value/no formula)") | D87: ='Difference Engine'!B87 | E87: ='Difference Engine'!C87 | F87: =IF(OR(D87="",E87=""),"WAIT",IF(AND(ISNUMBER(D87),ISNUMBER(E87)),IF(ABS(E87-D87)>0.005,"YES","NO"),IF(D87=E87,"NO","YES"))) | G87: =IF(AND(ISNUMBER('Difference Engine'!E87),ABS('Difference Engine'!E87)>0.005),"YES","NO") | H87: =IF(OR(F87="WAIT",D87=""),"WAIT",IF(F87=G87,"PASS","FAIL"))
A88: C37 | B88: Analysis Engine | C88: =IFERROR(FORMULATEXT('[FinanceOS_v1.0-QA-RC1.xlsx]Analysis Engine'!C37),"(value/no formula)") | D88: ='Difference Engine'!B88 | E88: ='Difference Engine'!C88 | F88: =IF(OR(D88="",E88=""),"WAIT",IF(AND(ISNUMBER(D88),ISNUMBER(E88)),IF(ABS(E88-D88)>0.005,"YES","NO"),IF(D88=E88,"NO","YES"))) | G88: =IF(AND(ISNUMBER('Difference Engine'!E88),ABS('Difference Engine'!E88)>0.005),"YES","NO") | H88: =IF(OR(F88="WAIT",D88=""),"WAIT",IF(F88=G88,"PASS","FAIL"))
A89: C38 | B89: Analysis Engine | C89: =IFERROR(FORMULATEXT('[FinanceOS_v1.0-QA-RC1.xlsx]Analysis Engine'!C38),"(value/no formula)") | D89: ='Difference Engine'!B89 | E89: ='Difference Engine'!C89 | F89: =IF(OR(D89="",E89=""),"WAIT",IF(AND(ISNUMBER(D89),ISNUMBER(E89)),IF(ABS(E89-D89)>0.005,"YES","NO"),IF(D89=E89,"NO","YES"))) | G89: =IF(AND(ISNUMBER('Difference Engine'!E89),ABS('Difference Engine'!E89)>0.005),"YES","NO") | H89: =IF(OR(F89="WAIT",D89=""),"WAIT",IF(F89=G89,"PASS","FAIL"))
A90: D38 | B90: Analysis Engine | C90: =IFERROR(FORMULATEXT('[FinanceOS_v1.0-QA-RC1.xlsx]Analysis Engine'!D38),"(value/no formula)") | D90: ='Difference Engine'!B90 | E90: ='Difference Engine'!C90 | F90: =IF(OR(D90="",E90=""),"WAIT",IF(AND(ISNUMBER(D90),ISNUMBER(E90)),IF(ABS(E90-D90)>0.005,"YES","NO"),IF(D90=E90,"NO","YES"))) | G90: =IF(AND(ISNUMBER('Difference Engine'!E90),ABS('Difference Engine'!E90)>0.005),"YES","NO") | H90: =IF(OR(F90="WAIT",D90=""),"WAIT",IF(F90=G90,"PASS","FAIL"))
A91: B17 | B91: Analysis Engine | C91: =IFERROR(FORMULATEXT('[FinanceOS_v1.0-QA-RC1.xlsx]Analysis Engine'!B17),"(value/no formula)") | D91: ='Difference Engine'!B91 | E91: ='Difference Engine'!C91 | F91: =IF(OR(D91="",E91=""),"WAIT",IF(AND(ISNUMBER(D91),ISNUMBER(E91)),IF(ABS(E91-D91)>0.005,"YES","NO"),IF(D91=E91,"NO","YES"))) | G91: =IF(AND(ISNUMBER('Difference Engine'!E91),ABS('Difference Engine'!E91)>0.005),"YES","NO") | H91: =IF(OR(F91="WAIT",D91=""),"WAIT",IF(F91=G91,"PASS","FAIL"))
A92: B18 | B92: Analysis Engine | C92: =IFERROR(FORMULATEXT('[FinanceOS_v1.0-QA-RC1.xlsx]Analysis Engine'!B18),"(value/no formula)") | D92: ='Difference Engine'!B92 | E92: ='Difference Engine'!C92 | F92: =IF(OR(D92="",E92=""),"WAIT",IF(AND(ISNUMBER(D92),ISNUMBER(E92)),IF(ABS(E92-D92)>0.005,"YES","NO"),IF(D92=E92,"NO","YES"))) | G92: =IF(AND(ISNUMBER('Difference Engine'!E92),ABS('Difference Engine'!E92)>0.005),"YES","NO") | H92: =IF(OR(F92="WAIT",D92=""),"WAIT",IF(F92=G92,"PASS","FAIL"))
A93: B19 | B93: Analysis Engine | C93: =IFERROR(FORMULATEXT('[FinanceOS_v1.0-QA-RC1.xlsx]Analysis Engine'!B19),"(value/no formula)") | D93: ='Difference Engine'!B93 | E93: ='Difference Engine'!C93 | F93: =IF(OR(D93="",E93=""),"WAIT",IF(AND(ISNUMBER(D93),ISNUMBER(E93)),IF(ABS(E93-D93)>0.005,"YES","NO"),IF(D93=E93,"NO","YES"))) | G93: =IF(AND(ISNUMBER('Difference Engine'!E93),ABS('Difference Engine'!E93)>0.005),"YES","NO") | H93: =IF(OR(F93="WAIT",D93=""),"WAIT",IF(F93=G93,"PASS","FAIL"))
A94: D7 | B94: Analysis Engine | C94: =IFERROR(FORMULATEXT('[FinanceOS_v1.0-QA-RC1.xlsx]Analysis Engine'!D7),"(value/no formula)") | D94: ='Difference Engine'!B94 | E94: ='Difference Engine'!C94 | F94: =IF(OR(D94="",E94=""),"WAIT",IF(AND(ISNUMBER(D94),ISNUMBER(E94)),IF(ABS(E94-D94)>0.005,"YES","NO"),IF(D94=E94,"NO","YES"))) | G94: =IF(AND(ISNUMBER('Difference Engine'!E94),ABS('Difference Engine'!E94)>0.005),"YES","NO") | H94: =IF(OR(F94="WAIT",D94=""),"WAIT",IF(F94=G94,"PASS","FAIL"))
A95: D9 | B95: Analysis Engine | C95: =IFERROR(FORMULATEXT('[FinanceOS_v1.0-QA-RC1.xlsx]Analysis Engine'!D9),"(value/no formula)") | D95: ='Difference Engine'!B95 | E95: ='Difference Engine'!C95 | F95: =IF(OR(D95="",E95=""),"WAIT",IF(AND(ISNUMBER(D95),ISNUMBER(E95)),IF(ABS(E95-D95)>0.005,"YES","NO"),IF(D95=E95,"NO","YES"))) | G95: =IF(AND(ISNUMBER('Difference Engine'!E95),ABS('Difference Engine'!E95)>0.005),"YES","NO") | H95: =IF(OR(F95="WAIT",D95=""),"WAIT",IF(F95=G95,"PASS","FAIL"))
A96: B50 | B96: Analysis Engine | C96: =IFERROR(FORMULATEXT('[FinanceOS_v1.0-QA-RC1.xlsx]Analysis Engine'!B50),"(value/no formula)") | D96: ='Difference Engine'!B96 | E96: ='Difference Engine'!C96 | F96: =IF(OR(D96="",E96=""),"WAIT",IF(AND(ISNUMBER(D96),ISNUMBER(E96)),IF(ABS(E96-D96)>0.005,"YES","NO"),IF(D96=E96,"NO","YES"))) | G96: =IF(AND(ISNUMBER('Difference Engine'!E96),ABS('Difference Engine'!E96)>0.005),"YES","NO") | H96: =IF(OR(F96="WAIT",D96=""),"WAIT",IF(F96=G96,"PASS","FAIL"))

Sheet Coverage Matrix
A1: Business Engine Section | B1: Formula Range | C1: Cells | D1: Tested By Scenario IDs | E1: Coverage Status
A2: Accounts Summary | B2: B4:B9 | C2: 6 | D2: SCN-BASE, SCN-C, SCN-I, SCN-N, SCN-O | E2: BASELINE ONLY
A3: Account Engine H2/I2 | B3: not in RC1 freeze | C3: 0 | D3: SCN-K, SCN-L, SCN-M — no LAST cell on engine-foundation RC1 | E3: N/A — RC1
A4: Income Summary | B4: B12:B19 | C4: 8 | D4: SCN-BASE, SCN-A, SCN-F, SCN-P | E4: STRESSED
A5: Expense Summary | B5: B22:B25 | C5: 4 | D5: SCN-BASE, SCN-B, SCN-D, SCN-E, SCN-G, SCN-H, SCN-J (B23 must NOT change) | E5: STRESSED
A6: Savings Summary | B6: B28:B31 | C6: 4 | D6: SCN-BASE, SCN-A, SCN-B | E6: STRESSED
A7: Asset Summary | B7: B34:B38 | C7: 5 | D7: SCN-BASE, SCN-J (value table not auto) | E7: BASELINE ONLY
A8: Liability Summary | B8: B41:B45 | C8: 5 | D8: SCN-BASE | E8: BASELINE ONLY
A9: Net Worth | B9: B48:B50 | C9: 3 | D9: SCN-BASE, SCN-A, SCN-B | E9: STRESSED
A10: Goal Summary | B10: B53:B58 | C10: 6 | D10: SCN-BASE, SCN-G (saved amount not auto) | E10: BASELINE ONLY
A11: Financial Health | B11: B61:B68 | C11: 8 | D11: SCN-BASE, SCN-A, SCN-B | E11: STRESSED
A12: As-Of Date | B12: B1 | C12: 1 | D12: SCN-BASE | E12: STRESSED
A13: Analysis Engine | B13: B2:B109 | C13: 45 | D13: Follows Business Engine via links | E13: STRESSED

Sheet Compatibility Gate
A1: Compatibility Gate
A3: Platform | B3: Check | C3: Result
A4: Desktop | B4: Excel Desktop opens | C4: WAIT
A5: Excel Web | B5: Excel Web opens | C5: WAIT
A6: Mobile | B6: Excel Mobile opens | C6: WAIT
A7: Excel Web | B7: No compatibility popup | C7: WAIT
A8: Excel Web | B8: Business Engine visible | C8: WAIT
A9: Excel Web | B9: Analysis Engine visible | C9: WAIT
A10: Excel Web | B10: Workbook links working | C10: WAIT
A11: Excel Web | B11: All scenarios passed | C11: WAIT
A13: Overall Compatibility | B13: =IF(COUNTIF(C4:C11,"FAIL")>0,"FAIL",IF(COUNTIF(C4:C11,"PASS")=8,"PASS","WAIT"))

Sheet Formula Inventory
A1: Formula Inventory — QA-RC1 FORMULATEXT
A3: Cell | B3: FORMULATEXT | C3: Contains MAXIFS? | D3: Family flags | F3: Family | G3: Count
A4: B4 | B4: =IFERROR(FORMULATEXT('[FinanceOS_v1.0-QA-RC1.xlsx]Business Engine'!B4),"") | C4: =IF(ISNUMBER(SEARCH("MAXIFS",B4)),"YES","NO") | D4: =IF(ISNUMBER(SEARCH("AGGREGATE",B4)),"AGGREGATE ","")&IF(ISNUMBER(SEARCH("LOOKUP",B4)),"LOOKUP ","")&IF(ISNUMBER(SEARCH("FILTER",B4)),"FILTER ","") | F4: IF | G4: =COUNTIF(B:B,"*IF(*")
A5: B5 | B5: =IFERROR(FORMULATEXT('[FinanceOS_v1.0-QA-RC1.xlsx]Business Engine'!B5),"") | C5: =IF(ISNUMBER(SEARCH("MAXIFS",B5)),"YES","NO") | D5: =IF(ISNUMBER(SEARCH("AGGREGATE",B5)),"AGGREGATE ","")&IF(ISNUMBER(SEARCH("LOOKUP",B5)),"LOOKUP ","")&IF(ISNUMBER(SEARCH("FILTER",B5)),"FILTER ","") | F5: IFERROR | G5: =COUNTIF(B:B,"*IFERROR(*")
A6: B6 | B6: =IFERROR(FORMULATEXT('[FinanceOS_v1.0-QA-RC1.xlsx]Business Engine'!B6),"") | C6: =IF(ISNUMBER(SEARCH("MAXIFS",B6)),"YES","NO") | D6: =IF(ISNUMBER(SEARCH("AGGREGATE",B6)),"AGGREGATE ","")&IF(ISNUMBER(SEARCH("LOOKUP",B6)),"LOOKUP ","")&IF(ISNUMBER(SEARCH("FILTER",B6)),"FILTER ","") | F6: SUMIFS | G6: =COUNTIF(B:B,"*SUMIFS(*")
A7: B7 | B7: =IFERROR(FORMULATEXT('[FinanceOS_v1.0-QA-RC1.xlsx]Business Engine'!B7),"") | C7: =IF(ISNUMBER(SEARCH("MAXIFS",B7)),"YES","NO") | D7: =IF(ISNUMBER(SEARCH("AGGREGATE",B7)),"AGGREGATE ","")&IF(ISNUMBER(SEARCH("LOOKUP",B7)),"LOOKUP ","")&IF(ISNUMBER(SEARCH("FILTER",B7)),"FILTER ","") | F7: COUNTIFS | G7: =COUNTIF(B:B,"*COUNTIFS(*")
A8: B8 | B8: =IFERROR(FORMULATEXT('[FinanceOS_v1.0-QA-RC1.xlsx]Business Engine'!B8),"") | C8: =IF(ISNUMBER(SEARCH("MAXIFS",B8)),"YES","NO") | D8: =IF(ISNUMBER(SEARCH("AGGREGATE",B8)),"AGGREGATE ","")&IF(ISNUMBER(SEARCH("LOOKUP",B8)),"LOOKUP ","")&IF(ISNUMBER(SEARCH("FILTER",B8)),"FILTER ","") | F8: INDEX | G8: =COUNTIF(B:B,"*INDEX(*")
A9: B9 | B9: =IFERROR(FORMULATEXT('[FinanceOS_v1.0-QA-RC1.xlsx]Business Engine'!B9),"") | C9: =IF(ISNUMBER(SEARCH("MAXIFS",B9)),"YES","NO") | D9: =IF(ISNUMBER(SEARCH("AGGREGATE",B9)),"AGGREGATE ","")&IF(ISNUMBER(SEARCH("LOOKUP",B9)),"LOOKUP ","")&IF(ISNUMBER(SEARCH("FILTER",B9)),"FILTER ","") | F9: MATCH | G9: =COUNTIF(B:B,"*MATCH(*")
A10: B12 | B10: =IFERROR(FORMULATEXT('[FinanceOS_v1.0-QA-RC1.xlsx]Business Engine'!B12),"") | C10: =IF(ISNUMBER(SEARCH("MAXIFS",B10)),"YES","NO") | D10: =IF(ISNUMBER(SEARCH("AGGREGATE",B10)),"AGGREGATE ","")&IF(ISNUMBER(SEARCH("LOOKUP",B10)),"LOOKUP ","")&IF(ISNUMBER(SEARCH("FILTER",B10)),"FILTER ","") | F10: MAX | G10: =COUNTIF(B:B,"*MAX(*")
A11: B13 | B11: =IFERROR(FORMULATEXT('[FinanceOS_v1.0-QA-RC1.xlsx]Business Engine'!B13),"") | C11: =IF(ISNUMBER(SEARCH("MAXIFS",B11)),"YES","NO") | D11: =IF(ISNUMBER(SEARCH("AGGREGATE",B11)),"AGGREGATE ","")&IF(ISNUMBER(SEARCH("LOOKUP",B11)),"LOOKUP ","")&IF(ISNUMBER(SEARCH("FILTER",B11)),"FILTER ","") | F11: LOOKUP | G11: =COUNTIF(B:B,"*LOOKUP(*")
A12: B14 | B12: =IFERROR(FORMULATEXT('[FinanceOS_v1.0-QA-RC1.xlsx]Business Engine'!B14),"") | C12: =IF(ISNUMBER(SEARCH("MAXIFS",B12)),"YES","NO") | D12: =IF(ISNUMBER(SEARCH("AGGREGATE",B12)),"AGGREGATE ","")&IF(ISNUMBER(SEARCH("LOOKUP",B12)),"LOOKUP ","")&IF(ISNUMBER(SEARCH("FILTER",B12)),"FILTER ","") | F12: AGGREGATE | G12: =COUNTIF(B:B,"*AGGREGATE(*")
A13: B15 | B13: =IFERROR(FORMULATEXT('[FinanceOS_v1.0-QA-RC1.xlsx]Business Engine'!B15),"") | C13: =IF(ISNUMBER(SEARCH("MAXIFS",B13)),"YES","NO") | D13: =IF(ISNUMBER(SEARCH("AGGREGATE",B13)),"AGGREGATE ","")&IF(ISNUMBER(SEARCH("LOOKUP",B13)),"LOOKUP ","")&IF(ISNUMBER(SEARCH("FILTER",B13)),"FILTER ","") | F13: MAXIFS | G13: =COUNTIF(B:B,"*MAXIFS(*")
A14: B16 | B14: =IFERROR(FORMULATEXT('[FinanceOS_v1.0-QA-RC1.xlsx]Business Engine'!B16),"") | C14: =IF(ISNUMBER(SEARCH("MAXIFS",B14)),"YES","NO") | D14: =IF(ISNUMBER(SEARCH("AGGREGATE",B14)),"AGGREGATE ","")&IF(ISNUMBER(SEARCH("LOOKUP",B14)),"LOOKUP ","")&IF(ISNUMBER(SEARCH("FILTER",B14)),"FILTER ","") | F14: SUMPRODUCT | G14: =COUNTIF(B:B,"*SUMPRODUCT(*")
A15: B17 | B15: =IFERROR(FORMULATEXT('[FinanceOS_v1.0-QA-RC1.xlsx]Business Engine'!B17),"") | C15: =IF(ISNUMBER(SEARCH("MAXIFS",B15)),"YES","NO") | D15: =IF(ISNUMBER(SEARCH("AGGREGATE",B15)),"AGGREGATE ","")&IF(ISNUMBER(SEARCH("LOOKUP",B15)),"LOOKUP ","")&IF(ISNUMBER(SEARCH("FILTER",B15)),"FILTER ","")
A16: B18 | B16: =IFERROR(FORMULATEXT('[FinanceOS_v1.0-QA-RC1.xlsx]Business Engine'!B18),"") | C16: =IF(ISNUMBER(SEARCH("MAXIFS",B16)),"YES","NO") | D16: =IF(ISNUMBER(SEARCH("AGGREGATE",B16)),"AGGREGATE ","")&IF(ISNUMBER(SEARCH("LOOKUP",B16)),"LOOKUP ","")&IF(ISNUMBER(SEARCH("FILTER",B16)),"FILTER ","") | F16: MAXIFS GATE | G16: =IF(COUNTIF(C4:C53,"YES")>0,"MAXIFS PRESENT","OK — no MAXIFS")
A17: B19 | B17: =IFERROR(FORMULATEXT('[FinanceOS_v1.0-QA-RC1.xlsx]Business Engine'!B19),"") | C17: =IF(ISNUMBER(SEARCH("MAXIFS",B17)),"YES","NO") | D17: =IF(ISNUMBER(SEARCH("AGGREGATE",B17)),"AGGREGATE ","")&IF(ISNUMBER(SEARCH("LOOKUP",B17)),"LOOKUP ","")&IF(ISNUMBER(SEARCH("FILTER",B17)),"FILTER ","")
A18: B22 | B18: =IFERROR(FORMULATEXT('[FinanceOS_v1.0-QA-RC1.xlsx]Business Engine'!B22),"") | C18: =IF(ISNUMBER(SEARCH("MAXIFS",B18)),"YES","NO") | D18: =IF(ISNUMBER(SEARCH("AGGREGATE",B18)),"AGGREGATE ","")&IF(ISNUMBER(SEARCH("LOOKUP",B18)),"LOOKUP ","")&IF(ISNUMBER(SEARCH("FILTER",B18)),"FILTER ","")
A19: B23 | B19: =IFERROR(FORMULATEXT('[FinanceOS_v1.0-QA-RC1.xlsx]Business Engine'!B23),"") | C19: =IF(ISNUMBER(SEARCH("MAXIFS",B19)),"YES","NO") | D19: =IF(ISNUMBER(SEARCH("AGGREGATE",B19)),"AGGREGATE ","")&IF(ISNUMBER(SEARCH("LOOKUP",B19)),"LOOKUP ","")&IF(ISNUMBER(SEARCH("FILTER",B19)),"FILTER ","")
A20: B24 | B20: =IFERROR(FORMULATEXT('[FinanceOS_v1.0-QA-RC1.xlsx]Business Engine'!B24),"") | C20: =IF(ISNUMBER(SEARCH("MAXIFS",B20)),"YES","NO") | D20: =IF(ISNUMBER(SEARCH("AGGREGATE",B20)),"AGGREGATE ","")&IF(ISNUMBER(SEARCH("LOOKUP",B20)),"LOOKUP ","")&IF(ISNUMBER(SEARCH("FILTER",B20)),"FILTER ","")
A21: B25 | B21: =IFERROR(FORMULATEXT('[FinanceOS_v1.0-QA-RC1.xlsx]Business Engine'!B25),"") | C21: =IF(ISNUMBER(SEARCH("MAXIFS",B21)),"YES","NO") | D21: =IF(ISNUMBER(SEARCH("AGGREGATE",B21)),"AGGREGATE ","")&IF(ISNUMBER(SEARCH("LOOKUP",B21)),"LOOKUP ","")&IF(ISNUMBER(SEARCH("FILTER",B21)),"FILTER ","")
A22: B28 | B22: =IFERROR(FORMULATEXT('[FinanceOS_v1.0-QA-RC1.xlsx]Business Engine'!B28),"") | C22: =IF(ISNUMBER(SEARCH("MAXIFS",B22)),"YES","NO") | D22: =IF(ISNUMBER(SEARCH("AGGREGATE",B22)),"AGGREGATE ","")&IF(ISNUMBER(SEARCH("LOOKUP",B22)),"LOOKUP ","")&IF(ISNUMBER(SEARCH("FILTER",B22)),"FILTER ","")
A23: B29 | B23: =IFERROR(FORMULATEXT('[FinanceOS_v1.0-QA-RC1.xlsx]Business Engine'!B29),"") | C23: =IF(ISNUMBER(SEARCH("MAXIFS",B23)),"YES","NO") | D23: =IF(ISNUMBER(SEARCH("AGGREGATE",B23)),"AGGREGATE ","")&IF(ISNUMBER(SEARCH("LOOKUP",B23)),"LOOKUP ","")&IF(ISNUMBER(SEARCH("FILTER",B23)),"FILTER ","")
A24: B30 | B24: =IFERROR(FORMULATEXT('[FinanceOS_v1.0-QA-RC1.xlsx]Business Engine'!B30),"") | C24: =IF(ISNUMBER(SEARCH("MAXIFS",B24)),"YES","NO") | D24: =IF(ISNUMBER(SEARCH("AGGREGATE",B24)),"AGGREGATE ","")&IF(ISNUMBER(SEARCH("LOOKUP",B24)),"LOOKUP ","")&IF(ISNUMBER(SEARCH("FILTER",B24)),"FILTER ","")
A25: B31 | B25: =IFERROR(FORMULATEXT('[FinanceOS_v1.0-QA-RC1.xlsx]Business Engine'!B31),"") | C25: =IF(ISNUMBER(SEARCH("MAXIFS",B25)),"YES","NO") | D25: =IF(ISNUMBER(SEARCH("AGGREGATE",B25)),"AGGREGATE ","")&IF(ISNUMBER(SEARCH("LOOKUP",B25)),"LOOKUP ","")&IF(ISNUMBER(SEARCH("FILTER",B25)),"FILTER ","")
A26: B34 | B26: =IFERROR(FORMULATEXT('[FinanceOS_v1.0-QA-RC1.xlsx]Business Engine'!B34),"") | C26: =IF(ISNUMBER(SEARCH("MAXIFS",B26)),"YES","NO") | D26: =IF(ISNUMBER(SEARCH("AGGREGATE",B26)),"AGGREGATE ","")&IF(ISNUMBER(SEARCH("LOOKUP",B26)),"LOOKUP ","")&IF(ISNUMBER(SEARCH("FILTER",B26)),"FILTER ","")
A27: B35 | B27: =IFERROR(FORMULATEXT('[FinanceOS_v1.0-QA-RC1.xlsx]Business Engine'!B35),"") | C27: =IF(ISNUMBER(SEARCH("MAXIFS",B27)),"YES","NO") | D27: =IF(ISNUMBER(SEARCH("AGGREGATE",B27)),"AGGREGATE ","")&IF(ISNUMBER(SEARCH("LOOKUP",B27)),"LOOKUP ","")&IF(ISNUMBER(SEARCH("FILTER",B27)),"FILTER ","")
A28: B36 | B28: =IFERROR(FORMULATEXT('[FinanceOS_v1.0-QA-RC1.xlsx]Business Engine'!B36),"") | C28: =IF(ISNUMBER(SEARCH("MAXIFS",B28)),"YES","NO") | D28: =IF(ISNUMBER(SEARCH("AGGREGATE",B28)),"AGGREGATE ","")&IF(ISNUMBER(SEARCH("LOOKUP",B28)),"LOOKUP ","")&IF(ISNUMBER(SEARCH("FILTER",B28)),"FILTER ","")
A29: B37 | B29: =IFERROR(FORMULATEXT('[FinanceOS_v1.0-QA-RC1.xlsx]Business Engine'!B37),"") | C29: =IF(ISNUMBER(SEARCH("MAXIFS",B29)),"YES","NO") | D29: =IF(ISNUMBER(SEARCH("AGGREGATE",B29)),"AGGREGATE ","")&IF(ISNUMBER(SEARCH("LOOKUP",B29)),"LOOKUP ","")&IF(ISNUMBER(SEARCH("FILTER",B29)),"FILTER ","")
A30: B38 | B30: =IFERROR(FORMULATEXT('[FinanceOS_v1.0-QA-RC1.xlsx]Business Engine'!B38),"") | C30: =IF(ISNUMBER(SEARCH("MAXIFS",B30)),"YES","NO") | D30: =IF(ISNUMBER(SEARCH("AGGREGATE",B30)),"AGGREGATE ","")&IF(ISNUMBER(SEARCH("LOOKUP",B30)),"LOOKUP ","")&IF(ISNUMBER(SEARCH("FILTER",B30)),"FILTER ","")
A31: B41 | B31: =IFERROR(FORMULATEXT('[FinanceOS_v1.0-QA-RC1.xlsx]Business Engine'!B41),"") | C31: =IF(ISNUMBER(SEARCH("MAXIFS",B31)),"YES","NO") | D31: =IF(ISNUMBER(SEARCH("AGGREGATE",B31)),"AGGREGATE ","")&IF(ISNUMBER(SEARCH("LOOKUP",B31)),"LOOKUP ","")&IF(ISNUMBER(SEARCH("FILTER",B31)),"FILTER ","")
A32: B42 | B32: =IFERROR(FORMULATEXT('[FinanceOS_v1.0-QA-RC1.xlsx]Business Engine'!B42),"") | C32: =IF(ISNUMBER(SEARCH("MAXIFS",B32)),"YES","NO") | D32: =IF(ISNUMBER(SEARCH("AGGREGATE",B32)),"AGGREGATE ","")&IF(ISNUMBER(SEARCH("LOOKUP",B32)),"LOOKUP ","")&IF(ISNUMBER(SEARCH("FILTER",B32)),"FILTER ","")
A33: B43 | B33: =IFERROR(FORMULATEXT('[FinanceOS_v1.0-QA-RC1.xlsx]Business Engine'!B43),"") | C33: =IF(ISNUMBER(SEARCH("MAXIFS",B33)),"YES","NO") | D33: =IF(ISNUMBER(SEARCH("AGGREGATE",B33)),"AGGREGATE ","")&IF(ISNUMBER(SEARCH("LOOKUP",B33)),"LOOKUP ","")&IF(ISNUMBER(SEARCH("FILTER",B33)),"FILTER ","")
A34: B44 | B34: =IFERROR(FORMULATEXT('[FinanceOS_v1.0-QA-RC1.xlsx]Business Engine'!B44),"") | C34: =IF(ISNUMBER(SEARCH("MAXIFS",B34)),"YES","NO") | D34: =IF(ISNUMBER(SEARCH("AGGREGATE",B34)),"AGGREGATE ","")&IF(ISNUMBER(SEARCH("LOOKUP",B34)),"LOOKUP ","")&IF(ISNUMBER(SEARCH("FILTER",B34)),"FILTER ","")
A35: B45 | B35: =IFERROR(FORMULATEXT('[FinanceOS_v1.0-QA-RC1.xlsx]Business Engine'!B45),"") | C35: =IF(ISNUMBER(SEARCH("MAXIFS",B35)),"YES","NO") | D35: =IF(ISNUMBER(SEARCH("AGGREGATE",B35)),"AGGREGATE ","")&IF(ISNUMBER(SEARCH("LOOKUP",B35)),"LOOKUP ","")&IF(ISNUMBER(SEARCH("FILTER",B35)),"FILTER ","")
A36: B48 | B36: =IFERROR(FORMULATEXT('[FinanceOS_v1.0-QA-RC1.xlsx]Business Engine'!B48),"") | C36: =IF(ISNUMBER(SEARCH("MAXIFS",B36)),"YES","NO") | D36: =IF(ISNUMBER(SEARCH("AGGREGATE",B36)),"AGGREGATE ","")&IF(ISNUMBER(SEARCH("LOOKUP",B36)),"LOOKUP ","")&IF(ISNUMBER(SEARCH("FILTER",B36)),"FILTER ","")
A37: B49 | B37: =IFERROR(FORMULATEXT('[FinanceOS_v1.0-QA-RC1.xlsx]Business Engine'!B49),"") | C37: =IF(ISNUMBER(SEARCH("MAXIFS",B37)),"YES","NO") | D37: =IF(ISNUMBER(SEARCH("AGGREGATE",B37)),"AGGREGATE ","")&IF(ISNUMBER(SEARCH("LOOKUP",B37)),"LOOKUP ","")&IF(ISNUMBER(SEARCH("FILTER",B37)),"FILTER ","")
A38: B50 | B38: =IFERROR(FORMULATEXT('[FinanceOS_v1.0-QA-RC1.xlsx]Business Engine'!B50),"") | C38: =IF(ISNUMBER(SEARCH("MAXIFS",B38)),"YES","NO") | D38: =IF(ISNUMBER(SEARCH("AGGREGATE",B38)),"AGGREGATE ","")&IF(ISNUMBER(SEARCH("LOOKUP",B38)),"LOOKUP ","")&IF(ISNUMBER(SEARCH("FILTER",B38)),"FILTER ","")
A39: B53 | B39: =IFERROR(FORMULATEXT('[FinanceOS_v1.0-QA-RC1.xlsx]Business Engine'!B53),"") | C39: =IF(ISNUMBER(SEARCH("MAXIFS",B39)),"YES","NO") | D39: =IF(ISNUMBER(SEARCH("AGGREGATE",B39)),"AGGREGATE ","")&IF(ISNUMBER(SEARCH("LOOKUP",B39)),"LOOKUP ","")&IF(ISNUMBER(SEARCH("FILTER",B39)),"FILTER ","")
A40: B54 | B40: =IFERROR(FORMULATEXT('[FinanceOS_v1.0-QA-RC1.xlsx]Business Engine'!B54),"") | C40: =IF(ISNUMBER(SEARCH("MAXIFS",B40)),"YES","NO") | D40: =IF(ISNUMBER(SEARCH("AGGREGATE",B40)),"AGGREGATE ","")&IF(ISNUMBER(SEARCH("LOOKUP",B40)),"LOOKUP ","")&IF(ISNUMBER(SEARCH("FILTER",B40)),"FILTER ","")
A41: B55 | B41: =IFERROR(FORMULATEXT('[FinanceOS_v1.0-QA-RC1.xlsx]Business Engine'!B55),"") | C41: =IF(ISNUMBER(SEARCH("MAXIFS",B41)),"YES","NO") | D41: =IF(ISNUMBER(SEARCH("AGGREGATE",B41)),"AGGREGATE ","")&IF(ISNUMBER(SEARCH("LOOKUP",B41)),"LOOKUP ","")&IF(ISNUMBER(SEARCH("FILTER",B41)),"FILTER ","")
A42: B56 | B42: =IFERROR(FORMULATEXT('[FinanceOS_v1.0-QA-RC1.xlsx]Business Engine'!B56),"") | C42: =IF(ISNUMBER(SEARCH("MAXIFS",B42)),"YES","NO") | D42: =IF(ISNUMBER(SEARCH("AGGREGATE",B42)),"AGGREGATE ","")&IF(ISNUMBER(SEARCH("LOOKUP",B42)),"LOOKUP ","")&IF(ISNUMBER(SEARCH("FILTER",B42)),"FILTER ","")
A43: B57 | B43: =IFERROR(FORMULATEXT('[FinanceOS_v1.0-QA-RC1.xlsx]Business Engine'!B57),"") | C43: =IF(ISNUMBER(SEARCH("MAXIFS",B43)),"YES","NO") | D43: =IF(ISNUMBER(SEARCH("AGGREGATE",B43)),"AGGREGATE ","")&IF(ISNUMBER(SEARCH("LOOKUP",B43)),"LOOKUP ","")&IF(ISNUMBER(SEARCH("FILTER",B43)),"FILTER ","")
A44: B58 | B44: =IFERROR(FORMULATEXT('[FinanceOS_v1.0-QA-RC1.xlsx]Business Engine'!B58),"") | C44: =IF(ISNUMBER(SEARCH("MAXIFS",B44)),"YES","NO") | D44: =IF(ISNUMBER(SEARCH("AGGREGATE",B44)),"AGGREGATE ","")&IF(ISNUMBER(SEARCH("LOOKUP",B44)),"LOOKUP ","")&IF(ISNUMBER(SEARCH("FILTER",B44)),"FILTER ","")
A45: B61 | B45: =IFERROR(FORMULATEXT('[FinanceOS_v1.0-QA-RC1.xlsx]Business Engine'!B61),"") | C45: =IF(ISNUMBER(SEARCH("MAXIFS",B45)),"YES","NO") | D45: =IF(ISNUMBER(SEARCH("AGGREGATE",B45)),"AGGREGATE ","")&IF(ISNUMBER(SEARCH("LOOKUP",B45)),"LOOKUP ","")&IF(ISNUMBER(SEARCH("FILTER",B45)),"FILTER ","")
A46: B62 | B46: =IFERROR(FORMULATEXT('[FinanceOS_v1.0-QA-RC1.xlsx]Business Engine'!B62),"") | C46: =IF(ISNUMBER(SEARCH("MAXIFS",B46)),"YES","NO") | D46: =IF(ISNUMBER(SEARCH("AGGREGATE",B46)),"AGGREGATE ","")&IF(ISNUMBER(SEARCH("LOOKUP",B46)),"LOOKUP ","")&IF(ISNUMBER(SEARCH("FILTER",B46)),"FILTER ","")
A47: B63 | B47: =IFERROR(FORMULATEXT('[FinanceOS_v1.0-QA-RC1.xlsx]Business Engine'!B63),"") | C47: =IF(ISNUMBER(SEARCH("MAXIFS",B47)),"YES","NO") | D47: =IF(ISNUMBER(SEARCH("AGGREGATE",B47)),"AGGREGATE ","")&IF(ISNUMBER(SEARCH("LOOKUP",B47)),"LOOKUP ","")&IF(ISNUMBER(SEARCH("FILTER",B47)),"FILTER ","")
A48: B64 | B48: =IFERROR(FORMULATEXT('[FinanceOS_v1.0-QA-RC1.xlsx]Business Engine'!B64),"") | C48: =IF(ISNUMBER(SEARCH("MAXIFS",B48)),"YES","NO") | D48: =IF(ISNUMBER(SEARCH("AGGREGATE",B48)),"AGGREGATE ","")&IF(ISNUMBER(SEARCH("LOOKUP",B48)),"LOOKUP ","")&IF(ISNUMBER(SEARCH("FILTER",B48)),"FILTER ","")
A49: B65 | B49: =IFERROR(FORMULATEXT('[FinanceOS_v1.0-QA-RC1.xlsx]Business Engine'!B65),"") | C49: =IF(ISNUMBER(SEARCH("MAXIFS",B49)),"YES","NO") | D49: =IF(ISNUMBER(SEARCH("AGGREGATE",B49)),"AGGREGATE ","")&IF(ISNUMBER(SEARCH("LOOKUP",B49)),"LOOKUP ","")&IF(ISNUMBER(SEARCH("FILTER",B49)),"FILTER ","")
A50: B66 | B50: =IFERROR(FORMULATEXT('[FinanceOS_v1.0-QA-RC1.xlsx]Business Engine'!B66),"") | C50: =IF(ISNUMBER(SEARCH("MAXIFS",B50)),"YES","NO") | D50: =IF(ISNUMBER(SEARCH("AGGREGATE",B50)),"AGGREGATE ","")&IF(ISNUMBER(SEARCH("LOOKUP",B50)),"LOOKUP ","")&IF(ISNUMBER(SEARCH("FILTER",B50)),"FILTER ","")
A51: B67 | B51: =IFERROR(FORMULATEXT('[FinanceOS_v1.0-QA-RC1.xlsx]Business Engine'!B67),"") | C51: =IF(ISNUMBER(SEARCH("MAXIFS",B51)),"YES","NO") | D51: =IF(ISNUMBER(SEARCH("AGGREGATE",B51)),"AGGREGATE ","")&IF(ISNUMBER(SEARCH("LOOKUP",B51)),"LOOKUP ","")&IF(ISNUMBER(SEARCH("FILTER",B51)),"FILTER ","")
A52: B68 | B52: =IFERROR(FORMULATEXT('[FinanceOS_v1.0-QA-RC1.xlsx]Business Engine'!B68),"") | C52: =IF(ISNUMBER(SEARCH("MAXIFS",B52)),"YES","NO") | D52: =IF(ISNUMBER(SEARCH("AGGREGATE",B52)),"AGGREGATE ","")&IF(ISNUMBER(SEARCH("LOOKUP",B52)),"LOOKUP ","")&IF(ISNUMBER(SEARCH("FILTER",B52)),"FILTER ","")
A53: B1 | B53: =IFERROR(FORMULATEXT('[FinanceOS_v1.0-QA-RC1.xlsx]Business Engine'!B1),"") | C53: =IF(ISNUMBER(SEARCH("MAXIFS",B53)),"YES","NO") | D53: =IF(ISNUMBER(SEARCH("AGGREGATE",B53)),"AGGREGATE ","")&IF(ISNUMBER(SEARCH("LOOKUP",B53)),"LOOKUP ","")&IF(ISNUMBER(SEARCH("FILTER",B53)),"FILTER ","")

Sheet Expected Results
A1: Metric ID | B1: Metric | C1: Cell | D1: Baseline | E1: Expected Difference | F1: Expected After | G1: Actual After | H1: PASS / FAIL
A2: ='Difference Engine'!A2 | B2: ='Difference Engine'!G2 | C2: ='Difference Engine'!I2 | D2: ='Difference Engine'!B2 | E2: ='Difference Engine'!E2 | F2: =IF(AND(ISNUMBER(D2),ISNUMBER(E2)),D2+E2,D2) | G2: ='Difference Engine'!C2 | H2: ='Difference Engine'!F2
A3: ='Difference Engine'!A3 | B3: ='Difference Engine'!G3 | C3: ='Difference Engine'!I3 | D3: ='Difference Engine'!B3 | E3: ='Difference Engine'!E3 | F3: =IF(AND(ISNUMBER(D3),ISNUMBER(E3)),D3+E3,D3) | G3: ='Difference Engine'!C3 | H3: ='Difference Engine'!F3
A4: ='Difference Engine'!A4 | B4: ='Difference Engine'!G4 | C4: ='Difference Engine'!I4 | D4: ='Difference Engine'!B4 | E4: ='Difference Engine'!E4 | F4: =IF(AND(ISNUMBER(D4),ISNUMBER(E4)),D4+E4,D4) | G4: ='Difference Engine'!C4 | H4: ='Difference Engine'!F4
A5: ='Difference Engine'!A5 | B5: ='Difference Engine'!G5 | C5: ='Difference Engine'!I5 | D5: ='Difference Engine'!B5 | E5: ='Difference Engine'!E5 | F5: =IF(AND(ISNUMBER(D5),ISNUMBER(E5)),D5+E5,D5) | G5: ='Difference Engine'!C5 | H5: ='Difference Engine'!F5
A6: ='Difference Engine'!A6 | B6: ='Difference Engine'!G6 | C6: ='Difference Engine'!I6 | D6: ='Difference Engine'!B6 | E6: ='Difference Engine'!E6 | F6: =IF(AND(ISNUMBER(D6),ISNUMBER(E6)),D6+E6,D6) | G6: ='Difference Engine'!C6 | H6: ='Difference Engine'!F6
A7: ='Difference Engine'!A7 | B7: ='Difference Engine'!G7 | C7: ='Difference Engine'!I7 | D7: ='Difference Engine'!B7 | E7: ='Difference Engine'!E7 | F7: =IF(AND(ISNUMBER(D7),ISNUMBER(E7)),D7+E7,D7) | G7: ='Difference Engine'!C7 | H7: ='Difference Engine'!F7
A8: ='Difference Engine'!A8 | B8: ='Difference Engine'!G8 | C8: ='Difference Engine'!I8 | D8: ='Difference Engine'!B8 | E8: ='Difference Engine'!E8 | F8: =IF(AND(ISNUMBER(D8),ISNUMBER(E8)),D8+E8,D8) | G8: ='Difference Engine'!C8 | H8: ='Difference Engine'!F8
A9: ='Difference Engine'!A9 | B9: ='Difference Engine'!G9 | C9: ='Difference Engine'!I9 | D9: ='Difference Engine'!B9 | E9: ='Difference Engine'!E9 | F9: =IF(AND(ISNUMBER(D9),ISNUMBER(E9)),D9+E9,D9) | G9: ='Difference Engine'!C9 | H9: ='Difference Engine'!F9
A10: ='Difference Engine'!A10 | B10: ='Difference Engine'!G10 | C10: ='Difference Engine'!I10 | D10: ='Difference Engine'!B10 | E10: ='Difference Engine'!E10 | F10: =IF(AND(ISNUMBER(D10),ISNUMBER(E10)),D10+E10,D10) | G10: ='Difference Engine'!C10 | H10: ='Difference Engine'!F10
A11: ='Difference Engine'!A11 | B11: ='Difference Engine'!G11 | C11: ='Difference Engine'!I11 | D11: ='Difference Engine'!B11 | E11: ='Difference Engine'!E11 | F11: =IF(AND(ISNUMBER(D11),ISNUMBER(E11)),D11+E11,D11) | G11: ='Difference Engine'!C11 | H11: ='Difference Engine'!F11
A12: ='Difference Engine'!A12 | B12: ='Difference Engine'!G12 | C12: ='Difference Engine'!I12 | D12: ='Difference Engine'!B12 | E12: ='Difference Engine'!E12 | F12: =IF(AND(ISNUMBER(D12),ISNUMBER(E12)),D12+E12,D12) | G12: ='Difference Engine'!C12 | H12: ='Difference Engine'!F12
A13: ='Difference Engine'!A13 | B13: ='Difference Engine'!G13 | C13: ='Difference Engine'!I13 | D13: ='Difference Engine'!B13 | E13: ='Difference Engine'!E13 | F13: =IF(AND(ISNUMBER(D13),ISNUMBER(E13)),D13+E13,D13) | G13: ='Difference Engine'!C13 | H13: ='Difference Engine'!F13
... A96: ='Difference Engine'!A96 | B96: ='Difference Engine'!G96 | C96: ='Difference Engine'!I96 | D96: ='Difference Engine'!B96 | E96: ='Difference Engine'!E96 | F96: =IF(AND(ISNUMBER(D96),ISNUMBER(E96)),D96+E96,D96) | G96: ='Difference Engine'!C96 | H96: ='Difference Engine'!F96

Sheet Actual Results
A1: Metric ID | B1: Section | C1: Metric | D1: Cell | E1: QA-RC1 (live)
A2: ACC_TOTAL_BAL | B2: Accounts Summary | C2: Total Active Account Balance | D2: B4 | E2: ='[FinanceOS_v1.0-QA-RC1.xlsx]Business Engine'!B4
A3: ACC_ACTIVE_N | B3: Accounts Summary | C3: Number of Active Accounts | D3: B5 | E3: ='[FinanceOS_v1.0-QA-RC1.xlsx]Business Engine'!B5
A4: ACC_CASH | B4: Accounts Summary | C4: Cash Accounts Total | D4: B6 | E4: ='[FinanceOS_v1.0-QA-RC1.xlsx]Business Engine'!B6
A5: ACC_SAVINGS | B5: Accounts Summary | C5: Savings Accounts Total | D5: B7 | E5: ='[FinanceOS_v1.0-QA-RC1.xlsx]Business Engine'!B7
A6: ACC_INVEST | B6: Accounts Summary | C6: Investment Accounts Total | D6: B8 | E6: ='[FinanceOS_v1.0-QA-RC1.xlsx]Business Engine'!B8
A7: ACC_CREDIT | B7: Accounts Summary | C7: Credit Accounts Total | D7: B9 | E7: ='[FinanceOS_v1.0-QA-RC1.xlsx]Business Engine'!B9
A8: INC_SALARY | B8: Income Summary | C8: Monthly Salary Income | D8: B12 | E8: ='[FinanceOS_v1.0-QA-RC1.xlsx]Business Engine'!B12
A9: INC_BIZ | B9: Income Summary | C9: Monthly Business Income | D9: B13 | E9: ='[FinanceOS_v1.0-QA-RC1.xlsx]Business Engine'!B13
A10: INC_FREE | B10: Income Summary | C10: Monthly Freelance Income | D10: B14 | E10: ='[FinanceOS_v1.0-QA-RC1.xlsx]Business Engine'!B14
A11: INC_INV | B11: Income Summary | C11: Monthly Investment Income | D11: B15 | E11: ='[FinanceOS_v1.0-QA-RC1.xlsx]Business Engine'!B15
A12: INC_MONTH | B12: Income Summary | C12: Total Monthly Income | D12: B16 | E12: ='[FinanceOS_v1.0-QA-RC1.xlsx]Business Engine'!B16
A13: INC_OTHER | B13: Income Summary | C13: Monthly Other Income | D13: B17 | E13: ='[FinanceOS_v1.0-QA-RC1.xlsx]Business Engine'!B17
A14: INC_ANNUAL | B14: Income Summary | C14: Total Annual Income | D14: B18 | E14: ='[FinanceOS_v1.0-QA-RC1.xlsx]Business Engine'!B18
A15: INC_SRC_N | B15: Income Summary | C15: Active Income Source Count | D15: B19 | E15: ='[FinanceOS_v1.0-QA-RC1.xlsx]Business Engine'!B19
A16: EXP_CM | B16: Expense Summary | C16: Current Month Expenses | D16: B22 | E16: ='[FinanceOS_v1.0-QA-RC1.xlsx]Business Engine'!B22
A17: EXP_PM | B17: Expense Summary | C17: Previous Month Expenses | D17: B23 | E17: ='[FinanceOS_v1.0-QA-RC1.xlsx]Business Engine'!B23
A18: EXP_YTD | B18: Expense Summary | C18: Year-to-Date Expenses | D18: B24 | E18: ='[FinanceOS_v1.0-QA-RC1.xlsx]Business Engine'!B24
A19: EXP_N | B19: Expense Summary | C19: Expense Transaction Count | D19: B25 | E19: ='[FinanceOS_v1.0-QA-RC1.xlsx]Business Engine'!B25
A20: SAV_INC | B20: Savings Summary | C20: Current Month Income | D20: B28 | E20: ='[FinanceOS_v1.0-QA-RC1.xlsx]Business Engine'!B28
A21: SAV_AMT | B21: Savings Summary | C21: Current Month Savings | D21: B29 | E21: ='[FinanceOS_v1.0-QA-RC1.xlsx]Business Engine'!B29
A22: SAV_RATE | B22: Savings Summary | C22: Savings Rate (%) | D22: B30 | E22: ='[FinanceOS_v1.0-QA-RC1.xlsx]Business Engine'!B30
A23: SAV_AVG | B23: Savings Summary | C23: Average Monthly Savings | D23: B31 | E23: ='[FinanceOS_v1.0-QA-RC1.xlsx]Business Engine'!B31
A24: AST_PUR | B24: Asset Summary | C24: Total Purchase Value | D24: B34 | E24: ='[FinanceOS_v1.0-QA-RC1.xlsx]Business Engine'!B34
A25: AST_CUR | B25: Asset Summary | C25: Total Current Value | D25: B35 | E25: ='[FinanceOS_v1.0-QA-RC1.xlsx]Business Engine'!B35
A26: AST_APP | B26: Asset Summary | C26: Total Appreciation Amount | D26: B36 | E26: ='[FinanceOS_v1.0-QA-RC1.xlsx]Business Engine'!B36
A27: AST_PCT | B27: Asset Summary | C27: Weighted Appreciation % | D27: B37 | E27: ='[FinanceOS_v1.0-QA-RC1.xlsx]Business Engine'!B37
A28: AST_N | B28: Asset Summary | C28: Active Asset Count | D28: B38 | E28: ='[FinanceOS_v1.0-QA-RC1.xlsx]Business Engine'!B38
A29: LIA_ORIG | B29: Liability Summary | C29: Total Original Liability | D29: B41 | E29: ='[FinanceOS_v1.0-QA-RC1.xlsx]Business Engine'!B41
A30: LIA_OUT | B30: Liability Summary | C30: Total Outstanding Balance | D30: B42 | E30: ='[FinanceOS_v1.0-QA-RC1.xlsx]Business Engine'!B42
A31: LIA_EMI | B31: Liability Summary | C31: Total Monthly EMI | D31: B43 | E31: ='[FinanceOS_v1.0-QA-RC1.xlsx]Business Engine'!B43
A32: LIA_INT | B32: Liability Summary | C32: Weighted Interest Rate | D32: B44 | E32: ='[FinanceOS_v1.0-QA-RC1.xlsx]Business Engine'!B44
A33: LIA_N | B33: Liability Summary | C33: Active Liability Count | D33: B45 | E33: ='[FinanceOS_v1.0-QA-RC1.xlsx]Business Engine'!B45
A34: NW_TOTAL | B34: Net Worth | C34: Net Worth | D34: B48 | E34: ='[FinanceOS_v1.0-QA-RC1.xlsx]Business Engine'!B48
A35: NW_LIQ | B35: Net Worth | C35: Liquid Net Worth | D35: B49 | E35: ='[FinanceOS_v1.0-QA-RC1.xlsx]Business Engine'!B49
A36: NW_INV | B36: Net Worth | C36: Invested Net Worth | D36: B50 | E36: ='[FinanceOS_v1.0-QA-RC1.xlsx]Business Engine'!B50
A37: GOAL_TGT | B37: Goal Summary | C37: Total Goal Target Amount | D37: B53 | E37: ='[FinanceOS_v1.0-QA-RC1.xlsx]Business Engine'!B53
A38: GOAL_SAV | B38: Goal Summary | C38: Total Saved Toward Goals | D38: B54 | E38: ='[FinanceOS_v1.0-QA-RC1.xlsx]Business Engine'!B54
A39: GOAL_REM | B39: Goal Summary | C39: Remaining Goal Amount | D39: B55 | E39: ='[FinanceOS_v1.0-QA-RC1.xlsx]Business Engine'!B55
A40: GOAL_ACT | B40: Goal Summary | C40: Active Goal Count | D40: B56 | E40: ='[FinanceOS_v1.0-QA-RC1.xlsx]Business Engine'!B56
A41: GOAL_DONE | B41: Goal Summary | C41: Completed Goal Count | D41: B57 | E41: ='[FinanceOS_v1.0-QA-RC1.xlsx]Business Engine'!B57
A42: GOAL_PCT | B42: Goal Summary | C42: Goal Completion % | D42: B58 | E42: ='[FinanceOS_v1.0-QA-RC1.xlsx]Business Engine'!B58
A43: HLTH_INC | B43: Financial Health | C43: Income | D43: B61 | E43: ='[FinanceOS_v1.0-QA-RC1.xlsx]Business Engine'!B61
A44: HLTH_EXP | B44: Financial Health | C44: Expenses | D44: B62 | E44: ='[FinanceOS_v1.0-QA-RC1.xlsx]Business Engine'!B62
A45: HLTH_SAV | B45: Financial Health | C45: Savings | D45: B63 | E45: ='[FinanceOS_v1.0-QA-RC1.xlsx]Business Engine'!B63
A46: HLTH_RATE | B46: Financial Health | C46: Savings Rate | D46: B64 | E46: ='[FinanceOS_v1.0-QA-RC1.xlsx]Business Engine'!B64
A47: HLTH_NW | B47: Financial Health | C47: Net Worth | D47: B65 | E47: ='[FinanceOS_v1.0-QA-RC1.xlsx]Business Engine'!B65
A48: HLTH_EMI | B48: Financial Health | C48: EMI Ratio | D48: B66 | E48: ='[FinanceOS_v1.0-QA-RC1.xlsx]Business Engine'!B66
A49: HLTH_ALLOC | B49: Financial Health | C49: Asset Allocation | D49: B67 | E49: ='[FinanceOS_v1.0-QA-RC1.xlsx]Business Engine'!B67
A50: HLTH_DEBT | B50: Financial Health | C50: Debt Ratio | D50: B68 | E50: ='[FinanceOS_v1.0-QA-RC1.xlsx]Business Engine'!B68
A51: ASOF | B51: Formula Integrity | C51: As-Of Date | D51: B1 | E51: ='[FinanceOS_v1.0-QA-RC1.xlsx]Business Engine'!B1
A52: AE_ASOF | B52: Analysis Engine | C52: As-Of Date | D52: B2 | E52: ='[FinanceOS_v1.0-QA-RC1.xlsx]Analysis Engine'!B2
A53: AE_INC_CM | B53: Analysis Engine | C53: Total Income CM | D53: B6 | E53: ='[FinanceOS_v1.0-QA-RC1.xlsx]Analysis Engine'!B6
A54: AE_SAL_CM | B54: Analysis Engine | C54: Salary CM | D54: B7 | E54: ='[FinanceOS_v1.0-QA-RC1.xlsx]Analysis Engine'!B7
A55: AE_BIZ_CM | B55: Analysis Engine | C55: Business Income CM | D55: B8 | E55: ='[FinanceOS_v1.0-QA-RC1.xlsx]Analysis Engine'!B8
A56: AE_FREE_CM | B56: Analysis Engine | C56: Freelance CM | D56: B9 | E56: ='[FinanceOS_v1.0-QA-RC1.xlsx]Analysis Engine'!B9
A57: AE_INV_CM | B57: Analysis Engine | C57: Investment CM | D57: B10 | E57: ='[FinanceOS_v1.0-QA-RC1.xlsx]Analysis Engine'!B10
A58: AE_OTH_CM | B58: Analysis Engine | C58: Other Income CM | D58: B11 | E58: ='[FinanceOS_v1.0-QA-RC1.xlsx]Analysis Engine'!B11
A59: AE_INC_PM | B59: Analysis Engine | C59: Total Income PM | D59: C6 | E59: ='[FinanceOS_v1.0-QA-RC1.xlsx]Analysis Engine'!C6
A60: AE_INC_YTD | B60: Analysis Engine | C60: Total Income YTD | D60: D6 | E60: ='[FinanceOS_v1.0-QA-RC1.xlsx]Analysis Engine'!D6
A61: AE_EXP_CM | B61: Analysis Engine | C61: Total Expenses CM | D61: B14 | E61: ='[FinanceOS_v1.0-QA-RC1.xlsx]Analysis Engine'!B14
A62: AE_EXP_PM | B62: Analysis Engine | C62: Total Expenses PM | D62: C14 | E62: ='[FinanceOS_v1.0-QA-RC1.xlsx]Analysis Engine'!C14
A63: AE_EXP_YTD | B63: Analysis Engine | C63: Total Expenses YTD | D63: D14 | E63: ='[FinanceOS_v1.0-QA-RC1.xlsx]Analysis Engine'!D14
A64: AE_CF_INC | B64: Analysis Engine | C64: Cash Flow Income | D64: B44 | E64: ='[FinanceOS_v1.0-QA-RC1.xlsx]Analysis Engine'!B44
A65: AE_CF_EXP | B65: Analysis Engine | C65: Cash Flow Expenses | D65: B45 | E65: ='[FinanceOS_v1.0-QA-RC1.xlsx]Analysis Engine'!B45
A66: AE_CF_SAV | B66: Analysis Engine | C66: Cash Flow Savings | D66: B46 | E66: ='[FinanceOS_v1.0-QA-RC1.xlsx]Analysis Engine'!B46
A67: AE_CF_RATE | B67: Analysis Engine | C67: Cash Flow Savings Rate | D67: B47 | E67: ='[FinanceOS_v1.0-QA-RC1.xlsx]Analysis Engine'!B47
A68: AE_CF_PMEXP | B68: Analysis Engine | C68: Previous Month Expenses | D68: B48 | E68: ='[FinanceOS_v1.0-QA-RC1.xlsx]Analysis Engine'!B48
A69: AE_CF_MOM | B69: Analysis Engine | C69: MoM Expense Change | D69: B49 | E69: ='[FinanceOS_v1.0-QA-RC1.xlsx]Analysis Engine'!B49
A70: AE_AST_PUR | B70: Analysis Engine | C70: Asset Purchase Value | D70: B54 | E70: ='[FinanceOS_v1.0-QA-RC1.xlsx]Analysis Engine'!B54
A71: AE_AST_CUR | B71: Analysis Engine | C71: Asset Current Value | D71: B55 | E71: ='[FinanceOS_v1.0-QA-RC1.xlsx]Analysis Engine'!B55
A72: AE_AST_APP | B72: Analysis Engine | C72: Asset Appreciation | D72: B56 | E72: ='[FinanceOS_v1.0-QA-RC1.xlsx]Analysis Engine'!B56
A73: AE_AST_PCT | B73: Analysis Engine | C73: Asset Appreciation % | D73: B57 | E73: ='[FinanceOS_v1.0-QA-RC1.xlsx]Analysis Engine'!B57
A74: AE_AST_N | B74: Analysis Engine | C74: Active Asset Count | D74: B58 | E74: ='[FinanceOS_v1.0-QA-RC1.xlsx]Analysis Engine'!B58
A75: AE_LIA_ORIG | B75: Analysis Engine | C75: Total Original Liability | D75: B74 | E75: ='[FinanceOS_v1.0-QA-RC1.xlsx]Analysis Engine'!B74
A76: AE_LIA_OUT | B76: Analysis Engine | C76: Outstanding Balance | D76: B75 | E76: ='[FinanceOS_v1.0-QA-RC1.xlsx]Analysis Engine'!B75
A77: AE_LIA_EMI | B77: Analysis Engine | C77: Total Monthly EMI | D77: B76 | E77: ='[FinanceOS_v1.0-QA-RC1.xlsx]Analysis Engine'!B76
A78: AE_LIA_INT | B78: Analysis Engine | C78: Weighted Interest Rate | D78: B77 | E78: ='[FinanceOS_v1.0-QA-RC1.xlsx]Analysis Engine'!B77
A79: AE_LIA_N | B79: Analysis Engine | C79: Active Liability Count | D79: B79 | E79: ='[FinanceOS_v1.0-QA-RC1.xlsx]Analysis Engine'!B79
A80: AE_EMI_RATIO | B80: Analysis Engine | C80: EMI Ratio | D80: B80 | E80: ='[FinanceOS_v1.0-QA-RC1.xlsx]Analysis Engine'!B80
A81: AE_DEBT | B81: Analysis Engine | C81: Debt Ratio | D81: B81 | E81: ='[FinanceOS_v1.0-QA-RC1.xlsx]Analysis Engine'!B81
A82: AE_GOAL_OVER | B82: Analysis Engine | C82: Overdue Goal Count | D82: B107 | E82: ='[FinanceOS_v1.0-QA-RC1.xlsx]Analysis Engine'!B107
A83: AE_GOAL_PCT | B83: Analysis Engine | C83: Goal Completion % | D83: B108 | E83: ='[FinanceOS_v1.0-QA-RC1.xlsx]Analysis Engine'!B108
A84: AE_GOAL_N | B84: Analysis Engine | C84: Active Goal Count | D84: B109 | E84: ='[FinanceOS_v1.0-QA-RC1.xlsx]Analysis Engine'!B109
A85: AE_JAN_INC | B85: Analysis Engine | C85: Jan Income | D85: B30 | E85: ='[FinanceOS_v1.0-QA-RC1.xlsx]Analysis Engine'!B30
A86: AE_AUG_INC | B86: Analysis Engine | C86: Aug Income | D86: B37 | E86: ='[FinanceOS_v1.0-QA-RC1.xlsx]Analysis Engine'!B37
A87: AE_SEP_INC | B87: Analysis Engine | C87: Sep Income | D87: B38 | E87: ='[FinanceOS_v1.0-QA-RC1.xlsx]Analysis Engine'!B38
A88: AE_AUG_EXP | B88: Analysis Engine | C88: Aug Expenses | D88: C37 | E88: ='[FinanceOS_v1.0-QA-RC1.xlsx]Analysis Engine'!C37
A89: AE_SEP_EXP | B89: Analysis Engine | C89: Sep Expenses | D89: C38 | E89: ='[FinanceOS_v1.0-QA-RC1.xlsx]Analysis Engine'!C38
A90: AE_SEP_SAV | B90: Analysis Engine | C90: Sep Savings | D90: D38 | E90: ='[FinanceOS_v1.0-QA-RC1.xlsx]Analysis Engine'!D38
A91: AE_CAT1 | B91: Analysis Engine | C91: Category 1 CM | D91: B17 | E91: ='[FinanceOS_v1.0-QA-RC1.xlsx]Analysis Engine'!B17
A92: AE_CAT2 | B92: Analysis Engine | C92: Category 2 CM | D92: B18 | E92: ='[FinanceOS_v1.0-QA-RC1.xlsx]Analysis Engine'!B18
A93: AE_CAT3 | B93: Analysis Engine | C93: Category 3 CM | D93: B19 | E93: ='[FinanceOS_v1.0-QA-RC1.xlsx]Analysis Engine'!B19
A94: AE_SAL_YTD | B94: Analysis Engine | C94: Salary YTD | D94: D7 | E94: ='[FinanceOS_v1.0-QA-RC1.xlsx]Analysis Engine'!D7
A95: AE_FREE_YTD | B95: Analysis Engine | C95: Freelance YTD | D95: D9 | E95: ='[FinanceOS_v1.0-QA-RC1.xlsx]Analysis Engine'!D9
A96: AE_MOM_PCT | B96: Analysis Engine | C96: MoM Expense Change % | D96: B50 | E96: ='[FinanceOS_v1.0-QA-RC1.xlsx]Analysis Engine'!B50
