Workbook
Name rngAccounts: Accounts!$B$2:$B$200
Name rngAccountStatus: Helpers!$A$70:$A$71
Name rngAccountType: Helpers!$A$91:$A$98
Name rngActiveAccounts: Helpers!$B$132
Name rngActiveAssets: Helpers!$B$134
Name rngActiveGoals: Helpers!$B$133
Name rngActiveLiabilities: Helpers!$B$135
Name rngAssets: Assets!$B$2:$B$200
Name rngAssetType: Helpers!$AG$2:$AG$25
Name rngBoolean: Helpers!$A$86:$A$87
Name rngCategories: Categories!$B$2:$B$200
Name rngCategoryType: Helpers!$A$102:$A$103
Name rngCurrency: Helpers!$A$2:$A$6
Name rngExpenseCategories: Helpers!$B$130
Name rngFinancialYears: Helpers!$A$126
Name rngFrequency: Helpers!$A$38:$A$41
Name rngGoals: Goals!$B$2:$B$200
Name rngGoalStatus: Helpers!$A$59:$A$61
Name rngIncomeCategories: Helpers!$B$131
Name rngIncomeSources: 'Income Sources'!$B$2:$B$200
Name rngIncomeType: Helpers!$AI$2:$AI$10
Name rngLiabilities: Liabilities!$B$2:$B$200
Name rngLiabilityType: Helpers!$AH$2:$AH$11
Name rngMonths: Helpers!$B$111:$B$122
Name rngPaymentMethods: Helpers!$A$10:$A$17
Name rngPriority: Helpers!$A$45:$A$47
Name rngTransactionType: Helpers!$A$21:$A$24
Name valAccountStatus: Helpers!$B$147
Name valAccountTypes: Helpers!$B$140
Name valActiveAccounts: Helpers!$B$132
Name valActiveAssets: Helpers!$B$134
Name valActiveGoals: Helpers!$B$133
Name valActiveLiabilities: Helpers!$B$135
Name valCategoryTypes: Helpers!$B$141
Name valCommitmentStatus: Helpers!$B$148
Name valCurrencies: Helpers!$B$143
Name valDestinationTypes: Helpers!$B$144
Name valExpenseCategories: Helpers!$B$130
Name valFrequency: Helpers!$B$138
Name valGoalStatus: Helpers!$B$146
Name valIncomeCategories: Helpers!$B$131
Name valIncomeSources: Helpers!$B$136
Name valPaymentMethods: Helpers!$B$137
Name valPriority: Helpers!$B$139
Name valThemes: Helpers!$B$142
Name valTransactionTypes: Helpers!$B$145
Name rngDestinationType: Helpers!$A$28:$A$34
Name rngOwnershipType: Helpers!$A$81:$A$82
Name rngCommitmentStatus: Helpers!$A$75:$A$77
Name rngLiabilityStatus: Helpers!$A$65:$A$66

Sheet Settings
A1: Setting ID | B1: Setting Name | C1: Setting Value | D1: Setting Category | E1: Description
A2: SET-0001 | B2: Currency | C2: INR | D2: Currency | E2: Display currency
A3: SET-0002 | B3: Financial Year Start | C3: April | D3: Date | E3: Indian fiscal year
A4: SET-0003 | B4: Week Starts | C4: Monday | D4: Date | E4: Week start day
A5: SET-0004 | B5: Dashboard Theme | C5: FinanceOS Default | D5: Theme | E5: Workbook theme
A6: SET-0005 | B6: Decimal Places | C6: 2 | D6: Display | E6: Amount precision
A7: SET-0006 | B7: Date Format | C7: DD/MM/YYYY | D7: Date | E7: Display date format
A8: SET-0007 | B8: As-Of Date | C8: 12/09/2026 | D8: Date | E8: Business Engine as-of date

Sheet Categories
A1: Category ID | B1: Category Name | C1: Category Type | D1: Parent Category | E1: Status | F1: Display Order | G1: Notes
A2: CAT-0001 | B2: Rent | C2: Expense | E2: Active | F2: 1 | G2: Housing
A3: CAT-0002 | B3: Groceries | C3: Expense | E3: Active | F3: 2 | G3: Food at home
A4: CAT-0003 | B4: Dining | C4: Expense | E4: Active | F4: 3 | G4: Restaurants
A5: CAT-0004 | B5: Transport | C5: Expense | E5: Active | F5: 4 | G5: Commute
A6: CAT-0005 | B6: Utilities | C6: Expense | E6: Active | F6: 5 | G6: Power and internet
A7: CAT-0006 | B7: Subscriptions | C7: Expense | E7: Active | F7: 6 | G7: OTT and apps
A8: CAT-0007 | B8: Shopping | C8: Expense | E8: Active | F8: 7 | G8: Retail
A9: CAT-0008 | B9: Healthcare | C9: Expense | E9: Active | F9: 8 | G9: Medical
A10: CAT-0009 | B10: Entertainment | C10: Expense | E10: Active | F10: 9 | G10: Leisure
A11: CAT-0010 | B11: Insurance | C11: Expense | E11: Active | F11: 10 | G11: Policies
A12: CAT-0011 | B12: EMI | C12: Expense | E12: Active | F12: 11 | G12: Loan payments
A13: CAT-0012 | B13: SIP | C13: Expense | E13: Active | F13: 12 | G13: Investments
... A17: CAT-0016 | B17: Cashback Income | C17: Income | E17: Active | F17: 16 | G17: Card cashback

Sheet Accounts
A1: Account ID | B1: Account Name | C1: Account Type | D1: Institution | E1: Opening Balance | F1: Current Balance | G1: Currency | H1: Status | I1: Notes
A2: ACC-0001 | B2: HDFC Salary | C2: Savings Bank | D2: HDFC Bank | E2: 125000 | G2: INR | H2: Active | I2: Primary salary account
A3: ACC-0002 | B3: SBI Savings | C3: Savings Bank | D3: State Bank of India | E3: 82000 | G3: INR | H3: Active | I3: Secondary savings
A4: ACC-0003 | B4: Axis Savings | C4: Savings Bank | D4: Axis Bank | E4: 45000 | G4: INR | H4: Active | I4: Trip and freelance
A5: ACC-0004 | B5: ICICI Credit Card | C5: Credit Card | D5: ICICI Bank | E5: 0 | G5: INR | H5: Active | I5: Everyday card
A6: ACC-0005 | B6: Cash Wallet | C6: Wallet | D6: Cash | E6: 8500 | G6: INR | H6: Active | I6: Pocket cash
A7: ACC-0006 | B7: Emergency Cash | C7: Cash | D7: Home | E7: 20000 | G7: INR | H7: Active | I7: Physical emergency cash

Sheet Income Sources
A1: Income Source ID | B1: Income Source Name | C1: Income Category | D1: Default Receiving Account | E1: Status | F1: Notes
A2: INC-0001 | B2: Acme Payroll | C2: Salary | D2: HDFC Salary | E2: Active | F2: Monthly salary
A3: INC-0002 | B3: Freelance Gigs | C3: Freelance | D3: Axis Savings | E3: Active | F3: Design and writing
A4: INC-0003 | B4: HDFC Cashback | C4: Cashback | D4: HDFC Salary | E4: Active | F4: Card cashback
A5: INC-0004 | B5: FD Interest | C5: Interest | D5: SBI Savings | E5: Active | F5: Fixed deposit interest

Sheet Assets
A1: Asset ID | B1: Asset Name | C1: Asset Category | D1: Asset Type | E1: Linked Account | F1: Purchase Date | G1: Purchase Value | H1: Current Value | I1: Appreciation Amount | J1: Appreciation % | K1: Ownership Type | L1: Status | M1: Notes
I2: =tblAssets[[#This Row],[Current Value]]-tblAssets[[#This Row],[Purchase Value]] | J2: =IFERROR(tblAssets[[#This Row],[Appreciation Amount]]/tblAssets[[#This Row],[Purchase Value]],0)
I3: =tblAssets[[#This Row],[Current Value]]-tblAssets[[#This Row],[Purchase Value]] | J3: =IFERROR(tblAssets[[#This Row],[Appreciation Amount]]/tblAssets[[#This Row],[Purchase Value]],0)
I4: =tblAssets[[#This Row],[Current Value]]-tblAssets[[#This Row],[Purchase Value]] | J4: =IFERROR(tblAssets[[#This Row],[Appreciation Amount]]/tblAssets[[#This Row],[Purchase Value]],0)
I5: =tblAssets[[#This Row],[Current Value]]-tblAssets[[#This Row],[Purchase Value]] | J5: =IFERROR(tblAssets[[#This Row],[Appreciation Amount]]/tblAssets[[#This Row],[Purchase Value]],0)
I6: =tblAssets[[#This Row],[Current Value]]-tblAssets[[#This Row],[Purchase Value]] | J6: =IFERROR(tblAssets[[#This Row],[Appreciation Amount]]/tblAssets[[#This Row],[Purchase Value]],0)
I7: =tblAssets[[#This Row],[Current Value]]-tblAssets[[#This Row],[Purchase Value]] | J7: =IFERROR(tblAssets[[#This Row],[Appreciation Amount]]/tblAssets[[#This Row],[Purchase Value]],0)
I8: =tblAssets[[#This Row],[Current Value]]-tblAssets[[#This Row],[Purchase Value]] | J8: =IFERROR(tblAssets[[#This Row],[Appreciation Amount]]/tblAssets[[#This Row],[Purchase Value]],0)
I9: =tblAssets[[#This Row],[Current Value]]-tblAssets[[#This Row],[Purchase Value]] | J9: =IFERROR(tblAssets[[#This Row],[Appreciation Amount]]/tblAssets[[#This Row],[Purchase Value]],0)
I10: =tblAssets[[#This Row],[Current Value]]-tblAssets[[#This Row],[Purchase Value]] | J10: =IFERROR(tblAssets[[#This Row],[Appreciation Amount]]/tblAssets[[#This Row],[Purchase Value]],0)
I11: =tblAssets[[#This Row],[Current Value]]-tblAssets[[#This Row],[Purchase Value]] | J11: =IFERROR(tblAssets[[#This Row],[Appreciation Amount]]/tblAssets[[#This Row],[Purchase Value]],0)
I12: =tblAssets[[#This Row],[Current Value]]-tblAssets[[#This Row],[Purchase Value]] | J12: =IFERROR(tblAssets[[#This Row],[Appreciation Amount]]/tblAssets[[#This Row],[Purchase Value]],0)
I13: =tblAssets[[#This Row],[Current Value]]-tblAssets[[#This Row],[Purchase Value]] | J13: =IFERROR(tblAssets[[#This Row],[Appreciation Amount]]/tblAssets[[#This Row],[Purchase Value]],0)
... I200: =tblAssets[[#This Row],[Current Value]]-tblAssets[[#This Row],[Purchase Value]] | J200: =IFERROR(tblAssets[[#This Row],[Appreciation Amount]]/tblAssets[[#This Row],[Purchase Value]],0)

Sheet Liabilities
A1: Liability ID | B1: Liability Name | C1: Liability Type | D1: Institution | E1: Original Amount | F1: Outstanding Balance | G1: Interest Rate | H1: EMI Amount | I1: EMI Frequency | J1: EMI Due Day | K1: Start Date | L1: End Date | M1: Linked Payment Account | N1: Auto EMI | O1: Status | P1: Notes
A2: LIA-0001 | B2: Personal Loan | C2: Personal Loan | D2: HDFC Bank | E2: 200000 | F2: 145000 | G2: 0.145 | H2: 8500 | I2: Monthly | J2: 5 | K2: 45662 | L2: 46392 | M2: HDFC Salary | N2: Yes | O2: Active | P2: Consolidation loan
A3: LIA-0002 | B3: Bike EMI | C3: Vehicle Loan | D3: HDFC Bank | E3: 120000 | F3: 72000 | G3: 0.11 | H3: 4200 | I3: Monthly | J3: 8 | K3: 45724 | L3: 46454 | M3: HDFC Salary | N3: Yes | O3: Active | P3: Two-wheeler
A4: LIA-0003 | B4: Credit Card EMI | C4: Credit Card | D4: ICICI Bank | E4: 35000 | F4: 18000 | G4: 0.18 | H4: 3000 | I4: Monthly | J4: 12 | K4: 46034 | L4: 46368 | M4: HDFC Salary | N4: Yes | O4: Active | P4: Converted EMI

Sheet Recurring Commitments
A1: Commitment ID | B1: Commitment Name | C1: Commitment Type | D1: Linked Liability ID | E1: Linked Goal ID | F1: Payment Account | G1: Amount | H1: Frequency | I1: Due Day | J1: Start Date | K1: End Date | L1: Auto Generate | M1: Status | N1: Notes
A2: COM-0001 | B2: Rent | C2: Rent | F2: HDFC Salary | G2: 18000 | H2: Monthly | I2: 1 | J2: 46023 | L2: Yes | M2: Active | N2: House rent
A3: COM-0002 | B3: Electricity | C3: Utility | F3: HDFC Salary | G3: 2200 | H3: Monthly | I3: 10 | J3: 46023 | L3: Yes | M3: Active | N3: BESCOM
A4: COM-0003 | B4: Internet | C4: Utility | F4: HDFC Salary | G4: 999 | H4: Monthly | I4: 7 | J4: 46023 | L4: Yes | M4: Active | N4: Fiber
A5: COM-0004 | B5: Mobile Recharge | C5: Utility | F5: HDFC Salary | G5: 599 | H5: Monthly | I5: 3 | J5: 46023 | L5: Yes | M5: Active | N5: Jio
A6: COM-0005 | B6: Spotify | C6: Subscription | F6: HDFC Salary | G6: 119 | H6: Monthly | I6: 15 | J6: 46023 | L6: Yes | M6: Active | N6: Family plan
A7: COM-0006 | B7: Netflix | C7: Subscription | F7: HDFC Salary | G7: 649 | H7: Monthly | I7: 16 | J7: 46023 | L7: Yes | M7: Active | N7: Premium
A8: COM-0007 | B8: SIP | C8: SIP | E8: GOAL-0001 | F8: SBI Savings | G8: 10000 | H8: Monthly | I8: 5 | J8: 46027 | L8: Yes | M8: Active | N8: Emergency fund SIP
A9: COM-0008 | B9: Insurance | C9: Insurance | F9: HDFC Salary | G9: 3500 | H9: Monthly | I9: 20 | J9: 46023 | L9: Yes | M9: Active | N9: Term + health
A10: COM-0009 | B10: Gym | C10: Membership | F10: HDFC Salary | G10: 1500 | H10: Monthly | I10: 2 | J10: 46023 | L10: Yes | M10: Active | N10: Cult
A11: COM-0010 | B11: Amazon Prime | C11: Subscription | F11: HDFC Salary | G11: 299 | H11: Monthly | I11: 18 | J11: 46023 | L11: Yes | M11: Active | N11: Prime monthly

Sheet Transactions
A1: Transaction ID | B1: Transaction Date | C1: Transaction Type | D1: Source Account | E1: Destination Type | F1: Destination Name | G1: Category | H1: Income Source | I1: Amount | J1: Payment Method | K1: Transaction Status | L1: Notes | M1: Created Timestamp
A2: TXN-000090 | B2: 46295 | C2: Income | D2: HDFC Salary | E2: Income Category | F2: Salary Income | G2: Salary Income | H2: Acme Payroll | I2: 85000 | J2: Bank Transfer | K2: Completed | L2: BUG-003 later salary ABOVE Jan salary
A3: TXN-000010 | B3: 46023 | C3: Income | D3: HDFC Salary | E3: Income Category | F3: Salary Income | G3: Salary Income | H3: Acme Payroll | I3: 85000 | J3: Bank Transfer | K3: Completed | L3: BUG-003 earlier salary BELOW Sep salary
A4: TXN-000001 | B4: 46054 | C4: Income | D4: HDFC Salary | E4: Income Category | F4: Salary Income | G4: Salary Income | H4: Acme Payroll | I4: 85000 | J4: Bank Transfer | K4: Completed | L4: Monthly salary
A5: TXN-000002 | B5: 46082 | C5: Income | D5: HDFC Salary | E5: Income Category | F5: Salary Income | G5: Salary Income | H5: Acme Payroll | I5: 85000 | J5: Bank Transfer | K5: Completed | L5: Monthly salary
A6: TXN-000003 | B6: 46113 | C6: Income | D6: HDFC Salary | E6: Income Category | F6: Salary Income | G6: Salary Income | H6: Acme Payroll | I6: 85000 | J6: Bank Transfer | K6: Completed | L6: Monthly salary
A7: TXN-000004 | B7: 46143 | C7: Income | D7: HDFC Salary | E7: Income Category | F7: Salary Income | G7: Salary Income | H7: Acme Payroll | I7: 85000 | J7: Bank Transfer | K7: Completed | L7: Monthly salary
A8: TXN-000005 | B8: 46174 | C8: Income | D8: HDFC Salary | E8: Income Category | F8: Salary Income | G8: Salary Income | H8: Acme Payroll | I8: 85000 | J8: Bank Transfer | K8: Completed | L8: Monthly salary
A9: TXN-000006 | B9: 46204 | C9: Income | D9: HDFC Salary | E9: Income Category | F9: Salary Income | G9: Salary Income | H9: Acme Payroll | I9: 85000 | J9: Bank Transfer | K9: Completed | L9: Monthly salary
A10: TXN-000007 | B10: 46235 | C10: Income | D10: HDFC Salary | E10: Income Category | F10: Salary Income | G10: Salary Income | H10: Acme Payroll | I10: 85000 | J10: Bank Transfer | K10: Completed | L10: Monthly salary
A11: TXN-000008 | B11: 46266 | C11: Income | D11: HDFC Salary | E11: Income Category | F11: Salary Income | G11: Salary Income | H11: Acme Payroll | I11: 85000 | J11: Bank Transfer | K11: Completed | L11: Monthly salary
A12: TXN-000009 | B12: 46040 | C12: Income | D12: Axis Savings | E12: Income Category | F12: Freelance Income | G12: Freelance Income | H12: Freelance Gigs | I12: 12000 | J12: UPI | K12: Completed | L12: Freelance invoice
A13: TXN-000010 | B13: 46073 | C13: Income | D13: Axis Savings | E13: Income Category | F13: Freelance Income | G13: Freelance Income | H13: Freelance Gigs | I13: 15000 | J13: UPI | K13: Completed | L13: Freelance invoice
... A28: TXN-000025 | B28: 46273 | C28: Income | D28: HDFC Salary | E28: Income Category | F28: Cashback Income | G28: Cashback Income | H28: HDFC Cashback | I28: 490 | J28: Credit Card | K28: Completed | L28: Card cashback
A29: TXN-000026 | B29: 46023 | C29: Expense | D29: HDFC Salary | E29: Expense Category | F29: Rent | G29: Rent | I29: 18000 | J29: Bank Transfer | K29: Completed | L29: Rent
A30: TXN-000027 | B30: 46029 | C30: Expense | D30: HDFC Salary | E30: Expense Category | F30: Utilities | G30: Utilities | I30: 999 | J30: UPI | K30: Completed | L30: Internet
A31: TXN-000028 | B31: 46027 | C31: Expense | D31: SBI Savings | E31: Asset | F31: Mutual Fund | G31: SIP | I31: 10000 | J31: Bank Transfer | K31: Completed | L31: Monthly SIP
A32: TXN-000029 | B32: 46027 | C32: Expense | D32: HDFC Salary | E32: Liability | F32: Personal Loan | G32: EMI | I32: 8500 | J32: Bank Transfer | K32: Completed | L32: Personal loan EMI
A33: TXN-000030 | B33: 46054 | C33: Expense | D33: HDFC Salary | E33: Expense Category | F33: Rent | G33: Rent | I33: 18000 | J33: Bank Transfer | K33: Completed | L33: Rent
A34: TXN-000031 | B34: 46060 | C34: Expense | D34: HDFC Salary | E34: Expense Category | F34: Utilities | G34: Utilities | I34: 999 | J34: UPI | K34: Completed | L34: Internet
A35: TXN-000032 | B35: 46058 | C35: Expense | D35: SBI Savings | E35: Asset | F35: Mutual Fund | G35: SIP | I35: 10000 | J35: Bank Transfer | K35: Completed | L35: Monthly SIP
A36: TXN-000033 | B36: 46058 | C36: Expense | D36: HDFC Salary | E36: Liability | F36: Personal Loan | G36: EMI | I36: 8500 | J36: Bank Transfer | K36: Completed | L36: Personal loan EMI
A37: TXN-000034 | B37: 46082 | C37: Expense | D37: HDFC Salary | E37: Expense Category | F37: Rent | G37: Rent | I37: 18000 | J37: Bank Transfer | K37: Completed | L37: Rent
A38: TXN-000035 | B38: 46088 | C38: Expense | D38: HDFC Salary | E38: Expense Category | F38: Utilities | G38: Utilities | I38: 999 | J38: UPI | K38: Completed | L38: Internet
A39: TXN-000036 | B39: 46086 | C39: Expense | D39: SBI Savings | E39: Asset | F39: Mutual Fund | G39: SIP | I39: 10000 | J39: Bank Transfer | K39: Completed | L39: Monthly SIP
A40: TXN-000037 | B40: 46086 | C40: Expense | D40: HDFC Salary | E40: Liability | F40: Personal Loan | G40: EMI | I40: 8500 | J40: Bank Transfer | K40: Completed | L40: Personal loan EMI
... A107: TXN-000104 | B107: 46274 | C107: Expense | D107: Cash Wallet | E107: Expense Category | F107: Transport | G107: Transport | I107: 175 | J107: Cash | K107: Completed | L107: Local transport
A108: TXN-000105 | B108: 46055 | C108: Transfer | D108: HDFC Salary | E108: Account | F108: SBI Savings | I108: 15000 | J108: Bank Transfer | K108: Completed | L108: Sweep to SBI
A109: TXN-000106 | B109: 46115 | C109: Transfer | D109: HDFC Salary | E109: Account | F109: SBI Savings | I109: 10000 | J109: Bank Transfer | K109: Completed | L109: Sweep to SBI
A110: TXN-000107 | B110: 46177 | C110: Transfer | D110: SBI Savings | E110: Account | F110: HDFC Salary | I110: 8000 | J110: Bank Transfer | K110: Completed | L110: Inbound to HDFC
A111: TXN-000108 | B111: 46240 | C111: Transfer | D111: HDFC Salary | E111: Account | F111: Axis Savings | I111: 7000 | J111: Bank Transfer | K111: Completed | L111: Trip fund
A112: TXN-000109 | B112: 46033 | C112: Transfer | D112: HDFC Salary | E112: Account | F112: Cash Wallet | I112: 4000 | J112: Cash | K112: Completed | L112: Cash withdrawal
A113: TXN-000110 | B113: 46095 | C113: Transfer | D113: HDFC Salary | E113: Account | F113: Cash Wallet | I113: 3000 | J113: Cash | K113: Completed | L113: Cash withdrawal
A114: TXN-000111 | B114: 46158 | C114: Transfer | D114: HDFC Salary | E114: Account | F114: Cash Wallet | I114: 2500 | J114: Cash | K114: Completed | L114: Cash withdrawal
A115: TXN-000112 | B115: 46221 | C115: Transfer | D115: HDFC Salary | E115: Account | F115: Cash Wallet | I115: 3500 | J115: Cash | K115: Completed | L115: Cash withdrawal
A116: TXN-000113 | B116: 46031 | C116: Expense | D116: ICICI Credit Card | E116: Expense Category | F116: Shopping | G116: Shopping | I116: 2400 | J116: Credit Card | K116: Completed | L116: Credit card spend
A117: TXN-000114 | B117: 46086 | C117: Expense | D117: ICICI Credit Card | E117: Expense Category | F117: Shopping | G117: Shopping | I117: 3200 | J117: Credit Card | K117: Completed | L117: Credit card spend
A118: TXN-000115 | B118: 46153 | C118: Expense | D118: ICICI Credit Card | E118: Expense Category | F118: Shopping | G118: Shopping | I118: 4100 | J118: Credit Card | K118: Completed | L118: Credit card spend
A119: TXN-000116 | B119: 46210 | C119: Expense | D119: ICICI Credit Card | E119: Expense Category | F119: Shopping | G119: Shopping | I119: 2200 | J119: Credit Card | K119: Completed | L119: Credit card spend
A120: TXN-000117 | B120: 46268 | C120: Expense | D120: ICICI Credit Card | E120: Expense Category | F120: Shopping | G120: Shopping | I120: 2800 | J120: Credit Card | K120: Completed | L120: Credit card spend
A121: TXN-000118 | B121: 46047 | C121: Transfer | D121: HDFC Salary | E121: Account | F121: ICICI Credit Card | I121: 5000 | J121: Net Banking | K121: Completed | L121: Credit card payment
A122: TXN-000119 | B122: 46167 | C122: Transfer | D122: HDFC Salary | E122: Account | F122: ICICI Credit Card | I122: 5500 | J122: Net Banking | K122: Completed | L122: Credit card payment
A123: TXN-000120 | B123: 46275 | C123: Transfer | D123: HDFC Salary | E123: Account | F123: ICICI Credit Card | I123: 4000 | J123: Net Banking | K123: Completed | L123: Credit card payment
A124: TXN-000121 | B124: 46063 | C124: Expense | D124: HDFC Salary | E124: Goal | F124: Emergency Fund | G124: SIP | I124: 8000 | J124: Bank Transfer | K124: Completed | L124: Goal contribution
A125: TXN-000122 | B125: 46122 | C125: Expense | D125: HDFC Salary | E125: Goal | F125: Emergency Fund | G125: SIP | I125: 8000 | J125: Bank Transfer | K125: Completed | L125: Goal contribution
A126: TXN-000123 | B126: 46183 | C126: Expense | D126: SBI Savings | E126: Goal | F126: Home Fund | G126: SIP | I126: 15000 | J126: Bank Transfer | K126: Completed | L126: Goal contribution
A127: TXN-000124 | B127: 46244 | C127: Expense | D127: HDFC Salary | E127: Goal | F127: Bike Down Payment | G127: SIP | I127: 5000 | J127: UPI | K127: Completed | L127: Goal contribution
A128: TXN-000125 | B128: 46102 | C128: Expense | D128: Axis Savings | E128: Goal | F128: Goa Trip | G128: SIP | I128: 4000 | J128: UPI | K128: Completed | L128: Goal contribution
A129: TXN-000126 | B129: 46224 | C129: Expense | D129: HDFC Salary | E129: Goal | F129: iPhone | G129: Shopping | I129: 5000 | J129: UPI | K129: Completed | L129: Goal contribution
A130: TXN-000127 | B130: 46174 | C130: Expense | D130: HDFC Salary | E130: Asset | F130: Laptop | G130: Shopping | I130: 72000 | J130: Bank Transfer | K130: Completed | L130: Asset purchase laptop (historical matching)
A131: TXN-000128 | B131: 46277 | C131: Expense | D131: HDFC Salary | E131: Expense Category | F131: Groceries | G131: Groceries | I131: 19 | J131: UPI | K131: Completed | L131: Small amount
A132: TXN-000129 | B132: 46264 | C132: Expense | D132: Cash Wallet | E132: Expense Category | F132: Transport | G132: Transport | I132: 25 | J132: Cash | K132: Completed | L132: Small amount
A133: TXN-000130 | B133: 46143 | C133: Income | D133: HDFC Salary | E133: Income Category | F133: Salary Income | G133: Salary Income | H133: Acme Payroll | I133: 50000 | J133: Bank Transfer | K133: Reconciled | L133: Large bonus reconciled
A134: TXN-000131 | B134: 46277 | C134: Expense | D134: HDFC Salary | E134: Expense Category | F134: Dining | G134: Dining | I134: 640 | J134: UPI | K134: Completed | L134: Same-day as groceries 19
A135: TXN-000132 | B135: 46127 | C135: Expense | D135: HDFC Salary | E135: Expense Category | F135: Healthcare | G135: Healthcare | I135: 2300 | J135: UPI | K135: Completed | L135: Clinic
A136: TXN-000133 | B136: 46236 | C136: Expense | D136: HDFC Salary | E136: Expense Category | F136: Healthcare | G136: Healthcare | I136: 890 | J136: UPI | K136: Completed | L136: Pharmacy
A137: TXN-000134 | B137: 46290 | C137: Expense | D137: HDFC Salary | E137: Expense Category | F137: Shopping | G137: Shopping | I137: 2500 | J137: UPI | K137: Pending | L137: Pending latest after as-of
A138: TXN-000135 | B138: 46287 | C138: Expense | D138: HDFC Salary | E138: Expense Category | F138: Dining | G138: Dining | I138: 900 | J138: UPI | K138: Cancelled | L138: Cancelled latest after as-of
A139: TXN-000136 | B139: 46276 | C139: Income | D139: Axis Savings | E139: Income Category | F139: Freelance Income | G139: Freelance Income | H139: Freelance Gigs | I139: 1 | J139: UPI | K139: Reconciled | L139: Reconciled latest near as-of
A140: TXN-000137 | B140: 46310 | C140: Income | D140: HDFC Salary | E140: Income Category | F140: Salary Income | G140: Salary Income | H140: Acme Payroll | I140: 85000 | J140: Bank Transfer | K140: Pending | L140: Future dated pending salary
A141: TXN-000138 | B141: 46273 | C141: Transfer | D141: SBI Savings | E141: Account | F141: HDFC Salary | I141: 2500 | J141: UPI | K141: Completed | L141: Inbound transfer near as-of
A142: TXN-000139 | B142: 46274 | C142: Transfer | D142: HDFC Salary | E142: Account | F142: SBI Savings | I142: 2500 | J142: UPI | K142: Completed | L142: Outbound transfer near as-of

Sheet Goals
A1: Goal ID | B1: Goal Name | C1: Goal Category | D1: Goal Account | E1: Target Amount | F1: Current Saved Amount | G1: Remaining Amount | H1: Monthly Contribution Target | I1: Target Date | J1: Priority | K1: Goal Status | L1: Notes
G2: =MAX(0,tblGoals[[#This Row],[Target Amount]]-tblGoals[[#This Row],[Current Saved Amount]])
G3: =MAX(0,tblGoals[[#This Row],[Target Amount]]-tblGoals[[#This Row],[Current Saved Amount]])
G4: =MAX(0,tblGoals[[#This Row],[Target Amount]]-tblGoals[[#This Row],[Current Saved Amount]])
G5: =MAX(0,tblGoals[[#This Row],[Target Amount]]-tblGoals[[#This Row],[Current Saved Amount]])
G6: =MAX(0,tblGoals[[#This Row],[Target Amount]]-tblGoals[[#This Row],[Current Saved Amount]])
G7: =MAX(0,tblGoals[[#This Row],[Target Amount]]-tblGoals[[#This Row],[Current Saved Amount]])
G8: =MAX(0,tblGoals[[#This Row],[Target Amount]]-tblGoals[[#This Row],[Current Saved Amount]])
G9: =MAX(0,tblGoals[[#This Row],[Target Amount]]-tblGoals[[#This Row],[Current Saved Amount]])
G10: =MAX(0,tblGoals[[#This Row],[Target Amount]]-tblGoals[[#This Row],[Current Saved Amount]])
G11: =MAX(0,tblGoals[[#This Row],[Target Amount]]-tblGoals[[#This Row],[Current Saved Amount]])
G12: =MAX(0,tblGoals[[#This Row],[Target Amount]]-tblGoals[[#This Row],[Current Saved Amount]])
G13: =MAX(0,tblGoals[[#This Row],[Target Amount]]-tblGoals[[#This Row],[Current Saved Amount]])
... G200: =MAX(0,tblGoals[[#This Row],[Target Amount]]-tblGoals[[#This Row],[Current Saved Amount]])

Sheet Helpers
A1: Currency Code | B1: Currency Name | C1: Symbol | AG1: Asset Type | AH1: Liability Type | AI1: Income Type
A2: INR | AG2: Mutual Fund | AH2: Home Loan | AI2: Salary
A3: USD | AG3: Stock | AH3: Personal Loan | AI3: Freelance
A4: EUR | AG4: ETF | AH4: Education Loan | AI4: Bonus
A5: GBP | AG5: Gold ETF | AH5: Vehicle Loan | AI5: Rental Income
A6: AED | AG6: Bond | AH6: Gold Loan | AI6: Interest
AG7: SIP | AH7: Credit Card | AI7: Cashback
AG8: Fixed Deposit | AH8: Buy Now Pay Later | AI8: Refund
A9: Payment Method | AG9: PPF | AH9: Family Loan | AI9: Business Income
A10: Bank Transfer | AG10: EPF | AH10: Business Loan | AI10: Investment
A11: Cash | AG11: NPS | AH11: Other Liability
A12: UPI | AG12: Gold Jewellery
A13: Debit Card | AG13: Gold Coin
A14: Credit Card | AG14: Vehicle
A15: Wallet | AG15: Electronics
A16: Net Banking | AG16: Furniture
A17: Other | AG17: Watch
AG18: Other Physical Asset
AG19: Residential Property
A20: Transaction Type | AG20: Commercial Property
A21: Income | AG21: Land
A22: Expense | AG22: Plot
A23: Transfer | AG23: Emergency Cash
A24: Adjustment | AG24: Foreign Currency
AG25: Cash Reserve
A27: Destination Type
A28: Expense Category
A29: Income Category
A30: Account
A31: Goal
A32: Liability
A33: Asset
A34: Other
A37: Frequency
A38: Monthly
A39: Quarterly
A40: Half-Yearly
... A107: FinanceOS Default
A110: Month Number | B110: Month Name | C110: Short Name
A111: 1 | B111: January | C111: Jan
A112: 2 | B112: February | C112: Feb
A113: 3 | B113: March | C113: Mar
A114: 4 | B114: April | C114: Apr
A115: 5 | B115: May | C115: May
A116: 6 | B116: June | C116: Jun
A117: 7 | B117: July | C117: Jul
A118: 8 | B118: August | C118: Aug
A119: 9 | B119: September | C119: Sep
A120: 10 | B120: October | C120: Oct
A121: 11 | B121: November | C121: Nov
A122: 12 | B122: December | C122: Dec
A125: Financial Year
A129: Validation Output Placeholders
A130: valExpenseCategories
A131: valIncomeCategories
A132: valActiveAccounts
A133: valActiveGoals
A134: valActiveAssets
A135: valActiveLiabilities
A136: valIncomeSources
A137: valPaymentMethods
A138: valFrequency
A139: valPriority
... A148: valCommitmentStatus

Sheet Business Engine
A1: As-Of Date | B1: 46277
A4: Total Active Account Balance | B4: =IFERROR(SUMPRODUCT((tblAccounts[Status]="Active")*(tblAccounts[Opening Balance]))+SUMPRODUCT((tblTransactions[Transaction Type]="Income")*((tblTransactions[Transaction Status]="Completed")+(tblTransactions[Transaction Status]="Reconciled"))*(tblTransactions[Amount])*(COUNTIFS(tblAccounts[Account Name],tblTransactions[Source Account],tblAccounts[Status],"Active")>0))-SUMPRODUCT((tblTransactions[Transaction Type]="Expense")*((tblTransactions[Transaction Status]="Completed")+(tblTransactions[Transaction Status]="Reconciled"))*(tblTransactions[Amount])*(COUNTIFS(tblAccounts[Account Name],tblTransactions[Source Account],tblAccounts[Status],"Active")>0))+SUMPRODUCT((tblTransactions[Transaction Type]="Transfer")*(tblTransactions[Destination Type]="Account")*((tblTransactions[Transaction Status]="Completed")+(tblTransactions[Transaction Status]="Reconciled"))*(tblTransactions[Amount])*(COUNTIFS(tblAccounts[Account Name],tblTransactions[Destination Name],tblAccounts[Status],"Active")>0))-SUMPRODUCT((tblTransactions[Transaction Type]="Transfer")*((tblTransactions[Transaction Status]="Completed")+(tblTransactions[Transaction Status]="Reconciled"))*(tblTransactions[Amount])*(COUNTIFS(tblAccounts[Account Name],tblTransactions[Source Account],tblAccounts[Status],"Active")>0))+SUMPRODUCT((tblTransactions[Transaction Type]="Adjustment")*((tblTransactions[Transaction Status]="Completed")+(tblTransactions[Transaction Status]="Reconciled"))*(tblTransactions[Amount])*(COUNTIFS(tblAccounts[Account Name],tblTransactions[Source Account],tblAccounts[Status],"Active")>0)),0)
A5: Number of Active Accounts | B5: =COUNTIFS(tblAccounts[Status],"Active")
A6: Cash Accounts Total | B6: =IFERROR(SUMPRODUCT((tblAccounts[Status]="Active")*(tblAccounts[Account Type]="Cash")*(tblAccounts[Opening Balance]))+SUMPRODUCT((tblTransactions[Transaction Type]="Income")*((tblTransactions[Transaction Status]="Completed")+(tblTransactions[Transaction Status]="Reconciled"))*(tblTransactions[Amount])*(COUNTIFS(tblAccounts[Account Name],tblTransactions[Source Account],tblAccounts[Status],"Active",tblAccounts[Account Type],"Cash")>0))-SUMPRODUCT((tblTransactions[Transaction Type]="Expense")*((tblTransactions[Transaction Status]="Completed")+(tblTransactions[Transaction Status]="Reconciled"))*(tblTransactions[Amount])*(COUNTIFS(tblAccounts[Account Name],tblTransactions[Source Account],tblAccounts[Status],"Active",tblAccounts[Account Type],"Cash")>0))+SUMPRODUCT((tblTransactions[Transaction Type]="Transfer")*(tblTransactions[Destination Type]="Account")*((tblTransactions[Transaction Status]="Completed")+(tblTransactions[Transaction Status]="Reconciled"))*(tblTransactions[Amount])*(COUNTIFS(tblAccounts[Account Name],tblTransactions[Destination Name],tblAccounts[Status],"Active",tblAccounts[Account Type],"Cash")>0))-SUMPRODUCT((tblTransactions[Transaction Type]="Transfer")*((tblTransactions[Transaction Status]="Completed")+(tblTransactions[Transaction Status]="Reconciled"))*(tblTransactions[Amount])*(COUNTIFS(tblAccounts[Account Name],tblTransactions[Source Account],tblAccounts[Status],"Active",tblAccounts[Account Type],"Cash")>0))+SUMPRODUCT((tblTransactions[Transaction Type]="Adjustment")*((tblTransactions[Transaction Status]="Completed")+(tblTransactions[Transaction Status]="Reconciled"))*(tblTransactions[Amount])*(COUNTIFS(tblAccounts[Account Name],tblTransactions[Source Account],tblAccounts[Status],"Active",tblAccounts[Account Type],"Cash")>0)),0)
A7: Savings Accounts Total | B7: =IFERROR(SUMPRODUCT((tblAccounts[Status]="Active")*(tblAccounts[Account Type]="Savings Bank")*(tblAccounts[Opening Balance]))+SUMPRODUCT((tblTransactions[Transaction Type]="Income")*((tblTransactions[Transaction Status]="Completed")+(tblTransactions[Transaction Status]="Reconciled"))*(tblTransactions[Amount])*(COUNTIFS(tblAccounts[Account Name],tblTransactions[Source Account],tblAccounts[Status],"Active",tblAccounts[Account Type],"Savings Bank")>0))-SUMPRODUCT((tblTransactions[Transaction Type]="Expense")*((tblTransactions[Transaction Status]="Completed")+(tblTransactions[Transaction Status]="Reconciled"))*(tblTransactions[Amount])*(COUNTIFS(tblAccounts[Account Name],tblTransactions[Source Account],tblAccounts[Status],"Active",tblAccounts[Account Type],"Savings Bank")>0))+SUMPRODUCT((tblTransactions[Transaction Type]="Transfer")*(tblTransactions[Destination Type]="Account")*((tblTransactions[Transaction Status]="Completed")+(tblTransactions[Transaction Status]="Reconciled"))*(tblTransactions[Amount])*(COUNTIFS(tblAccounts[Account Name],tblTransactions[Destination Name],tblAccounts[Status],"Active",tblAccounts[Account Type],"Savings Bank")>0))-SUMPRODUCT((tblTransactions[Transaction Type]="Transfer")*((tblTransactions[Transaction Status]="Completed")+(tblTransactions[Transaction Status]="Reconciled"))*(tblTransactions[Amount])*(COUNTIFS(tblAccounts[Account Name],tblTransactions[Source Account],tblAccounts[Status],"Active",tblAccounts[Account Type],"Savings Bank")>0))+SUMPRODUCT((tblTransactions[Transaction Type]="Adjustment")*((tblTransactions[Transaction Status]="Completed")+(tblTransactions[Transaction Status]="Reconciled"))*(tblTransactions[Amount])*(COUNTIFS(tblAccounts[Account Name],tblTransactions[Source Account],tblAccounts[Status],"Active",tblAccounts[Account Type],"Savings Bank")>0)),0)
A8: Investment Accounts Total | B8: =IFERROR(SUMPRODUCT((tblAccounts[Status]="Active")*(tblAccounts[Account Type]="Investment Account")*(tblAccounts[Opening Balance]))+SUMPRODUCT((tblTransactions[Transaction Type]="Income")*((tblTransactions[Transaction Status]="Completed")+(tblTransactions[Transaction Status]="Reconciled"))*(tblTransactions[Amount])*(COUNTIFS(tblAccounts[Account Name],tblTransactions[Source Account],tblAccounts[Status],"Active",tblAccounts[Account Type],"Investment Account")>0))-SUMPRODUCT((tblTransactions[Transaction Type]="Expense")*((tblTransactions[Transaction Status]="Completed")+(tblTransactions[Transaction Status]="Reconciled"))*(tblTransactions[Amount])*(COUNTIFS(tblAccounts[Account Name],tblTransactions[Source Account],tblAccounts[Status],"Active",tblAccounts[Account Type],"Investment Account")>0))+SUMPRODUCT((tblTransactions[Transaction Type]="Transfer")*(tblTransactions[Destination Type]="Account")*((tblTransactions[Transaction Status]="Completed")+(tblTransactions[Transaction Status]="Reconciled"))*(tblTransactions[Amount])*(COUNTIFS(tblAccounts[Account Name],tblTransactions[Destination Name],tblAccounts[Status],"Active",tblAccounts[Account Type],"Investment Account")>0))-SUMPRODUCT((tblTransactions[Transaction Type]="Transfer")*((tblTransactions[Transaction Status]="Completed")+(tblTransactions[Transaction Status]="Reconciled"))*(tblTransactions[Amount])*(COUNTIFS(tblAccounts[Account Name],tblTransactions[Source Account],tblAccounts[Status],"Active",tblAccounts[Account Type],"Investment Account")>0))+SUMPRODUCT((tblTransactions[Transaction Type]="Adjustment")*((tblTransactions[Transaction Status]="Completed")+(tblTransactions[Transaction Status]="Reconciled"))*(tblTransactions[Amount])*(COUNTIFS(tblAccounts[Account Name],tblTransactions[Source Account],tblAccounts[Status],"Active",tblAccounts[Account Type],"Investment Account")>0)),0)
A9: Credit Accounts Total | B9: =IFERROR(SUMPRODUCT((tblAccounts[Status]="Active")*(tblAccounts[Account Type]="Credit Card")*(tblAccounts[Opening Balance]))+SUMPRODUCT((tblTransactions[Transaction Type]="Income")*((tblTransactions[Transaction Status]="Completed")+(tblTransactions[Transaction Status]="Reconciled"))*(tblTransactions[Amount])*(COUNTIFS(tblAccounts[Account Name],tblTransactions[Source Account],tblAccounts[Status],"Active",tblAccounts[Account Type],"Credit Card")>0))-SUMPRODUCT((tblTransactions[Transaction Type]="Expense")*((tblTransactions[Transaction Status]="Completed")+(tblTransactions[Transaction Status]="Reconciled"))*(tblTransactions[Amount])*(COUNTIFS(tblAccounts[Account Name],tblTransactions[Source Account],tblAccounts[Status],"Active",tblAccounts[Account Type],"Credit Card")>0))+SUMPRODUCT((tblTransactions[Transaction Type]="Transfer")*(tblTransactions[Destination Type]="Account")*((tblTransactions[Transaction Status]="Completed")+(tblTransactions[Transaction Status]="Reconciled"))*(tblTransactions[Amount])*(COUNTIFS(tblAccounts[Account Name],tblTransactions[Destination Name],tblAccounts[Status],"Active",tblAccounts[Account Type],"Credit Card")>0))-SUMPRODUCT((tblTransactions[Transaction Type]="Transfer")*((tblTransactions[Transaction Status]="Completed")+(tblTransactions[Transaction Status]="Reconciled"))*(tblTransactions[Amount])*(COUNTIFS(tblAccounts[Account Name],tblTransactions[Source Account],tblAccounts[Status],"Active",tblAccounts[Account Type],"Credit Card")>0))+SUMPRODUCT((tblTransactions[Transaction Type]="Adjustment")*((tblTransactions[Transaction Status]="Completed")+(tblTransactions[Transaction Status]="Reconciled"))*(tblTransactions[Amount])*(COUNTIFS(tblAccounts[Account Name],tblTransactions[Source Account],tblAccounts[Status],"Active",tblAccounts[Account Type],"Credit Card")>0)),0)
A11: SECTION 2 — Income Summary
A12: Monthly Salary Income | B12: =IFERROR(SUMPRODUCT((tblTransactions[Transaction Type]="Income")*(tblTransactions[Transaction Date]>=DATE(YEAR($B$1),MONTH($B$1),1))*(tblTransactions[Transaction Date]<DATE(YEAR($B$1),MONTH($B$1)+1,1))*(tblTransactions[Amount])*(IFERROR(INDEX(tblIncomeSources[Income Category],MATCH(tblTransactions[Income Source],tblIncomeSources[Income Source Name],0)),"")="Salary")),0)
A13: Monthly Business Income | B13: =IFERROR(SUMPRODUCT((tblTransactions[Transaction Type]="Income")*(tblTransactions[Transaction Date]>=DATE(YEAR($B$1),MONTH($B$1),1))*(tblTransactions[Transaction Date]<DATE(YEAR($B$1),MONTH($B$1)+1,1))*(tblTransactions[Amount])*(IFERROR(INDEX(tblIncomeSources[Income Category],MATCH(tblTransactions[Income Source],tblIncomeSources[Income Source Name],0)),"")="Business Income")),0)
A14: Monthly Freelance Income | B14: =IFERROR(SUMPRODUCT((tblTransactions[Transaction Type]="Income")*(tblTransactions[Transaction Date]>=DATE(YEAR($B$1),MONTH($B$1),1))*(tblTransactions[Transaction Date]<DATE(YEAR($B$1),MONTH($B$1)+1,1))*(tblTransactions[Amount])*(IFERROR(INDEX(tblIncomeSources[Income Category],MATCH(tblTransactions[Income Source],tblIncomeSources[Income Source Name],0)),"")="Freelance")),0)
A15: Monthly Investment Income | B15: =IFERROR(SUMPRODUCT((tblTransactions[Transaction Type]="Income")*(tblTransactions[Transaction Date]>=DATE(YEAR($B$1),MONTH($B$1),1))*(tblTransactions[Transaction Date]<DATE(YEAR($B$1),MONTH($B$1)+1,1))*(tblTransactions[Amount])*(IFERROR(INDEX(tblIncomeSources[Income Category],MATCH(tblTransactions[Income Source],tblIncomeSources[Income Source Name],0)),"")="Investment")),0)
A16: Total Monthly Income | B16: =IFERROR(SUMIFS(tblTransactions[Amount],tblTransactions[Transaction Type],"Income",tblTransactions[Transaction Date],">="&DATE(YEAR($B$1),MONTH($B$1),1),tblTransactions[Transaction Date],"<"&DATE(YEAR($B$1),MONTH($B$1)+1,1)),0)
A17: Monthly Other Income | B17: =MAX(0,$B$16-($B$12+$B$13+$B$14+$B$15))
A18: Total Annual Income | B18: =IFERROR(SUMIFS(tblTransactions[Amount],tblTransactions[Transaction Type],"Income",tblTransactions[Transaction Date],">="&DATE(YEAR($B$1),1,1),tblTransactions[Transaction Date],"<"&DATE(YEAR($B$1)+1,1,1)),0)
A19: Active Income Source Count | B19: =COUNTIFS(tblIncomeSources[Status],"Active")
A21: SECTION 3 — Expense Summary
A22: Current Month Expenses | B22: =IFERROR(SUMIFS(tblTransactions[Amount],tblTransactions[Transaction Type],"Expense",tblTransactions[Transaction Date],">="&DATE(YEAR($B$1),MONTH($B$1),1),tblTransactions[Transaction Date],"<"&DATE(YEAR($B$1),MONTH($B$1)+1,1)),0)
A23: Previous Month Expenses | B23: =IFERROR(SUMIFS(tblTransactions[Amount],tblTransactions[Transaction Type],"Expense",tblTransactions[Transaction Date],">="&DATE(YEAR($B$1),MONTH($B$1)-1,1),tblTransactions[Transaction Date],"<"&DATE(YEAR($B$1),MONTH($B$1),1)),0)
A24: Year-to-Date Expenses | B24: =IFERROR(SUMIFS(tblTransactions[Amount],tblTransactions[Transaction Type],"Expense",tblTransactions[Transaction Date],">="&DATE(YEAR($B$1),1,1),tblTransactions[Transaction Date],"<="&$B$1),0)
A25: Expense Transaction Count | B25: =COUNTIFS(tblTransactions[Transaction Type],"Expense",tblTransactions[Transaction Date],">="&DATE(YEAR($B$1),MONTH($B$1),1),tblTransactions[Transaction Date],"<"&DATE(YEAR($B$1),MONTH($B$1)+1,1))
A27: SECTION 4 — Savings Summary
A28: Current Month Income | B28: =$B$16
A29: Current Month Savings | B29: =$B$28-$B$22
A30: Savings Rate (%) | B30: =IFERROR($B$29/$B$28,0)
A31: Average Monthly Savings | B31: =IFERROR(($B$18-$B$24)/MAX(1,MONTH($B$1)),0)
A33: SECTION 5 — Asset Summary
A34: Total Purchase Value | B34: =IFERROR(SUMIFS(tblAssets[Purchase Value],tblAssets[Status],"Active"),0)
A35: Total Current Value | B35: =IFERROR(SUMIFS(tblAssets[Current Value],tblAssets[Status],"Active"),0)
A36: Total Appreciation Amount | B36: =IFERROR(SUMIFS(tblAssets[Appreciation Amount],tblAssets[Status],"Active"),0)
A37: Weighted Appreciation % | B37: =IFERROR($B$36/$B$34,0)
A38: Active Asset Count | B38: =COUNTIFS(tblAssets[Status],"Active")
A40: SECTION 6 — Liability Summary
A41: Total Original Liability | B41: =IFERROR(SUMIFS(tblLiabilities[Original Amount],tblLiabilities[Status],"Active"),0)
A42: Total Outstanding Balance | B42: =IFERROR(SUMIFS(tblLiabilities[Outstanding Balance],tblLiabilities[Status],"Active"),0)
A43: Total Monthly EMI | B43: =IFERROR(SUMPRODUCT((tblLiabilities[Status]="Active")*(tblLiabilities[EMI Amount])*((tblLiabilities[EMI Frequency]="Monthly")*1+(tblLiabilities[EMI Frequency]="Quarterly")*(1/3)+(tblLiabilities[EMI Frequency]="Half-Yearly")*(1/6)+(tblLiabilities[EMI Frequency]="Yearly")*(1/12))),0)
A44: Weighted Interest Rate | B44: =IFERROR(SUMPRODUCT((tblLiabilities[Status]="Active")*(tblLiabilities[Outstanding Balance])*(tblLiabilities[Interest Rate]))/$B$42,0)
A45: Active Liability Count | B45: =COUNTIFS(tblLiabilities[Status],"Active")
A47: SECTION 7 — Net Worth
A48: Net Worth | B48: =$B$4+$B$35-$B$42
A49: Liquid Net Worth | B49: =0
A50: Invested Net Worth | B50: =$B$35
A52: SECTION 8 — Goal Summary
A53: Total Goal Target Amount | B53: =IFERROR(SUMIFS(tblGoals[Target Amount],tblGoals[Goal Status],"Active")+SUMIFS(tblGoals[Target Amount],tblGoals[Goal Status],"Completed"),0)
A54: Total Saved Toward Goals | B54: =IFERROR(SUMIFS(tblGoals[Current Saved Amount],tblGoals[Goal Status],"Active")+SUMIFS(tblGoals[Current Saved Amount],tblGoals[Goal Status],"Completed"),0)
A55: Remaining Goal Amount | B55: =IFERROR(SUMIFS(tblGoals[Remaining Amount],tblGoals[Goal Status],"Active"),0)
A56: Active Goal Count | B56: =COUNTIFS(tblGoals[Goal Status],"Active")
A57: Completed Goal Count | B57: =COUNTIFS(tblGoals[Goal Status],"Completed")
A58: Goal Completion % | B58: =IFERROR($B$54/$B$53,0)
A60: SECTION 9 — Monthly Financial Health
A61: Income | B61: =$B$16
A62: Expenses | B62: =$B$22
A63: Savings | B63: =$B$29
A64: Savings Rate | B64: =$B$30
A65: Net Worth | B65: =$B$48
A66: EMI Ratio | B66: =IFERROR($B$43/$B$16,0)
A67: Asset Allocation | B67: =IFERROR($B$35/$B$48,0)
A68: Debt Ratio | B68: =IFERROR($B$42/($B$42+$B$35),0)

Sheet Analysis Engine
A1: Analysis Engine | Z1: CMStart | AA1: =DATE(YEAR('Business Engine'!$B$1),MONTH('Business Engine'!$B$1),1)
A2: As-Of Date | B2: ='Business Engine'!$B$1 | Z2: NMStart | AA2: =DATE(YEAR('Business Engine'!$B$1),MONTH('Business Engine'!$B$1)+1,1)
Z3: PMStart | AA3: =DATE(YEAR('Business Engine'!$B$1),MONTH('Business Engine'!$B$1)-1,1)
A4: SECTION 1 â€” Monthly Income Summary | Z4: YearStart | AA4: =DATE(YEAR('Business Engine'!$B$1),1,1)
A5: Metric | B5: Current Month | C5: Previous Month | D5: YTD (through As-Of) | Z5: AsOf | AA5: ='Business Engine'!$B$1
A6: Total Income | B6: ='Business Engine'!$B$16 | C6: =IFERROR(SUMIFS(tblTransactions[Amount],tblTransactions[Transaction Type],"Income",tblTransactions[Transaction Date],">="&$AA$3,tblTransactions[Transaction Date],"<"&$AA$1),0) | D6: =IFERROR(SUMIFS(tblTransactions[Amount],tblTransactions[Transaction Type],"Income",tblTransactions[Transaction Date],">="&$AA$4,tblTransactions[Transaction Date],"<="&$AA$5),0) | Z6: NextYear | AA6: =DATE(YEAR('Business Engine'!$B$1)+1,1,1)
A7: Salary | B7: ='Business Engine'!$B$12 | C7: =IFERROR(SUMPRODUCT((tblTransactions[Transaction Type]="Income")*(tblTransactions[Transaction Date]>=$AA$3)*(tblTransactions[Transaction Date]<$AA$1)*(tblTransactions[Amount])*(IFERROR(INDEX(tblIncomeSources[Income Category],MATCH(tblTransactions[Income Source],tblIncomeSources[Income Source Name],0)),"")="Salary")),0) | D7: =IFERROR(SUMPRODUCT((tblTransactions[Transaction Type]="Income")*(tblTransactions[Transaction Date]>=$AA$4)*(tblTransactions[Transaction Date]<=$AA$5)*(tblTransactions[Amount])*(IFERROR(INDEX(tblIncomeSources[Income Category],MATCH(tblTransactions[Income Source],tblIncomeSources[Income Source Name],0)),"")="Salary")),0)
A8: Business Income | B8: ='Business Engine'!$B$13 | C8: =IFERROR(SUMPRODUCT((tblTransactions[Transaction Type]="Income")*(tblTransactions[Transaction Date]>=$AA$3)*(tblTransactions[Transaction Date]<$AA$1)*(tblTransactions[Amount])*(IFERROR(INDEX(tblIncomeSources[Income Category],MATCH(tblTransactions[Income Source],tblIncomeSources[Income Source Name],0)),"")="Business Income")),0) | D8: =IFERROR(SUMPRODUCT((tblTransactions[Transaction Type]="Income")*(tblTransactions[Transaction Date]>=$AA$4)*(tblTransactions[Transaction Date]<=$AA$5)*(tblTransactions[Amount])*(IFERROR(INDEX(tblIncomeSources[Income Category],MATCH(tblTransactions[Income Source],tblIncomeSources[Income Source Name],0)),"")="Business Income")),0)
A9: Freelance | B9: ='Business Engine'!$B$14 | C9: =IFERROR(SUMPRODUCT((tblTransactions[Transaction Type]="Income")*(tblTransactions[Transaction Date]>=$AA$3)*(tblTransactions[Transaction Date]<$AA$1)*(tblTransactions[Amount])*(IFERROR(INDEX(tblIncomeSources[Income Category],MATCH(tblTransactions[Income Source],tblIncomeSources[Income Source Name],0)),"")="Freelance")),0) | D9: =IFERROR(SUMPRODUCT((tblTransactions[Transaction Type]="Income")*(tblTransactions[Transaction Date]>=$AA$4)*(tblTransactions[Transaction Date]<=$AA$5)*(tblTransactions[Amount])*(IFERROR(INDEX(tblIncomeSources[Income Category],MATCH(tblTransactions[Income Source],tblIncomeSources[Income Source Name],0)),"")="Freelance")),0)
A10: Investment | B10: ='Business Engine'!$B$15 | C10: =IFERROR(SUMPRODUCT((tblTransactions[Transaction Type]="Income")*(tblTransactions[Transaction Date]>=$AA$3)*(tblTransactions[Transaction Date]<$AA$1)*(tblTransactions[Amount])*(IFERROR(INDEX(tblIncomeSources[Income Category],MATCH(tblTransactions[Income Source],tblIncomeSources[Income Source Name],0)),"")="Investment")),0) | D10: =IFERROR(SUMPRODUCT((tblTransactions[Transaction Type]="Income")*(tblTransactions[Transaction Date]>=$AA$4)*(tblTransactions[Transaction Date]<=$AA$5)*(tblTransactions[Amount])*(IFERROR(INDEX(tblIncomeSources[Income Category],MATCH(tblTransactions[Income Source],tblIncomeSources[Income Source Name],0)),"")="Investment")),0)
A11: Other Income | B11: ='Business Engine'!$B$17 | C11: =IFERROR(MAX(0,$C$6-($C$7+$C$8+$C$9+$C$10)),0) | D11: =IFERROR(MAX(0,$D$6-($D$7+$D$8+$D$9+$D$10)),0)
A13: SECTION 2 â€” Monthly Expense Summary | B13: Current Month | C13: Previous Month | D13: YTD (through As-Of)
A14: Total Expenses | B14: ='Business Engine'!$B$22 | C14: =IFERROR(SUMIFS(tblTransactions[Amount],tblTransactions[Transaction Type],"Expense",tblTransactions[Transaction Date],">="&$AA$3,tblTransactions[Transaction Date],"<"&$AA$1),0) | D14: ='Business Engine'!$B$24
A16: Category | B16: Current Month | C16: Previous Month | D16: YTD | E16: Share of Current | F16: Rank
A17: =IFERROR(INDEX(tblCategories[Category Name],1),"") | B17: =IFERROR(SUMIFS(tblTransactions[Amount],tblTransactions[Transaction Type],"Expense",tblTransactions[Category],A17,tblTransactions[Transaction Date],">="&$AA$1,tblTransactions[Transaction Date],"<"&$AA$2),0) | C17: =IFERROR(SUMIFS(tblTransactions[Amount],tblTransactions[Transaction Type],"Expense",tblTransactions[Category],A17,tblTransactions[Transaction Date],">="&$AA$3,tblTransactions[Transaction Date],"<"&$AA$1),0) | D17: =IFERROR(SUMIFS(tblTransactions[Amount],tblTransactions[Transaction Type],"Expense",tblTransactions[Category],A17,tblTransactions[Transaction Date],">="&$AA$4,tblTransactions[Transaction Date],"<="&$AA$5),0) | E17: =IFERROR(B17/$B$14,0) | F17: =IF(A17="" ,"",1+COUNTIFS($B$17:$B$26,">"&B17))
A18: =IFERROR(INDEX(tblCategories[Category Name],2),"") | B18: =IFERROR(SUMIFS(tblTransactions[Amount],tblTransactions[Transaction Type],"Expense",tblTransactions[Category],A18,tblTransactions[Transaction Date],">="&$AA$1,tblTransactions[Transaction Date],"<"&$AA$2),0) | C18: =IFERROR(SUMIFS(tblTransactions[Amount],tblTransactions[Transaction Type],"Expense",tblTransactions[Category],A18,tblTransactions[Transaction Date],">="&$AA$3,tblTransactions[Transaction Date],"<"&$AA$1),0) | D18: =IFERROR(SUMIFS(tblTransactions[Amount],tblTransactions[Transaction Type],"Expense",tblTransactions[Category],A18,tblTransactions[Transaction Date],">="&$AA$4,tblTransactions[Transaction Date],"<="&$AA$5),0) | E18: =IFERROR(B18/$B$14,0) | F18: =IF(A18="" ,"",1+COUNTIFS($B$17:$B$26,">"&B18))
A19: =IFERROR(INDEX(tblCategories[Category Name],3),"") | B19: =IFERROR(SUMIFS(tblTransactions[Amount],tblTransactions[Transaction Type],"Expense",tblTransactions[Category],A19,tblTransactions[Transaction Date],">="&$AA$1,tblTransactions[Transaction Date],"<"&$AA$2),0) | C19: =IFERROR(SUMIFS(tblTransactions[Amount],tblTransactions[Transaction Type],"Expense",tblTransactions[Category],A19,tblTransactions[Transaction Date],">="&$AA$3,tblTransactions[Transaction Date],"<"&$AA$1),0) | D19: =IFERROR(SUMIFS(tblTransactions[Amount],tblTransactions[Transaction Type],"Expense",tblTransactions[Category],A19,tblTransactions[Transaction Date],">="&$AA$4,tblTransactions[Transaction Date],"<="&$AA$5),0) | E19: =IFERROR(B19/$B$14,0) | F19: =IF(A19="" ,"",1+COUNTIFS($B$17:$B$26,">"&B19))
A20: =IFERROR(INDEX(tblCategories[Category Name],4),"") | B20: =IFERROR(SUMIFS(tblTransactions[Amount],tblTransactions[Transaction Type],"Expense",tblTransactions[Category],A20,tblTransactions[Transaction Date],">="&$AA$1,tblTransactions[Transaction Date],"<"&$AA$2),0) | C20: =IFERROR(SUMIFS(tblTransactions[Amount],tblTransactions[Transaction Type],"Expense",tblTransactions[Category],A20,tblTransactions[Transaction Date],">="&$AA$3,tblTransactions[Transaction Date],"<"&$AA$1),0) | D20: =IFERROR(SUMIFS(tblTransactions[Amount],tblTransactions[Transaction Type],"Expense",tblTransactions[Category],A20,tblTransactions[Transaction Date],">="&$AA$4,tblTransactions[Transaction Date],"<="&$AA$5),0) | E20: =IFERROR(B20/$B$14,0) | F20: =IF(A20="" ,"",1+COUNTIFS($B$17:$B$26,">"&B20))
A21: =IFERROR(INDEX(tblCategories[Category Name],5),"") | B21: =IFERROR(SUMIFS(tblTransactions[Amount],tblTransactions[Transaction Type],"Expense",tblTransactions[Category],A21,tblTransactions[Transaction Date],">="&$AA$1,tblTransactions[Transaction Date],"<"&$AA$2),0) | C21: =IFERROR(SUMIFS(tblTransactions[Amount],tblTransactions[Transaction Type],"Expense",tblTransactions[Category],A21,tblTransactions[Transaction Date],">="&$AA$3,tblTransactions[Transaction Date],"<"&$AA$1),0) | D21: =IFERROR(SUMIFS(tblTransactions[Amount],tblTransactions[Transaction Type],"Expense",tblTransactions[Category],A21,tblTransactions[Transaction Date],">="&$AA$4,tblTransactions[Transaction Date],"<="&$AA$5),0) | E21: =IFERROR(B21/$B$14,0) | F21: =IF(A21="" ,"",1+COUNTIFS($B$17:$B$26,">"&B21))
A22: =IFERROR(INDEX(tblCategories[Category Name],6),"") | B22: =IFERROR(SUMIFS(tblTransactions[Amount],tblTransactions[Transaction Type],"Expense",tblTransactions[Category],A22,tblTransactions[Transaction Date],">="&$AA$1,tblTransactions[Transaction Date],"<"&$AA$2),0) | C22: =IFERROR(SUMIFS(tblTransactions[Amount],tblTransactions[Transaction Type],"Expense",tblTransactions[Category],A22,tblTransactions[Transaction Date],">="&$AA$3,tblTransactions[Transaction Date],"<"&$AA$1),0) | D22: =IFERROR(SUMIFS(tblTransactions[Amount],tblTransactions[Transaction Type],"Expense",tblTransactions[Category],A22,tblTransactions[Transaction Date],">="&$AA$4,tblTransactions[Transaction Date],"<="&$AA$5),0) | E22: =IFERROR(B22/$B$14,0) | F22: =IF(A22="" ,"",1+COUNTIFS($B$17:$B$26,">"&B22))
A23: =IFERROR(INDEX(tblCategories[Category Name],7),"") | B23: =IFERROR(SUMIFS(tblTransactions[Amount],tblTransactions[Transaction Type],"Expense",tblTransactions[Category],A23,tblTransactions[Transaction Date],">="&$AA$1,tblTransactions[Transaction Date],"<"&$AA$2),0) | C23: =IFERROR(SUMIFS(tblTransactions[Amount],tblTransactions[Transaction Type],"Expense",tblTransactions[Category],A23,tblTransactions[Transaction Date],">="&$AA$3,tblTransactions[Transaction Date],"<"&$AA$1),0) | D23: =IFERROR(SUMIFS(tblTransactions[Amount],tblTransactions[Transaction Type],"Expense",tblTransactions[Category],A23,tblTransactions[Transaction Date],">="&$AA$4,tblTransactions[Transaction Date],"<="&$AA$5),0) | E23: =IFERROR(B23/$B$14,0) | F23: =IF(A23="" ,"",1+COUNTIFS($B$17:$B$26,">"&B23))
A24: =IFERROR(INDEX(tblCategories[Category Name],8),"") | B24: =IFERROR(SUMIFS(tblTransactions[Amount],tblTransactions[Transaction Type],"Expense",tblTransactions[Category],A24,tblTransactions[Transaction Date],">="&$AA$1,tblTransactions[Transaction Date],"<"&$AA$2),0) | C24: =IFERROR(SUMIFS(tblTransactions[Amount],tblTransactions[Transaction Type],"Expense",tblTransactions[Category],A24,tblTransactions[Transaction Date],">="&$AA$3,tblTransactions[Transaction Date],"<"&$AA$1),0) | D24: =IFERROR(SUMIFS(tblTransactions[Amount],tblTransactions[Transaction Type],"Expense",tblTransactions[Category],A24,tblTransactions[Transaction Date],">="&$AA$4,tblTransactions[Transaction Date],"<="&$AA$5),0) | E24: =IFERROR(B24/$B$14,0) | F24: =IF(A24="" ,"",1+COUNTIFS($B$17:$B$26,">"&B24))
A25: =IFERROR(INDEX(tblCategories[Category Name],9),"") | B25: =IFERROR(SUMIFS(tblTransactions[Amount],tblTransactions[Transaction Type],"Expense",tblTransactions[Category],A25,tblTransactions[Transaction Date],">="&$AA$1,tblTransactions[Transaction Date],"<"&$AA$2),0) | C25: =IFERROR(SUMIFS(tblTransactions[Amount],tblTransactions[Transaction Type],"Expense",tblTransactions[Category],A25,tblTransactions[Transaction Date],">="&$AA$3,tblTransactions[Transaction Date],"<"&$AA$1),0) | D25: =IFERROR(SUMIFS(tblTransactions[Amount],tblTransactions[Transaction Type],"Expense",tblTransactions[Category],A25,tblTransactions[Transaction Date],">="&$AA$4,tblTransactions[Transaction Date],"<="&$AA$5),0) | E25: =IFERROR(B25/$B$14,0) | F25: =IF(A25="" ,"",1+COUNTIFS($B$17:$B$26,">"&B25))
A26: =IFERROR(INDEX(tblCategories[Category Name],10),"") | B26: =IFERROR(SUMIFS(tblTransactions[Amount],tblTransactions[Transaction Type],"Expense",tblTransactions[Category],A26,tblTransactions[Transaction Date],">="&$AA$1,tblTransactions[Transaction Date],"<"&$AA$2),0) | C26: =IFERROR(SUMIFS(tblTransactions[Amount],tblTransactions[Transaction Type],"Expense",tblTransactions[Category],A26,tblTransactions[Transaction Date],">="&$AA$3,tblTransactions[Transaction Date],"<"&$AA$1),0) | D26: =IFERROR(SUMIFS(tblTransactions[Amount],tblTransactions[Transaction Type],"Expense",tblTransactions[Category],A26,tblTransactions[Transaction Date],">="&$AA$4,tblTransactions[Transaction Date],"<="&$AA$5),0) | E26: =IFERROR(B26/$B$14,0) | F26: =IF(A26="" ,"",1+COUNTIFS($B$17:$B$26,">"&B26))
A28: Monthly Trend (calendar year of As-Of Date)
A29: Month | B29: Income | C29: Expenses | D29: Savings | E29: Savings Rate
A30: =DATE(YEAR($AA$5),1,1) | B30: =IFERROR(SUMIFS(tblTransactions[Amount],tblTransactions[Transaction Type],"Income",tblTransactions[Transaction Date],">="&A30,tblTransactions[Transaction Date],"<"&DATE(YEAR($AA$5),1+1,1)),0) | C30: =IFERROR(SUMIFS(tblTransactions[Amount],tblTransactions[Transaction Type],"Expense",tblTransactions[Transaction Date],">="&A30,tblTransactions[Transaction Date],"<"&DATE(YEAR($AA$5),1+1,1)),0) | D30: =B30-C30 | E30: =IFERROR(D30/B30,0)
A31: =DATE(YEAR($AA$5),2,1) | B31: =IFERROR(SUMIFS(tblTransactions[Amount],tblTransactions[Transaction Type],"Income",tblTransactions[Transaction Date],">="&A31,tblTransactions[Transaction Date],"<"&DATE(YEAR($AA$5),2+1,1)),0) | C31: =IFERROR(SUMIFS(tblTransactions[Amount],tblTransactions[Transaction Type],"Expense",tblTransactions[Transaction Date],">="&A31,tblTransactions[Transaction Date],"<"&DATE(YEAR($AA$5),2+1,1)),0) | D31: =B31-C31 | E31: =IFERROR(D31/B31,0)
A32: =DATE(YEAR($AA$5),3,1) | B32: =IFERROR(SUMIFS(tblTransactions[Amount],tblTransactions[Transaction Type],"Income",tblTransactions[Transaction Date],">="&A32,tblTransactions[Transaction Date],"<"&DATE(YEAR($AA$5),3+1,1)),0) | C32: =IFERROR(SUMIFS(tblTransactions[Amount],tblTransactions[Transaction Type],"Expense",tblTransactions[Transaction Date],">="&A32,tblTransactions[Transaction Date],"<"&DATE(YEAR($AA$5),3+1,1)),0) | D32: =B32-C32 | E32: =IFERROR(D32/B32,0)
A33: =DATE(YEAR($AA$5),4,1) | B33: =IFERROR(SUMIFS(tblTransactions[Amount],tblTransactions[Transaction Type],"Income",tblTransactions[Transaction Date],">="&A33,tblTransactions[Transaction Date],"<"&DATE(YEAR($AA$5),4+1,1)),0) | C33: =IFERROR(SUMIFS(tblTransactions[Amount],tblTransactions[Transaction Type],"Expense",tblTransactions[Transaction Date],">="&A33,tblTransactions[Transaction Date],"<"&DATE(YEAR($AA$5),4+1,1)),0) | D33: =B33-C33 | E33: =IFERROR(D33/B33,0)
A34: =DATE(YEAR($AA$5),5,1) | B34: =IFERROR(SUMIFS(tblTransactions[Amount],tblTransactions[Transaction Type],"Income",tblTransactions[Transaction Date],">="&A34,tblTransactions[Transaction Date],"<"&DATE(YEAR($AA$5),5+1,1)),0) | C34: =IFERROR(SUMIFS(tblTransactions[Amount],tblTransactions[Transaction Type],"Expense",tblTransactions[Transaction Date],">="&A34,tblTransactions[Transaction Date],"<"&DATE(YEAR($AA$5),5+1,1)),0) | D34: =B34-C34 | E34: =IFERROR(D34/B34,0)
A35: =DATE(YEAR($AA$5),6,1) | B35: =IFERROR(SUMIFS(tblTransactions[Amount],tblTransactions[Transaction Type],"Income",tblTransactions[Transaction Date],">="&A35,tblTransactions[Transaction Date],"<"&DATE(YEAR($AA$5),6+1,1)),0) | C35: =IFERROR(SUMIFS(tblTransactions[Amount],tblTransactions[Transaction Type],"Expense",tblTransactions[Transaction Date],">="&A35,tblTransactions[Transaction Date],"<"&DATE(YEAR($AA$5),6+1,1)),0) | D35: =B35-C35 | E35: =IFERROR(D35/B35,0)
A36: =DATE(YEAR($AA$5),7,1) | B36: =IFERROR(SUMIFS(tblTransactions[Amount],tblTransactions[Transaction Type],"Income",tblTransactions[Transaction Date],">="&A36,tblTransactions[Transaction Date],"<"&DATE(YEAR($AA$5),7+1,1)),0) | C36: =IFERROR(SUMIFS(tblTransactions[Amount],tblTransactions[Transaction Type],"Expense",tblTransactions[Transaction Date],">="&A36,tblTransactions[Transaction Date],"<"&DATE(YEAR($AA$5),7+1,1)),0) | D36: =B36-C36 | E36: =IFERROR(D36/B36,0)
A37: =DATE(YEAR($AA$5),8,1) | B37: =IFERROR(SUMIFS(tblTransactions[Amount],tblTransactions[Transaction Type],"Income",tblTransactions[Transaction Date],">="&A37,tblTransactions[Transaction Date],"<"&DATE(YEAR($AA$5),8+1,1)),0) | C37: =IFERROR(SUMIFS(tblTransactions[Amount],tblTransactions[Transaction Type],"Expense",tblTransactions[Transaction Date],">="&A37,tblTransactions[Transaction Date],"<"&DATE(YEAR($AA$5),8+1,1)),0) | D37: =B37-C37 | E37: =IFERROR(D37/B37,0)
A38: =DATE(YEAR($AA$5),9,1) | B38: =IFERROR(SUMIFS(tblTransactions[Amount],tblTransactions[Transaction Type],"Income",tblTransactions[Transaction Date],">="&A38,tblTransactions[Transaction Date],"<"&DATE(YEAR($AA$5),9+1,1)),0) | C38: =IFERROR(SUMIFS(tblTransactions[Amount],tblTransactions[Transaction Type],"Expense",tblTransactions[Transaction Date],">="&A38,tblTransactions[Transaction Date],"<"&DATE(YEAR($AA$5),9+1,1)),0) | D38: =B38-C38 | E38: =IFERROR(D38/B38,0)
A39: =DATE(YEAR($AA$5),10,1) | B39: =IFERROR(SUMIFS(tblTransactions[Amount],tblTransactions[Transaction Type],"Income",tblTransactions[Transaction Date],">="&A39,tblTransactions[Transaction Date],"<"&DATE(YEAR($AA$5),10+1,1)),0) | C39: =IFERROR(SUMIFS(tblTransactions[Amount],tblTransactions[Transaction Type],"Expense",tblTransactions[Transaction Date],">="&A39,tblTransactions[Transaction Date],"<"&DATE(YEAR($AA$5),10+1,1)),0) | D39: =B39-C39 | E39: =IFERROR(D39/B39,0)
A40: =DATE(YEAR($AA$5),11,1) | B40: =IFERROR(SUMIFS(tblTransactions[Amount],tblTransactions[Transaction Type],"Income",tblTransactions[Transaction Date],">="&A40,tblTransactions[Transaction Date],"<"&DATE(YEAR($AA$5),11+1,1)),0) | C40: =IFERROR(SUMIFS(tblTransactions[Amount],tblTransactions[Transaction Type],"Expense",tblTransactions[Transaction Date],">="&A40,tblTransactions[Transaction Date],"<"&DATE(YEAR($AA$5),11+1,1)),0) | D40: =B40-C40 | E40: =IFERROR(D40/B40,0)
A41: =DATE(YEAR($AA$5),12,1) | B41: =IFERROR(SUMIFS(tblTransactions[Amount],tblTransactions[Transaction Type],"Income",tblTransactions[Transaction Date],">="&A41,tblTransactions[Transaction Date],"<"&DATE(YEAR($AA$5),12+1,1)),0) | C41: =IFERROR(SUMIFS(tblTransactions[Amount],tblTransactions[Transaction Type],"Expense",tblTransactions[Transaction Date],">="&A41,tblTransactions[Transaction Date],"<"&DATE(YEAR($AA$5),12+1,1)),0) | D41: =B41-C41 | E41: =IFERROR(D41/B41,0)
A43: SECTION 3 â€” Cash Flow Analysis
A44: Income | B44: ='Business Engine'!$B$16
A45: Expenses | B45: ='Business Engine'!$B$22
A46: Savings | B46: ='Business Engine'!$B$29
A47: Savings Rate | B47: ='Business Engine'!$B$30
A48: Previous Month Expenses | B48: ='Business Engine'!$B$23
A49: MoM Expense Change | B49: =IFERROR($B$45-$B$48,0)
A50: MoM Expense Change % | B50: =IFERROR(($B$45-$B$48)/$B$48,0)
A51: Running monthly table | B51: See Section 2 rows 30-41
A53: SECTION 4 â€” Asset Analysis
A54: Total Purchase Value | B54: ='Business Engine'!$B$34
A55: Total Current Value | B55: ='Business Engine'!$B$35
A56: Appreciation | B56: ='Business Engine'!$B$36
A57: Appreciation % | B57: ='Business Engine'!$B$37
A58: Active Asset Count | B58: ='Business Engine'!$B$38
A60: Allocation by Asset Type
A61: Asset Type | B61: Current Value | C61: Allocation %
A62: =IFERROR(INDEX(lkpAssetType[Asset Type],1),"") | B62: =IFERROR(SUMIFS(tblAssets[Current Value],tblAssets[Asset Type],A62,tblAssets[Status],"Active"),0) | C62: =IFERROR(B62/$B$55,0)
A63: =IFERROR(INDEX(lkpAssetType[Asset Type],2),"") | B63: =IFERROR(SUMIFS(tblAssets[Current Value],tblAssets[Asset Type],A63,tblAssets[Status],"Active"),0) | C63: =IFERROR(B63/$B$55,0)
A64: =IFERROR(INDEX(lkpAssetType[Asset Type],3),"") | B64: =IFERROR(SUMIFS(tblAssets[Current Value],tblAssets[Asset Type],A64,tblAssets[Status],"Active"),0) | C64: =IFERROR(B64/$B$55,0)
A65: =IFERROR(INDEX(lkpAssetType[Asset Type],4),"") | B65: =IFERROR(SUMIFS(tblAssets[Current Value],tblAssets[Asset Type],A65,tblAssets[Status],"Active"),0) | C65: =IFERROR(B65/$B$55,0)
A66: =IFERROR(INDEX(lkpAssetType[Asset Type],5),"") | B66: =IFERROR(SUMIFS(tblAssets[Current Value],tblAssets[Asset Type],A66,tblAssets[Status],"Active"),0) | C66: =IFERROR(B66/$B$55,0)
A67: =IFERROR(INDEX(lkpAssetType[Asset Type],6),"") | B67: =IFERROR(SUMIFS(tblAssets[Current Value],tblAssets[Asset Type],A67,tblAssets[Status],"Active"),0) | C67: =IFERROR(B67/$B$55,0)
A68: =IFERROR(INDEX(lkpAssetType[Asset Type],7),"") | B68: =IFERROR(SUMIFS(tblAssets[Current Value],tblAssets[Asset Type],A68,tblAssets[Status],"Active"),0) | C68: =IFERROR(B68/$B$55,0)
A69: =IFERROR(INDEX(lkpAssetType[Asset Type],8),"") | B69: =IFERROR(SUMIFS(tblAssets[Current Value],tblAssets[Asset Type],A69,tblAssets[Status],"Active"),0) | C69: =IFERROR(B69/$B$55,0)
A70: =IFERROR(INDEX(lkpAssetType[Asset Type],9),"") | B70: =IFERROR(SUMIFS(tblAssets[Current Value],tblAssets[Asset Type],A70,tblAssets[Status],"Active"),0) | C70: =IFERROR(B70/$B$55,0)
A71: =IFERROR(INDEX(lkpAssetType[Asset Type],10),"") | B71: =IFERROR(SUMIFS(tblAssets[Current Value],tblAssets[Asset Type],A71,tblAssets[Status],"Active"),0) | C71: =IFERROR(B71/$B$55,0)
A73: SECTION 5 â€” Liability Analysis
A74: Total Original Liability | B74: ='Business Engine'!$B$41
A75: Outstanding Balance | B75: ='Business Engine'!$B$42
A76: Total Monthly EMI | B76: ='Business Engine'!$B$43
A77: Weighted Interest Rate | B77: ='Business Engine'!$B$44
A78: Est. Monthly Interest | B78: =IFERROR($B$75*$B$77/12,0)
A79: Active Liability Count | B79: ='Business Engine'!$B$45
A80: EMI Ratio (from BE) | B80: ='Business Engine'!$B$66
A81: Debt Ratio (from BE) | B81: ='Business Engine'!$B$68
A83: Liability breakdown by type
A84: Liability Type | B84: Outstanding | C84: Mix %
A85: =IFERROR(INDEX(lkpLiabilityType[Liability Type],1),"") | B85: =IFERROR(SUMIFS(tblLiabilities[Outstanding Balance],tblLiabilities[Liability Type],A85,tblLiabilities[Status],"Active"),0) | C85: =IFERROR(B85/$B$75,0)
A86: =IFERROR(INDEX(lkpLiabilityType[Liability Type],2),"") | B86: =IFERROR(SUMIFS(tblLiabilities[Outstanding Balance],tblLiabilities[Liability Type],A86,tblLiabilities[Status],"Active"),0) | C86: =IFERROR(B86/$B$75,0)
A87: =IFERROR(INDEX(lkpLiabilityType[Liability Type],3),"") | B87: =IFERROR(SUMIFS(tblLiabilities[Outstanding Balance],tblLiabilities[Liability Type],A87,tblLiabilities[Status],"Active"),0) | C87: =IFERROR(B87/$B$75,0)
A88: =IFERROR(INDEX(lkpLiabilityType[Liability Type],4),"") | B88: =IFERROR(SUMIFS(tblLiabilities[Outstanding Balance],tblLiabilities[Liability Type],A88,tblLiabilities[Status],"Active"),0) | C88: =IFERROR(B88/$B$75,0)
A89: =IFERROR(INDEX(lkpLiabilityType[Liability Type],5),"") | B89: =IFERROR(SUMIFS(tblLiabilities[Outstanding Balance],tblLiabilities[Liability Type],A89,tblLiabilities[Status],"Active"),0) | C89: =IFERROR(B89/$B$75,0)
A90: =IFERROR(INDEX(lkpLiabilityType[Liability Type],6),"") | B90: =IFERROR(SUMIFS(tblLiabilities[Outstanding Balance],tblLiabilities[Liability Type],A90,tblLiabilities[Status],"Active"),0) | C90: =IFERROR(B90/$B$75,0)
A91: =IFERROR(INDEX(lkpLiabilityType[Liability Type],7),"") | B91: =IFERROR(SUMIFS(tblLiabilities[Outstanding Balance],tblLiabilities[Liability Type],A91,tblLiabilities[Status],"Active"),0) | C91: =IFERROR(B91/$B$75,0)
A92: =IFERROR(INDEX(lkpLiabilityType[Liability Type],8),"") | B92: =IFERROR(SUMIFS(tblLiabilities[Outstanding Balance],tblLiabilities[Liability Type],A92,tblLiabilities[Status],"Active"),0) | C92: =IFERROR(B92/$B$75,0)
A93: =IFERROR(INDEX(lkpLiabilityType[Liability Type],9),"") | B93: =IFERROR(SUMIFS(tblLiabilities[Outstanding Balance],tblLiabilities[Liability Type],A93,tblLiabilities[Status],"Active"),0) | C93: =IFERROR(B93/$B$75,0)
A94: =IFERROR(INDEX(lkpLiabilityType[Liability Type],10),"") | B94: =IFERROR(SUMIFS(tblLiabilities[Outstanding Balance],tblLiabilities[Liability Type],A94,tblLiabilities[Status],"Active"),0) | C94: =IFERROR(B94/$B$75,0)
A96: SECTION 6 â€” Goal Analysis
A97: Goal | B97: Progress % | C97: Remaining | D97: Monthly Contribution Needed | E97: Overdue Flag
A98: =IFERROR(INDEX(tblGoals[Goal Name],1),"") | B98: =IFERROR(INDEX(tblGoals[Current Saved Amount],1)/INDEX(tblGoals[Target Amount],1),0) | C98: =IFERROR(INDEX(tblGoals[Remaining Amount],1),0) | D98: =IFERROR(INDEX(tblGoals[Remaining Amount],1)/MAX(1,(YEAR(INDEX(tblGoals[Target Date],1))-YEAR($AA$5))*12+MONTH(INDEX(tblGoals[Target Date],1))-MONTH($AA$5)),0) | E98: =IF((IFERROR(INDEX(tblGoals[Goal Status],1),"")="Active")*(IFERROR(INDEX(tblGoals[Target Date],1),0)<$AA$5)*(IFERROR(INDEX(tblGoals[Remaining Amount],1),0)>0),1,0)
A99: =IFERROR(INDEX(tblGoals[Goal Name],2),"") | B99: =IFERROR(INDEX(tblGoals[Current Saved Amount],2)/INDEX(tblGoals[Target Amount],2),0) | C99: =IFERROR(INDEX(tblGoals[Remaining Amount],2),0) | D99: =IFERROR(INDEX(tblGoals[Remaining Amount],2)/MAX(1,(YEAR(INDEX(tblGoals[Target Date],2))-YEAR($AA$5))*12+MONTH(INDEX(tblGoals[Target Date],2))-MONTH($AA$5)),0) | E99: =IF((IFERROR(INDEX(tblGoals[Goal Status],2),"")="Active")*(IFERROR(INDEX(tblGoals[Target Date],2),0)<$AA$5)*(IFERROR(INDEX(tblGoals[Remaining Amount],2),0)>0),1,0)
A100: =IFERROR(INDEX(tblGoals[Goal Name],3),"") | B100: =IFERROR(INDEX(tblGoals[Current Saved Amount],3)/INDEX(tblGoals[Target Amount],3),0) | C100: =IFERROR(INDEX(tblGoals[Remaining Amount],3),0) | D100: =IFERROR(INDEX(tblGoals[Remaining Amount],3)/MAX(1,(YEAR(INDEX(tblGoals[Target Date],3))-YEAR($AA$5))*12+MONTH(INDEX(tblGoals[Target Date],3))-MONTH($AA$5)),0) | E100: =IF((IFERROR(INDEX(tblGoals[Goal Status],3),"")="Active")*(IFERROR(INDEX(tblGoals[Target Date],3),0)<$AA$5)*(IFERROR(INDEX(tblGoals[Remaining Amount],3),0)>0),1,0)
A101: =IFERROR(INDEX(tblGoals[Goal Name],4),"") | B101: =IFERROR(INDEX(tblGoals[Current Saved Amount],4)/INDEX(tblGoals[Target Amount],4),0) | C101: =IFERROR(INDEX(tblGoals[Remaining Amount],4),0) | D101: =IFERROR(INDEX(tblGoals[Remaining Amount],4)/MAX(1,(YEAR(INDEX(tblGoals[Target Date],4))-YEAR($AA$5))*12+MONTH(INDEX(tblGoals[Target Date],4))-MONTH($AA$5)),0) | E101: =IF((IFERROR(INDEX(tblGoals[Goal Status],4),"")="Active")*(IFERROR(INDEX(tblGoals[Target Date],4),0)<$AA$5)*(IFERROR(INDEX(tblGoals[Remaining Amount],4),0)>0),1,0)
A102: =IFERROR(INDEX(tblGoals[Goal Name],5),"") | B102: =IFERROR(INDEX(tblGoals[Current Saved Amount],5)/INDEX(tblGoals[Target Amount],5),0) | C102: =IFERROR(INDEX(tblGoals[Remaining Amount],5),0) | D102: =IFERROR(INDEX(tblGoals[Remaining Amount],5)/MAX(1,(YEAR(INDEX(tblGoals[Target Date],5))-YEAR($AA$5))*12+MONTH(INDEX(tblGoals[Target Date],5))-MONTH($AA$5)),0) | E102: =IF((IFERROR(INDEX(tblGoals[Goal Status],5),"")="Active")*(IFERROR(INDEX(tblGoals[Target Date],5),0)<$AA$5)*(IFERROR(INDEX(tblGoals[Remaining Amount],5),0)>0),1,0)
A103: =IFERROR(INDEX(tblGoals[Goal Name],6),"") | B103: =IFERROR(INDEX(tblGoals[Current Saved Amount],6)/INDEX(tblGoals[Target Amount],6),0) | C103: =IFERROR(INDEX(tblGoals[Remaining Amount],6),0) | D103: =IFERROR(INDEX(tblGoals[Remaining Amount],6)/MAX(1,(YEAR(INDEX(tblGoals[Target Date],6))-YEAR($AA$5))*12+MONTH(INDEX(tblGoals[Target Date],6))-MONTH($AA$5)),0) | E103: =IF((IFERROR(INDEX(tblGoals[Goal Status],6),"")="Active")*(IFERROR(INDEX(tblGoals[Target Date],6),0)<$AA$5)*(IFERROR(INDEX(tblGoals[Remaining Amount],6),0)>0),1,0)
A104: =IFERROR(INDEX(tblGoals[Goal Name],7),"") | B104: =IFERROR(INDEX(tblGoals[Current Saved Amount],7)/INDEX(tblGoals[Target Amount],7),0) | C104: =IFERROR(INDEX(tblGoals[Remaining Amount],7),0) | D104: =IFERROR(INDEX(tblGoals[Remaining Amount],7)/MAX(1,(YEAR(INDEX(tblGoals[Target Date],7))-YEAR($AA$5))*12+MONTH(INDEX(tblGoals[Target Date],7))-MONTH($AA$5)),0) | E104: =IF((IFERROR(INDEX(tblGoals[Goal Status],7),"")="Active")*(IFERROR(INDEX(tblGoals[Target Date],7),0)<$AA$5)*(IFERROR(INDEX(tblGoals[Remaining Amount],7),0)>0),1,0)
A105: =IFERROR(INDEX(tblGoals[Goal Name],8),"") | B105: =IFERROR(INDEX(tblGoals[Current Saved Amount],8)/INDEX(tblGoals[Target Amount],8),0) | C105: =IFERROR(INDEX(tblGoals[Remaining Amount],8),0) | D105: =IFERROR(INDEX(tblGoals[Remaining Amount],8)/MAX(1,(YEAR(INDEX(tblGoals[Target Date],8))-YEAR($AA$5))*12+MONTH(INDEX(tblGoals[Target Date],8))-MONTH($AA$5)),0) | E105: =IF((IFERROR(INDEX(tblGoals[Goal Status],8),"")="Active")*(IFERROR(INDEX(tblGoals[Target Date],8),0)<$AA$5)*(IFERROR(INDEX(tblGoals[Remaining Amount],8),0)>0),1,0)
A107: Overdue Goal Count | B107: =SUM($E$98:$E$105)
A108: Goal Completion % (BE) | B108: ='Business Engine'!$B$58
A109: Active Goal Count (BE) | B109: ='Business Engine'!$B$56
A111: SECTION 7 â€” Category Analysis
...

Sheet Dashboard
A1: Dashboard

Sheet Insights
A1: Insights
