Workbook
Name rngAccounts: Accounts!$B$2:$B$200
Name rngAccountStatus: Helpers!$A$70:$A$71
Name rngAccountType: Helpers!$A$91:$A$98
Name rngActiveAccounts: Helpers!$G$2:$G$201
Name rngActiveAssets: Helpers!$I$2:$I$201
Name rngActiveGoals: Helpers!$H$2:$H$201
Name rngActiveLiabilities: Helpers!$J$2:$J$201
Name rngAssets: Assets!$B$2:$B$200
Name rngAssetType: Helpers!$AG$2:$AG$25
Name rngBlank: Helpers!$L$2
Name rngBoolean: Helpers!$A$86:$A$87
Name rngCategories: Categories!$B$2:$B$200
Name rngCategoryType: Helpers!$A$102:$A$103
Name rngCommitmentStatus: Helpers!$A$75:$A$77
Name rngCurrency: Helpers!$A$2:$A$6
Name rngDestinationType: Helpers!$A$28:$A$34
Name rngExpenseCategories: Helpers!$E$2:$E$201
Name rngFinancialYears: Helpers!$A$126
Name rngFrequency: Helpers!$A$38:$A$41
Name rngGoals: Goals!$B$2:$B$200
Name rngGoalStatus: Helpers!$A$59:$A$61
Name rngIncomeCategories: Helpers!$F$2:$F$201
Name rngIncomeSources: 'Income Sources'!$B$2:$B$200
Name rngIncomeType: Helpers!$AI$2:$AI$10
Name rngLiabilities: Liabilities!$B$2:$B$200
Name rngLiabilityStatus: Helpers!$A$65:$A$66
Name rngLiabilityType: Helpers!$AH$2:$AH$11
Name rngMonths: Helpers!$B$111:$B$122
Name rngOwnershipType: Helpers!$A$81:$A$82
Name rngPaymentMethods: Helpers!$A$10:$A$17
Name rngPriority: Helpers!$A$45:$A$47
Name rngTransactionStatus: Helpers!$D$1:$D$4
Name rngTransactionType: Helpers!$A$21:$A$24
Name rngYesNo: Helpers!$A$86:$A$87
Name valAccountStatus: Helpers!$B$147
Name valAccountTypes: Helpers!$B$140
Name valActiveAccounts: Helpers!$G$2:$G$201
Name valActiveAssets: Helpers!$I$2:$I$201
Name valActiveGoals: Helpers!$H$2:$H$201
Name valActiveLiabilities: Helpers!$J$2:$J$201
Name valBlank: Helpers!$L$2
Name valCategoryTypes: Helpers!$B$141
Name valCommitmentStatus: Helpers!$B$148
Name valCurrencies: Helpers!$B$143
Name valDestinationTypes: Helpers!$B$144
Name valExpenseCategories: Helpers!$E$2:$E$201
Name valFrequency: Helpers!$B$138
Name valGoalStatus: Helpers!$B$146
Name valIncomeCategories: Helpers!$F$2:$F$201
Name valIncomeSources: Helpers!$K$2:$K$201
Name valPaymentMethods: Helpers!$B$137
Name valPriority: Helpers!$B$139
Name valThemes: Helpers!$B$142
Name valTransactionTypes: Helpers!$B$145
Name outLiabilityPaymentTotal: 'Business Engine'!$B$46
Name outAssetPurchaseTotal: 'Business Engine'!$B$39
Name analysisSavingsHealth: 'Analysis Engine'!$B$158
Name analysisExpenseHealth: 'Analysis Engine'!$B$159
Name analysisDebtHealth: 'Analysis Engine'!$B$160
Name analysisAssetHealth: 'Analysis Engine'!$B$161

Sheet Settings
A1: Setting ID | B1: Setting Name | C1: Setting Value | D1: Setting Category | E1: Description

Sheet Categories
A1: Category ID | B1: Category Name | C1: Category Type | D1: Parent Category | E1: Status | F1: Display Order | G1: Notes

Sheet Accounts
A1: Account ID | B1: Account Name | C1: Account Type | D1: Institution | E1: Opening Balance | F1: Current Balance | G1: Currency | H1: Include in Dashboard | I1: Status | J1: Notes
F2: =IF(tblAccounts[[#This Row],[Account Name]]="","",INDEX('Business Engine'!$H$2:$H$200,ROW()-ROW(tblAccounts[#Headers])))
F3: =IF(tblAccounts[[#This Row],[Account Name]]="","",INDEX('Business Engine'!$H$2:$H$200,ROW()-ROW(tblAccounts[#Headers])))
F4: =IF(tblAccounts[[#This Row],[Account Name]]="","",INDEX('Business Engine'!$H$2:$H$200,ROW()-ROW(tblAccounts[#Headers])))
F5: =IF(tblAccounts[[#This Row],[Account Name]]="","",INDEX('Business Engine'!$H$2:$H$200,ROW()-ROW(tblAccounts[#Headers])))
F6: =IF(tblAccounts[[#This Row],[Account Name]]="","",INDEX('Business Engine'!$H$2:$H$200,ROW()-ROW(tblAccounts[#Headers])))
F7: =IF(tblAccounts[[#This Row],[Account Name]]="","",INDEX('Business Engine'!$H$2:$H$200,ROW()-ROW(tblAccounts[#Headers])))
F8: =IF(tblAccounts[[#This Row],[Account Name]]="","",INDEX('Business Engine'!$H$2:$H$200,ROW()-ROW(tblAccounts[#Headers])))
F9: =IF(tblAccounts[[#This Row],[Account Name]]="","",INDEX('Business Engine'!$H$2:$H$200,ROW()-ROW(tblAccounts[#Headers])))
F10: =IF(tblAccounts[[#This Row],[Account Name]]="","",INDEX('Business Engine'!$H$2:$H$200,ROW()-ROW(tblAccounts[#Headers])))
F11: =IF(tblAccounts[[#This Row],[Account Name]]="","",INDEX('Business Engine'!$H$2:$H$200,ROW()-ROW(tblAccounts[#Headers])))
F12: =IF(tblAccounts[[#This Row],[Account Name]]="","",INDEX('Business Engine'!$H$2:$H$200,ROW()-ROW(tblAccounts[#Headers])))
F13: =IF(tblAccounts[[#This Row],[Account Name]]="","",INDEX('Business Engine'!$H$2:$H$200,ROW()-ROW(tblAccounts[#Headers])))
... F200: =IF(tblAccounts[[#This Row],[Account Name]]="","",INDEX('Business Engine'!$H$2:$H$200,ROW()-ROW(tblAccounts[#Headers])))

Sheet Income Sources
A1: Income Source ID | B1: Income Source Name | C1: Income Category | D1: Default Receiving Account | E1: Status | F1: Notes

Sheet Assets
A1: Asset ID | B1: Asset Name | C1: Asset Category | D1: Asset Type | E1: Linked Account | F1: Purchase Date | G1: Purchase Value | H1: Current Value | I1: Appreciation Amount | J1: Appreciation % | K1: Ownership Type | L1: Status | M1: Notes
I2: =IF(tblAssets[[#This Row],[Asset ID]]="","",tblAssets[[#This Row],[Current Value]]-tblAssets[[#This Row],[Purchase Value]]) -> 0 | J2: =IF(OR(tblAssets[[#This Row],[Asset ID]]="",tblAssets[[#This Row],[Purchase Value]]=0),"",tblAssets[[#This Row],[Appreciation Amount]]/tblAssets[[#This Row],[Purchase Value]]) -> 0
I3: =IF(tblAssets[[#This Row],[Asset ID]]="","",tblAssets[[#This Row],[Current Value]]-tblAssets[[#This Row],[Purchase Value]]) -> 0 | J3: =IF(OR(tblAssets[[#This Row],[Asset ID]]="",tblAssets[[#This Row],[Purchase Value]]=0),"",tblAssets[[#This Row],[Appreciation Amount]]/tblAssets[[#This Row],[Purchase Value]]) -> 0
I4: =IF(tblAssets[[#This Row],[Asset ID]]="","",tblAssets[[#This Row],[Current Value]]-tblAssets[[#This Row],[Purchase Value]]) -> 0 | J4: =IF(OR(tblAssets[[#This Row],[Asset ID]]="",tblAssets[[#This Row],[Purchase Value]]=0),"",tblAssets[[#This Row],[Appreciation Amount]]/tblAssets[[#This Row],[Purchase Value]]) -> 0
I5: =IF(tblAssets[[#This Row],[Asset ID]]="","",tblAssets[[#This Row],[Current Value]]-tblAssets[[#This Row],[Purchase Value]]) -> 0 | J5: =IF(OR(tblAssets[[#This Row],[Asset ID]]="",tblAssets[[#This Row],[Purchase Value]]=0),"",tblAssets[[#This Row],[Appreciation Amount]]/tblAssets[[#This Row],[Purchase Value]]) -> 0
I6: =IF(tblAssets[[#This Row],[Asset ID]]="","",tblAssets[[#This Row],[Current Value]]-tblAssets[[#This Row],[Purchase Value]]) -> 0 | J6: =IF(OR(tblAssets[[#This Row],[Asset ID]]="",tblAssets[[#This Row],[Purchase Value]]=0),"",tblAssets[[#This Row],[Appreciation Amount]]/tblAssets[[#This Row],[Purchase Value]]) -> 0
I7: =IF(tblAssets[[#This Row],[Asset ID]]="","",tblAssets[[#This Row],[Current Value]]-tblAssets[[#This Row],[Purchase Value]]) -> 0 | J7: =IF(OR(tblAssets[[#This Row],[Asset ID]]="",tblAssets[[#This Row],[Purchase Value]]=0),"",tblAssets[[#This Row],[Appreciation Amount]]/tblAssets[[#This Row],[Purchase Value]]) -> 0
I8: =IF(tblAssets[[#This Row],[Asset ID]]="","",tblAssets[[#This Row],[Current Value]]-tblAssets[[#This Row],[Purchase Value]]) -> 0 | J8: =IF(OR(tblAssets[[#This Row],[Asset ID]]="",tblAssets[[#This Row],[Purchase Value]]=0),"",tblAssets[[#This Row],[Appreciation Amount]]/tblAssets[[#This Row],[Purchase Value]]) -> 0
I9: =IF(tblAssets[[#This Row],[Asset ID]]="","",tblAssets[[#This Row],[Current Value]]-tblAssets[[#This Row],[Purchase Value]]) -> 0 | J9: =IF(OR(tblAssets[[#This Row],[Asset ID]]="",tblAssets[[#This Row],[Purchase Value]]=0),"",tblAssets[[#This Row],[Appreciation Amount]]/tblAssets[[#This Row],[Purchase Value]]) -> 0
I10: =IF(tblAssets[[#This Row],[Asset ID]]="","",tblAssets[[#This Row],[Current Value]]-tblAssets[[#This Row],[Purchase Value]]) -> 0 | J10: =IF(OR(tblAssets[[#This Row],[Asset ID]]="",tblAssets[[#This Row],[Purchase Value]]=0),"",tblAssets[[#This Row],[Appreciation Amount]]/tblAssets[[#This Row],[Purchase Value]]) -> 0
I11: =IF(tblAssets[[#This Row],[Asset ID]]="","",tblAssets[[#This Row],[Current Value]]-tblAssets[[#This Row],[Purchase Value]]) -> 0 | J11: =IF(OR(tblAssets[[#This Row],[Asset ID]]="",tblAssets[[#This Row],[Purchase Value]]=0),"",tblAssets[[#This Row],[Appreciation Amount]]/tblAssets[[#This Row],[Purchase Value]]) -> 0
I12: =IF(tblAssets[[#This Row],[Asset ID]]="","",tblAssets[[#This Row],[Current Value]]-tblAssets[[#This Row],[Purchase Value]]) -> 0 | J12: =IF(OR(tblAssets[[#This Row],[Asset ID]]="",tblAssets[[#This Row],[Purchase Value]]=0),"",tblAssets[[#This Row],[Appreciation Amount]]/tblAssets[[#This Row],[Purchase Value]]) -> 0
I13: =IF(tblAssets[[#This Row],[Asset ID]]="","",tblAssets[[#This Row],[Current Value]]-tblAssets[[#This Row],[Purchase Value]]) -> 0 | J13: =IF(OR(tblAssets[[#This Row],[Asset ID]]="",tblAssets[[#This Row],[Purchase Value]]=0),"",tblAssets[[#This Row],[Appreciation Amount]]/tblAssets[[#This Row],[Purchase Value]]) -> 0
... I200: =IF(tblAssets[[#This Row],[Asset ID]]="","",tblAssets[[#This Row],[Current Value]]-tblAssets[[#This Row],[Purchase Value]]) -> 0 | J200: =IF(OR(tblAssets[[#This Row],[Asset ID]]="",tblAssets[[#This Row],[Purchase Value]]=0),"",tblAssets[[#This Row],[Appreciation Amount]]/tblAssets[[#This Row],[Purchase Value]]) -> 0

Sheet Liabilities
A1: Liability ID | B1: Liability Name | C1: Liability Type | D1: Institution | E1: Original Amount | F1: Outstanding Balance | G1: Interest Rate | H1: EMI Amount | I1: EMI Frequency | J1: EMI Due Day | K1: Start Date | L1: End Date | M1: Linked Payment Account | N1: Auto EMI | O1: Status | P1: Notes

Sheet Recurring Commitments
A1: Commitment ID | B1: Commitment Name | C1: Commitment Type | D1: Linked Liability ID | E1: Linked Goal ID | F1: Payment Account | G1: Amount | H1: Frequency | I1: Due Day | J1: Start Date | K1: End Date | L1: Auto Generate | M1: Status | N1: Notes

Sheet Transactions
A1: Transaction ID | B1: Transaction Date | C1: Transaction Type | D1: Source Account | E1: Destination Type | F1: Destination Name | G1: Category | H1: Income Source | I1: Amount | J1: Payment Method | K1: Transaction Status | L1: Notes | M1: Created Timestamp

Sheet Goals
A1: Goal ID | B1: Goal Name | C1: Goal Category | D1: Goal Account | E1: Target Amount | F1: Current Saved Amount | G1: Remaining Amount | H1: Monthly Contribution Target | I1: Target Date | J1: Priority | K1: Goal Status | L1: Notes
F2: =IF(tblGoals[[#This Row],[Goal ID]]="","",IFERROR(SUMPRODUCT((tblTransactions[Transaction Type]="Expense")*(tblTransactions[Destination Type]="Goal")*((tblTransactions[Transaction Status]="Completed")+(tblTransactions[Transaction Status]="Reconciled"))*(IFERROR(INDEX(tblGoals[Goal ID],MATCH(tblTransactions[Destination Name],tblGoals[Goal ID],0)),IFERROR(INDEX(tblGoals[Goal ID],MATCH(tblTransactions[Destination Name],tblGoals[Goal Name],0)),""))=tblGoals[[#This Row],[Goal ID]])*(tblTransactions[Amount])),0)) | G2: =MAX(0,tblGoals[[#This Row],[Target Amount]]-tblGoals[[#This Row],[Current Saved Amount]]) -> 0
F3: =IF(tblGoals[[#This Row],[Goal ID]]="","",IFERROR(SUMPRODUCT((tblTransactions[Transaction Type]="Expense")*(tblTransactions[Destination Type]="Goal")*((tblTransactions[Transaction Status]="Completed")+(tblTransactions[Transaction Status]="Reconciled"))*(IFERROR(INDEX(tblGoals[Goal ID],MATCH(tblTransactions[Destination Name],tblGoals[Goal ID],0)),IFERROR(INDEX(tblGoals[Goal ID],MATCH(tblTransactions[Destination Name],tblGoals[Goal Name],0)),""))=tblGoals[[#This Row],[Goal ID]])*(tblTransactions[Amount])),0)) | G3: =MAX(0,tblGoals[[#This Row],[Target Amount]]-tblGoals[[#This Row],[Current Saved Amount]]) -> 0
F4: =IF(tblGoals[[#This Row],[Goal ID]]="","",IFERROR(SUMPRODUCT((tblTransactions[Transaction Type]="Expense")*(tblTransactions[Destination Type]="Goal")*((tblTransactions[Transaction Status]="Completed")+(tblTransactions[Transaction Status]="Reconciled"))*(IFERROR(INDEX(tblGoals[Goal ID],MATCH(tblTransactions[Destination Name],tblGoals[Goal ID],0)),IFERROR(INDEX(tblGoals[Goal ID],MATCH(tblTransactions[Destination Name],tblGoals[Goal Name],0)),""))=tblGoals[[#This Row],[Goal ID]])*(tblTransactions[Amount])),0)) | G4: =MAX(0,tblGoals[[#This Row],[Target Amount]]-tblGoals[[#This Row],[Current Saved Amount]]) -> 0
F5: =IF(tblGoals[[#This Row],[Goal ID]]="","",IFERROR(SUMPRODUCT((tblTransactions[Transaction Type]="Expense")*(tblTransactions[Destination Type]="Goal")*((tblTransactions[Transaction Status]="Completed")+(tblTransactions[Transaction Status]="Reconciled"))*(IFERROR(INDEX(tblGoals[Goal ID],MATCH(tblTransactions[Destination Name],tblGoals[Goal ID],0)),IFERROR(INDEX(tblGoals[Goal ID],MATCH(tblTransactions[Destination Name],tblGoals[Goal Name],0)),""))=tblGoals[[#This Row],[Goal ID]])*(tblTransactions[Amount])),0)) | G5: =MAX(0,tblGoals[[#This Row],[Target Amount]]-tblGoals[[#This Row],[Current Saved Amount]]) -> 0
F6: =IF(tblGoals[[#This Row],[Goal ID]]="","",IFERROR(SUMPRODUCT((tblTransactions[Transaction Type]="Expense")*(tblTransactions[Destination Type]="Goal")*((tblTransactions[Transaction Status]="Completed")+(tblTransactions[Transaction Status]="Reconciled"))*(IFERROR(INDEX(tblGoals[Goal ID],MATCH(tblTransactions[Destination Name],tblGoals[Goal ID],0)),IFERROR(INDEX(tblGoals[Goal ID],MATCH(tblTransactions[Destination Name],tblGoals[Goal Name],0)),""))=tblGoals[[#This Row],[Goal ID]])*(tblTransactions[Amount])),0)) | G6: =MAX(0,tblGoals[[#This Row],[Target Amount]]-tblGoals[[#This Row],[Current Saved Amount]]) -> 0
F7: =IF(tblGoals[[#This Row],[Goal ID]]="","",IFERROR(SUMPRODUCT((tblTransactions[Transaction Type]="Expense")*(tblTransactions[Destination Type]="Goal")*((tblTransactions[Transaction Status]="Completed")+(tblTransactions[Transaction Status]="Reconciled"))*(IFERROR(INDEX(tblGoals[Goal ID],MATCH(tblTransactions[Destination Name],tblGoals[Goal ID],0)),IFERROR(INDEX(tblGoals[Goal ID],MATCH(tblTransactions[Destination Name],tblGoals[Goal Name],0)),""))=tblGoals[[#This Row],[Goal ID]])*(tblTransactions[Amount])),0)) | G7: =MAX(0,tblGoals[[#This Row],[Target Amount]]-tblGoals[[#This Row],[Current Saved Amount]]) -> 0
F8: =IF(tblGoals[[#This Row],[Goal ID]]="","",IFERROR(SUMPRODUCT((tblTransactions[Transaction Type]="Expense")*(tblTransactions[Destination Type]="Goal")*((tblTransactions[Transaction Status]="Completed")+(tblTransactions[Transaction Status]="Reconciled"))*(IFERROR(INDEX(tblGoals[Goal ID],MATCH(tblTransactions[Destination Name],tblGoals[Goal ID],0)),IFERROR(INDEX(tblGoals[Goal ID],MATCH(tblTransactions[Destination Name],tblGoals[Goal Name],0)),""))=tblGoals[[#This Row],[Goal ID]])*(tblTransactions[Amount])),0)) | G8: =MAX(0,tblGoals[[#This Row],[Target Amount]]-tblGoals[[#This Row],[Current Saved Amount]]) -> 0
F9: =IF(tblGoals[[#This Row],[Goal ID]]="","",IFERROR(SUMPRODUCT((tblTransactions[Transaction Type]="Expense")*(tblTransactions[Destination Type]="Goal")*((tblTransactions[Transaction Status]="Completed")+(tblTransactions[Transaction Status]="Reconciled"))*(IFERROR(INDEX(tblGoals[Goal ID],MATCH(tblTransactions[Destination Name],tblGoals[Goal ID],0)),IFERROR(INDEX(tblGoals[Goal ID],MATCH(tblTransactions[Destination Name],tblGoals[Goal Name],0)),""))=tblGoals[[#This Row],[Goal ID]])*(tblTransactions[Amount])),0)) | G9: =MAX(0,tblGoals[[#This Row],[Target Amount]]-tblGoals[[#This Row],[Current Saved Amount]]) -> 0
F10: =IF(tblGoals[[#This Row],[Goal ID]]="","",IFERROR(SUMPRODUCT((tblTransactions[Transaction Type]="Expense")*(tblTransactions[Destination Type]="Goal")*((tblTransactions[Transaction Status]="Completed")+(tblTransactions[Transaction Status]="Reconciled"))*(IFERROR(INDEX(tblGoals[Goal ID],MATCH(tblTransactions[Destination Name],tblGoals[Goal ID],0)),IFERROR(INDEX(tblGoals[Goal ID],MATCH(tblTransactions[Destination Name],tblGoals[Goal Name],0)),""))=tblGoals[[#This Row],[Goal ID]])*(tblTransactions[Amount])),0)) | G10: =MAX(0,tblGoals[[#This Row],[Target Amount]]-tblGoals[[#This Row],[Current Saved Amount]]) -> 0
F11: =IF(tblGoals[[#This Row],[Goal ID]]="","",IFERROR(SUMPRODUCT((tblTransactions[Transaction Type]="Expense")*(tblTransactions[Destination Type]="Goal")*((tblTransactions[Transaction Status]="Completed")+(tblTransactions[Transaction Status]="Reconciled"))*(IFERROR(INDEX(tblGoals[Goal ID],MATCH(tblTransactions[Destination Name],tblGoals[Goal ID],0)),IFERROR(INDEX(tblGoals[Goal ID],MATCH(tblTransactions[Destination Name],tblGoals[Goal Name],0)),""))=tblGoals[[#This Row],[Goal ID]])*(tblTransactions[Amount])),0)) | G11: =MAX(0,tblGoals[[#This Row],[Target Amount]]-tblGoals[[#This Row],[Current Saved Amount]]) -> 0
F12: =IF(tblGoals[[#This Row],[Goal ID]]="","",IFERROR(SUMPRODUCT((tblTransactions[Transaction Type]="Expense")*(tblTransactions[Destination Type]="Goal")*((tblTransactions[Transaction Status]="Completed")+(tblTransactions[Transaction Status]="Reconciled"))*(IFERROR(INDEX(tblGoals[Goal ID],MATCH(tblTransactions[Destination Name],tblGoals[Goal ID],0)),IFERROR(INDEX(tblGoals[Goal ID],MATCH(tblTransactions[Destination Name],tblGoals[Goal Name],0)),""))=tblGoals[[#This Row],[Goal ID]])*(tblTransactions[Amount])),0)) | G12: =MAX(0,tblGoals[[#This Row],[Target Amount]]-tblGoals[[#This Row],[Current Saved Amount]]) -> 0
F13: =IF(tblGoals[[#This Row],[Goal ID]]="","",IFERROR(SUMPRODUCT((tblTransactions[Transaction Type]="Expense")*(tblTransactions[Destination Type]="Goal")*((tblTransactions[Transaction Status]="Completed")+(tblTransactions[Transaction Status]="Reconciled"))*(IFERROR(INDEX(tblGoals[Goal ID],MATCH(tblTransactions[Destination Name],tblGoals[Goal ID],0)),IFERROR(INDEX(tblGoals[Goal ID],MATCH(tblTransactions[Destination Name],tblGoals[Goal Name],0)),""))=tblGoals[[#This Row],[Goal ID]])*(tblTransactions[Amount])),0)) | G13: =MAX(0,tblGoals[[#This Row],[Target Amount]]-tblGoals[[#This Row],[Current Saved Amount]]) -> 0
... F200: =IF(tblGoals[[#This Row],[Goal ID]]="","",IFERROR(SUMPRODUCT((tblTransactions[Transaction Type]="Expense")*(tblTransactions[Destination Type]="Goal")*((tblTransactions[Transaction Status]="Completed")+(tblTransactions[Transaction Status]="Reconciled"))*(IFERROR(INDEX(tblGoals[Goal ID],MATCH(tblTransactions[Destination Name],tblGoals[Goal ID],0)),IFERROR(INDEX(tblGoals[Goal ID],MATCH(tblTransactions[Destination Name],tblGoals[Goal Name],0)),""))=tblGoals[[#This Row],[Goal ID]])*(tblTransactions[Amount])),0)) | G200: =MAX(0,tblGoals[[#This Row],[Target Amount]]-tblGoals[[#This Row],[Current Saved Amount]]) -> 0

Sheet Helpers
A1: Currency Code | B1: Currency Name | C1: Symbol | D1: Completed | E1: valExpenseCategories | F1: valIncomeCategories | G1: valActiveAccounts | H1: valActiveGoals | I1: valActiveAssets | J1: valActiveLiabilities | K1: valIncomeSources | L1: valBlank | AG1: Asset Type | AH1: Liability Type | AI1: Income Type
A2: INR | D2: Pending | E2: =IFERROR(SORT(UNIQUE(FILTER(tblCategories[Category Name],(tblCategories[Category Type]="Expense")*(tblCategories[Status]="Active")))),"") | F2: =IFERROR(SORT(UNIQUE(FILTER(tblCategories[Category Name],(tblCategories[Category Type]="Income")*(tblCategories[Status]="Active")))),"") | G2: =IFERROR(SORT(UNIQUE(FILTER(tblAccounts[Account Name],tblAccounts[Status]="Active"))),"") | H2: =IFERROR(SORT(UNIQUE(FILTER(tblGoals[Goal Name],tblGoals[Goal Status]="Active"))),"") | I2: =IFERROR(SORT(UNIQUE(FILTER(tblAssets[Asset Name],tblAssets[Status]="Active"))),"") | J2: =IFERROR(SORT(UNIQUE(FILTER(tblLiabilities[Liability Name],tblLiabilities[Status]="Active"))),"") | K2: =IFERROR(SORT(UNIQUE(FILTER(tblIncomeSources[Income Source Name],tblIncomeSources[Status]="Active"))),"") | AG2: Mutual Fund | AH2: Home Loan | AI2: Salary
A3: USD | D3: Cancelled | AG3: Stock | AH3: Personal Loan | AI3: Freelance
A4: EUR | D4: Reconciled | AG4: ETF | AH4: Education Loan | AI4: Bonus
A5: GBP | AG5: Gold ETF | AH5: Vehicle Loan | AI5: Rental Income
A6: AED | AG6: Bond | AH6: Gold Loan | AI6: Interest
AG7: SIP | AH7: Credit Card | AI7: Cashback
AG8: Fixed Deposit | AH8: Buy Now Pay Later | AI8: Refund
A9: Payment Method | AG9: PPF | AH9: Family Loan | AI9: Business Income
A10: Bank Transfer | AG10: EPF | AH10: Business Loan | AI10: Investment
A11: Cash | AG11: NPS | AH11: Other Liability
A12: UPI | AG12: Gold Jewellery
A13: Debit Card | AG13: Gold Coin
A14: Credit Card | AG14: Vehicle
A15: Wallet | AG15: Electronics
A16: Net Banking | AG16: Furniture
A17: Other | AG17: Watch
AG18: Other Physical Asset
AG19: Residential Property
A20: Transaction Type | AG20: Commercial Property
A21: Income | AG21: Land
A22: Expense | AG22: Plot
A23: Transfer | AG23: Emergency Cash
A24: Adjustment | AG24: Foreign Currency
AG25: Cash Reserve
A27: Destination Type
A28: Expense Category
A29: Income Category
A30: Account
A31: Goal
A32: Liability
A33: Asset
A34: Other
A37: Frequency
A38: Monthly
A39: Quarterly
A40: Half-Yearly
... A107: FinanceOS Default
A110: Month Number | B110: Month Name | C110: Short Name
A111: 1 | B111: January | C111: Jan
A112: 2 | B112: February | C112: Feb
A113: 3 | B113: March | C113: Mar
A114: 4 | B114: April | C114: Apr
A115: 5 | B115: May | C115: May
A116: 6 | B116: June | C116: Jun
A117: 7 | B117: July | C117: Jul
A118: 8 | B118: August | C118: Aug
A119: 9 | B119: September | C119: Sep
A120: 10 | B120: October | C120: Oct
A121: 11 | B121: November | C121: Nov
A122: 12 | B122: December | C122: Dec
A125: Financial Year
A129: Validation Output Placeholders
A130: valExpenseCategories
A131: valIncomeCategories
A132: valActiveAccounts
A133: valActiveGoals
A134: valActiveAssets
A135: valActiveLiabilities
A136: valIncomeSources
A137: valPaymentMethods
A138: valFrequency
A139: valPriority
... A148: valCommitmentStatus

Sheet Business Engine
A1: As-Of Date | D1: Account Name | E1: Opening Balance | F1: Money In | G1: Money Out | H1: Current Balance | I1: Last Transaction Date | J1: Account Type | K1: Dashboard Enabled | L1: Status
D2: =IF(INDEX(tblAccounts[Account Name],ROW()-1)="","",INDEX(tblAccounts[Account Name],ROW()-1)) | E2: =IF($D2="","",IFERROR(INDEX(tblAccounts[Opening Balance],ROW()-1),0)) | F2: =IF($D2="","",SUMIFS(tblTransactions[Amount],tblTransactions[Transaction Type],"Income",tblTransactions[Transaction Status],"Completed",tblTransactions[Source Account],$D2)+SUMIFS(tblTransactions[Amount],tblTransactions[Transaction Type],"Income",tblTransactions[Transaction Status],"Reconciled",tblTransactions[Source Account],$D2)+SUMIFS(tblTransactions[Amount],tblTransactions[Transaction Type],"Transfer",tblTransactions[Transaction Status],"Completed",tblTransactions[Destination Type],"Account",tblTransactions[Destination Name],$D2)+SUMIFS(tblTransactions[Amount],tblTransactions[Transaction Type],"Transfer",tblTransactions[Transaction Status],"Reconciled",tblTransactions[Destination Type],"Account",tblTransactions[Destination Name],$D2)+SUMIFS(tblTransactions[Amount],tblTransactions[Transaction Type],"Adjustment",tblTransactions[Transaction Status],"Completed",tblTransactions[Source Account],$D2,tblTransactions[Amount],">0")+SUMIFS(tblTransactions[Amount],tblTransactions[Transaction Type],"Adjustment",tblTransactions[Transaction Status],"Reconciled",tblTransactions[Source Account],$D2,tblTransactions[Amount],">0")) | G2: =IF($D2="","",SUMIFS(tblTransactions[Amount],tblTransactions[Transaction Type],"Expense",tblTransactions[Transaction Status],"Completed",tblTransactions[Source Account],$D2)+SUMIFS(tblTransactions[Amount],tblTransactions[Transaction Type],"Expense",tblTransactions[Transaction Status],"Reconciled",tblTransactions[Source Account],$D2)+SUMIFS(tblTransactions[Amount],tblTransactions[Transaction Type],"Transfer",tblTransactions[Transaction Status],"Completed",tblTransactions[Source Account],$D2)+SUMIFS(tblTransactions[Amount],tblTransactions[Transaction Type],"Transfer",tblTransactions[Transaction Status],"Reconciled",tblTransactions[Source Account],$D2)-SUMIFS(tblTransactions[Amount],tblTransactions[Transaction Type],"Adjustment",tblTransactions[Transaction Status],"Completed",tblTransactions[Source Account],$D2,tblTransactions[Amount],"<0")-SUMIFS(tblTransactions[Amount],tblTransactions[Transaction Type],"Adjustment",tblTransactions[Transaction Status],"Reconciled",tblTransactions[Source Account],$D2,tblTransactions[Amount],"<0")) | H2: =IF($D2="","",$E2+$F2-$G2) | I2: =#N/A -> #N/A | J2: =IF($D2="","",IFERROR(INDEX(tblAccounts[Account Type],ROW()-1),"")) | K2: =IF($D2="","",IFERROR(INDEX(tblAccounts[Include in Dashboard],ROW()-1),"")) | L2: =IF($D2="","",IFERROR(INDEX(tblAccounts[Status],ROW()-1),""))
A3: SECTION 1 — Accounts Summary | D3: =IF(INDEX(tblAccounts[Account Name],ROW()-1)="","",INDEX(tblAccounts[Account Name],ROW()-1)) | E3: =IF($D3="","",IFERROR(INDEX(tblAccounts[Opening Balance],ROW()-1),0)) | F3: =IF($D3="","",SUMIFS(tblTransactions[Amount],tblTransactions[Transaction Type],"Income",tblTransactions[Transaction Status],"Completed",tblTransactions[Source Account],$D3)+SUMIFS(tblTransactions[Amount],tblTransactions[Transaction Type],"Income",tblTransactions[Transaction Status],"Reconciled",tblTransactions[Source Account],$D3)+SUMIFS(tblTransactions[Amount],tblTransactions[Transaction Type],"Transfer",tblTransactions[Transaction Status],"Completed",tblTransactions[Destination Type],"Account",tblTransactions[Destination Name],$D3)+SUMIFS(tblTransactions[Amount],tblTransactions[Transaction Type],"Transfer",tblTransactions[Transaction Status],"Reconciled",tblTransactions[Destination Type],"Account",tblTransactions[Destination Name],$D3)+SUMIFS(tblTransactions[Amount],tblTransactions[Transaction Type],"Adjustment",tblTransactions[Transaction Status],"Completed",tblTransactions[Source Account],$D3,tblTransactions[Amount],">0")+SUMIFS(tblTransactions[Amount],tblTransactions[Transaction Type],"Adjustment",tblTransactions[Transaction Status],"Reconciled",tblTransactions[Source Account],$D3,tblTransactions[Amount],">0")) | G3: =IF($D3="","",SUMIFS(tblTransactions[Amount],tblTransactions[Transaction Type],"Expense",tblTransactions[Transaction Status],"Completed",tblTransactions[Source Account],$D3)+SUMIFS(tblTransactions[Amount],tblTransactions[Transaction Type],"Expense",tblTransactions[Transaction Status],"Reconciled",tblTransactions[Source Account],$D3)+SUMIFS(tblTransactions[Amount],tblTransactions[Transaction Type],"Transfer",tblTransactions[Transaction Status],"Completed",tblTransactions[Source Account],$D3)+SUMIFS(tblTransactions[Amount],tblTransactions[Transaction Type],"Transfer",tblTransactions[Transaction Status],"Reconciled",tblTransactions[Source Account],$D3)-SUMIFS(tblTransactions[Amount],tblTransactions[Transaction Type],"Adjustment",tblTransactions[Transaction Status],"Completed",tblTransactions[Source Account],$D3,tblTransactions[Amount],"<0")-SUMIFS(tblTransactions[Amount],tblTransactions[Transaction Type],"Adjustment",tblTransactions[Transaction Status],"Reconciled",tblTransactions[Source Account],$D3,tblTransactions[Amount],"<0")) | H3: =IF($D3="","",$E3+$F3-$G3) | I3: =#N/A -> #N/A | J3: =IF($D3="","",IFERROR(INDEX(tblAccounts[Account Type],ROW()-1),"")) | K3: =IF($D3="","",IFERROR(INDEX(tblAccounts[Include in Dashboard],ROW()-1),"")) | L3: =IF($D3="","",IFERROR(INDEX(tblAccounts[Status],ROW()-1),""))
A4: Total Active Account Balance | B4: =IFERROR(SUMIFS($H$2:$H$200,$L$2:$L$200,"Active",$K$2:$K$200,"Yes"),0) -> 0 | D4: =IF(INDEX(tblAccounts[Account Name],ROW()-1)="","",INDEX(tblAccounts[Account Name],ROW()-1)) | E4: =IF($D4="","",IFERROR(INDEX(tblAccounts[Opening Balance],ROW()-1),0)) | F4: =IF($D4="","",SUMIFS(tblTransactions[Amount],tblTransactions[Transaction Type],"Income",tblTransactions[Transaction Status],"Completed",tblTransactions[Source Account],$D4)+SUMIFS(tblTransactions[Amount],tblTransactions[Transaction Type],"Income",tblTransactions[Transaction Status],"Reconciled",tblTransactions[Source Account],$D4)+SUMIFS(tblTransactions[Amount],tblTransactions[Transaction Type],"Transfer",tblTransactions[Transaction Status],"Completed",tblTransactions[Destination Type],"Account",tblTransactions[Destination Name],$D4)+SUMIFS(tblTransactions[Amount],tblTransactions[Transaction Type],"Transfer",tblTransactions[Transaction Status],"Reconciled",tblTransactions[Destination Type],"Account",tblTransactions[Destination Name],$D4)+SUMIFS(tblTransactions[Amount],tblTransactions[Transaction Type],"Adjustment",tblTransactions[Transaction Status],"Completed",tblTransactions[Source Account],$D4,tblTransactions[Amount],">0")+SUMIFS(tblTransactions[Amount],tblTransactions[Transaction Type],"Adjustment",tblTransactions[Transaction Status],"Reconciled",tblTransactions[Source Account],$D4,tblTransactions[Amount],">0")) | G4: =IF($D4="","",SUMIFS(tblTransactions[Amount],tblTransactions[Transaction Type],"Expense",tblTransactions[Transaction Status],"Completed",tblTransactions[Source Account],$D4)+SUMIFS(tblTransactions[Amount],tblTransactions[Transaction Type],"Expense",tblTransactions[Transaction Status],"Reconciled",tblTransactions[Source Account],$D4)+SUMIFS(tblTransactions[Amount],tblTransactions[Transaction Type],"Transfer",tblTransactions[Transaction Status],"Completed",tblTransactions[Source Account],$D4)+SUMIFS(tblTransactions[Amount],tblTransactions[Transaction Type],"Transfer",tblTransactions[Transaction Status],"Reconciled",tblTransactions[Source Account],$D4)-SUMIFS(tblTransactions[Amount],tblTransactions[Transaction Type],"Adjustment",tblTransactions[Transaction Status],"Completed",tblTransactions[Source Account],$D4,tblTransactions[Amount],"<0")-SUMIFS(tblTransactions[Amount],tblTransactions[Transaction Type],"Adjustment",tblTransactions[Transaction Status],"Reconciled",tblTransactions[Source Account],$D4,tblTransactions[Amount],"<0")) | H4: =IF($D4="","",$E4+$F4-$G4) | I4: =#N/A -> #N/A | J4: =IF($D4="","",IFERROR(INDEX(tblAccounts[Account Type],ROW()-1),"")) | K4: =IF($D4="","",IFERROR(INDEX(tblAccounts[Include in Dashboard],ROW()-1),"")) | L4: =IF($D4="","",IFERROR(INDEX(tblAccounts[Status],ROW()-1),""))
A5: Number of Active Accounts | B5: =COUNTIFS($D$2:$D$200,"<>",$L$2:$L$200,"Active",$K$2:$K$200,"Yes") -> 0 | D5: =IF(INDEX(tblAccounts[Account Name],ROW()-1)="","",INDEX(tblAccounts[Account Name],ROW()-1)) | E5: =IF($D5="","",IFERROR(INDEX(tblAccounts[Opening Balance],ROW()-1),0)) | F5: =IF($D5="","",SUMIFS(tblTransactions[Amount],tblTransactions[Transaction Type],"Income",tblTransactions[Transaction Status],"Completed",tblTransactions[Source Account],$D5)+SUMIFS(tblTransactions[Amount],tblTransactions[Transaction Type],"Income",tblTransactions[Transaction Status],"Reconciled",tblTransactions[Source Account],$D5)+SUMIFS(tblTransactions[Amount],tblTransactions[Transaction Type],"Transfer",tblTransactions[Transaction Status],"Completed",tblTransactions[Destination Type],"Account",tblTransactions[Destination Name],$D5)+SUMIFS(tblTransactions[Amount],tblTransactions[Transaction Type],"Transfer",tblTransactions[Transaction Status],"Reconciled",tblTransactions[Destination Type],"Account",tblTransactions[Destination Name],$D5)+SUMIFS(tblTransactions[Amount],tblTransactions[Transaction Type],"Adjustment",tblTransactions[Transaction Status],"Completed",tblTransactions[Source Account],$D5,tblTransactions[Amount],">0")+SUMIFS(tblTransactions[Amount],tblTransactions[Transaction Type],"Adjustment",tblTransactions[Transaction Status],"Reconciled",tblTransactions[Source Account],$D5,tblTransactions[Amount],">0")) | G5: =IF($D5="","",SUMIFS(tblTransactions[Amount],tblTransactions[Transaction Type],"Expense",tblTransactions[Transaction Status],"Completed",tblTransactions[Source Account],$D5)+SUMIFS(tblTransactions[Amount],tblTransactions[Transaction Type],"Expense",tblTransactions[Transaction Status],"Reconciled",tblTransactions[Source Account],$D5)+SUMIFS(tblTransactions[Amount],tblTransactions[Transaction Type],"Transfer",tblTransactions[Transaction Status],"Completed",tblTransactions[Source Account],$D5)+SUMIFS(tblTransactions[Amount],tblTransactions[Transaction Type],"Transfer",tblTransactions[Transaction Status],"Reconciled",tblTransactions[Source Account],$D5)-SUMIFS(tblTransactions[Amount],tblTransactions[Transaction Type],"Adjustment",tblTransactions[Transaction Status],"Completed",tblTransactions[Source Account],$D5,tblTransactions[Amount],"<0")-SUMIFS(tblTransactions[Amount],tblTransactions[Transaction Type],"Adjustment",tblTransactions[Transaction Status],"Reconciled",tblTransactions[Source Account],$D5,tblTransactions[Amount],"<0")) | H5: =IF($D5="","",$E5+$F5-$G5) | I5: =#N/A -> #N/A | J5: =IF($D5="","",IFERROR(INDEX(tblAccounts[Account Type],ROW()-1),"")) | K5: =IF($D5="","",IFERROR(INDEX(tblAccounts[Include in Dashboard],ROW()-1),"")) | L5: =IF($D5="","",IFERROR(INDEX(tblAccounts[Status],ROW()-1),""))
A6: Cash Accounts Total | B6: =IFERROR(SUMIFS($H$2:$H$200,$J$2:$J$200,"Cash",$L$2:$L$200,"Active",$K$2:$K$200,"Yes"),0) -> 0 | D6: =IF(INDEX(tblAccounts[Account Name],ROW()-1)="","",INDEX(tblAccounts[Account Name],ROW()-1)) | E6: =IF($D6="","",IFERROR(INDEX(tblAccounts[Opening Balance],ROW()-1),0)) | F6: =IF($D6="","",SUMIFS(tblTransactions[Amount],tblTransactions[Transaction Type],"Income",tblTransactions[Transaction Status],"Completed",tblTransactions[Source Account],$D6)+SUMIFS(tblTransactions[Amount],tblTransactions[Transaction Type],"Income",tblTransactions[Transaction Status],"Reconciled",tblTransactions[Source Account],$D6)+SUMIFS(tblTransactions[Amount],tblTransactions[Transaction Type],"Transfer",tblTransactions[Transaction Status],"Completed",tblTransactions[Destination Type],"Account",tblTransactions[Destination Name],$D6)+SUMIFS(tblTransactions[Amount],tblTransactions[Transaction Type],"Transfer",tblTransactions[Transaction Status],"Reconciled",tblTransactions[Destination Type],"Account",tblTransactions[Destination Name],$D6)+SUMIFS(tblTransactions[Amount],tblTransactions[Transaction Type],"Adjustment",tblTransactions[Transaction Status],"Completed",tblTransactions[Source Account],$D6,tblTransactions[Amount],">0")+SUMIFS(tblTransactions[Amount],tblTransactions[Transaction Type],"Adjustment",tblTransactions[Transaction Status],"Reconciled",tblTransactions[Source Account],$D6,tblTransactions[Amount],">0")) | G6: =IF($D6="","",SUMIFS(tblTransactions[Amount],tblTransactions[Transaction Type],"Expense",tblTransactions[Transaction Status],"Completed",tblTransactions[Source Account],$D6)+SUMIFS(tblTransactions[Amount],tblTransactions[Transaction Type],"Expense",tblTransactions[Transaction Status],"Reconciled",tblTransactions[Source Account],$D6)+SUMIFS(tblTransactions[Amount],tblTransactions[Transaction Type],"Transfer",tblTransactions[Transaction Status],"Completed",tblTransactions[Source Account],$D6)+SUMIFS(tblTransactions[Amount],tblTransactions[Transaction Type],"Transfer",tblTransactions[Transaction Status],"Reconciled",tblTransactions[Source Account],$D6)-SUMIFS(tblTransactions[Amount],tblTransactions[Transaction Type],"Adjustment",tblTransactions[Transaction Status],"Completed",tblTransactions[Source Account],$D6,tblTransactions[Amount],"<0")-SUMIFS(tblTransactions[Amount],tblTransactions[Transaction Type],"Adjustment",tblTransactions[Transaction Status],"Reconciled",tblTransactions[Source Account],$D6,tblTransactions[Amount],"<0")) | H6: =IF($D6="","",$E6+$F6-$G6) | I6: =#N/A -> #N/A | J6: =IF($D6="","",IFERROR(INDEX(tblAccounts[Account Type],ROW()-1),"")) | K6: =IF($D6="","",IFERROR(INDEX(tblAccounts[Include in Dashboard],ROW()-1),"")) | L6: =IF($D6="","",IFERROR(INDEX(tblAccounts[Status],ROW()-1),""))
A7: Savings Accounts Total | B7: =IFERROR(SUMIFS($H$2:$H$200,$J$2:$J$200,"Savings Bank",$L$2:$L$200,"Active",$K$2:$K$200,"Yes"),0) -> 0 | D7: =IF(INDEX(tblAccounts[Account Name],ROW()-1)="","",INDEX(tblAccounts[Account Name],ROW()-1)) | E7: =IF($D7="","",IFERROR(INDEX(tblAccounts[Opening Balance],ROW()-1),0)) | F7: =IF($D7="","",SUMIFS(tblTransactions[Amount],tblTransactions[Transaction Type],"Income",tblTransactions[Transaction Status],"Completed",tblTransactions[Source Account],$D7)+SUMIFS(tblTransactions[Amount],tblTransactions[Transaction Type],"Income",tblTransactions[Transaction Status],"Reconciled",tblTransactions[Source Account],$D7)+SUMIFS(tblTransactions[Amount],tblTransactions[Transaction Type],"Transfer",tblTransactions[Transaction Status],"Completed",tblTransactions[Destination Type],"Account",tblTransactions[Destination Name],$D7)+SUMIFS(tblTransactions[Amount],tblTransactions[Transaction Type],"Transfer",tblTransactions[Transaction Status],"Reconciled",tblTransactions[Destination Type],"Account",tblTransactions[Destination Name],$D7)+SUMIFS(tblTransactions[Amount],tblTransactions[Transaction Type],"Adjustment",tblTransactions[Transaction Status],"Completed",tblTransactions[Source Account],$D7,tblTransactions[Amount],">0")+SUMIFS(tblTransactions[Amount],tblTransactions[Transaction Type],"Adjustment",tblTransactions[Transaction Status],"Reconciled",tblTransactions[Source Account],$D7,tblTransactions[Amount],">0")) | G7: =IF($D7="","",SUMIFS(tblTransactions[Amount],tblTransactions[Transaction Type],"Expense",tblTransactions[Transaction Status],"Completed",tblTransactions[Source Account],$D7)+SUMIFS(tblTransactions[Amount],tblTransactions[Transaction Type],"Expense",tblTransactions[Transaction Status],"Reconciled",tblTransactions[Source Account],$D7)+SUMIFS(tblTransactions[Amount],tblTransactions[Transaction Type],"Transfer",tblTransactions[Transaction Status],"Completed",tblTransactions[Source Account],$D7)+SUMIFS(tblTransactions[Amount],tblTransactions[Transaction Type],"Transfer",tblTransactions[Transaction Status],"Reconciled",tblTransactions[Source Account],$D7)-SUMIFS(tblTransactions[Amount],tblTransactions[Transaction Type],"Adjustment",tblTransactions[Transaction Status],"Completed",tblTransactions[Source Account],$D7,tblTransactions[Amount],"<0")-SUMIFS(tblTransactions[Amount],tblTransactions[Transaction Type],"Adjustment",tblTransactions[Transaction Status],"Reconciled",tblTransactions[Source Account],$D7,tblTransactions[Amount],"<0")) | H7: =IF($D7="","",$E7+$F7-$G7) | I7: =#N/A -> #N/A | J7: =IF($D7="","",IFERROR(INDEX(tblAccounts[Account Type],ROW()-1),"")) | K7: =IF($D7="","",IFERROR(INDEX(tblAccounts[Include in Dashboard],ROW()-1),"")) | L7: =IF($D7="","",IFERROR(INDEX(tblAccounts[Status],ROW()-1),""))
A8: Investment Accounts Total | B8: =IFERROR(SUMIFS($H$2:$H$200,$J$2:$J$200,"Investment Account",$L$2:$L$200,"Active",$K$2:$K$200,"Yes"),0) -> 0 | D8: =IF(INDEX(tblAccounts[Account Name],ROW()-1)="","",INDEX(tblAccounts[Account Name],ROW()-1)) | E8: =IF($D8="","",IFERROR(INDEX(tblAccounts[Opening Balance],ROW()-1),0)) | F8: =IF($D8="","",SUMIFS(tblTransactions[Amount],tblTransactions[Transaction Type],"Income",tblTransactions[Transaction Status],"Completed",tblTransactions[Source Account],$D8)+SUMIFS(tblTransactions[Amount],tblTransactions[Transaction Type],"Income",tblTransactions[Transaction Status],"Reconciled",tblTransactions[Source Account],$D8)+SUMIFS(tblTransactions[Amount],tblTransactions[Transaction Type],"Transfer",tblTransactions[Transaction Status],"Completed",tblTransactions[Destination Type],"Account",tblTransactions[Destination Name],$D8)+SUMIFS(tblTransactions[Amount],tblTransactions[Transaction Type],"Transfer",tblTransactions[Transaction Status],"Reconciled",tblTransactions[Destination Type],"Account",tblTransactions[Destination Name],$D8)+SUMIFS(tblTransactions[Amount],tblTransactions[Transaction Type],"Adjustment",tblTransactions[Transaction Status],"Completed",tblTransactions[Source Account],$D8,tblTransactions[Amount],">0")+SUMIFS(tblTransactions[Amount],tblTransactions[Transaction Type],"Adjustment",tblTransactions[Transaction Status],"Reconciled",tblTransactions[Source Account],$D8,tblTransactions[Amount],">0")) | G8: =IF($D8="","",SUMIFS(tblTransactions[Amount],tblTransactions[Transaction Type],"Expense",tblTransactions[Transaction Status],"Completed",tblTransactions[Source Account],$D8)+SUMIFS(tblTransactions[Amount],tblTransactions[Transaction Type],"Expense",tblTransactions[Transaction Status],"Reconciled",tblTransactions[Source Account],$D8)+SUMIFS(tblTransactions[Amount],tblTransactions[Transaction Type],"Transfer",tblTransactions[Transaction Status],"Completed",tblTransactions[Source Account],$D8)+SUMIFS(tblTransactions[Amount],tblTransactions[Transaction Type],"Transfer",tblTransactions[Transaction Status],"Reconciled",tblTransactions[Source Account],$D8)-SUMIFS(tblTransactions[Amount],tblTransactions[Transaction Type],"Adjustment",tblTransactions[Transaction Status],"Completed",tblTransactions[Source Account],$D8,tblTransactions[Amount],"<0")-SUMIFS(tblTransactions[Amount],tblTransactions[Transaction Type],"Adjustment",tblTransactions[Transaction Status],"Reconciled",tblTransactions[Source Account],$D8,tblTransactions[Amount],"<0")) | H8: =IF($D8="","",$E8+$F8-$G8) | I8: =#N/A -> #N/A | J8: =IF($D8="","",IFERROR(INDEX(tblAccounts[Account Type],ROW()-1),"")) | K8: =IF($D8="","",IFERROR(INDEX(tblAccounts[Include in Dashboard],ROW()-1),"")) | L8: =IF($D8="","",IFERROR(INDEX(tblAccounts[Status],ROW()-1),""))
A9: Credit Accounts Total | B9: =IFERROR(SUMIFS($H$2:$H$200,$J$2:$J$200,"Credit Card",$L$2:$L$200,"Active",$K$2:$K$200,"Yes"),0) -> 0 | D9: =IF(INDEX(tblAccounts[Account Name],ROW()-1)="","",INDEX(tblAccounts[Account Name],ROW()-1)) | E9: =IF($D9="","",IFERROR(INDEX(tblAccounts[Opening Balance],ROW()-1),0)) | F9: =IF($D9="","",SUMIFS(tblTransactions[Amount],tblTransactions[Transaction Type],"Income",tblTransactions[Transaction Status],"Completed",tblTransactions[Source Account],$D9)+SUMIFS(tblTransactions[Amount],tblTransactions[Transaction Type],"Income",tblTransactions[Transaction Status],"Reconciled",tblTransactions[Source Account],$D9)+SUMIFS(tblTransactions[Amount],tblTransactions[Transaction Type],"Transfer",tblTransactions[Transaction Status],"Completed",tblTransactions[Destination Type],"Account",tblTransactions[Destination Name],$D9)+SUMIFS(tblTransactions[Amount],tblTransactions[Transaction Type],"Transfer",tblTransactions[Transaction Status],"Reconciled",tblTransactions[Destination Type],"Account",tblTransactions[Destination Name],$D9)+SUMIFS(tblTransactions[Amount],tblTransactions[Transaction Type],"Adjustment",tblTransactions[Transaction Status],"Completed",tblTransactions[Source Account],$D9,tblTransactions[Amount],">0")+SUMIFS(tblTransactions[Amount],tblTransactions[Transaction Type],"Adjustment",tblTransactions[Transaction Status],"Reconciled",tblTransactions[Source Account],$D9,tblTransactions[Amount],">0")) | G9: =IF($D9="","",SUMIFS(tblTransactions[Amount],tblTransactions[Transaction Type],"Expense",tblTransactions[Transaction Status],"Completed",tblTransactions[Source Account],$D9)+SUMIFS(tblTransactions[Amount],tblTransactions[Transaction Type],"Expense",tblTransactions[Transaction Status],"Reconciled",tblTransactions[Source Account],$D9)+SUMIFS(tblTransactions[Amount],tblTransactions[Transaction Type],"Transfer",tblTransactions[Transaction Status],"Completed",tblTransactions[Source Account],$D9)+SUMIFS(tblTransactions[Amount],tblTransactions[Transaction Type],"Transfer",tblTransactions[Transaction Status],"Reconciled",tblTransactions[Source Account],$D9)-SUMIFS(tblTransactions[Amount],tblTransactions[Transaction Type],"Adjustment",tblTransactions[Transaction Status],"Completed",tblTransactions[Source Account],$D9,tblTransactions[Amount],"<0")-SUMIFS(tblTransactions[Amount],tblTransactions[Transaction Type],"Adjustment",tblTransactions[Transaction Status],"Reconciled",tblTransactions[Source Account],$D9,tblTransactions[Amount],"<0")) | H9: =IF($D9="","",$E9+$F9-$G9) | I9: =#N/A -> #N/A | J9: =IF($D9="","",IFERROR(INDEX(tblAccounts[Account Type],ROW()-1),"")) | K9: =IF($D9="","",IFERROR(INDEX(tblAccounts[Include in Dashboard],ROW()-1),"")) | L9: =IF($D9="","",IFERROR(INDEX(tblAccounts[Status],ROW()-1),""))
D10: =IF(INDEX(tblAccounts[Account Name],ROW()-1)="","",INDEX(tblAccounts[Account Name],ROW()-1)) | E10: =IF($D10="","",IFERROR(INDEX(tblAccounts[Opening Balance],ROW()-1),0)) | F10: =IF($D10="","",SUMIFS(tblTransactions[Amount],tblTransactions[Transaction Type],"Income",tblTransactions[Transaction Status],"Completed",tblTransactions[Source Account],$D10)+SUMIFS(tblTransactions[Amount],tblTransactions[Transaction Type],"Income",tblTransactions[Transaction Status],"Reconciled",tblTransactions[Source Account],$D10)+SUMIFS(tblTransactions[Amount],tblTransactions[Transaction Type],"Transfer",tblTransactions[Transaction Status],"Completed",tblTransactions[Destination Type],"Account",tblTransactions[Destination Name],$D10)+SUMIFS(tblTransactions[Amount],tblTransactions[Transaction Type],"Transfer",tblTransactions[Transaction Status],"Reconciled",tblTransactions[Destination Type],"Account",tblTransactions[Destination Name],$D10)+SUMIFS(tblTransactions[Amount],tblTransactions[Transaction Type],"Adjustment",tblTransactions[Transaction Status],"Completed",tblTransactions[Source Account],$D10,tblTransactions[Amount],">0")+SUMIFS(tblTransactions[Amount],tblTransactions[Transaction Type],"Adjustment",tblTransactions[Transaction Status],"Reconciled",tblTransactions[Source Account],$D10,tblTransactions[Amount],">0")) | G10: =IF($D10="","",SUMIFS(tblTransactions[Amount],tblTransactions[Transaction Type],"Expense",tblTransactions[Transaction Status],"Completed",tblTransactions[Source Account],$D10)+SUMIFS(tblTransactions[Amount],tblTransactions[Transaction Type],"Expense",tblTransactions[Transaction Status],"Reconciled",tblTransactions[Source Account],$D10)+SUMIFS(tblTransactions[Amount],tblTransactions[Transaction Type],"Transfer",tblTransactions[Transaction Status],"Completed",tblTransactions[Source Account],$D10)+SUMIFS(tblTransactions[Amount],tblTransactions[Transaction Type],"Transfer",tblTransactions[Transaction Status],"Reconciled",tblTransactions[Source Account],$D10)-SUMIFS(tblTransactions[Amount],tblTransactions[Transaction Type],"Adjustment",tblTransactions[Transaction Status],"Completed",tblTransactions[Source Account],$D10,tblTransactions[Amount],"<0")-SUMIFS(tblTransactions[Amount],tblTransactions[Transaction Type],"Adjustment",tblTransactions[Transaction Status],"Reconciled",tblTransactions[Source Account],$D10,tblTransactions[Amount],"<0")) | H10: =IF($D10="","",$E10+$F10-$G10) | I10: =#N/A -> #N/A | J10: =IF($D10="","",IFERROR(INDEX(tblAccounts[Account Type],ROW()-1),"")) | K10: =IF($D10="","",IFERROR(INDEX(tblAccounts[Include in Dashboard],ROW()-1),"")) | L10: =IF($D10="","",IFERROR(INDEX(tblAccounts[Status],ROW()-1),""))
A11: SECTION 2 — Income Summary | D11: =IF(INDEX(tblAccounts[Account Name],ROW()-1)="","",INDEX(tblAccounts[Account Name],ROW()-1)) | E11: =IF($D11="","",IFERROR(INDEX(tblAccounts[Opening Balance],ROW()-1),0)) | F11: =IF($D11="","",SUMIFS(tblTransactions[Amount],tblTransactions[Transaction Type],"Income",tblTransactions[Transaction Status],"Completed",tblTransactions[Source Account],$D11)+SUMIFS(tblTransactions[Amount],tblTransactions[Transaction Type],"Income",tblTransactions[Transaction Status],"Reconciled",tblTransactions[Source Account],$D11)+SUMIFS(tblTransactions[Amount],tblTransactions[Transaction Type],"Transfer",tblTransactions[Transaction Status],"Completed",tblTransactions[Destination Type],"Account",tblTransactions[Destination Name],$D11)+SUMIFS(tblTransactions[Amount],tblTransactions[Transaction Type],"Transfer",tblTransactions[Transaction Status],"Reconciled",tblTransactions[Destination Type],"Account",tblTransactions[Destination Name],$D11)+SUMIFS(tblTransactions[Amount],tblTransactions[Transaction Type],"Adjustment",tblTransactions[Transaction Status],"Completed",tblTransactions[Source Account],$D11,tblTransactions[Amount],">0")+SUMIFS(tblTransactions[Amount],tblTransactions[Transaction Type],"Adjustment",tblTransactions[Transaction Status],"Reconciled",tblTransactions[Source Account],$D11,tblTransactions[Amount],">0")) | G11: =IF($D11="","",SUMIFS(tblTransactions[Amount],tblTransactions[Transaction Type],"Expense",tblTransactions[Transaction Status],"Completed",tblTransactions[Source Account],$D11)+SUMIFS(tblTransactions[Amount],tblTransactions[Transaction Type],"Expense",tblTransactions[Transaction Status],"Reconciled",tblTransactions[Source Account],$D11)+SUMIFS(tblTransactions[Amount],tblTransactions[Transaction Type],"Transfer",tblTransactions[Transaction Status],"Completed",tblTransactions[Source Account],$D11)+SUMIFS(tblTransactions[Amount],tblTransactions[Transaction Type],"Transfer",tblTransactions[Transaction Status],"Reconciled",tblTransactions[Source Account],$D11)-SUMIFS(tblTransactions[Amount],tblTransactions[Transaction Type],"Adjustment",tblTransactions[Transaction Status],"Completed",tblTransactions[Source Account],$D11,tblTransactions[Amount],"<0")-SUMIFS(tblTransactions[Amount],tblTransactions[Transaction Type],"Adjustment",tblTransactions[Transaction Status],"Reconciled",tblTransactions[Source Account],$D11,tblTransactions[Amount],"<0")) | H11: =IF($D11="","",$E11+$F11-$G11) | I11: =#N/A -> #N/A | J11: =IF($D11="","",IFERROR(INDEX(tblAccounts[Account Type],ROW()-1),"")) | K11: =IF($D11="","",IFERROR(INDEX(tblAccounts[Include in Dashboard],ROW()-1),"")) | L11: =IF($D11="","",IFERROR(INDEX(tblAccounts[Status],ROW()-1),""))
A12: Monthly Salary Income | B12: =IFERROR(SUMPRODUCT((tblTransactions[Transaction Type]="Income")*(tblTransactions[Transaction Date]>=DATE(YEAR($B$1),MONTH($B$1),1))*(tblTransactions[Transaction Date]<DATE(YEAR($B$1),MONTH($B$1)+1,1))*(tblTransactions[Amount])*((tblTransactions[Transaction Status]="Completed")+(tblTransactions[Transaction Status]="Reconciled"))*(IFERROR(INDEX(tblIncomeSources[Income Category],MATCH(tblTransactions[Income Source],tblIncomeSources[Income Source Name],0)),"")="Salary")),0) -> 0 | D12: =IF(INDEX(tblAccounts[Account Name],ROW()-1)="","",INDEX(tblAccounts[Account Name],ROW()-1)) | E12: =IF($D12="","",IFERROR(INDEX(tblAccounts[Opening Balance],ROW()-1),0)) | F12: =IF($D12="","",SUMIFS(tblTransactions[Amount],tblTransactions[Transaction Type],"Income",tblTransactions[Transaction Status],"Completed",tblTransactions[Source Account],$D12)+SUMIFS(tblTransactions[Amount],tblTransactions[Transaction Type],"Income",tblTransactions[Transaction Status],"Reconciled",tblTransactions[Source Account],$D12)+SUMIFS(tblTransactions[Amount],tblTransactions[Transaction Type],"Transfer",tblTransactions[Transaction Status],"Completed",tblTransactions[Destination Type],"Account",tblTransactions[Destination Name],$D12)+SUMIFS(tblTransactions[Amount],tblTransactions[Transaction Type],"Transfer",tblTransactions[Transaction Status],"Reconciled",tblTransactions[Destination Type],"Account",tblTransactions[Destination Name],$D12)+SUMIFS(tblTransactions[Amount],tblTransactions[Transaction Type],"Adjustment",tblTransactions[Transaction Status],"Completed",tblTransactions[Source Account],$D12,tblTransactions[Amount],">0")+SUMIFS(tblTransactions[Amount],tblTransactions[Transaction Type],"Adjustment",tblTransactions[Transaction Status],"Reconciled",tblTransactions[Source Account],$D12,tblTransactions[Amount],">0")) | G12: =IF($D12="","",SUMIFS(tblTransactions[Amount],tblTransactions[Transaction Type],"Expense",tblTransactions[Transaction Status],"Completed",tblTransactions[Source Account],$D12)+SUMIFS(tblTransactions[Amount],tblTransactions[Transaction Type],"Expense",tblTransactions[Transaction Status],"Reconciled",tblTransactions[Source Account],$D12)+SUMIFS(tblTransactions[Amount],tblTransactions[Transaction Type],"Transfer",tblTransactions[Transaction Status],"Completed",tblTransactions[Source Account],$D12)+SUMIFS(tblTransactions[Amount],tblTransactions[Transaction Type],"Transfer",tblTransactions[Transaction Status],"Reconciled",tblTransactions[Source Account],$D12)-SUMIFS(tblTransactions[Amount],tblTransactions[Transaction Type],"Adjustment",tblTransactions[Transaction Status],"Completed",tblTransactions[Source Account],$D12,tblTransactions[Amount],"<0")-SUMIFS(tblTransactions[Amount],tblTransactions[Transaction Type],"Adjustment",tblTransactions[Transaction Status],"Reconciled",tblTransactions[Source Account],$D12,tblTransactions[Amount],"<0")) | H12: =IF($D12="","",$E12+$F12-$G12) | I12: =#N/A -> #N/A | J12: =IF($D12="","",IFERROR(INDEX(tblAccounts[Account Type],ROW()-1),"")) | K12: =IF($D12="","",IFERROR(INDEX(tblAccounts[Include in Dashboard],ROW()-1),"")) | L12: =IF($D12="","",IFERROR(INDEX(tblAccounts[Status],ROW()-1),""))
A13: Monthly Business Income | B13: =IFERROR(SUMPRODUCT((tblTransactions[Transaction Type]="Income")*(tblTransactions[Transaction Date]>=DATE(YEAR($B$1),MONTH($B$1),1))*(tblTransactions[Transaction Date]<DATE(YEAR($B$1),MONTH($B$1)+1,1))*(tblTransactions[Amount])*((tblTransactions[Transaction Status]="Completed")+(tblTransactions[Transaction Status]="Reconciled"))*(IFERROR(INDEX(tblIncomeSources[Income Category],MATCH(tblTransactions[Income Source],tblIncomeSources[Income Source Name],0)),"")="Business Income")),0) -> 0 | D13: =IF(INDEX(tblAccounts[Account Name],ROW()-1)="","",INDEX(tblAccounts[Account Name],ROW()-1)) | E13: =IF($D13="","",IFERROR(INDEX(tblAccounts[Opening Balance],ROW()-1),0)) | F13: =IF($D13="","",SUMIFS(tblTransactions[Amount],tblTransactions[Transaction Type],"Income",tblTransactions[Transaction Status],"Completed",tblTransactions[Source Account],$D13)+SUMIFS(tblTransactions[Amount],tblTransactions[Transaction Type],"Income",tblTransactions[Transaction Status],"Reconciled",tblTransactions[Source Account],$D13)+SUMIFS(tblTransactions[Amount],tblTransactions[Transaction Type],"Transfer",tblTransactions[Transaction Status],"Completed",tblTransactions[Destination Type],"Account",tblTransactions[Destination Name],$D13)+SUMIFS(tblTransactions[Amount],tblTransactions[Transaction Type],"Transfer",tblTransactions[Transaction Status],"Reconciled",tblTransactions[Destination Type],"Account",tblTransactions[Destination Name],$D13)+SUMIFS(tblTransactions[Amount],tblTransactions[Transaction Type],"Adjustment",tblTransactions[Transaction Status],"Completed",tblTransactions[Source Account],$D13,tblTransactions[Amount],">0")+SUMIFS(tblTransactions[Amount],tblTransactions[Transaction Type],"Adjustment",tblTransactions[Transaction Status],"Reconciled",tblTransactions[Source Account],$D13,tblTransactions[Amount],">0")) | G13: =IF($D13="","",SUMIFS(tblTransactions[Amount],tblTransactions[Transaction Type],"Expense",tblTransactions[Transaction Status],"Completed",tblTransactions[Source Account],$D13)+SUMIFS(tblTransactions[Amount],tblTransactions[Transaction Type],"Expense",tblTransactions[Transaction Status],"Reconciled",tblTransactions[Source Account],$D13)+SUMIFS(tblTransactions[Amount],tblTransactions[Transaction Type],"Transfer",tblTransactions[Transaction Status],"Completed",tblTransactions[Source Account],$D13)+SUMIFS(tblTransactions[Amount],tblTransactions[Transaction Type],"Transfer",tblTransactions[Transaction Status],"Reconciled",tblTransactions[Source Account],$D13)-SUMIFS(tblTransactions[Amount],tblTransactions[Transaction Type],"Adjustment",tblTransactions[Transaction Status],"Completed",tblTransactions[Source Account],$D13,tblTransactions[Amount],"<0")-SUMIFS(tblTransactions[Amount],tblTransactions[Transaction Type],"Adjustment",tblTransactions[Transaction Status],"Reconciled",tblTransactions[Source Account],$D13,tblTransactions[Amount],"<0")) | H13: =IF($D13="","",$E13+$F13-$G13) | I13: =#N/A -> #N/A | J13: =IF($D13="","",IFERROR(INDEX(tblAccounts[Account Type],ROW()-1),"")) | K13: =IF($D13="","",IFERROR(INDEX(tblAccounts[Include in Dashboard],ROW()-1),"")) | L13: =IF($D13="","",IFERROR(INDEX(tblAccounts[Status],ROW()-1),""))
A14: Monthly Freelance Income | B14: =IFERROR(SUMPRODUCT((tblTransactions[Transaction Type]="Income")*(tblTransactions[Transaction Date]>=DATE(YEAR($B$1),MONTH($B$1),1))*(tblTransactions[Transaction Date]<DATE(YEAR($B$1),MONTH($B$1)+1,1))*(tblTransactions[Amount])*((tblTransactions[Transaction Status]="Completed")+(tblTransactions[Transaction Status]="Reconciled"))*(IFERROR(INDEX(tblIncomeSources[Income Category],MATCH(tblTransactions[Income Source],tblIncomeSources[Income Source Name],0)),"")="Freelance")),0) -> 0 | D14: =IF(INDEX(tblAccounts[Account Name],ROW()-1)="","",INDEX(tblAccounts[Account Name],ROW()-1)) | E14: =IF($D14="","",IFERROR(INDEX(tblAccounts[Opening Balance],ROW()-1),0)) | F14: =IF($D14="","",SUMIFS(tblTransactions[Amount],tblTransactions[Transaction Type],"Income",tblTransactions[Transaction Status],"Completed",tblTransactions[Source Account],$D14)+SUMIFS(tblTransactions[Amount],tblTransactions[Transaction Type],"Income",tblTransactions[Transaction Status],"Reconciled",tblTransactions[Source Account],$D14)+SUMIFS(tblTransactions[Amount],tblTransactions[Transaction Type],"Transfer",tblTransactions[Transaction Status],"Completed",tblTransactions[Destination Type],"Account",tblTransactions[Destination Name],$D14)+SUMIFS(tblTransactions[Amount],tblTransactions[Transaction Type],"Transfer",tblTransactions[Transaction Status],"Reconciled",tblTransactions[Destination Type],"Account",tblTransactions[Destination Name],$D14)+SUMIFS(tblTransactions[Amount],tblTransactions[Transaction Type],"Adjustment",tblTransactions[Transaction Status],"Completed",tblTransactions[Source Account],$D14,tblTransactions[Amount],">0")+SUMIFS(tblTransactions[Amount],tblTransactions[Transaction Type],"Adjustment",tblTransactions[Transaction Status],"Reconciled",tblTransactions[Source Account],$D14,tblTransactions[Amount],">0")) | G14: =IF($D14="","",SUMIFS(tblTransactions[Amount],tblTransactions[Transaction Type],"Expense",tblTransactions[Transaction Status],"Completed",tblTransactions[Source Account],$D14)+SUMIFS(tblTransactions[Amount],tblTransactions[Transaction Type],"Expense",tblTransactions[Transaction Status],"Reconciled",tblTransactions[Source Account],$D14)+SUMIFS(tblTransactions[Amount],tblTransactions[Transaction Type],"Transfer",tblTransactions[Transaction Status],"Completed",tblTransactions[Source Account],$D14)+SUMIFS(tblTransactions[Amount],tblTransactions[Transaction Type],"Transfer",tblTransactions[Transaction Status],"Reconciled",tblTransactions[Source Account],$D14)-SUMIFS(tblTransactions[Amount],tblTransactions[Transaction Type],"Adjustment",tblTransactions[Transaction Status],"Completed",tblTransactions[Source Account],$D14,tblTransactions[Amount],"<0")-SUMIFS(tblTransactions[Amount],tblTransactions[Transaction Type],"Adjustment",tblTransactions[Transaction Status],"Reconciled",tblTransactions[Source Account],$D14,tblTransactions[Amount],"<0")) | H14: =IF($D14="","",$E14+$F14-$G14) | I14: =#N/A -> #N/A | J14: =IF($D14="","",IFERROR(INDEX(tblAccounts[Account Type],ROW()-1),"")) | K14: =IF($D14="","",IFERROR(INDEX(tblAccounts[Include in Dashboard],ROW()-1),"")) | L14: =IF($D14="","",IFERROR(INDEX(tblAccounts[Status],ROW()-1),""))
A15: Monthly Investment Income | B15: =IFERROR(SUMPRODUCT((tblTransactions[Transaction Type]="Income")*(tblTransactions[Transaction Date]>=DATE(YEAR($B$1),MONTH($B$1),1))*(tblTransactions[Transaction Date]<DATE(YEAR($B$1),MONTH($B$1)+1,1))*(tblTransactions[Amount])*((tblTransactions[Transaction Status]="Completed")+(tblTransactions[Transaction Status]="Reconciled"))*(IFERROR(INDEX(tblIncomeSources[Income Category],MATCH(tblTransactions[Income Source],tblIncomeSources[Income Source Name],0)),"")="Investment")),0) -> 0 | D15: =IF(INDEX(tblAccounts[Account Name],ROW()-1)="","",INDEX(tblAccounts[Account Name],ROW()-1)) | E15: =IF($D15="","",IFERROR(INDEX(tblAccounts[Opening Balance],ROW()-1),0)) | F15: =IF($D15="","",SUMIFS(tblTransactions[Amount],tblTransactions[Transaction Type],"Income",tblTransactions[Transaction Status],"Completed",tblTransactions[Source Account],$D15)+SUMIFS(tblTransactions[Amount],tblTransactions[Transaction Type],"Income",tblTransactions[Transaction Status],"Reconciled",tblTransactions[Source Account],$D15)+SUMIFS(tblTransactions[Amount],tblTransactions[Transaction Type],"Transfer",tblTransactions[Transaction Status],"Completed",tblTransactions[Destination Type],"Account",tblTransactions[Destination Name],$D15)+SUMIFS(tblTransactions[Amount],tblTransactions[Transaction Type],"Transfer",tblTransactions[Transaction Status],"Reconciled",tblTransactions[Destination Type],"Account",tblTransactions[Destination Name],$D15)+SUMIFS(tblTransactions[Amount],tblTransactions[Transaction Type],"Adjustment",tblTransactions[Transaction Status],"Completed",tblTransactions[Source Account],$D15,tblTransactions[Amount],">0")+SUMIFS(tblTransactions[Amount],tblTransactions[Transaction Type],"Adjustment",tblTransactions[Transaction Status],"Reconciled",tblTransactions[Source Account],$D15,tblTransactions[Amount],">0")) | G15: =IF($D15="","",SUMIFS(tblTransactions[Amount],tblTransactions[Transaction Type],"Expense",tblTransactions[Transaction Status],"Completed",tblTransactions[Source Account],$D15)+SUMIFS(tblTransactions[Amount],tblTransactions[Transaction Type],"Expense",tblTransactions[Transaction Status],"Reconciled",tblTransactions[Source Account],$D15)+SUMIFS(tblTransactions[Amount],tblTransactions[Transaction Type],"Transfer",tblTransactions[Transaction Status],"Completed",tblTransactions[Source Account],$D15)+SUMIFS(tblTransactions[Amount],tblTransactions[Transaction Type],"Transfer",tblTransactions[Transaction Status],"Reconciled",tblTransactions[Source Account],$D15)-SUMIFS(tblTransactions[Amount],tblTransactions[Transaction Type],"Adjustment",tblTransactions[Transaction Status],"Completed",tblTransactions[Source Account],$D15,tblTransactions[Amount],"<0")-SUMIFS(tblTransactions[Amount],tblTransactions[Transaction Type],"Adjustment",tblTransactions[Transaction Status],"Reconciled",tblTransactions[Source Account],$D15,tblTransactions[Amount],"<0")) | H15: =IF($D15="","",$E15+$F15-$G15) | I15: =#N/A -> #N/A | J15: =IF($D15="","",IFERROR(INDEX(tblAccounts[Account Type],ROW()-1),"")) | K15: =IF($D15="","",IFERROR(INDEX(tblAccounts[Include in Dashboard],ROW()-1),"")) | L15: =IF($D15="","",IFERROR(INDEX(tblAccounts[Status],ROW()-1),""))
A16: Total Monthly Income | B16: =IFERROR(SUMIFS(tblTransactions[Amount],tblTransactions[Transaction Type],"Income",tblTransactions[Transaction Status],"Completed",tblTransactions[Transaction Date],">="&DATE(YEAR($B$1),MONTH($B$1),1),tblTransactions[Transaction Date],"<"&DATE(YEAR($B$1),MONTH($B$1)+1,1))+SUMIFS(tblTransactions[Amount],tblTransactions[Transaction Type],"Income",tblTransactions[Transaction Status],"Reconciled",tblTransactions[Transaction Date],">="&DATE(YEAR($B$1),MONTH($B$1),1),tblTransactions[Transaction Date],"<"&DATE(YEAR($B$1),MONTH($B$1)+1,1)),0) -> 0 | D16: =IF(INDEX(tblAccounts[Account Name],ROW()-1)="","",INDEX(tblAccounts[Account Name],ROW()-1)) | E16: =IF($D16="","",IFERROR(INDEX(tblAccounts[Opening Balance],ROW()-1),0)) | F16: =IF($D16="","",SUMIFS(tblTransactions[Amount],tblTransactions[Transaction Type],"Income",tblTransactions[Transaction Status],"Completed",tblTransactions[Source Account],$D16)+SUMIFS(tblTransactions[Amount],tblTransactions[Transaction Type],"Income",tblTransactions[Transaction Status],"Reconciled",tblTransactions[Source Account],$D16)+SUMIFS(tblTransactions[Amount],tblTransactions[Transaction Type],"Transfer",tblTransactions[Transaction Status],"Completed",tblTransactions[Destination Type],"Account",tblTransactions[Destination Name],$D16)+SUMIFS(tblTransactions[Amount],tblTransactions[Transaction Type],"Transfer",tblTransactions[Transaction Status],"Reconciled",tblTransactions[Destination Type],"Account",tblTransactions[Destination Name],$D16)+SUMIFS(tblTransactions[Amount],tblTransactions[Transaction Type],"Adjustment",tblTransactions[Transaction Status],"Completed",tblTransactions[Source Account],$D16,tblTransactions[Amount],">0")+SUMIFS(tblTransactions[Amount],tblTransactions[Transaction Type],"Adjustment",tblTransactions[Transaction Status],"Reconciled",tblTransactions[Source Account],$D16,tblTransactions[Amount],">0")) | G16: =IF($D16="","",SUMIFS(tblTransactions[Amount],tblTransactions[Transaction Type],"Expense",tblTransactions[Transaction Status],"Completed",tblTransactions[Source Account],$D16)+SUMIFS(tblTransactions[Amount],tblTransactions[Transaction Type],"Expense",tblTransactions[Transaction Status],"Reconciled",tblTransactions[Source Account],$D16)+SUMIFS(tblTransactions[Amount],tblTransactions[Transaction Type],"Transfer",tblTransactions[Transaction Status],"Completed",tblTransactions[Source Account],$D16)+SUMIFS(tblTransactions[Amount],tblTransactions[Transaction Type],"Transfer",tblTransactions[Transaction Status],"Reconciled",tblTransactions[Source Account],$D16)-SUMIFS(tblTransactions[Amount],tblTransactions[Transaction Type],"Adjustment",tblTransactions[Transaction Status],"Completed",tblTransactions[Source Account],$D16,tblTransactions[Amount],"<0")-SUMIFS(tblTransactions[Amount],tblTransactions[Transaction Type],"Adjustment",tblTransactions[Transaction Status],"Reconciled",tblTransactions[Source Account],$D16,tblTransactions[Amount],"<0")) | H16: =IF($D16="","",$E16+$F16-$G16) | I16: =#N/A -> #N/A | J16: =IF($D16="","",IFERROR(INDEX(tblAccounts[Account Type],ROW()-1),"")) | K16: =IF($D16="","",IFERROR(INDEX(tblAccounts[Include in Dashboard],ROW()-1),"")) | L16: =IF($D16="","",IFERROR(INDEX(tblAccounts[Status],ROW()-1),""))
A17: Monthly Other Income | B17: =MAX(0,$B$16-($B$12+$B$13+$B$14+$B$15)) -> 0 | D17: =IF(INDEX(tblAccounts[Account Name],ROW()-1)="","",INDEX(tblAccounts[Account Name],ROW()-1)) | E17: =IF($D17="","",IFERROR(INDEX(tblAccounts[Opening Balance],ROW()-1),0)) | F17: =IF($D17="","",SUMIFS(tblTransactions[Amount],tblTransactions[Transaction Type],"Income",tblTransactions[Transaction Status],"Completed",tblTransactions[Source Account],$D17)+SUMIFS(tblTransactions[Amount],tblTransactions[Transaction Type],"Income",tblTransactions[Transaction Status],"Reconciled",tblTransactions[Source Account],$D17)+SUMIFS(tblTransactions[Amount],tblTransactions[Transaction Type],"Transfer",tblTransactions[Transaction Status],"Completed",tblTransactions[Destination Type],"Account",tblTransactions[Destination Name],$D17)+SUMIFS(tblTransactions[Amount],tblTransactions[Transaction Type],"Transfer",tblTransactions[Transaction Status],"Reconciled",tblTransactions[Destination Type],"Account",tblTransactions[Destination Name],$D17)+SUMIFS(tblTransactions[Amount],tblTransactions[Transaction Type],"Adjustment",tblTransactions[Transaction Status],"Completed",tblTransactions[Source Account],$D17,tblTransactions[Amount],">0")+SUMIFS(tblTransactions[Amount],tblTransactions[Transaction Type],"Adjustment",tblTransactions[Transaction Status],"Reconciled",tblTransactions[Source Account],$D17,tblTransactions[Amount],">0")) | G17: =IF($D17="","",SUMIFS(tblTransactions[Amount],tblTransactions[Transaction Type],"Expense",tblTransactions[Transaction Status],"Completed",tblTransactions[Source Account],$D17)+SUMIFS(tblTransactions[Amount],tblTransactions[Transaction Type],"Expense",tblTransactions[Transaction Status],"Reconciled",tblTransactions[Source Account],$D17)+SUMIFS(tblTransactions[Amount],tblTransactions[Transaction Type],"Transfer",tblTransactions[Transaction Status],"Completed",tblTransactions[Source Account],$D17)+SUMIFS(tblTransactions[Amount],tblTransactions[Transaction Type],"Transfer",tblTransactions[Transaction Status],"Reconciled",tblTransactions[Source Account],$D17)-SUMIFS(tblTransactions[Amount],tblTransactions[Transaction Type],"Adjustment",tblTransactions[Transaction Status],"Completed",tblTransactions[Source Account],$D17,tblTransactions[Amount],"<0")-SUMIFS(tblTransactions[Amount],tblTransactions[Transaction Type],"Adjustment",tblTransactions[Transaction Status],"Reconciled",tblTransactions[Source Account],$D17,tblTransactions[Amount],"<0")) | H17: =IF($D17="","",$E17+$F17-$G17) | I17: =#N/A -> #N/A | J17: =IF($D17="","",IFERROR(INDEX(tblAccounts[Account Type],ROW()-1),"")) | K17: =IF($D17="","",IFERROR(INDEX(tblAccounts[Include in Dashboard],ROW()-1),"")) | L17: =IF($D17="","",IFERROR(INDEX(tblAccounts[Status],ROW()-1),""))
A18: Total Annual Income | B18: =IFERROR(SUMIFS(tblTransactions[Amount],tblTransactions[Transaction Type],"Income",tblTransactions[Transaction Status],"Completed",tblTransactions[Transaction Date],">="&DATE(YEAR($B$1),1,1),tblTransactions[Transaction Date],"<"&DATE(YEAR($B$1)+1,1,1))+SUMIFS(tblTransactions[Amount],tblTransactions[Transaction Type],"Income",tblTransactions[Transaction Status],"Reconciled",tblTransactions[Transaction Date],">="&DATE(YEAR($B$1),1,1),tblTransactions[Transaction Date],"<"&DATE(YEAR($B$1)+1,1,1)),0) -> 0 | D18: =IF(INDEX(tblAccounts[Account Name],ROW()-1)="","",INDEX(tblAccounts[Account Name],ROW()-1)) | E18: =IF($D18="","",IFERROR(INDEX(tblAccounts[Opening Balance],ROW()-1),0)) | F18: =IF($D18="","",SUMIFS(tblTransactions[Amount],tblTransactions[Transaction Type],"Income",tblTransactions[Transaction Status],"Completed",tblTransactions[Source Account],$D18)+SUMIFS(tblTransactions[Amount],tblTransactions[Transaction Type],"Income",tblTransactions[Transaction Status],"Reconciled",tblTransactions[Source Account],$D18)+SUMIFS(tblTransactions[Amount],tblTransactions[Transaction Type],"Transfer",tblTransactions[Transaction Status],"Completed",tblTransactions[Destination Type],"Account",tblTransactions[Destination Name],$D18)+SUMIFS(tblTransactions[Amount],tblTransactions[Transaction Type],"Transfer",tblTransactions[Transaction Status],"Reconciled",tblTransactions[Destination Type],"Account",tblTransactions[Destination Name],$D18)+SUMIFS(tblTransactions[Amount],tblTransactions[Transaction Type],"Adjustment",tblTransactions[Transaction Status],"Completed",tblTransactions[Source Account],$D18,tblTransactions[Amount],">0")+SUMIFS(tblTransactions[Amount],tblTransactions[Transaction Type],"Adjustment",tblTransactions[Transaction Status],"Reconciled",tblTransactions[Source Account],$D18,tblTransactions[Amount],">0")) | G18: =IF($D18="","",SUMIFS(tblTransactions[Amount],tblTransactions[Transaction Type],"Expense",tblTransactions[Transaction Status],"Completed",tblTransactions[Source Account],$D18)+SUMIFS(tblTransactions[Amount],tblTransactions[Transaction Type],"Expense",tblTransactions[Transaction Status],"Reconciled",tblTransactions[Source Account],$D18)+SUMIFS(tblTransactions[Amount],tblTransactions[Transaction Type],"Transfer",tblTransactions[Transaction Status],"Completed",tblTransactions[Source Account],$D18)+SUMIFS(tblTransactions[Amount],tblTransactions[Transaction Type],"Transfer",tblTransactions[Transaction Status],"Reconciled",tblTransactions[Source Account],$D18)-SUMIFS(tblTransactions[Amount],tblTransactions[Transaction Type],"Adjustment",tblTransactions[Transaction Status],"Completed",tblTransactions[Source Account],$D18,tblTransactions[Amount],"<0")-SUMIFS(tblTransactions[Amount],tblTransactions[Transaction Type],"Adjustment",tblTransactions[Transaction Status],"Reconciled",tblTransactions[Source Account],$D18,tblTransactions[Amount],"<0")) | H18: =IF($D18="","",$E18+$F18-$G18) | I18: =#N/A -> #N/A | J18: =IF($D18="","",IFERROR(INDEX(tblAccounts[Account Type],ROW()-1),"")) | K18: =IF($D18="","",IFERROR(INDEX(tblAccounts[Include in Dashboard],ROW()-1),"")) | L18: =IF($D18="","",IFERROR(INDEX(tblAccounts[Status],ROW()-1),""))
A19: Active Income Source Count | B19: =COUNTIFS(tblIncomeSources[Status],"Active") -> 0 | D19: =IF(INDEX(tblAccounts[Account Name],ROW()-1)="","",INDEX(tblAccounts[Account Name],ROW()-1)) | E19: =IF($D19="","",IFERROR(INDEX(tblAccounts[Opening Balance],ROW()-1),0)) | F19: =IF($D19="","",SUMIFS(tblTransactions[Amount],tblTransactions[Transaction Type],"Income",tblTransactions[Transaction Status],"Completed",tblTransactions[Source Account],$D19)+SUMIFS(tblTransactions[Amount],tblTransactions[Transaction Type],"Income",tblTransactions[Transaction Status],"Reconciled",tblTransactions[Source Account],$D19)+SUMIFS(tblTransactions[Amount],tblTransactions[Transaction Type],"Transfer",tblTransactions[Transaction Status],"Completed",tblTransactions[Destination Type],"Account",tblTransactions[Destination Name],$D19)+SUMIFS(tblTransactions[Amount],tblTransactions[Transaction Type],"Transfer",tblTransactions[Transaction Status],"Reconciled",tblTransactions[Destination Type],"Account",tblTransactions[Destination Name],$D19)+SUMIFS(tblTransactions[Amount],tblTransactions[Transaction Type],"Adjustment",tblTransactions[Transaction Status],"Completed",tblTransactions[Source Account],$D19,tblTransactions[Amount],">0")+SUMIFS(tblTransactions[Amount],tblTransactions[Transaction Type],"Adjustment",tblTransactions[Transaction Status],"Reconciled",tblTransactions[Source Account],$D19,tblTransactions[Amount],">0")) | G19: =IF($D19="","",SUMIFS(tblTransactions[Amount],tblTransactions[Transaction Type],"Expense",tblTransactions[Transaction Status],"Completed",tblTransactions[Source Account],$D19)+SUMIFS(tblTransactions[Amount],tblTransactions[Transaction Type],"Expense",tblTransactions[Transaction Status],"Reconciled",tblTransactions[Source Account],$D19)+SUMIFS(tblTransactions[Amount],tblTransactions[Transaction Type],"Transfer",tblTransactions[Transaction Status],"Completed",tblTransactions[Source Account],$D19)+SUMIFS(tblTransactions[Amount],tblTransactions[Transaction Type],"Transfer",tblTransactions[Transaction Status],"Reconciled",tblTransactions[Source Account],$D19)-SUMIFS(tblTransactions[Amount],tblTransactions[Transaction Type],"Adjustment",tblTransactions[Transaction Status],"Completed",tblTransactions[Source Account],$D19,tblTransactions[Amount],"<0")-SUMIFS(tblTransactions[Amount],tblTransactions[Transaction Type],"Adjustment",tblTransactions[Transaction Status],"Reconciled",tblTransactions[Source Account],$D19,tblTransactions[Amount],"<0")) | H19: =IF($D19="","",$E19+$F19-$G19) | I19: =#N/A -> #N/A | J19: =IF($D19="","",IFERROR(INDEX(tblAccounts[Account Type],ROW()-1),"")) | K19: =IF($D19="","",IFERROR(INDEX(tblAccounts[Include in Dashboard],ROW()-1),"")) | L19: =IF($D19="","",IFERROR(INDEX(tblAccounts[Status],ROW()-1),""))
D20: =IF(INDEX(tblAccounts[Account Name],ROW()-1)="","",INDEX(tblAccounts[Account Name],ROW()-1)) | E20: =IF($D20="","",IFERROR(INDEX(tblAccounts[Opening Balance],ROW()-1),0)) | F20: =IF($D20="","",SUMIFS(tblTransactions[Amount],tblTransactions[Transaction Type],"Income",tblTransactions[Transaction Status],"Completed",tblTransactions[Source Account],$D20)+SUMIFS(tblTransactions[Amount],tblTransactions[Transaction Type],"Income",tblTransactions[Transaction Status],"Reconciled",tblTransactions[Source Account],$D20)+SUMIFS(tblTransactions[Amount],tblTransactions[Transaction Type],"Transfer",tblTransactions[Transaction Status],"Completed",tblTransactions[Destination Type],"Account",tblTransactions[Destination Name],$D20)+SUMIFS(tblTransactions[Amount],tblTransactions[Transaction Type],"Transfer",tblTransactions[Transaction Status],"Reconciled",tblTransactions[Destination Type],"Account",tblTransactions[Destination Name],$D20)+SUMIFS(tblTransactions[Amount],tblTransactions[Transaction Type],"Adjustment",tblTransactions[Transaction Status],"Completed",tblTransactions[Source Account],$D20,tblTransactions[Amount],">0")+SUMIFS(tblTransactions[Amount],tblTransactions[Transaction Type],"Adjustment",tblTransactions[Transaction Status],"Reconciled",tblTransactions[Source Account],$D20,tblTransactions[Amount],">0")) | G20: =IF($D20="","",SUMIFS(tblTransactions[Amount],tblTransactions[Transaction Type],"Expense",tblTransactions[Transaction Status],"Completed",tblTransactions[Source Account],$D20)+SUMIFS(tblTransactions[Amount],tblTransactions[Transaction Type],"Expense",tblTransactions[Transaction Status],"Reconciled",tblTransactions[Source Account],$D20)+SUMIFS(tblTransactions[Amount],tblTransactions[Transaction Type],"Transfer",tblTransactions[Transaction Status],"Completed",tblTransactions[Source Account],$D20)+SUMIFS(tblTransactions[Amount],tblTransactions[Transaction Type],"Transfer",tblTransactions[Transaction Status],"Reconciled",tblTransactions[Source Account],$D20)-SUMIFS(tblTransactions[Amount],tblTransactions[Transaction Type],"Adjustment",tblTransactions[Transaction Status],"Completed",tblTransactions[Source Account],$D20,tblTransactions[Amount],"<0")-SUMIFS(tblTransactions[Amount],tblTransactions[Transaction Type],"Adjustment",tblTransactions[Transaction Status],"Reconciled",tblTransactions[Source Account],$D20,tblTransactions[Amount],"<0")) | H20: =IF($D20="","",$E20+$F20-$G20) | I20: =#N/A -> #N/A | J20: =IF($D20="","",IFERROR(INDEX(tblAccounts[Account Type],ROW()-1),"")) | K20: =IF($D20="","",IFERROR(INDEX(tblAccounts[Include in Dashboard],ROW()-1),"")) | L20: =IF($D20="","",IFERROR(INDEX(tblAccounts[Status],ROW()-1),""))
A21: SECTION 3 — Expense Summary | D21: =IF(INDEX(tblAccounts[Account Name],ROW()-1)="","",INDEX(tblAccounts[Account Name],ROW()-1)) | E21: =IF($D21="","",IFERROR(INDEX(tblAccounts[Opening Balance],ROW()-1),0)) | F21: =IF($D21="","",SUMIFS(tblTransactions[Amount],tblTransactions[Transaction Type],"Income",tblTransactions[Transaction Status],"Completed",tblTransactions[Source Account],$D21)+SUMIFS(tblTransactions[Amount],tblTransactions[Transaction Type],"Income",tblTransactions[Transaction Status],"Reconciled",tblTransactions[Source Account],$D21)+SUMIFS(tblTransactions[Amount],tblTransactions[Transaction Type],"Transfer",tblTransactions[Transaction Status],"Completed",tblTransactions[Destination Type],"Account",tblTransactions[Destination Name],$D21)+SUMIFS(tblTransactions[Amount],tblTransactions[Transaction Type],"Transfer",tblTransactions[Transaction Status],"Reconciled",tblTransactions[Destination Type],"Account",tblTransactions[Destination Name],$D21)+SUMIFS(tblTransactions[Amount],tblTransactions[Transaction Type],"Adjustment",tblTransactions[Transaction Status],"Completed",tblTransactions[Source Account],$D21,tblTransactions[Amount],">0")+SUMIFS(tblTransactions[Amount],tblTransactions[Transaction Type],"Adjustment",tblTransactions[Transaction Status],"Reconciled",tblTransactions[Source Account],$D21,tblTransactions[Amount],">0")) | G21: =IF($D21="","",SUMIFS(tblTransactions[Amount],tblTransactions[Transaction Type],"Expense",tblTransactions[Transaction Status],"Completed",tblTransactions[Source Account],$D21)+SUMIFS(tblTransactions[Amount],tblTransactions[Transaction Type],"Expense",tblTransactions[Transaction Status],"Reconciled",tblTransactions[Source Account],$D21)+SUMIFS(tblTransactions[Amount],tblTransactions[Transaction Type],"Transfer",tblTransactions[Transaction Status],"Completed",tblTransactions[Source Account],$D21)+SUMIFS(tblTransactions[Amount],tblTransactions[Transaction Type],"Transfer",tblTransactions[Transaction Status],"Reconciled",tblTransactions[Source Account],$D21)-SUMIFS(tblTransactions[Amount],tblTransactions[Transaction Type],"Adjustment",tblTransactions[Transaction Status],"Completed",tblTransactions[Source Account],$D21,tblTransactions[Amount],"<0")-SUMIFS(tblTransactions[Amount],tblTransactions[Transaction Type],"Adjustment",tblTransactions[Transaction Status],"Reconciled",tblTransactions[Source Account],$D21,tblTransactions[Amount],"<0")) | H21: =IF($D21="","",$E21+$F21-$G21) | I21: =#N/A -> #N/A | J21: =IF($D21="","",IFERROR(INDEX(tblAccounts[Account Type],ROW()-1),"")) | K21: =IF($D21="","",IFERROR(INDEX(tblAccounts[Include in Dashboard],ROW()-1),"")) | L21: =IF($D21="","",IFERROR(INDEX(tblAccounts[Status],ROW()-1),""))
A22: Current Month Expenses | B22: =IFERROR(SUMIFS(tblTransactions[Amount],tblTransactions[Transaction Type],"Expense",tblTransactions[Transaction Status],"Completed",tblTransactions[Transaction Date],">="&DATE(YEAR($B$1),MONTH($B$1),1),tblTransactions[Transaction Date],"<"&DATE(YEAR($B$1),MONTH($B$1)+1,1))+SUMIFS(tblTransactions[Amount],tblTransactions[Transaction Type],"Expense",tblTransactions[Transaction Status],"Reconciled",tblTransactions[Transaction Date],">="&DATE(YEAR($B$1),MONTH($B$1),1),tblTransactions[Transaction Date],"<"&DATE(YEAR($B$1),MONTH($B$1)+1,1))-SUMIFS(tblTransactions[Amount],tblTransactions[Transaction Type],"Expense",tblTransactions[Transaction Status],"Completed",tblTransactions[Destination Type],"Asset",tblTransactions[Transaction Date],">="&DATE(YEAR($B$1),MONTH($B$1),1),tblTransactions[Transaction Date],"<"&DATE(YEAR($B$1),MONTH($B$1)+1,1))-SUMIFS(tblTransactions[Amount],tblTransactions[Transaction Type],"Expense",tblTransactions[Transaction Status],"Reconciled",tblTransactions[Destination Type],"Asset",tblTransactions[Transaction Date],">="&DATE(YEAR($B$1),MONTH($B$1),1),tblTransactions[Transaction Date],"<"&DATE(YEAR($B$1),MONTH($B$1)+1,1)),0) -> 0 | D22: =IF(INDEX(tblAccounts[Account Name],ROW()-1)="","",INDEX(tblAccounts[Account Name],ROW()-1)) | E22: =IF($D22="","",IFERROR(INDEX(tblAccounts[Opening Balance],ROW()-1),0)) | F22: =IF($D22="","",SUMIFS(tblTransactions[Amount],tblTransactions[Transaction Type],"Income",tblTransactions[Transaction Status],"Completed",tblTransactions[Source Account],$D22)+SUMIFS(tblTransactions[Amount],tblTransactions[Transaction Type],"Income",tblTransactions[Transaction Status],"Reconciled",tblTransactions[Source Account],$D22)+SUMIFS(tblTransactions[Amount],tblTransactions[Transaction Type],"Transfer",tblTransactions[Transaction Status],"Completed",tblTransactions[Destination Type],"Account",tblTransactions[Destination Name],$D22)+SUMIFS(tblTransactions[Amount],tblTransactions[Transaction Type],"Transfer",tblTransactions[Transaction Status],"Reconciled",tblTransactions[Destination Type],"Account",tblTransactions[Destination Name],$D22)+SUMIFS(tblTransactions[Amount],tblTransactions[Transaction Type],"Adjustment",tblTransactions[Transaction Status],"Completed",tblTransactions[Source Account],$D22,tblTransactions[Amount],">0")+SUMIFS(tblTransactions[Amount],tblTransactions[Transaction Type],"Adjustment",tblTransactions[Transaction Status],"Reconciled",tblTransactions[Source Account],$D22,tblTransactions[Amount],">0")) | G22: =IF($D22="","",SUMIFS(tblTransactions[Amount],tblTransactions[Transaction Type],"Expense",tblTransactions[Transaction Status],"Completed",tblTransactions[Source Account],$D22)+SUMIFS(tblTransactions[Amount],tblTransactions[Transaction Type],"Expense",tblTransactions[Transaction Status],"Reconciled",tblTransactions[Source Account],$D22)+SUMIFS(tblTransactions[Amount],tblTransactions[Transaction Type],"Transfer",tblTransactions[Transaction Status],"Completed",tblTransactions[Source Account],$D22)+SUMIFS(tblTransactions[Amount],tblTransactions[Transaction Type],"Transfer",tblTransactions[Transaction Status],"Reconciled",tblTransactions[Source Account],$D22)-SUMIFS(tblTransactions[Amount],tblTransactions[Transaction Type],"Adjustment",tblTransactions[Transaction Status],"Completed",tblTransactions[Source Account],$D22,tblTransactions[Amount],"<0")-SUMIFS(tblTransactions[Amount],tblTransactions[Transaction Type],"Adjustment",tblTransactions[Transaction Status],"Reconciled",tblTransactions[Source Account],$D22,tblTransactions[Amount],"<0")) | H22: =IF($D22="","",$E22+$F22-$G22) | I22: =#N/A -> #N/A | J22: =IF($D22="","",IFERROR(INDEX(tblAccounts[Account Type],ROW()-1),"")) | K22: =IF($D22="","",IFERROR(INDEX(tblAccounts[Include in Dashboard],ROW()-1),"")) | L22: =IF($D22="","",IFERROR(INDEX(tblAccounts[Status],ROW()-1),""))
A23: Previous Month Expenses | B23: =IFERROR(SUMIFS(tblTransactions[Amount],tblTransactions[Transaction Type],"Expense",tblTransactions[Transaction Status],"Completed",tblTransactions[Transaction Date],">="&DATE(YEAR($B$1),MONTH($B$1)-1,1),tblTransactions[Transaction Date],"<"&DATE(YEAR($B$1),MONTH($B$1),1))+SUMIFS(tblTransactions[Amount],tblTransactions[Transaction Type],"Expense",tblTransactions[Transaction Status],"Reconciled",tblTransactions[Transaction Date],">="&DATE(YEAR($B$1),MONTH($B$1)-1,1),tblTransactions[Transaction Date],"<"&DATE(YEAR($B$1),MONTH($B$1),1))-SUMIFS(tblTransactions[Amount],tblTransactions[Transaction Type],"Expense",tblTransactions[Transaction Status],"Completed",tblTransactions[Destination Type],"Asset",tblTransactions[Transaction Date],">="&DATE(YEAR($B$1),MONTH($B$1)-1,1),tblTransactions[Transaction Date],"<"&DATE(YEAR($B$1),MONTH($B$1),1))-SUMIFS(tblTransactions[Amount],tblTransactions[Transaction Type],"Expense",tblTransactions[Transaction Status],"Reconciled",tblTransactions[Destination Type],"Asset",tblTransactions[Transaction Date],">="&DATE(YEAR($B$1),MONTH($B$1)-1,1),tblTransactions[Transaction Date],"<"&DATE(YEAR($B$1),MONTH($B$1),1)),0) -> 0 | D23: =IF(INDEX(tblAccounts[Account Name],ROW()-1)="","",INDEX(tblAccounts[Account Name],ROW()-1)) | E23: =IF($D23="","",IFERROR(INDEX(tblAccounts[Opening Balance],ROW()-1),0)) | F23: =IF($D23="","",SUMIFS(tblTransactions[Amount],tblTransactions[Transaction Type],"Income",tblTransactions[Transaction Status],"Completed",tblTransactions[Source Account],$D23)+SUMIFS(tblTransactions[Amount],tblTransactions[Transaction Type],"Income",tblTransactions[Transaction Status],"Reconciled",tblTransactions[Source Account],$D23)+SUMIFS(tblTransactions[Amount],tblTransactions[Transaction Type],"Transfer",tblTransactions[Transaction Status],"Completed",tblTransactions[Destination Type],"Account",tblTransactions[Destination Name],$D23)+SUMIFS(tblTransactions[Amount],tblTransactions[Transaction Type],"Transfer",tblTransactions[Transaction Status],"Reconciled",tblTransactions[Destination Type],"Account",tblTransactions[Destination Name],$D23)+SUMIFS(tblTransactions[Amount],tblTransactions[Transaction Type],"Adjustment",tblTransactions[Transaction Status],"Completed",tblTransactions[Source Account],$D23,tblTransactions[Amount],">0")+SUMIFS(tblTransactions[Amount],tblTransactions[Transaction Type],"Adjustment",tblTransactions[Transaction Status],"Reconciled",tblTransactions[Source Account],$D23,tblTransactions[Amount],">0")) | G23: =IF($D23="","",SUMIFS(tblTransactions[Amount],tblTransactions[Transaction Type],"Expense",tblTransactions[Transaction Status],"Completed",tblTransactions[Source Account],$D23)+SUMIFS(tblTransactions[Amount],tblTransactions[Transaction Type],"Expense",tblTransactions[Transaction Status],"Reconciled",tblTransactions[Source Account],$D23)+SUMIFS(tblTransactions[Amount],tblTransactions[Transaction Type],"Transfer",tblTransactions[Transaction Status],"Completed",tblTransactions[Source Account],$D23)+SUMIFS(tblTransactions[Amount],tblTransactions[Transaction Type],"Transfer",tblTransactions[Transaction Status],"Reconciled",tblTransactions[Source Account],$D23)-SUMIFS(tblTransactions[Amount],tblTransactions[Transaction Type],"Adjustment",tblTransactions[Transaction Status],"Completed",tblTransactions[Source Account],$D23,tblTransactions[Amount],"<0")-SUMIFS(tblTransactions[Amount],tblTransactions[Transaction Type],"Adjustment",tblTransactions[Transaction Status],"Reconciled",tblTransactions[Source Account],$D23,tblTransactions[Amount],"<0")) | H23: =IF($D23="","",$E23+$F23-$G23) | I23: =#N/A -> #N/A | J23: =IF($D23="","",IFERROR(INDEX(tblAccounts[Account Type],ROW()-1),"")) | K23: =IF($D23="","",IFERROR(INDEX(tblAccounts[Include in Dashboard],ROW()-1),"")) | L23: =IF($D23="","",IFERROR(INDEX(tblAccounts[Status],ROW()-1),""))
A24: Year-to-Date Expenses | B24: =IFERROR(SUMIFS(tblTransactions[Amount],tblTransactions[Transaction Type],"Expense",tblTransactions[Transaction Status],"Completed",tblTransactions[Transaction Date],">="&DATE(YEAR($B$1),1,1),tblTransactions[Transaction Date],"<="&$B$1)+SUMIFS(tblTransactions[Amount],tblTransactions[Transaction Type],"Expense",tblTransactions[Transaction Status],"Reconciled",tblTransactions[Transaction Date],">="&DATE(YEAR($B$1),1,1),tblTransactions[Transaction Date],"<="&$B$1)-SUMIFS(tblTransactions[Amount],tblTransactions[Transaction Type],"Expense",tblTransactions[Transaction Status],"Completed",tblTransactions[Destination Type],"Asset",tblTransactions[Transaction Date],">="&DATE(YEAR($B$1),1,1),tblTransactions[Transaction Date],"<="&$B$1)-SUMIFS(tblTransactions[Amount],tblTransactions[Transaction Type],"Expense",tblTransactions[Transaction Status],"Reconciled",tblTransactions[Destination Type],"Asset",tblTransactions[Transaction Date],">="&DATE(YEAR($B$1),1,1),tblTransactions[Transaction Date],"<="&$B$1),0) -> 0 | D24: =IF(INDEX(tblAccounts[Account Name],ROW()-1)="","",INDEX(tblAccounts[Account Name],ROW()-1)) | E24: =IF($D24="","",IFERROR(INDEX(tblAccounts[Opening Balance],ROW()-1),0)) | F24: =IF($D24="","",SUMIFS(tblTransactions[Amount],tblTransactions[Transaction Type],"Income",tblTransactions[Transaction Status],"Completed",tblTransactions[Source Account],$D24)+SUMIFS(tblTransactions[Amount],tblTransactions[Transaction Type],"Income",tblTransactions[Transaction Status],"Reconciled",tblTransactions[Source Account],$D24)+SUMIFS(tblTransactions[Amount],tblTransactions[Transaction Type],"Transfer",tblTransactions[Transaction Status],"Completed",tblTransactions[Destination Type],"Account",tblTransactions[Destination Name],$D24)+SUMIFS(tblTransactions[Amount],tblTransactions[Transaction Type],"Transfer",tblTransactions[Transaction Status],"Reconciled",tblTransactions[Destination Type],"Account",tblTransactions[Destination Name],$D24)+SUMIFS(tblTransactions[Amount],tblTransactions[Transaction Type],"Adjustment",tblTransactions[Transaction Status],"Completed",tblTransactions[Source Account],$D24,tblTransactions[Amount],">0")+SUMIFS(tblTransactions[Amount],tblTransactions[Transaction Type],"Adjustment",tblTransactions[Transaction Status],"Reconciled",tblTransactions[Source Account],$D24,tblTransactions[Amount],">0")) | G24: =IF($D24="","",SUMIFS(tblTransactions[Amount],tblTransactions[Transaction Type],"Expense",tblTransactions[Transaction Status],"Completed",tblTransactions[Source Account],$D24)+SUMIFS(tblTransactions[Amount],tblTransactions[Transaction Type],"Expense",tblTransactions[Transaction Status],"Reconciled",tblTransactions[Source Account],$D24)+SUMIFS(tblTransactions[Amount],tblTransactions[Transaction Type],"Transfer",tblTransactions[Transaction Status],"Completed",tblTransactions[Source Account],$D24)+SUMIFS(tblTransactions[Amount],tblTransactions[Transaction Type],"Transfer",tblTransactions[Transaction Status],"Reconciled",tblTransactions[Source Account],$D24)-SUMIFS(tblTransactions[Amount],tblTransactions[Transaction Type],"Adjustment",tblTransactions[Transaction Status],"Completed",tblTransactions[Source Account],$D24,tblTransactions[Amount],"<0")-SUMIFS(tblTransactions[Amount],tblTransactions[Transaction Type],"Adjustment",tblTransactions[Transaction Status],"Reconciled",tblTransactions[Source Account],$D24,tblTransactions[Amount],"<0")) | H24: =IF($D24="","",$E24+$F24-$G24) | I24: =#N/A -> #N/A | J24: =IF($D24="","",IFERROR(INDEX(tblAccounts[Account Type],ROW()-1),"")) | K24: =IF($D24="","",IFERROR(INDEX(tblAccounts[Include in Dashboard],ROW()-1),"")) | L24: =IF($D24="","",IFERROR(INDEX(tblAccounts[Status],ROW()-1),""))
A25: Expense Transaction Count | B25: =COUNTIFS(tblTransactions[Transaction Type],"Expense",tblTransactions[Transaction Status],"Completed",tblTransactions[Transaction Date],">="&DATE(YEAR($B$1),MONTH($B$1),1),tblTransactions[Transaction Date],"<"&DATE(YEAR($B$1),MONTH($B$1)+1,1))+COUNTIFS(tblTransactions[Transaction Type],"Expense",tblTransactions[Transaction Status],"Reconciled",tblTransactions[Transaction Date],">="&DATE(YEAR($B$1),MONTH($B$1),1),tblTransactions[Transaction Date],"<"&DATE(YEAR($B$1),MONTH($B$1)+1,1))-COUNTIFS(tblTransactions[Transaction Type],"Expense",tblTransactions[Transaction Status],"Completed",tblTransactions[Destination Type],"Asset",tblTransactions[Transaction Date],">="&DATE(YEAR($B$1),MONTH($B$1),1),tblTransactions[Transaction Date],"<"&DATE(YEAR($B$1),MONTH($B$1)+1,1))-COUNTIFS(tblTransactions[Transaction Type],"Expense",tblTransactions[Transaction Status],"Reconciled",tblTransactions[Destination Type],"Asset",tblTransactions[Transaction Date],">="&DATE(YEAR($B$1),MONTH($B$1),1),tblTransactions[Transaction Date],"<"&DATE(YEAR($B$1),MONTH($B$1)+1,1)) -> 0 | D25: =IF(INDEX(tblAccounts[Account Name],ROW()-1)="","",INDEX(tblAccounts[Account Name],ROW()-1)) | E25: =IF($D25="","",IFERROR(INDEX(tblAccounts[Opening Balance],ROW()-1),0)) | F25: =IF($D25="","",SUMIFS(tblTransactions[Amount],tblTransactions[Transaction Type],"Income",tblTransactions[Transaction Status],"Completed",tblTransactions[Source Account],$D25)+SUMIFS(tblTransactions[Amount],tblTransactions[Transaction Type],"Income",tblTransactions[Transaction Status],"Reconciled",tblTransactions[Source Account],$D25)+SUMIFS(tblTransactions[Amount],tblTransactions[Transaction Type],"Transfer",tblTransactions[Transaction Status],"Completed",tblTransactions[Destination Type],"Account",tblTransactions[Destination Name],$D25)+SUMIFS(tblTransactions[Amount],tblTransactions[Transaction Type],"Transfer",tblTransactions[Transaction Status],"Reconciled",tblTransactions[Destination Type],"Account",tblTransactions[Destination Name],$D25)+SUMIFS(tblTransactions[Amount],tblTransactions[Transaction Type],"Adjustment",tblTransactions[Transaction Status],"Completed",tblTransactions[Source Account],$D25,tblTransactions[Amount],">0")+SUMIFS(tblTransactions[Amount],tblTransactions[Transaction Type],"Adjustment",tblTransactions[Transaction Status],"Reconciled",tblTransactions[Source Account],$D25,tblTransactions[Amount],">0")) | G25: =IF($D25="","",SUMIFS(tblTransactions[Amount],tblTransactions[Transaction Type],"Expense",tblTransactions[Transaction Status],"Completed",tblTransactions[Source Account],$D25)+SUMIFS(tblTransactions[Amount],tblTransactions[Transaction Type],"Expense",tblTransactions[Transaction Status],"Reconciled",tblTransactions[Source Account],$D25)+SUMIFS(tblTransactions[Amount],tblTransactions[Transaction Type],"Transfer",tblTransactions[Transaction Status],"Completed",tblTransactions[Source Account],$D25)+SUMIFS(tblTransactions[Amount],tblTransactions[Transaction Type],"Transfer",tblTransactions[Transaction Status],"Reconciled",tblTransactions[Source Account],$D25)-SUMIFS(tblTransactions[Amount],tblTransactions[Transaction Type],"Adjustment",tblTransactions[Transaction Status],"Completed",tblTransactions[Source Account],$D25,tblTransactions[Amount],"<0")-SUMIFS(tblTransactions[Amount],tblTransactions[Transaction Type],"Adjustment",tblTransactions[Transaction Status],"Reconciled",tblTransactions[Source Account],$D25,tblTransactions[Amount],"<0")) | H25: =IF($D25="","",$E25+$F25-$G25) | I25: =#N/A -> #N/A | J25: =IF($D25="","",IFERROR(INDEX(tblAccounts[Account Type],ROW()-1),"")) | K25: =IF($D25="","",IFERROR(INDEX(tblAccounts[Include in Dashboard],ROW()-1),"")) | L25: =IF($D25="","",IFERROR(INDEX(tblAccounts[Status],ROW()-1),""))
D26: =IF(INDEX(tblAccounts[Account Name],ROW()-1)="","",INDEX(tblAccounts[Account Name],ROW()-1)) | E26: =IF($D26="","",IFERROR(INDEX(tblAccounts[Opening Balance],ROW()-1),0)) | F26: =IF($D26="","",SUMIFS(tblTransactions[Amount],tblTransactions[Transaction Type],"Income",tblTransactions[Transaction Status],"Completed",tblTransactions[Source Account],$D26)+SUMIFS(tblTransactions[Amount],tblTransactions[Transaction Type],"Income",tblTransactions[Transaction Status],"Reconciled",tblTransactions[Source Account],$D26)+SUMIFS(tblTransactions[Amount],tblTransactions[Transaction Type],"Transfer",tblTransactions[Transaction Status],"Completed",tblTransactions[Destination Type],"Account",tblTransactions[Destination Name],$D26)+SUMIFS(tblTransactions[Amount],tblTransactions[Transaction Type],"Transfer",tblTransactions[Transaction Status],"Reconciled",tblTransactions[Destination Type],"Account",tblTransactions[Destination Name],$D26)+SUMIFS(tblTransactions[Amount],tblTransactions[Transaction Type],"Adjustment",tblTransactions[Transaction Status],"Completed",tblTransactions[Source Account],$D26,tblTransactions[Amount],">0")+SUMIFS(tblTransactions[Amount],tblTransactions[Transaction Type],"Adjustment",tblTransactions[Transaction Status],"Reconciled",tblTransactions[Source Account],$D26,tblTransactions[Amount],">0")) | G26: =IF($D26="","",SUMIFS(tblTransactions[Amount],tblTransactions[Transaction Type],"Expense",tblTransactions[Transaction Status],"Completed",tblTransactions[Source Account],$D26)+SUMIFS(tblTransactions[Amount],tblTransactions[Transaction Type],"Expense",tblTransactions[Transaction Status],"Reconciled",tblTransactions[Source Account],$D26)+SUMIFS(tblTransactions[Amount],tblTransactions[Transaction Type],"Transfer",tblTransactions[Transaction Status],"Completed",tblTransactions[Source Account],$D26)+SUMIFS(tblTransactions[Amount],tblTransactions[Transaction Type],"Transfer",tblTransactions[Transaction Status],"Reconciled",tblTransactions[Source Account],$D26)-SUMIFS(tblTransactions[Amount],tblTransactions[Transaction Type],"Adjustment",tblTransactions[Transaction Status],"Completed",tblTransactions[Source Account],$D26,tblTransactions[Amount],"<0")-SUMIFS(tblTransactions[Amount],tblTransactions[Transaction Type],"Adjustment",tblTransactions[Transaction Status],"Reconciled",tblTransactions[Source Account],$D26,tblTransactions[Amount],"<0")) | H26: =IF($D26="","",$E26+$F26-$G26) | I26: =#N/A -> #N/A | J26: =IF($D26="","",IFERROR(INDEX(tblAccounts[Account Type],ROW()-1),"")) | K26: =IF($D26="","",IFERROR(INDEX(tblAccounts[Include in Dashboard],ROW()-1),"")) | L26: =IF($D26="","",IFERROR(INDEX(tblAccounts[Status],ROW()-1),""))
A27: SECTION 4 — Savings Summary | D27: =IF(INDEX(tblAccounts[Account Name],ROW()-1)="","",INDEX(tblAccounts[Account Name],ROW()-1)) | E27: =IF($D27="","",IFERROR(INDEX(tblAccounts[Opening Balance],ROW()-1),0)) | F27: =IF($D27="","",SUMIFS(tblTransactions[Amount],tblTransactions[Transaction Type],"Income",tblTransactions[Transaction Status],"Completed",tblTransactions[Source Account],$D27)+SUMIFS(tblTransactions[Amount],tblTransactions[Transaction Type],"Income",tblTransactions[Transaction Status],"Reconciled",tblTransactions[Source Account],$D27)+SUMIFS(tblTransactions[Amount],tblTransactions[Transaction Type],"Transfer",tblTransactions[Transaction Status],"Completed",tblTransactions[Destination Type],"Account",tblTransactions[Destination Name],$D27)+SUMIFS(tblTransactions[Amount],tblTransactions[Transaction Type],"Transfer",tblTransactions[Transaction Status],"Reconciled",tblTransactions[Destination Type],"Account",tblTransactions[Destination Name],$D27)+SUMIFS(tblTransactions[Amount],tblTransactions[Transaction Type],"Adjustment",tblTransactions[Transaction Status],"Completed",tblTransactions[Source Account],$D27,tblTransactions[Amount],">0")+SUMIFS(tblTransactions[Amount],tblTransactions[Transaction Type],"Adjustment",tblTransactions[Transaction Status],"Reconciled",tblTransactions[Source Account],$D27,tblTransactions[Amount],">0")) | G27: =IF($D27="","",SUMIFS(tblTransactions[Amount],tblTransactions[Transaction Type],"Expense",tblTransactions[Transaction Status],"Completed",tblTransactions[Source Account],$D27)+SUMIFS(tblTransactions[Amount],tblTransactions[Transaction Type],"Expense",tblTransactions[Transaction Status],"Reconciled",tblTransactions[Source Account],$D27)+SUMIFS(tblTransactions[Amount],tblTransactions[Transaction Type],"Transfer",tblTransactions[Transaction Status],"Completed",tblTransactions[Source Account],$D27)+SUMIFS(tblTransactions[Amount],tblTransactions[Transaction Type],"Transfer",tblTransactions[Transaction Status],"Reconciled",tblTransactions[Source Account],$D27)-SUMIFS(tblTransactions[Amount],tblTransactions[Transaction Type],"Adjustment",tblTransactions[Transaction Status],"Completed",tblTransactions[Source Account],$D27,tblTransactions[Amount],"<0")-SUMIFS(tblTransactions[Amount],tblTransactions[Transaction Type],"Adjustment",tblTransactions[Transaction Status],"Reconciled",tblTransactions[Source Account],$D27,tblTransactions[Amount],"<0")) | H27: =IF($D27="","",$E27+$F27-$G27) | I27: =#N/A -> #N/A | J27: =IF($D27="","",IFERROR(INDEX(tblAccounts[Account Type],ROW()-1),"")) | K27: =IF($D27="","",IFERROR(INDEX(tblAccounts[Include in Dashboard],ROW()-1),"")) | L27: =IF($D27="","",IFERROR(INDEX(tblAccounts[Status],ROW()-1),""))
A28: Current Month Income | B28: =$B$16 -> 0 | D28: =IF(INDEX(tblAccounts[Account Name],ROW()-1)="","",INDEX(tblAccounts[Account Name],ROW()-1)) | E28: =IF($D28="","",IFERROR(INDEX(tblAccounts[Opening Balance],ROW()-1),0)) | F28: =IF($D28="","",SUMIFS(tblTransactions[Amount],tblTransactions[Transaction Type],"Income",tblTransactions[Transaction Status],"Completed",tblTransactions[Source Account],$D28)+SUMIFS(tblTransactions[Amount],tblTransactions[Transaction Type],"Income",tblTransactions[Transaction Status],"Reconciled",tblTransactions[Source Account],$D28)+SUMIFS(tblTransactions[Amount],tblTransactions[Transaction Type],"Transfer",tblTransactions[Transaction Status],"Completed",tblTransactions[Destination Type],"Account",tblTransactions[Destination Name],$D28)+SUMIFS(tblTransactions[Amount],tblTransactions[Transaction Type],"Transfer",tblTransactions[Transaction Status],"Reconciled",tblTransactions[Destination Type],"Account",tblTransactions[Destination Name],$D28)+SUMIFS(tblTransactions[Amount],tblTransactions[Transaction Type],"Adjustment",tblTransactions[Transaction Status],"Completed",tblTransactions[Source Account],$D28,tblTransactions[Amount],">0")+SUMIFS(tblTransactions[Amount],tblTransactions[Transaction Type],"Adjustment",tblTransactions[Transaction Status],"Reconciled",tblTransactions[Source Account],$D28,tblTransactions[Amount],">0")) | G28: =IF($D28="","",SUMIFS(tblTransactions[Amount],tblTransactions[Transaction Type],"Expense",tblTransactions[Transaction Status],"Completed",tblTransactions[Source Account],$D28)+SUMIFS(tblTransactions[Amount],tblTransactions[Transaction Type],"Expense",tblTransactions[Transaction Status],"Reconciled",tblTransactions[Source Account],$D28)+SUMIFS(tblTransactions[Amount],tblTransactions[Transaction Type],"Transfer",tblTransactions[Transaction Status],"Completed",tblTransactions[Source Account],$D28)+SUMIFS(tblTransactions[Amount],tblTransactions[Transaction Type],"Transfer",tblTransactions[Transaction Status],"Reconciled",tblTransactions[Source Account],$D28)-SUMIFS(tblTransactions[Amount],tblTransactions[Transaction Type],"Adjustment",tblTransactions[Transaction Status],"Completed",tblTransactions[Source Account],$D28,tblTransactions[Amount],"<0")-SUMIFS(tblTransactions[Amount],tblTransactions[Transaction Type],"Adjustment",tblTransactions[Transaction Status],"Reconciled",tblTransactions[Source Account],$D28,tblTransactions[Amount],"<0")) | H28: =IF($D28="","",$E28+$F28-$G28) | I28: =#N/A -> #N/A | J28: =IF($D28="","",IFERROR(INDEX(tblAccounts[Account Type],ROW()-1),"")) | K28: =IF($D28="","",IFERROR(INDEX(tblAccounts[Include in Dashboard],ROW()-1),"")) | L28: =IF($D28="","",IFERROR(INDEX(tblAccounts[Status],ROW()-1),""))
A29: Current Month Savings | B29: =$B$28-$B$22 -> 0 | D29: =IF(INDEX(tblAccounts[Account Name],ROW()-1)="","",INDEX(tblAccounts[Account Name],ROW()-1)) | E29: =IF($D29="","",IFERROR(INDEX(tblAccounts[Opening Balance],ROW()-1),0)) | F29: =IF($D29="","",SUMIFS(tblTransactions[Amount],tblTransactions[Transaction Type],"Income",tblTransactions[Transaction Status],"Completed",tblTransactions[Source Account],$D29)+SUMIFS(tblTransactions[Amount],tblTransactions[Transaction Type],"Income",tblTransactions[Transaction Status],"Reconciled",tblTransactions[Source Account],$D29)+SUMIFS(tblTransactions[Amount],tblTransactions[Transaction Type],"Transfer",tblTransactions[Transaction Status],"Completed",tblTransactions[Destination Type],"Account",tblTransactions[Destination Name],$D29)+SUMIFS(tblTransactions[Amount],tblTransactions[Transaction Type],"Transfer",tblTransactions[Transaction Status],"Reconciled",tblTransactions[Destination Type],"Account",tblTransactions[Destination Name],$D29)+SUMIFS(tblTransactions[Amount],tblTransactions[Transaction Type],"Adjustment",tblTransactions[Transaction Status],"Completed",tblTransactions[Source Account],$D29,tblTransactions[Amount],">0")+SUMIFS(tblTransactions[Amount],tblTransactions[Transaction Type],"Adjustment",tblTransactions[Transaction Status],"Reconciled",tblTransactions[Source Account],$D29,tblTransactions[Amount],">0")) | G29: =IF($D29="","",SUMIFS(tblTransactions[Amount],tblTransactions[Transaction Type],"Expense",tblTransactions[Transaction Status],"Completed",tblTransactions[Source Account],$D29)+SUMIFS(tblTransactions[Amount],tblTransactions[Transaction Type],"Expense",tblTransactions[Transaction Status],"Reconciled",tblTransactions[Source Account],$D29)+SUMIFS(tblTransactions[Amount],tblTransactions[Transaction Type],"Transfer",tblTransactions[Transaction Status],"Completed",tblTransactions[Source Account],$D29)+SUMIFS(tblTransactions[Amount],tblTransactions[Transaction Type],"Transfer",tblTransactions[Transaction Status],"Reconciled",tblTransactions[Source Account],$D29)-SUMIFS(tblTransactions[Amount],tblTransactions[Transaction Type],"Adjustment",tblTransactions[Transaction Status],"Completed",tblTransactions[Source Account],$D29,tblTransactions[Amount],"<0")-SUMIFS(tblTransactions[Amount],tblTransactions[Transaction Type],"Adjustment",tblTransactions[Transaction Status],"Reconciled",tblTransactions[Source Account],$D29,tblTransactions[Amount],"<0")) | H29: =IF($D29="","",$E29+$F29-$G29) | I29: =#N/A -> #N/A | J29: =IF($D29="","",IFERROR(INDEX(tblAccounts[Account Type],ROW()-1),"")) | K29: =IF($D29="","",IFERROR(INDEX(tblAccounts[Include in Dashboard],ROW()-1),"")) | L29: =IF($D29="","",IFERROR(INDEX(tblAccounts[Status],ROW()-1),""))
A30: Savings Rate (%) | B30: =IFERROR($B$29/$B$28,0) -> 0 | D30: =IF(INDEX(tblAccounts[Account Name],ROW()-1)="","",INDEX(tblAccounts[Account Name],ROW()-1)) | E30: =IF($D30="","",IFERROR(INDEX(tblAccounts[Opening Balance],ROW()-1),0)) | F30: =IF($D30="","",SUMIFS(tblTransactions[Amount],tblTransactions[Transaction Type],"Income",tblTransactions[Transaction Status],"Completed",tblTransactions[Source Account],$D30)+SUMIFS(tblTransactions[Amount],tblTransactions[Transaction Type],"Income",tblTransactions[Transaction Status],"Reconciled",tblTransactions[Source Account],$D30)+SUMIFS(tblTransactions[Amount],tblTransactions[Transaction Type],"Transfer",tblTransactions[Transaction Status],"Completed",tblTransactions[Destination Type],"Account",tblTransactions[Destination Name],$D30)+SUMIFS(tblTransactions[Amount],tblTransactions[Transaction Type],"Transfer",tblTransactions[Transaction Status],"Reconciled",tblTransactions[Destination Type],"Account",tblTransactions[Destination Name],$D30)+SUMIFS(tblTransactions[Amount],tblTransactions[Transaction Type],"Adjustment",tblTransactions[Transaction Status],"Completed",tblTransactions[Source Account],$D30,tblTransactions[Amount],">0")+SUMIFS(tblTransactions[Amount],tblTransactions[Transaction Type],"Adjustment",tblTransactions[Transaction Status],"Reconciled",tblTransactions[Source Account],$D30,tblTransactions[Amount],">0")) | G30: =IF($D30="","",SUMIFS(tblTransactions[Amount],tblTransactions[Transaction Type],"Expense",tblTransactions[Transaction Status],"Completed",tblTransactions[Source Account],$D30)+SUMIFS(tblTransactions[Amount],tblTransactions[Transaction Type],"Expense",tblTransactions[Transaction Status],"Reconciled",tblTransactions[Source Account],$D30)+SUMIFS(tblTransactions[Amount],tblTransactions[Transaction Type],"Transfer",tblTransactions[Transaction Status],"Completed",tblTransactions[Source Account],$D30)+SUMIFS(tblTransactions[Amount],tblTransactions[Transaction Type],"Transfer",tblTransactions[Transaction Status],"Reconciled",tblTransactions[Source Account],$D30)-SUMIFS(tblTransactions[Amount],tblTransactions[Transaction Type],"Adjustment",tblTransactions[Transaction Status],"Completed",tblTransactions[Source Account],$D30,tblTransactions[Amount],"<0")-SUMIFS(tblTransactions[Amount],tblTransactions[Transaction Type],"Adjustment",tblTransactions[Transaction Status],"Reconciled",tblTransactions[Source Account],$D30,tblTransactions[Amount],"<0")) | H30: =IF($D30="","",$E30+$F30-$G30) | I30: =#N/A -> #N/A | J30: =IF($D30="","",IFERROR(INDEX(tblAccounts[Account Type],ROW()-1),"")) | K30: =IF($D30="","",IFERROR(INDEX(tblAccounts[Include in Dashboard],ROW()-1),"")) | L30: =IF($D30="","",IFERROR(INDEX(tblAccounts[Status],ROW()-1),""))
A31: Average Monthly Savings | B31: =IFERROR(($B$18-$B$24)/MAX(1,MONTH($B$1)),0) -> 0 | D31: =IF(INDEX(tblAccounts[Account Name],ROW()-1)="","",INDEX(tblAccounts[Account Name],ROW()-1)) | E31: =IF($D31="","",IFERROR(INDEX(tblAccounts[Opening Balance],ROW()-1),0)) | F31: =IF($D31="","",SUMIFS(tblTransactions[Amount],tblTransactions[Transaction Type],"Income",tblTransactions[Transaction Status],"Completed",tblTransactions[Source Account],$D31)+SUMIFS(tblTransactions[Amount],tblTransactions[Transaction Type],"Income",tblTransactions[Transaction Status],"Reconciled",tblTransactions[Source Account],$D31)+SUMIFS(tblTransactions[Amount],tblTransactions[Transaction Type],"Transfer",tblTransactions[Transaction Status],"Completed",tblTransactions[Destination Type],"Account",tblTransactions[Destination Name],$D31)+SUMIFS(tblTransactions[Amount],tblTransactions[Transaction Type],"Transfer",tblTransactions[Transaction Status],"Reconciled",tblTransactions[Destination Type],"Account",tblTransactions[Destination Name],$D31)+SUMIFS(tblTransactions[Amount],tblTransactions[Transaction Type],"Adjustment",tblTransactions[Transaction Status],"Completed",tblTransactions[Source Account],$D31,tblTransactions[Amount],">0")+SUMIFS(tblTransactions[Amount],tblTransactions[Transaction Type],"Adjustment",tblTransactions[Transaction Status],"Reconciled",tblTransactions[Source Account],$D31,tblTransactions[Amount],">0")) | G31: =IF($D31="","",SUMIFS(tblTransactions[Amount],tblTransactions[Transaction Type],"Expense",tblTransactions[Transaction Status],"Completed",tblTransactions[Source Account],$D31)+SUMIFS(tblTransactions[Amount],tblTransactions[Transaction Type],"Expense",tblTransactions[Transaction Status],"Reconciled",tblTransactions[Source Account],$D31)+SUMIFS(tblTransactions[Amount],tblTransactions[Transaction Type],"Transfer",tblTransactions[Transaction Status],"Completed",tblTransactions[Source Account],$D31)+SUMIFS(tblTransactions[Amount],tblTransactions[Transaction Type],"Transfer",tblTransactions[Transaction Status],"Reconciled",tblTransactions[Source Account],$D31)-SUMIFS(tblTransactions[Amount],tblTransactions[Transaction Type],"Adjustment",tblTransactions[Transaction Status],"Completed",tblTransactions[Source Account],$D31,tblTransactions[Amount],"<0")-SUMIFS(tblTransactions[Amount],tblTransactions[Transaction Type],"Adjustment",tblTransactions[Transaction Status],"Reconciled",tblTransactions[Source Account],$D31,tblTransactions[Amount],"<0")) | H31: =IF($D31="","",$E31+$F31-$G31) | I31: =#N/A -> #N/A | J31: =IF($D31="","",IFERROR(INDEX(tblAccounts[Account Type],ROW()-1),"")) | K31: =IF($D31="","",IFERROR(INDEX(tblAccounts[Include in Dashboard],ROW()-1),"")) | L31: =IF($D31="","",IFERROR(INDEX(tblAccounts[Status],ROW()-1),""))
D32: =IF(INDEX(tblAccounts[Account Name],ROW()-1)="","",INDEX(tblAccounts[Account Name],ROW()-1)) | E32: =IF($D32="","",IFERROR(INDEX(tblAccounts[Opening Balance],ROW()-1),0)) | F32: =IF($D32="","",SUMIFS(tblTransactions[Amount],tblTransactions[Transaction Type],"Income",tblTransactions[Transaction Status],"Completed",tblTransactions[Source Account],$D32)+SUMIFS(tblTransactions[Amount],tblTransactions[Transaction Type],"Income",tblTransactions[Transaction Status],"Reconciled",tblTransactions[Source Account],$D32)+SUMIFS(tblTransactions[Amount],tblTransactions[Transaction Type],"Transfer",tblTransactions[Transaction Status],"Completed",tblTransactions[Destination Type],"Account",tblTransactions[Destination Name],$D32)+SUMIFS(tblTransactions[Amount],tblTransactions[Transaction Type],"Transfer",tblTransactions[Transaction Status],"Reconciled",tblTransactions[Destination Type],"Account",tblTransactions[Destination Name],$D32)+SUMIFS(tblTransactions[Amount],tblTransactions[Transaction Type],"Adjustment",tblTransactions[Transaction Status],"Completed",tblTransactions[Source Account],$D32,tblTransactions[Amount],">0")+SUMIFS(tblTransactions[Amount],tblTransactions[Transaction Type],"Adjustment",tblTransactions[Transaction Status],"Reconciled",tblTransactions[Source Account],$D32,tblTransactions[Amount],">0")) | G32: =IF($D32="","",SUMIFS(tblTransactions[Amount],tblTransactions[Transaction Type],"Expense",tblTransactions[Transaction Status],"Completed",tblTransactions[Source Account],$D32)+SUMIFS(tblTransactions[Amount],tblTransactions[Transaction Type],"Expense",tblTransactions[Transaction Status],"Reconciled",tblTransactions[Source Account],$D32)+SUMIFS(tblTransactions[Amount],tblTransactions[Transaction Type],"Transfer",tblTransactions[Transaction Status],"Completed",tblTransactions[Source Account],$D32)+SUMIFS(tblTransactions[Amount],tblTransactions[Transaction Type],"Transfer",tblTransactions[Transaction Status],"Reconciled",tblTransactions[Source Account],$D32)-SUMIFS(tblTransactions[Amount],tblTransactions[Transaction Type],"Adjustment",tblTransactions[Transaction Status],"Completed",tblTransactions[Source Account],$D32,tblTransactions[Amount],"<0")-SUMIFS(tblTransactions[Amount],tblTransactions[Transaction Type],"Adjustment",tblTransactions[Transaction Status],"Reconciled",tblTransactions[Source Account],$D32,tblTransactions[Amount],"<0")) | H32: =IF($D32="","",$E32+$F32-$G32) | I32: =#N/A -> #N/A | J32: =IF($D32="","",IFERROR(INDEX(tblAccounts[Account Type],ROW()-1),"")) | K32: =IF($D32="","",IFERROR(INDEX(tblAccounts[Include in Dashboard],ROW()-1),"")) | L32: =IF($D32="","",IFERROR(INDEX(tblAccounts[Status],ROW()-1),""))
A33: SECTION 5 — Asset Summary | D33: =IF(INDEX(tblAccounts[Account Name],ROW()-1)="","",INDEX(tblAccounts[Account Name],ROW()-1)) | E33: =IF($D33="","",IFERROR(INDEX(tblAccounts[Opening Balance],ROW()-1),0)) | F33: =IF($D33="","",SUMIFS(tblTransactions[Amount],tblTransactions[Transaction Type],"Income",tblTransactions[Transaction Status],"Completed",tblTransactions[Source Account],$D33)+SUMIFS(tblTransactions[Amount],tblTransactions[Transaction Type],"Income",tblTransactions[Transaction Status],"Reconciled",tblTransactions[Source Account],$D33)+SUMIFS(tblTransactions[Amount],tblTransactions[Transaction Type],"Transfer",tblTransactions[Transaction Status],"Completed",tblTransactions[Destination Type],"Account",tblTransactions[Destination Name],$D33)+SUMIFS(tblTransactions[Amount],tblTransactions[Transaction Type],"Transfer",tblTransactions[Transaction Status],"Reconciled",tblTransactions[Destination Type],"Account",tblTransactions[Destination Name],$D33)+SUMIFS(tblTransactions[Amount],tblTransactions[Transaction Type],"Adjustment",tblTransactions[Transaction Status],"Completed",tblTransactions[Source Account],$D33,tblTransactions[Amount],">0")+SUMIFS(tblTransactions[Amount],tblTransactions[Transaction Type],"Adjustment",tblTransactions[Transaction Status],"Reconciled",tblTransactions[Source Account],$D33,tblTransactions[Amount],">0")) | G33: =IF($D33="","",SUMIFS(tblTransactions[Amount],tblTransactions[Transaction Type],"Expense",tblTransactions[Transaction Status],"Completed",tblTransactions[Source Account],$D33)+SUMIFS(tblTransactions[Amount],tblTransactions[Transaction Type],"Expense",tblTransactions[Transaction Status],"Reconciled",tblTransactions[Source Account],$D33)+SUMIFS(tblTransactions[Amount],tblTransactions[Transaction Type],"Transfer",tblTransactions[Transaction Status],"Completed",tblTransactions[Source Account],$D33)+SUMIFS(tblTransactions[Amount],tblTransactions[Transaction Type],"Transfer",tblTransactions[Transaction Status],"Reconciled",tblTransactions[Source Account],$D33)-SUMIFS(tblTransactions[Amount],tblTransactions[Transaction Type],"Adjustment",tblTransactions[Transaction Status],"Completed",tblTransactions[Source Account],$D33,tblTransactions[Amount],"<0")-SUMIFS(tblTransactions[Amount],tblTransactions[Transaction Type],"Adjustment",tblTransactions[Transaction Status],"Reconciled",tblTransactions[Source Account],$D33,tblTransactions[Amount],"<0")) | H33: =IF($D33="","",$E33+$F33-$G33) | I33: =#N/A -> #N/A | J33: =IF($D33="","",IFERROR(INDEX(tblAccounts[Account Type],ROW()-1),"")) | K33: =IF($D33="","",IFERROR(INDEX(tblAccounts[Include in Dashboard],ROW()-1),"")) | L33: =IF($D33="","",IFERROR(INDEX(tblAccounts[Status],ROW()-1),""))
A34: Total Purchase Value | B34: =IFERROR(SUMIFS(tblAssets[Purchase Value],tblAssets[Status],"Active"),0) -> 0 | D34: =IF(INDEX(tblAccounts[Account Name],ROW()-1)="","",INDEX(tblAccounts[Account Name],ROW()-1)) | E34: =IF($D34="","",IFERROR(INDEX(tblAccounts[Opening Balance],ROW()-1),0)) | F34: =IF($D34="","",SUMIFS(tblTransactions[Amount],tblTransactions[Transaction Type],"Income",tblTransactions[Transaction Status],"Completed",tblTransactions[Source Account],$D34)+SUMIFS(tblTransactions[Amount],tblTransactions[Transaction Type],"Income",tblTransactions[Transaction Status],"Reconciled",tblTransactions[Source Account],$D34)+SUMIFS(tblTransactions[Amount],tblTransactions[Transaction Type],"Transfer",tblTransactions[Transaction Status],"Completed",tblTransactions[Destination Type],"Account",tblTransactions[Destination Name],$D34)+SUMIFS(tblTransactions[Amount],tblTransactions[Transaction Type],"Transfer",tblTransactions[Transaction Status],"Reconciled",tblTransactions[Destination Type],"Account",tblTransactions[Destination Name],$D34)+SUMIFS(tblTransactions[Amount],tblTransactions[Transaction Type],"Adjustment",tblTransactions[Transaction Status],"Completed",tblTransactions[Source Account],$D34,tblTransactions[Amount],">0")+SUMIFS(tblTransactions[Amount],tblTransactions[Transaction Type],"Adjustment",tblTransactions[Transaction Status],"Reconciled",tblTransactions[Source Account],$D34,tblTransactions[Amount],">0")) | G34: =IF($D34="","",SUMIFS(tblTransactions[Amount],tblTransactions[Transaction Type],"Expense",tblTransactions[Transaction Status],"Completed",tblTransactions[Source Account],$D34)+SUMIFS(tblTransactions[Amount],tblTransactions[Transaction Type],"Expense",tblTransactions[Transaction Status],"Reconciled",tblTransactions[Source Account],$D34)+SUMIFS(tblTransactions[Amount],tblTransactions[Transaction Type],"Transfer",tblTransactions[Transaction Status],"Completed",tblTransactions[Source Account],$D34)+SUMIFS(tblTransactions[Amount],tblTransactions[Transaction Type],"Transfer",tblTransactions[Transaction Status],"Reconciled",tblTransactions[Source Account],$D34)-SUMIFS(tblTransactions[Amount],tblTransactions[Transaction Type],"Adjustment",tblTransactions[Transaction Status],"Completed",tblTransactions[Source Account],$D34,tblTransactions[Amount],"<0")-SUMIFS(tblTransactions[Amount],tblTransactions[Transaction Type],"Adjustment",tblTransactions[Transaction Status],"Reconciled",tblTransactions[Source Account],$D34,tblTransactions[Amount],"<0")) | H34: =IF($D34="","",$E34+$F34-$G34) | I34: =#N/A -> #N/A | J34: =IF($D34="","",IFERROR(INDEX(tblAccounts[Account Type],ROW()-1),"")) | K34: =IF($D34="","",IFERROR(INDEX(tblAccounts[Include in Dashboard],ROW()-1),"")) | L34: =IF($D34="","",IFERROR(INDEX(tblAccounts[Status],ROW()-1),""))
A35: Total Current Value | B35: =IFERROR(SUMIFS(tblAssets[Current Value],tblAssets[Status],"Active"),0) -> 0 | D35: =IF(INDEX(tblAccounts[Account Name],ROW()-1)="","",INDEX(tblAccounts[Account Name],ROW()-1)) | E35: =IF($D35="","",IFERROR(INDEX(tblAccounts[Opening Balance],ROW()-1),0)) | F35: =IF($D35="","",SUMIFS(tblTransactions[Amount],tblTransactions[Transaction Type],"Income",tblTransactions[Transaction Status],"Completed",tblTransactions[Source Account],$D35)+SUMIFS(tblTransactions[Amount],tblTransactions[Transaction Type],"Income",tblTransactions[Transaction Status],"Reconciled",tblTransactions[Source Account],$D35)+SUMIFS(tblTransactions[Amount],tblTransactions[Transaction Type],"Transfer",tblTransactions[Transaction Status],"Completed",tblTransactions[Destination Type],"Account",tblTransactions[Destination Name],$D35)+SUMIFS(tblTransactions[Amount],tblTransactions[Transaction Type],"Transfer",tblTransactions[Transaction Status],"Reconciled",tblTransactions[Destination Type],"Account",tblTransactions[Destination Name],$D35)+SUMIFS(tblTransactions[Amount],tblTransactions[Transaction Type],"Adjustment",tblTransactions[Transaction Status],"Completed",tblTransactions[Source Account],$D35,tblTransactions[Amount],">0")+SUMIFS(tblTransactions[Amount],tblTransactions[Transaction Type],"Adjustment",tblTransactions[Transaction Status],"Reconciled",tblTransactions[Source Account],$D35,tblTransactions[Amount],">0")) | G35: =IF($D35="","",SUMIFS(tblTransactions[Amount],tblTransactions[Transaction Type],"Expense",tblTransactions[Transaction Status],"Completed",tblTransactions[Source Account],$D35)+SUMIFS(tblTransactions[Amount],tblTransactions[Transaction Type],"Expense",tblTransactions[Transaction Status],"Reconciled",tblTransactions[Source Account],$D35)+SUMIFS(tblTransactions[Amount],tblTransactions[Transaction Type],"Transfer",tblTransactions[Transaction Status],"Completed",tblTransactions[Source Account],$D35)+SUMIFS(tblTransactions[Amount],tblTransactions[Transaction Type],"Transfer",tblTransactions[Transaction Status],"Reconciled",tblTransactions[Source Account],$D35)-SUMIFS(tblTransactions[Amount],tblTransactions[Transaction Type],"Adjustment",tblTransactions[Transaction Status],"Completed",tblTransactions[Source Account],$D35,tblTransactions[Amount],"<0")-SUMIFS(tblTransactions[Amount],tblTransactions[Transaction Type],"Adjustment",tblTransactions[Transaction Status],"Reconciled",tblTransactions[Source Account],$D35,tblTransactions[Amount],"<0")) | H35: =IF($D35="","",$E35+$F35-$G35) | I35: =#N/A -> #N/A | J35: =IF($D35="","",IFERROR(INDEX(tblAccounts[Account Type],ROW()-1),"")) | K35: =IF($D35="","",IFERROR(INDEX(tblAccounts[Include in Dashboard],ROW()-1),"")) | L35: =IF($D35="","",IFERROR(INDEX(tblAccounts[Status],ROW()-1),""))
A36: Total Appreciation Amount | B36: =IFERROR(SUMIFS(tblAssets[Appreciation Amount],tblAssets[Status],"Active"),0) -> 0 | D36: =IF(INDEX(tblAccounts[Account Name],ROW()-1)="","",INDEX(tblAccounts[Account Name],ROW()-1)) | E36: =IF($D36="","",IFERROR(INDEX(tblAccounts[Opening Balance],ROW()-1),0)) | F36: =IF($D36="","",SUMIFS(tblTransactions[Amount],tblTransactions[Transaction Type],"Income",tblTransactions[Transaction Status],"Completed",tblTransactions[Source Account],$D36)+SUMIFS(tblTransactions[Amount],tblTransactions[Transaction Type],"Income",tblTransactions[Transaction Status],"Reconciled",tblTransactions[Source Account],$D36)+SUMIFS(tblTransactions[Amount],tblTransactions[Transaction Type],"Transfer",tblTransactions[Transaction Status],"Completed",tblTransactions[Destination Type],"Account",tblTransactions[Destination Name],$D36)+SUMIFS(tblTransactions[Amount],tblTransactions[Transaction Type],"Transfer",tblTransactions[Transaction Status],"Reconciled",tblTransactions[Destination Type],"Account",tblTransactions[Destination Name],$D36)+SUMIFS(tblTransactions[Amount],tblTransactions[Transaction Type],"Adjustment",tblTransactions[Transaction Status],"Completed",tblTransactions[Source Account],$D36,tblTransactions[Amount],">0")+SUMIFS(tblTransactions[Amount],tblTransactions[Transaction Type],"Adjustment",tblTransactions[Transaction Status],"Reconciled",tblTransactions[Source Account],$D36,tblTransactions[Amount],">0")) | G36: =IF($D36="","",SUMIFS(tblTransactions[Amount],tblTransactions[Transaction Type],"Expense",tblTransactions[Transaction Status],"Completed",tblTransactions[Source Account],$D36)+SUMIFS(tblTransactions[Amount],tblTransactions[Transaction Type],"Expense",tblTransactions[Transaction Status],"Reconciled",tblTransactions[Source Account],$D36)+SUMIFS(tblTransactions[Amount],tblTransactions[Transaction Type],"Transfer",tblTransactions[Transaction Status],"Completed",tblTransactions[Source Account],$D36)+SUMIFS(tblTransactions[Amount],tblTransactions[Transaction Type],"Transfer",tblTransactions[Transaction Status],"Reconciled",tblTransactions[Source Account],$D36)-SUMIFS(tblTransactions[Amount],tblTransactions[Transaction Type],"Adjustment",tblTransactions[Transaction Status],"Completed",tblTransactions[Source Account],$D36,tblTransactions[Amount],"<0")-SUMIFS(tblTransactions[Amount],tblTransactions[Transaction Type],"Adjustment",tblTransactions[Transaction Status],"Reconciled",tblTransactions[Source Account],$D36,tblTransactions[Amount],"<0")) | H36: =IF($D36="","",$E36+$F36-$G36) | I36: =#N/A -> #N/A | J36: =IF($D36="","",IFERROR(INDEX(tblAccounts[Account Type],ROW()-1),"")) | K36: =IF($D36="","",IFERROR(INDEX(tblAccounts[Include in Dashboard],ROW()-1),"")) | L36: =IF($D36="","",IFERROR(INDEX(tblAccounts[Status],ROW()-1),""))
A37: Weighted Appreciation % | B37: =IFERROR($B$36/$B$34,0) -> 0 | D37: =IF(INDEX(tblAccounts[Account Name],ROW()-1)="","",INDEX(tblAccounts[Account Name],ROW()-1)) | E37: =IF($D37="","",IFERROR(INDEX(tblAccounts[Opening Balance],ROW()-1),0)) | F37: =IF($D37="","",SUMIFS(tblTransactions[Amount],tblTransactions[Transaction Type],"Income",tblTransactions[Transaction Status],"Completed",tblTransactions[Source Account],$D37)+SUMIFS(tblTransactions[Amount],tblTransactions[Transaction Type],"Income",tblTransactions[Transaction Status],"Reconciled",tblTransactions[Source Account],$D37)+SUMIFS(tblTransactions[Amount],tblTransactions[Transaction Type],"Transfer",tblTransactions[Transaction Status],"Completed",tblTransactions[Destination Type],"Account",tblTransactions[Destination Name],$D37)+SUMIFS(tblTransactions[Amount],tblTransactions[Transaction Type],"Transfer",tblTransactions[Transaction Status],"Reconciled",tblTransactions[Destination Type],"Account",tblTransactions[Destination Name],$D37)+SUMIFS(tblTransactions[Amount],tblTransactions[Transaction Type],"Adjustment",tblTransactions[Transaction Status],"Completed",tblTransactions[Source Account],$D37,tblTransactions[Amount],">0")+SUMIFS(tblTransactions[Amount],tblTransactions[Transaction Type],"Adjustment",tblTransactions[Transaction Status],"Reconciled",tblTransactions[Source Account],$D37,tblTransactions[Amount],">0")) | G37: =IF($D37="","",SUMIFS(tblTransactions[Amount],tblTransactions[Transaction Type],"Expense",tblTransactions[Transaction Status],"Completed",tblTransactions[Source Account],$D37)+SUMIFS(tblTransactions[Amount],tblTransactions[Transaction Type],"Expense",tblTransactions[Transaction Status],"Reconciled",tblTransactions[Source Account],$D37)+SUMIFS(tblTransactions[Amount],tblTransactions[Transaction Type],"Transfer",tblTransactions[Transaction Status],"Completed",tblTransactions[Source Account],$D37)+SUMIFS(tblTransactions[Amount],tblTransactions[Transaction Type],"Transfer",tblTransactions[Transaction Status],"Reconciled",tblTransactions[Source Account],$D37)-SUMIFS(tblTransactions[Amount],tblTransactions[Transaction Type],"Adjustment",tblTransactions[Transaction Status],"Completed",tblTransactions[Source Account],$D37,tblTransactions[Amount],"<0")-SUMIFS(tblTransactions[Amount],tblTransactions[Transaction Type],"Adjustment",tblTransactions[Transaction Status],"Reconciled",tblTransactions[Source Account],$D37,tblTransactions[Amount],"<0")) | H37: =IF($D37="","",$E37+$F37-$G37) | I37: =#N/A -> #N/A | J37: =IF($D37="","",IFERROR(INDEX(tblAccounts[Account Type],ROW()-1),"")) | K37: =IF($D37="","",IFERROR(INDEX(tblAccounts[Include in Dashboard],ROW()-1),"")) | L37: =IF($D37="","",IFERROR(INDEX(tblAccounts[Status],ROW()-1),""))
A38: Active Asset Count | B38: =COUNTIFS(tblAssets[Status],"Active") -> 0 | D38: =IF(INDEX(tblAccounts[Account Name],ROW()-1)="","",INDEX(tblAccounts[Account Name],ROW()-1)) | E38: =IF($D38="","",IFERROR(INDEX(tblAccounts[Opening Balance],ROW()-1),0)) | F38: =IF($D38="","",SUMIFS(tblTransactions[Amount],tblTransactions[Transaction Type],"Income",tblTransactions[Transaction Status],"Completed",tblTransactions[Source Account],$D38)+SUMIFS(tblTransactions[Amount],tblTransactions[Transaction Type],"Income",tblTransactions[Transaction Status],"Reconciled",tblTransactions[Source Account],$D38)+SUMIFS(tblTransactions[Amount],tblTransactions[Transaction Type],"Transfer",tblTransactions[Transaction Status],"Completed",tblTransactions[Destination Type],"Account",tblTransactions[Destination Name],$D38)+SUMIFS(tblTransactions[Amount],tblTransactions[Transaction Type],"Transfer",tblTransactions[Transaction Status],"Reconciled",tblTransactions[Destination Type],"Account",tblTransactions[Destination Name],$D38)+SUMIFS(tblTransactions[Amount],tblTransactions[Transaction Type],"Adjustment",tblTransactions[Transaction Status],"Completed",tblTransactions[Source Account],$D38,tblTransactions[Amount],">0")+SUMIFS(tblTransactions[Amount],tblTransactions[Transaction Type],"Adjustment",tblTransactions[Transaction Status],"Reconciled",tblTransactions[Source Account],$D38,tblTransactions[Amount],">0")) | G38: =IF($D38="","",SUMIFS(tblTransactions[Amount],tblTransactions[Transaction Type],"Expense",tblTransactions[Transaction Status],"Completed",tblTransactions[Source Account],$D38)+SUMIFS(tblTransactions[Amount],tblTransactions[Transaction Type],"Expense",tblTransactions[Transaction Status],"Reconciled",tblTransactions[Source Account],$D38)+SUMIFS(tblTransactions[Amount],tblTransactions[Transaction Type],"Transfer",tblTransactions[Transaction Status],"Completed",tblTransactions[Source Account],$D38)+SUMIFS(tblTransactions[Amount],tblTransactions[Transaction Type],"Transfer",tblTransactions[Transaction Status],"Reconciled",tblTransactions[Source Account],$D38)-SUMIFS(tblTransactions[Amount],tblTransactions[Transaction Type],"Adjustment",tblTransactions[Transaction Status],"Completed",tblTransactions[Source Account],$D38,tblTransactions[Amount],"<0")-SUMIFS(tblTransactions[Amount],tblTransactions[Transaction Type],"Adjustment",tblTransactions[Transaction Status],"Reconciled",tblTransactions[Source Account],$D38,tblTransactions[Amount],"<0")) | H38: =IF($D38="","",$E38+$F38-$G38) | I38: =#N/A -> #N/A | J38: =IF($D38="","",IFERROR(INDEX(tblAccounts[Account Type],ROW()-1),"")) | K38: =IF($D38="","",IFERROR(INDEX(tblAccounts[Include in Dashboard],ROW()-1),"")) | L38: =IF($D38="","",IFERROR(INDEX(tblAccounts[Status],ROW()-1),""))
A39: Asset Purchase Total | B39: =IFERROR(SUMIFS(tblTransactions[Amount],tblTransactions[Transaction Type],"Expense",tblTransactions[Destination Type],"Asset",tblTransactions[Transaction Status],"Completed")+SUMIFS(tblTransactions[Amount],tblTransactions[Transaction Type],"Expense",tblTransactions[Destination Type],"Asset",tblTransactions[Transaction Status],"Reconciled"),0) -> 0 | D39: =IF(INDEX(tblAccounts[Account Name],ROW()-1)="","",INDEX(tblAccounts[Account Name],ROW()-1)) | E39: =IF($D39="","",IFERROR(INDEX(tblAccounts[Opening Balance],ROW()-1),0)) | F39: =IF($D39="","",SUMIFS(tblTransactions[Amount],tblTransactions[Transaction Type],"Income",tblTransactions[Transaction Status],"Completed",tblTransactions[Source Account],$D39)+SUMIFS(tblTransactions[Amount],tblTransactions[Transaction Type],"Income",tblTransactions[Transaction Status],"Reconciled",tblTransactions[Source Account],$D39)+SUMIFS(tblTransactions[Amount],tblTransactions[Transaction Type],"Transfer",tblTransactions[Transaction Status],"Completed",tblTransactions[Destination Type],"Account",tblTransactions[Destination Name],$D39)+SUMIFS(tblTransactions[Amount],tblTransactions[Transaction Type],"Transfer",tblTransactions[Transaction Status],"Reconciled",tblTransactions[Destination Type],"Account",tblTransactions[Destination Name],$D39)+SUMIFS(tblTransactions[Amount],tblTransactions[Transaction Type],"Adjustment",tblTransactions[Transaction Status],"Completed",tblTransactions[Source Account],$D39,tblTransactions[Amount],">0")+SUMIFS(tblTransactions[Amount],tblTransactions[Transaction Type],"Adjustment",tblTransactions[Transaction Status],"Reconciled",tblTransactions[Source Account],$D39,tblTransactions[Amount],">0")) | G39: =IF($D39="","",SUMIFS(tblTransactions[Amount],tblTransactions[Transaction Type],"Expense",tblTransactions[Transaction Status],"Completed",tblTransactions[Source Account],$D39)+SUMIFS(tblTransactions[Amount],tblTransactions[Transaction Type],"Expense",tblTransactions[Transaction Status],"Reconciled",tblTransactions[Source Account],$D39)+SUMIFS(tblTransactions[Amount],tblTransactions[Transaction Type],"Transfer",tblTransactions[Transaction Status],"Completed",tblTransactions[Source Account],$D39)+SUMIFS(tblTransactions[Amount],tblTransactions[Transaction Type],"Transfer",tblTransactions[Transaction Status],"Reconciled",tblTransactions[Source Account],$D39)-SUMIFS(tblTransactions[Amount],tblTransactions[Transaction Type],"Adjustment",tblTransactions[Transaction Status],"Completed",tblTransactions[Source Account],$D39,tblTransactions[Amount],"<0")-SUMIFS(tblTransactions[Amount],tblTransactions[Transaction Type],"Adjustment",tblTransactions[Transaction Status],"Reconciled",tblTransactions[Source Account],$D39,tblTransactions[Amount],"<0")) | H39: =IF($D39="","",$E39+$F39-$G39) | I39: =#N/A -> #N/A | J39: =IF($D39="","",IFERROR(INDEX(tblAccounts[Account Type],ROW()-1),"")) | K39: =IF($D39="","",IFERROR(INDEX(tblAccounts[Include in Dashboard],ROW()-1),"")) | L39: =IF($D39="","",IFERROR(INDEX(tblAccounts[Status],ROW()-1),""))
A40: SECTION 6 — Liability Summary | D40: =IF(INDEX(tblAccounts[Account Name],ROW()-1)="","",INDEX(tblAccounts[Account Name],ROW()-1)) | E40: =IF($D40="","",IFERROR(INDEX(tblAccounts[Opening Balance],ROW()-1),0)) | F40: =IF($D40="","",SUMIFS(tblTransactions[Amount],tblTransactions[Transaction Type],"Income",tblTransactions[Transaction Status],"Completed",tblTransactions[Source Account],$D40)+SUMIFS(tblTransactions[Amount],tblTransactions[Transaction Type],"Income",tblTransactions[Transaction Status],"Reconciled",tblTransactions[Source Account],$D40)+SUMIFS(tblTransactions[Amount],tblTransactions[Transaction Type],"Transfer",tblTransactions[Transaction Status],"Completed",tblTransactions[Destination Type],"Account",tblTransactions[Destination Name],$D40)+SUMIFS(tblTransactions[Amount],tblTransactions[Transaction Type],"Transfer",tblTransactions[Transaction Status],"Reconciled",tblTransactions[Destination Type],"Account",tblTransactions[Destination Name],$D40)+SUMIFS(tblTransactions[Amount],tblTransactions[Transaction Type],"Adjustment",tblTransactions[Transaction Status],"Completed",tblTransactions[Source Account],$D40,tblTransactions[Amount],">0")+SUMIFS(tblTransactions[Amount],tblTransactions[Transaction Type],"Adjustment",tblTransactions[Transaction Status],"Reconciled",tblTransactions[Source Account],$D40,tblTransactions[Amount],">0")) | G40: =IF($D40="","",SUMIFS(tblTransactions[Amount],tblTransactions[Transaction Type],"Expense",tblTransactions[Transaction Status],"Completed",tblTransactions[Source Account],$D40)+SUMIFS(tblTransactions[Amount],tblTransactions[Transaction Type],"Expense",tblTransactions[Transaction Status],"Reconciled",tblTransactions[Source Account],$D40)+SUMIFS(tblTransactions[Amount],tblTransactions[Transaction Type],"Transfer",tblTransactions[Transaction Status],"Completed",tblTransactions[Source Account],$D40)+SUMIFS(tblTransactions[Amount],tblTransactions[Transaction Type],"Transfer",tblTransactions[Transaction Status],"Reconciled",tblTransactions[Source Account],$D40)-SUMIFS(tblTransactions[Amount],tblTransactions[Transaction Type],"Adjustment",tblTransactions[Transaction Status],"Completed",tblTransactions[Source Account],$D40,tblTransactions[Amount],"<0")-SUMIFS(tblTransactions[Amount],tblTransactions[Transaction Type],"Adjustment",tblTransactions[Transaction Status],"Reconciled",tblTransactions[Source Account],$D40,tblTransactions[Amount],"<0")) | H40: =IF($D40="","",$E40+$F40-$G40) | I40: =#N/A -> #N/A | J40: =IF($D40="","",IFERROR(INDEX(tblAccounts[Account Type],ROW()-1),"")) | K40: =IF($D40="","",IFERROR(INDEX(tblAccounts[Include in Dashboard],ROW()-1),"")) | L40: =IF($D40="","",IFERROR(INDEX(tblAccounts[Status],ROW()-1),""))
A41: Total Original Liability | B41: =IFERROR(SUMIFS(tblLiabilities[Original Amount],tblLiabilities[Status],"Active"),0) -> 0 | D41: =IF(INDEX(tblAccounts[Account Name],ROW()-1)="","",INDEX(tblAccounts[Account Name],ROW()-1)) | E41: =IF($D41="","",IFERROR(INDEX(tblAccounts[Opening Balance],ROW()-1),0)) | F41: =IF($D41="","",SUMIFS(tblTransactions[Amount],tblTransactions[Transaction Type],"Income",tblTransactions[Transaction Status],"Completed",tblTransactions[Source Account],$D41)+SUMIFS(tblTransactions[Amount],tblTransactions[Transaction Type],"Income",tblTransactions[Transaction Status],"Reconciled",tblTransactions[Source Account],$D41)+SUMIFS(tblTransactions[Amount],tblTransactions[Transaction Type],"Transfer",tblTransactions[Transaction Status],"Completed",tblTransactions[Destination Type],"Account",tblTransactions[Destination Name],$D41)+SUMIFS(tblTransactions[Amount],tblTransactions[Transaction Type],"Transfer",tblTransactions[Transaction Status],"Reconciled",tblTransactions[Destination Type],"Account",tblTransactions[Destination Name],$D41)+SUMIFS(tblTransactions[Amount],tblTransactions[Transaction Type],"Adjustment",tblTransactions[Transaction Status],"Completed",tblTransactions[Source Account],$D41,tblTransactions[Amount],">0")+SUMIFS(tblTransactions[Amount],tblTransactions[Transaction Type],"Adjustment",tblTransactions[Transaction Status],"Reconciled",tblTransactions[Source Account],$D41,tblTransactions[Amount],">0")) | G41: =IF($D41="","",SUMIFS(tblTransactions[Amount],tblTransactions[Transaction Type],"Expense",tblTransactions[Transaction Status],"Completed",tblTransactions[Source Account],$D41)+SUMIFS(tblTransactions[Amount],tblTransactions[Transaction Type],"Expense",tblTransactions[Transaction Status],"Reconciled",tblTransactions[Source Account],$D41)+SUMIFS(tblTransactions[Amount],tblTransactions[Transaction Type],"Transfer",tblTransactions[Transaction Status],"Completed",tblTransactions[Source Account],$D41)+SUMIFS(tblTransactions[Amount],tblTransactions[Transaction Type],"Transfer",tblTransactions[Transaction Status],"Reconciled",tblTransactions[Source Account],$D41)-SUMIFS(tblTransactions[Amount],tblTransactions[Transaction Type],"Adjustment",tblTransactions[Transaction Status],"Completed",tblTransactions[Source Account],$D41,tblTransactions[Amount],"<0")-SUMIFS(tblTransactions[Amount],tblTransactions[Transaction Type],"Adjustment",tblTransactions[Transaction Status],"Reconciled",tblTransactions[Source Account],$D41,tblTransactions[Amount],"<0")) | H41: =IF($D41="","",$E41+$F41-$G41) | I41: =#N/A -> #N/A | J41: =IF($D41="","",IFERROR(INDEX(tblAccounts[Account Type],ROW()-1),"")) | K41: =IF($D41="","",IFERROR(INDEX(tblAccounts[Include in Dashboard],ROW()-1),"")) | L41: =IF($D41="","",IFERROR(INDEX(tblAccounts[Status],ROW()-1),""))
A42: Total Outstanding Balance | B42: =IFERROR(MAX(0,SUMIFS(tblLiabilities[Outstanding Balance],tblLiabilities[Status],"Active")),0) -> 0 | D42: =IF(INDEX(tblAccounts[Account Name],ROW()-1)="","",INDEX(tblAccounts[Account Name],ROW()-1)) | E42: =IF($D42="","",IFERROR(INDEX(tblAccounts[Opening Balance],ROW()-1),0)) | F42: =IF($D42="","",SUMIFS(tblTransactions[Amount],tblTransactions[Transaction Type],"Income",tblTransactions[Transaction Status],"Completed",tblTransactions[Source Account],$D42)+SUMIFS(tblTransactions[Amount],tblTransactions[Transaction Type],"Income",tblTransactions[Transaction Status],"Reconciled",tblTransactions[Source Account],$D42)+SUMIFS(tblTransactions[Amount],tblTransactions[Transaction Type],"Transfer",tblTransactions[Transaction Status],"Completed",tblTransactions[Destination Type],"Account",tblTransactions[Destination Name],$D42)+SUMIFS(tblTransactions[Amount],tblTransactions[Transaction Type],"Transfer",tblTransactions[Transaction Status],"Reconciled",tblTransactions[Destination Type],"Account",tblTransactions[Destination Name],$D42)+SUMIFS(tblTransactions[Amount],tblTransactions[Transaction Type],"Adjustment",tblTransactions[Transaction Status],"Completed",tblTransactions[Source Account],$D42,tblTransactions[Amount],">0")+SUMIFS(tblTransactions[Amount],tblTransactions[Transaction Type],"Adjustment",tblTransactions[Transaction Status],"Reconciled",tblTransactions[Source Account],$D42,tblTransactions[Amount],">0")) | G42: =IF($D42="","",SUMIFS(tblTransactions[Amount],tblTransactions[Transaction Type],"Expense",tblTransactions[Transaction Status],"Completed",tblTransactions[Source Account],$D42)+SUMIFS(tblTransactions[Amount],tblTransactions[Transaction Type],"Expense",tblTransactions[Transaction Status],"Reconciled",tblTransactions[Source Account],$D42)+SUMIFS(tblTransactions[Amount],tblTransactions[Transaction Type],"Transfer",tblTransactions[Transaction Status],"Completed",tblTransactions[Source Account],$D42)+SUMIFS(tblTransactions[Amount],tblTransactions[Transaction Type],"Transfer",tblTransactions[Transaction Status],"Reconciled",tblTransactions[Source Account],$D42)-SUMIFS(tblTransactions[Amount],tblTransactions[Transaction Type],"Adjustment",tblTransactions[Transaction Status],"Completed",tblTransactions[Source Account],$D42,tblTransactions[Amount],"<0")-SUMIFS(tblTransactions[Amount],tblTransactions[Transaction Type],"Adjustment",tblTransactions[Transaction Status],"Reconciled",tblTransactions[Source Account],$D42,tblTransactions[Amount],"<0")) | H42: =IF($D42="","",$E42+$F42-$G42) | I42: =#N/A -> #N/A | J42: =IF($D42="","",IFERROR(INDEX(tblAccounts[Account Type],ROW()-1),"")) | K42: =IF($D42="","",IFERROR(INDEX(tblAccounts[Include in Dashboard],ROW()-1),"")) | L42: =IF($D42="","",IFERROR(INDEX(tblAccounts[Status],ROW()-1),""))
A43: Total Monthly EMI | B43: =IFERROR(SUMPRODUCT((tblLiabilities[Status]="Active")*(tblLiabilities[EMI Amount])*((tblLiabilities[EMI Frequency]="Monthly")*1+(tblLiabilities[EMI Frequency]="Quarterly")*(1/3)+(tblLiabilities[EMI Frequency]="Half-Yearly")*(1/6)+(tblLiabilities[EMI Frequency]="Yearly")*(1/12))),0) -> 0 | D43: =IF(INDEX(tblAccounts[Account Name],ROW()-1)="","",INDEX(tblAccounts[Account Name],ROW()-1)) | E43: =IF($D43="","",IFERROR(INDEX(tblAccounts[Opening Balance],ROW()-1),0)) | F43: =IF($D43="","",SUMIFS(tblTransactions[Amount],tblTransactions[Transaction Type],"Income",tblTransactions[Transaction Status],"Completed",tblTransactions[Source Account],$D43)+SUMIFS(tblTransactions[Amount],tblTransactions[Transaction Type],"Income",tblTransactions[Transaction Status],"Reconciled",tblTransactions[Source Account],$D43)+SUMIFS(tblTransactions[Amount],tblTransactions[Transaction Type],"Transfer",tblTransactions[Transaction Status],"Completed",tblTransactions[Destination Type],"Account",tblTransactions[Destination Name],$D43)+SUMIFS(tblTransactions[Amount],tblTransactions[Transaction Type],"Transfer",tblTransactions[Transaction Status],"Reconciled",tblTransactions[Destination Type],"Account",tblTransactions[Destination Name],$D43)+SUMIFS(tblTransactions[Amount],tblTransactions[Transaction Type],"Adjustment",tblTransactions[Transaction Status],"Completed",tblTransactions[Source Account],$D43,tblTransactions[Amount],">0")+SUMIFS(tblTransactions[Amount],tblTransactions[Transaction Type],"Adjustment",tblTransactions[Transaction Status],"Reconciled",tblTransactions[Source Account],$D43,tblTransactions[Amount],">0")) | G43: =IF($D43="","",SUMIFS(tblTransactions[Amount],tblTransactions[Transaction Type],"Expense",tblTransactions[Transaction Status],"Completed",tblTransactions[Source Account],$D43)+SUMIFS(tblTransactions[Amount],tblTransactions[Transaction Type],"Expense",tblTransactions[Transaction Status],"Reconciled",tblTransactions[Source Account],$D43)+SUMIFS(tblTransactions[Amount],tblTransactions[Transaction Type],"Transfer",tblTransactions[Transaction Status],"Completed",tblTransactions[Source Account],$D43)+SUMIFS(tblTransactions[Amount],tblTransactions[Transaction Type],"Transfer",tblTransactions[Transaction Status],"Reconciled",tblTransactions[Source Account],$D43)-SUMIFS(tblTransactions[Amount],tblTransactions[Transaction Type],"Adjustment",tblTransactions[Transaction Status],"Completed",tblTransactions[Source Account],$D43,tblTransactions[Amount],"<0")-SUMIFS(tblTransactions[Amount],tblTransactions[Transaction Type],"Adjustment",tblTransactions[Transaction Status],"Reconciled",tblTransactions[Source Account],$D43,tblTransactions[Amount],"<0")) | H43: =IF($D43="","",$E43+$F43-$G43) | I43: =#N/A -> #N/A | J43: =IF($D43="","",IFERROR(INDEX(tblAccounts[Account Type],ROW()-1),"")) | K43: =IF($D43="","",IFERROR(INDEX(tblAccounts[Include in Dashboard],ROW()-1),"")) | L43: =IF($D43="","",IFERROR(INDEX(tblAccounts[Status],ROW()-1),""))
A44: Weighted Interest Rate | B44: =IFERROR(SUMPRODUCT((tblLiabilities[Status]="Active")*(tblLiabilities[Outstanding Balance])*(tblLiabilities[Interest Rate]))/$B$42,0) -> 0 | D44: =IF(INDEX(tblAccounts[Account Name],ROW()-1)="","",INDEX(tblAccounts[Account Name],ROW()-1)) | E44: =IF($D44="","",IFERROR(INDEX(tblAccounts[Opening Balance],ROW()-1),0)) | F44: =IF($D44="","",SUMIFS(tblTransactions[Amount],tblTransactions[Transaction Type],"Income",tblTransactions[Transaction Status],"Completed",tblTransactions[Source Account],$D44)+SUMIFS(tblTransactions[Amount],tblTransactions[Transaction Type],"Income",tblTransactions[Transaction Status],"Reconciled",tblTransactions[Source Account],$D44)+SUMIFS(tblTransactions[Amount],tblTransactions[Transaction Type],"Transfer",tblTransactions[Transaction Status],"Completed",tblTransactions[Destination Type],"Account",tblTransactions[Destination Name],$D44)+SUMIFS(tblTransactions[Amount],tblTransactions[Transaction Type],"Transfer",tblTransactions[Transaction Status],"Reconciled",tblTransactions[Destination Type],"Account",tblTransactions[Destination Name],$D44)+SUMIFS(tblTransactions[Amount],tblTransactions[Transaction Type],"Adjustment",tblTransactions[Transaction Status],"Completed",tblTransactions[Source Account],$D44,tblTransactions[Amount],">0")+SUMIFS(tblTransactions[Amount],tblTransactions[Transaction Type],"Adjustment",tblTransactions[Transaction Status],"Reconciled",tblTransactions[Source Account],$D44,tblTransactions[Amount],">0")) | G44: =IF($D44="","",SUMIFS(tblTransactions[Amount],tblTransactions[Transaction Type],"Expense",tblTransactions[Transaction Status],"Completed",tblTransactions[Source Account],$D44)+SUMIFS(tblTransactions[Amount],tblTransactions[Transaction Type],"Expense",tblTransactions[Transaction Status],"Reconciled",tblTransactions[Source Account],$D44)+SUMIFS(tblTransactions[Amount],tblTransactions[Transaction Type],"Transfer",tblTransactions[Transaction Status],"Completed",tblTransactions[Source Account],$D44)+SUMIFS(tblTransactions[Amount],tblTransactions[Transaction Type],"Transfer",tblTransactions[Transaction Status],"Reconciled",tblTransactions[Source Account],$D44)-SUMIFS(tblTransactions[Amount],tblTransactions[Transaction Type],"Adjustment",tblTransactions[Transaction Status],"Completed",tblTransactions[Source Account],$D44,tblTransactions[Amount],"<0")-SUMIFS(tblTransactions[Amount],tblTransactions[Transaction Type],"Adjustment",tblTransactions[Transaction Status],"Reconciled",tblTransactions[Source Account],$D44,tblTransactions[Amount],"<0")) | H44: =IF($D44="","",$E44+$F44-$G44) | I44: =#N/A -> #N/A | J44: =IF($D44="","",IFERROR(INDEX(tblAccounts[Account Type],ROW()-1),"")) | K44: =IF($D44="","",IFERROR(INDEX(tblAccounts[Include in Dashboard],ROW()-1),"")) | L44: =IF($D44="","",IFERROR(INDEX(tblAccounts[Status],ROW()-1),""))
A45: Active Liability Count | B45: =COUNTIFS(tblLiabilities[Status],"Active") -> 0 | D45: =IF(INDEX(tblAccounts[Account Name],ROW()-1)="","",INDEX(tblAccounts[Account Name],ROW()-1)) | E45: =IF($D45="","",IFERROR(INDEX(tblAccounts[Opening Balance],ROW()-1),0)) | F45: =IF($D45="","",SUMIFS(tblTransactions[Amount],tblTransactions[Transaction Type],"Income",tblTransactions[Transaction Status],"Completed",tblTransactions[Source Account],$D45)+SUMIFS(tblTransactions[Amount],tblTransactions[Transaction Type],"Income",tblTransactions[Transaction Status],"Reconciled",tblTransactions[Source Account],$D45)+SUMIFS(tblTransactions[Amount],tblTransactions[Transaction Type],"Transfer",tblTransactions[Transaction Status],"Completed",tblTransactions[Destination Type],"Account",tblTransactions[Destination Name],$D45)+SUMIFS(tblTransactions[Amount],tblTransactions[Transaction Type],"Transfer",tblTransactions[Transaction Status],"Reconciled",tblTransactions[Destination Type],"Account",tblTransactions[Destination Name],$D45)+SUMIFS(tblTransactions[Amount],tblTransactions[Transaction Type],"Adjustment",tblTransactions[Transaction Status],"Completed",tblTransactions[Source Account],$D45,tblTransactions[Amount],">0")+SUMIFS(tblTransactions[Amount],tblTransactions[Transaction Type],"Adjustment",tblTransactions[Transaction Status],"Reconciled",tblTransactions[Source Account],$D45,tblTransactions[Amount],">0")) | G45: =IF($D45="","",SUMIFS(tblTransactions[Amount],tblTransactions[Transaction Type],"Expense",tblTransactions[Transaction Status],"Completed",tblTransactions[Source Account],$D45)+SUMIFS(tblTransactions[Amount],tblTransactions[Transaction Type],"Expense",tblTransactions[Transaction Status],"Reconciled",tblTransactions[Source Account],$D45)+SUMIFS(tblTransactions[Amount],tblTransactions[Transaction Type],"Transfer",tblTransactions[Transaction Status],"Completed",tblTransactions[Source Account],$D45)+SUMIFS(tblTransactions[Amount],tblTransactions[Transaction Type],"Transfer",tblTransactions[Transaction Status],"Reconciled",tblTransactions[Source Account],$D45)-SUMIFS(tblTransactions[Amount],tblTransactions[Transaction Type],"Adjustment",tblTransactions[Transaction Status],"Completed",tblTransactions[Source Account],$D45,tblTransactions[Amount],"<0")-SUMIFS(tblTransactions[Amount],tblTransactions[Transaction Type],"Adjustment",tblTransactions[Transaction Status],"Reconciled",tblTransactions[Source Account],$D45,tblTransactions[Amount],"<0")) | H45: =IF($D45="","",$E45+$F45-$G45) | I45: =#N/A -> #N/A | J45: =IF($D45="","",IFERROR(INDEX(tblAccounts[Account Type],ROW()-1),"")) | K45: =IF($D45="","",IFERROR(INDEX(tblAccounts[Include in Dashboard],ROW()-1),"")) | L45: =IF($D45="","",IFERROR(INDEX(tblAccounts[Status],ROW()-1),""))
A46: Liability Payment Total | B46: =SUM(SUMIFS(tblTransactions[Amount],tblTransactions[Destination Type],"Liability",tblTransactions[Transaction Type],{"Expense","Transfer"},tblTransactions[Transaction Status],"Completed"))+SUM(SUMIFS(tblTransactions[Amount],tblTransactions[Destination Type],"Liability",tblTransactions[Transaction Type],{"Expense","Transfer"},tblTransactions[Transaction Status],"Reconciled")) -> 0 | D46: =IF(INDEX(tblAccounts[Account Name],ROW()-1)="","",INDEX(tblAccounts[Account Name],ROW()-1)) | E46: =IF($D46="","",IFERROR(INDEX(tblAccounts[Opening Balance],ROW()-1),0)) | F46: =IF($D46="","",SUMIFS(tblTransactions[Amount],tblTransactions[Transaction Type],"Income",tblTransactions[Transaction Status],"Completed",tblTransactions[Source Account],$D46)+SUMIFS(tblTransactions[Amount],tblTransactions[Transaction Type],"Income",tblTransactions[Transaction Status],"Reconciled",tblTransactions[Source Account],$D46)+SUMIFS(tblTransactions[Amount],tblTransactions[Transaction Type],"Transfer",tblTransactions[Transaction Status],"Completed",tblTransactions[Destination Type],"Account",tblTransactions[Destination Name],$D46)+SUMIFS(tblTransactions[Amount],tblTransactions[Transaction Type],"Transfer",tblTransactions[Transaction Status],"Reconciled",tblTransactions[Destination Type],"Account",tblTransactions[Destination Name],$D46)+SUMIFS(tblTransactions[Amount],tblTransactions[Transaction Type],"Adjustment",tblTransactions[Transaction Status],"Completed",tblTransactions[Source Account],$D46,tblTransactions[Amount],">0")+SUMIFS(tblTransactions[Amount],tblTransactions[Transaction Type],"Adjustment",tblTransactions[Transaction Status],"Reconciled",tblTransactions[Source Account],$D46,tblTransactions[Amount],">0")) | G46: =IF($D46="","",SUMIFS(tblTransactions[Amount],tblTransactions[Transaction Type],"Expense",tblTransactions[Transaction Status],"Completed",tblTransactions[Source Account],$D46)+SUMIFS(tblTransactions[Amount],tblTransactions[Transaction Type],"Expense",tblTransactions[Transaction Status],"Reconciled",tblTransactions[Source Account],$D46)+SUMIFS(tblTransactions[Amount],tblTransactions[Transaction Type],"Transfer",tblTransactions[Transaction Status],"Completed",tblTransactions[Source Account],$D46)+SUMIFS(tblTransactions[Amount],tblTransactions[Transaction Type],"Transfer",tblTransactions[Transaction Status],"Reconciled",tblTransactions[Source Account],$D46)-SUMIFS(tblTransactions[Amount],tblTransactions[Transaction Type],"Adjustment",tblTransactions[Transaction Status],"Completed",tblTransactions[Source Account],$D46,tblTransactions[Amount],"<0")-SUMIFS(tblTransactions[Amount],tblTransactions[Transaction Type],"Adjustment",tblTransactions[Transaction Status],"Reconciled",tblTransactions[Source Account],$D46,tblTransactions[Amount],"<0")) | H46: =IF($D46="","",$E46+$F46-$G46) | I46: =#N/A -> #N/A | J46: =IF($D46="","",IFERROR(INDEX(tblAccounts[Account Type],ROW()-1),"")) | K46: =IF($D46="","",IFERROR(INDEX(tblAccounts[Include in Dashboard],ROW()-1),"")) | L46: =IF($D46="","",IFERROR(INDEX(tblAccounts[Status],ROW()-1),""))
A47: SECTION 7 — Net Worth | D47: =IF(INDEX(tblAccounts[Account Name],ROW()-1)="","",INDEX(tblAccounts[Account Name],ROW()-1)) | E47: =IF($D47="","",IFERROR(INDEX(tblAccounts[Opening Balance],ROW()-1),0)) | F47: =IF($D47="","",SUMIFS(tblTransactions[Amount],tblTransactions[Transaction Type],"Income",tblTransactions[Transaction Status],"Completed",tblTransactions[Source Account],$D47)+SUMIFS(tblTransactions[Amount],tblTransactions[Transaction Type],"Income",tblTransactions[Transaction Status],"Reconciled",tblTransactions[Source Account],$D47)+SUMIFS(tblTransactions[Amount],tblTransactions[Transaction Type],"Transfer",tblTransactions[Transaction Status],"Completed",tblTransactions[Destination Type],"Account",tblTransactions[Destination Name],$D47)+SUMIFS(tblTransactions[Amount],tblTransactions[Transaction Type],"Transfer",tblTransactions[Transaction Status],"Reconciled",tblTransactions[Destination Type],"Account",tblTransactions[Destination Name],$D47)+SUMIFS(tblTransactions[Amount],tblTransactions[Transaction Type],"Adjustment",tblTransactions[Transaction Status],"Completed",tblTransactions[Source Account],$D47,tblTransactions[Amount],">0")+SUMIFS(tblTransactions[Amount],tblTransactions[Transaction Type],"Adjustment",tblTransactions[Transaction Status],"Reconciled",tblTransactions[Source Account],$D47,tblTransactions[Amount],">0")) | G47: =IF($D47="","",SUMIFS(tblTransactions[Amount],tblTransactions[Transaction Type],"Expense",tblTransactions[Transaction Status],"Completed",tblTransactions[Source Account],$D47)+SUMIFS(tblTransactions[Amount],tblTransactions[Transaction Type],"Expense",tblTransactions[Transaction Status],"Reconciled",tblTransactions[Source Account],$D47)+SUMIFS(tblTransactions[Amount],tblTransactions[Transaction Type],"Transfer",tblTransactions[Transaction Status],"Completed",tblTransactions[Source Account],$D47)+SUMIFS(tblTransactions[Amount],tblTransactions[Transaction Type],"Transfer",tblTransactions[Transaction Status],"Reconciled",tblTransactions[Source Account],$D47)-SUMIFS(tblTransactions[Amount],tblTransactions[Transaction Type],"Adjustment",tblTransactions[Transaction Status],"Completed",tblTransactions[Source Account],$D47,tblTransactions[Amount],"<0")-SUMIFS(tblTransactions[Amount],tblTransactions[Transaction Type],"Adjustment",tblTransactions[Transaction Status],"Reconciled",tblTransactions[Source Account],$D47,tblTransactions[Amount],"<0")) | H47: =IF($D47="","",$E47+$F47-$G47) | I47: =#N/A -> #N/A | J47: =IF($D47="","",IFERROR(INDEX(tblAccounts[Account Type],ROW()-1),"")) | K47: =IF($D47="","",IFERROR(INDEX(tblAccounts[Include in Dashboard],ROW()-1),"")) | L47: =IF($D47="","",IFERROR(INDEX(tblAccounts[Status],ROW()-1),""))
A48: Net Worth | B48: =$B$4+$B$35-$B$42 -> 0 | D48: =IF(INDEX(tblAccounts[Account Name],ROW()-1)="","",INDEX(tblAccounts[Account Name],ROW()-1)) | E48: =IF($D48="","",IFERROR(INDEX(tblAccounts[Opening Balance],ROW()-1),0)) | F48: =IF($D48="","",SUMIFS(tblTransactions[Amount],tblTransactions[Transaction Type],"Income",tblTransactions[Transaction Status],"Completed",tblTransactions[Source Account],$D48)+SUMIFS(tblTransactions[Amount],tblTransactions[Transaction Type],"Income",tblTransactions[Transaction Status],"Reconciled",tblTransactions[Source Account],$D48)+SUMIFS(tblTransactions[Amount],tblTransactions[Transaction Type],"Transfer",tblTransactions[Transaction Status],"Completed",tblTransactions[Destination Type],"Account",tblTransactions[Destination Name],$D48)+SUMIFS(tblTransactions[Amount],tblTransactions[Transaction Type],"Transfer",tblTransactions[Transaction Status],"Reconciled",tblTransactions[Destination Type],"Account",tblTransactions[Destination Name],$D48)+SUMIFS(tblTransactions[Amount],tblTransactions[Transaction Type],"Adjustment",tblTransactions[Transaction Status],"Completed",tblTransactions[Source Account],$D48,tblTransactions[Amount],">0")+SUMIFS(tblTransactions[Amount],tblTransactions[Transaction Type],"Adjustment",tblTransactions[Transaction Status],"Reconciled",tblTransactions[Source Account],$D48,tblTransactions[Amount],">0")) | G48: =IF($D48="","",SUMIFS(tblTransactions[Amount],tblTransactions[Transaction Type],"Expense",tblTransactions[Transaction Status],"Completed",tblTransactions[Source Account],$D48)+SUMIFS(tblTransactions[Amount],tblTransactions[Transaction Type],"Expense",tblTransactions[Transaction Status],"Reconciled",tblTransactions[Source Account],$D48)+SUMIFS(tblTransactions[Amount],tblTransactions[Transaction Type],"Transfer",tblTransactions[Transaction Status],"Completed",tblTransactions[Source Account],$D48)+SUMIFS(tblTransactions[Amount],tblTransactions[Transaction Type],"Transfer",tblTransactions[Transaction Status],"Reconciled",tblTransactions[Source Account],$D48)-SUMIFS(tblTransactions[Amount],tblTransactions[Transaction Type],"Adjustment",tblTransactions[Transaction Status],"Completed",tblTransactions[Source Account],$D48,tblTransactions[Amount],"<0")-SUMIFS(tblTransactions[Amount],tblTransactions[Transaction Type],"Adjustment",tblTransactions[Transaction Status],"Reconciled",tblTransactions[Source Account],$D48,tblTransactions[Amount],"<0")) | H48: =IF($D48="","",$E48+$F48-$G48) | I48: =#N/A -> #N/A | J48: =IF($D48="","",IFERROR(INDEX(tblAccounts[Account Type],ROW()-1),"")) | K48: =IF($D48="","",IFERROR(INDEX(tblAccounts[Include in Dashboard],ROW()-1),"")) | L48: =IF($D48="","",IFERROR(INDEX(tblAccounts[Status],ROW()-1),""))
A49: Liquid Net Worth | B49: =0 -> 0 | D49: =IF(INDEX(tblAccounts[Account Name],ROW()-1)="","",INDEX(tblAccounts[Account Name],ROW()-1)) | E49: =IF($D49="","",IFERROR(INDEX(tblAccounts[Opening Balance],ROW()-1),0)) | F49: =IF($D49="","",SUMIFS(tblTransactions[Amount],tblTransactions[Transaction Type],"Income",tblTransactions[Transaction Status],"Completed",tblTransactions[Source Account],$D49)+SUMIFS(tblTransactions[Amount],tblTransactions[Transaction Type],"Income",tblTransactions[Transaction Status],"Reconciled",tblTransactions[Source Account],$D49)+SUMIFS(tblTransactions[Amount],tblTransactions[Transaction Type],"Transfer",tblTransactions[Transaction Status],"Completed",tblTransactions[Destination Type],"Account",tblTransactions[Destination Name],$D49)+SUMIFS(tblTransactions[Amount],tblTransactions[Transaction Type],"Transfer",tblTransactions[Transaction Status],"Reconciled",tblTransactions[Destination Type],"Account",tblTransactions[Destination Name],$D49)+SUMIFS(tblTransactions[Amount],tblTransactions[Transaction Type],"Adjustment",tblTransactions[Transaction Status],"Completed",tblTransactions[Source Account],$D49,tblTransactions[Amount],">0")+SUMIFS(tblTransactions[Amount],tblTransactions[Transaction Type],"Adjustment",tblTransactions[Transaction Status],"Reconciled",tblTransactions[Source Account],$D49,tblTransactions[Amount],">0")) | G49: =IF($D49="","",SUMIFS(tblTransactions[Amount],tblTransactions[Transaction Type],"Expense",tblTransactions[Transaction Status],"Completed",tblTransactions[Source Account],$D49)+SUMIFS(tblTransactions[Amount],tblTransactions[Transaction Type],"Expense",tblTransactions[Transaction Status],"Reconciled",tblTransactions[Source Account],$D49)+SUMIFS(tblTransactions[Amount],tblTransactions[Transaction Type],"Transfer",tblTransactions[Transaction Status],"Completed",tblTransactions[Source Account],$D49)+SUMIFS(tblTransactions[Amount],tblTransactions[Transaction Type],"Transfer",tblTransactions[Transaction Status],"Reconciled",tblTransactions[Source Account],$D49)-SUMIFS(tblTransactions[Amount],tblTransactions[Transaction Type],"Adjustment",tblTransactions[Transaction Status],"Completed",tblTransactions[Source Account],$D49,tblTransactions[Amount],"<0")-SUMIFS(tblTransactions[Amount],tblTransactions[Transaction Type],"Adjustment",tblTransactions[Transaction Status],"Reconciled",tblTransactions[Source Account],$D49,tblTransactions[Amount],"<0")) | H49: =IF($D49="","",$E49+$F49-$G49) | I49: =#N/A -> #N/A | J49: =IF($D49="","",IFERROR(INDEX(tblAccounts[Account Type],ROW()-1),"")) | K49: =IF($D49="","",IFERROR(INDEX(tblAccounts[Include in Dashboard],ROW()-1),"")) | L49: =IF($D49="","",IFERROR(INDEX(tblAccounts[Status],ROW()-1),""))
A50: Invested Net Worth | B50: =$B$35 -> 0 | D50: =IF(INDEX(tblAccounts[Account Name],ROW()-1)="","",INDEX(tblAccounts[Account Name],ROW()-1)) | E50: =IF($D50="","",IFERROR(INDEX(tblAccounts[Opening Balance],ROW()-1),0)) | F50: =IF($D50="","",SUMIFS(tblTransactions[Amount],tblTransactions[Transaction Type],"Income",tblTransactions[Transaction Status],"Completed",tblTransactions[Source Account],$D50)+SUMIFS(tblTransactions[Amount],tblTransactions[Transaction Type],"Income",tblTransactions[Transaction Status],"Reconciled",tblTransactions[Source Account],$D50)+SUMIFS(tblTransactions[Amount],tblTransactions[Transaction Type],"Transfer",tblTransactions[Transaction Status],"Completed",tblTransactions[Destination Type],"Account",tblTransactions[Destination Name],$D50)+SUMIFS(tblTransactions[Amount],tblTransactions[Transaction Type],"Transfer",tblTransactions[Transaction Status],"Reconciled",tblTransactions[Destination Type],"Account",tblTransactions[Destination Name],$D50)+SUMIFS(tblTransactions[Amount],tblTransactions[Transaction Type],"Adjustment",tblTransactions[Transaction Status],"Completed",tblTransactions[Source Account],$D50,tblTransactions[Amount],">0")+SUMIFS(tblTransactions[Amount],tblTransactions[Transaction Type],"Adjustment",tblTransactions[Transaction Status],"Reconciled",tblTransactions[Source Account],$D50,tblTransactions[Amount],">0")) | G50: =IF($D50="","",SUMIFS(tblTransactions[Amount],tblTransactions[Transaction Type],"Expense",tblTransactions[Transaction Status],"Completed",tblTransactions[Source Account],$D50)+SUMIFS(tblTransactions[Amount],tblTransactions[Transaction Type],"Expense",tblTransactions[Transaction Status],"Reconciled",tblTransactions[Source Account],$D50)+SUMIFS(tblTransactions[Amount],tblTransactions[Transaction Type],"Transfer",tblTransactions[Transaction Status],"Completed",tblTransactions[Source Account],$D50)+SUMIFS(tblTransactions[Amount],tblTransactions[Transaction Type],"Transfer",tblTransactions[Transaction Status],"Reconciled",tblTransactions[Source Account],$D50)-SUMIFS(tblTransactions[Amount],tblTransactions[Transaction Type],"Adjustment",tblTransactions[Transaction Status],"Completed",tblTransactions[Source Account],$D50,tblTransactions[Amount],"<0")-SUMIFS(tblTransactions[Amount],tblTransactions[Transaction Type],"Adjustment",tblTransactions[Transaction Status],"Reconciled",tblTransactions[Source Account],$D50,tblTransactions[Amount],"<0")) | H50: =IF($D50="","",$E50+$F50-$G50) | I50: =#N/A -> #N/A | J50: =IF($D50="","",IFERROR(INDEX(tblAccounts[Account Type],ROW()-1),"")) | K50: =IF($D50="","",IFERROR(INDEX(tblAccounts[Include in Dashboard],ROW()-1),"")) | L50: =IF($D50="","",IFERROR(INDEX(tblAccounts[Status],ROW()-1),""))
D51: =IF(INDEX(tblAccounts[Account Name],ROW()-1)="","",INDEX(tblAccounts[Account Name],ROW()-1)) | E51: =IF($D51="","",IFERROR(INDEX(tblAccounts[Opening Balance],ROW()-1),0)) | F51: =IF($D51="","",SUMIFS(tblTransactions[Amount],tblTransactions[Transaction Type],"Income",tblTransactions[Transaction Status],"Completed",tblTransactions[Source Account],$D51)+SUMIFS(tblTransactions[Amount],tblTransactions[Transaction Type],"Income",tblTransactions[Transaction Status],"Reconciled",tblTransactions[Source Account],$D51)+SUMIFS(tblTransactions[Amount],tblTransactions[Transaction Type],"Transfer",tblTransactions[Transaction Status],"Completed",tblTransactions[Destination Type],"Account",tblTransactions[Destination Name],$D51)+SUMIFS(tblTransactions[Amount],tblTransactions[Transaction Type],"Transfer",tblTransactions[Transaction Status],"Reconciled",tblTransactions[Destination Type],"Account",tblTransactions[Destination Name],$D51)+SUMIFS(tblTransactions[Amount],tblTransactions[Transaction Type],"Adjustment",tblTransactions[Transaction Status],"Completed",tblTransactions[Source Account],$D51,tblTransactions[Amount],">0")+SUMIFS(tblTransactions[Amount],tblTransactions[Transaction Type],"Adjustment",tblTransactions[Transaction Status],"Reconciled",tblTransactions[Source Account],$D51,tblTransactions[Amount],">0")) | G51: =IF($D51="","",SUMIFS(tblTransactions[Amount],tblTransactions[Transaction Type],"Expense",tblTransactions[Transaction Status],"Completed",tblTransactions[Source Account],$D51)+SUMIFS(tblTransactions[Amount],tblTransactions[Transaction Type],"Expense",tblTransactions[Transaction Status],"Reconciled",tblTransactions[Source Account],$D51)+SUMIFS(tblTransactions[Amount],tblTransactions[Transaction Type],"Transfer",tblTransactions[Transaction Status],"Completed",tblTransactions[Source Account],$D51)+SUMIFS(tblTransactions[Amount],tblTransactions[Transaction Type],"Transfer",tblTransactions[Transaction Status],"Reconciled",tblTransactions[Source Account],$D51)-SUMIFS(tblTransactions[Amount],tblTransactions[Transaction Type],"Adjustment",tblTransactions[Transaction Status],"Completed",tblTransactions[Source Account],$D51,tblTransactions[Amount],"<0")-SUMIFS(tblTransactions[Amount],tblTransactions[Transaction Type],"Adjustment",tblTransactions[Transaction Status],"Reconciled",tblTransactions[Source Account],$D51,tblTransactions[Amount],"<0")) | H51: =IF($D51="","",$E51+$F51-$G51) | I51: =#N/A -> #N/A | J51: =IF($D51="","",IFERROR(INDEX(tblAccounts[Account Type],ROW()-1),"")) | K51: =IF($D51="","",IFERROR(INDEX(tblAccounts[Include in Dashboard],ROW()-1),"")) | L51: =IF($D51="","",IFERROR(INDEX(tblAccounts[Status],ROW()-1),""))
A52: SECTION 8 — Goal Summary | D52: =IF(INDEX(tblAccounts[Account Name],ROW()-1)="","",INDEX(tblAccounts[Account Name],ROW()-1)) | E52: =IF($D52="","",IFERROR(INDEX(tblAccounts[Opening Balance],ROW()-1),0)) | F52: =IF($D52="","",SUMIFS(tblTransactions[Amount],tblTransactions[Transaction Type],"Income",tblTransactions[Transaction Status],"Completed",tblTransactions[Source Account],$D52)+SUMIFS(tblTransactions[Amount],tblTransactions[Transaction Type],"Income",tblTransactions[Transaction Status],"Reconciled",tblTransactions[Source Account],$D52)+SUMIFS(tblTransactions[Amount],tblTransactions[Transaction Type],"Transfer",tblTransactions[Transaction Status],"Completed",tblTransactions[Destination Type],"Account",tblTransactions[Destination Name],$D52)+SUMIFS(tblTransactions[Amount],tblTransactions[Transaction Type],"Transfer",tblTransactions[Transaction Status],"Reconciled",tblTransactions[Destination Type],"Account",tblTransactions[Destination Name],$D52)+SUMIFS(tblTransactions[Amount],tblTransactions[Transaction Type],"Adjustment",tblTransactions[Transaction Status],"Completed",tblTransactions[Source Account],$D52,tblTransactions[Amount],">0")+SUMIFS(tblTransactions[Amount],tblTransactions[Transaction Type],"Adjustment",tblTransactions[Transaction Status],"Reconciled",tblTransactions[Source Account],$D52,tblTransactions[Amount],">0")) | G52: =IF($D52="","",SUMIFS(tblTransactions[Amount],tblTransactions[Transaction Type],"Expense",tblTransactions[Transaction Status],"Completed",tblTransactions[Source Account],$D52)+SUMIFS(tblTransactions[Amount],tblTransactions[Transaction Type],"Expense",tblTransactions[Transaction Status],"Reconciled",tblTransactions[Source Account],$D52)+SUMIFS(tblTransactions[Amount],tblTransactions[Transaction Type],"Transfer",tblTransactions[Transaction Status],"Completed",tblTransactions[Source Account],$D52)+SUMIFS(tblTransactions[Amount],tblTransactions[Transaction Type],"Transfer",tblTransactions[Transaction Status],"Reconciled",tblTransactions[Source Account],$D52)-SUMIFS(tblTransactions[Amount],tblTransactions[Transaction Type],"Adjustment",tblTransactions[Transaction Status],"Completed",tblTransactions[Source Account],$D52,tblTransactions[Amount],"<0")-SUMIFS(tblTransactions[Amount],tblTransactions[Transaction Type],"Adjustment",tblTransactions[Transaction Status],"Reconciled",tblTransactions[Source Account],$D52,tblTransactions[Amount],"<0")) | H52: =IF($D52="","",$E52+$F52-$G52) | I52: =#N/A -> #N/A | J52: =IF($D52="","",IFERROR(INDEX(tblAccounts[Account Type],ROW()-1),"")) | K52: =IF($D52="","",IFERROR(INDEX(tblAccounts[Include in Dashboard],ROW()-1),"")) | L52: =IF($D52="","",IFERROR(INDEX(tblAccounts[Status],ROW()-1),""))
A53: Total Goal Target Amount | B53: =IFERROR(SUMIFS(tblGoals[Target Amount],tblGoals[Goal Status],"Active")+SUMIFS(tblGoals[Target Amount],tblGoals[Goal Status],"Completed"),0) -> 0 | D53: =IF(INDEX(tblAccounts[Account Name],ROW()-1)="","",INDEX(tblAccounts[Account Name],ROW()-1)) | E53: =IF($D53="","",IFERROR(INDEX(tblAccounts[Opening Balance],ROW()-1),0)) | F53: =IF($D53="","",SUMIFS(tblTransactions[Amount],tblTransactions[Transaction Type],"Income",tblTransactions[Transaction Status],"Completed",tblTransactions[Source Account],$D53)+SUMIFS(tblTransactions[Amount],tblTransactions[Transaction Type],"Income",tblTransactions[Transaction Status],"Reconciled",tblTransactions[Source Account],$D53)+SUMIFS(tblTransactions[Amount],tblTransactions[Transaction Type],"Transfer",tblTransactions[Transaction Status],"Completed",tblTransactions[Destination Type],"Account",tblTransactions[Destination Name],$D53)+SUMIFS(tblTransactions[Amount],tblTransactions[Transaction Type],"Transfer",tblTransactions[Transaction Status],"Reconciled",tblTransactions[Destination Type],"Account",tblTransactions[Destination Name],$D53)+SUMIFS(tblTransactions[Amount],tblTransactions[Transaction Type],"Adjustment",tblTransactions[Transaction Status],"Completed",tblTransactions[Source Account],$D53,tblTransactions[Amount],">0")+SUMIFS(tblTransactions[Amount],tblTransactions[Transaction Type],"Adjustment",tblTransactions[Transaction Status],"Reconciled",tblTransactions[Source Account],$D53,tblTransactions[Amount],">0")) | G53: =IF($D53="","",SUMIFS(tblTransactions[Amount],tblTransactions[Transaction Type],"Expense",tblTransactions[Transaction Status],"Completed",tblTransactions[Source Account],$D53)+SUMIFS(tblTransactions[Amount],tblTransactions[Transaction Type],"Expense",tblTransactions[Transaction Status],"Reconciled",tblTransactions[Source Account],$D53)+SUMIFS(tblTransactions[Amount],tblTransactions[Transaction Type],"Transfer",tblTransactions[Transaction Status],"Completed",tblTransactions[Source Account],$D53)+SUMIFS(tblTransactions[Amount],tblTransactions[Transaction Type],"Transfer",tblTransactions[Transaction Status],"Reconciled",tblTransactions[Source Account],$D53)-SUMIFS(tblTransactions[Amount],tblTransactions[Transaction Type],"Adjustment",tblTransactions[Transaction Status],"Completed",tblTransactions[Source Account],$D53,tblTransactions[Amount],"<0")-SUMIFS(tblTransactions[Amount],tblTransactions[Transaction Type],"Adjustment",tblTransactions[Transaction Status],"Reconciled",tblTransactions[Source Account],$D53,tblTransactions[Amount],"<0")) | H53: =IF($D53="","",$E53+$F53-$G53) | I53: =#N/A -> #N/A | J53: =IF($D53="","",IFERROR(INDEX(tblAccounts[Account Type],ROW()-1),"")) | K53: =IF($D53="","",IFERROR(INDEX(tblAccounts[Include in Dashboard],ROW()-1),"")) | L53: =IF($D53="","",IFERROR(INDEX(tblAccounts[Status],ROW()-1),""))
A54: Total Saved Toward Goals | B54: =IFERROR(SUMIFS(tblGoals[Current Saved Amount],tblGoals[Goal Status],"Active")+SUMIFS(tblGoals[Current Saved Amount],tblGoals[Goal Status],"Completed"),0) -> 0 | D54: =IF(INDEX(tblAccounts[Account Name],ROW()-1)="","",INDEX(tblAccounts[Account Name],ROW()-1)) | E54: =IF($D54="","",IFERROR(INDEX(tblAccounts[Opening Balance],ROW()-1),0)) | F54: =IF($D54="","",SUMIFS(tblTransactions[Amount],tblTransactions[Transaction Type],"Income",tblTransactions[Transaction Status],"Completed",tblTransactions[Source Account],$D54)+SUMIFS(tblTransactions[Amount],tblTransactions[Transaction Type],"Income",tblTransactions[Transaction Status],"Reconciled",tblTransactions[Source Account],$D54)+SUMIFS(tblTransactions[Amount],tblTransactions[Transaction Type],"Transfer",tblTransactions[Transaction Status],"Completed",tblTransactions[Destination Type],"Account",tblTransactions[Destination Name],$D54)+SUMIFS(tblTransactions[Amount],tblTransactions[Transaction Type],"Transfer",tblTransactions[Transaction Status],"Reconciled",tblTransactions[Destination Type],"Account",tblTransactions[Destination Name],$D54)+SUMIFS(tblTransactions[Amount],tblTransactions[Transaction Type],"Adjustment",tblTransactions[Transaction Status],"Completed",tblTransactions[Source Account],$D54,tblTransactions[Amount],">0")+SUMIFS(tblTransactions[Amount],tblTransactions[Transaction Type],"Adjustment",tblTransactions[Transaction Status],"Reconciled",tblTransactions[Source Account],$D54,tblTransactions[Amount],">0")) | G54: =IF($D54="","",SUMIFS(tblTransactions[Amount],tblTransactions[Transaction Type],"Expense",tblTransactions[Transaction Status],"Completed",tblTransactions[Source Account],$D54)+SUMIFS(tblTransactions[Amount],tblTransactions[Transaction Type],"Expense",tblTransactions[Transaction Status],"Reconciled",tblTransactions[Source Account],$D54)+SUMIFS(tblTransactions[Amount],tblTransactions[Transaction Type],"Transfer",tblTransactions[Transaction Status],"Completed",tblTransactions[Source Account],$D54)+SUMIFS(tblTransactions[Amount],tblTransactions[Transaction Type],"Transfer",tblTransactions[Transaction Status],"Reconciled",tblTransactions[Source Account],$D54)-SUMIFS(tblTransactions[Amount],tblTransactions[Transaction Type],"Adjustment",tblTransactions[Transaction Status],"Completed",tblTransactions[Source Account],$D54,tblTransactions[Amount],"<0")-SUMIFS(tblTransactions[Amount],tblTransactions[Transaction Type],"Adjustment",tblTransactions[Transaction Status],"Reconciled",tblTransactions[Source Account],$D54,tblTransactions[Amount],"<0")) | H54: =IF($D54="","",$E54+$F54-$G54) | I54: =#N/A -> #N/A | J54: =IF($D54="","",IFERROR(INDEX(tblAccounts[Account Type],ROW()-1),"")) | K54: =IF($D54="","",IFERROR(INDEX(tblAccounts[Include in Dashboard],ROW()-1),"")) | L54: =IF($D54="","",IFERROR(INDEX(tblAccounts[Status],ROW()-1),""))
A55: Remaining Goal Amount | B55: =IFERROR(SUMIFS(tblGoals[Remaining Amount],tblGoals[Goal Status],"Active"),0) -> 0 | D55: =IF(INDEX(tblAccounts[Account Name],ROW()-1)="","",INDEX(tblAccounts[Account Name],ROW()-1)) | E55: =IF($D55="","",IFERROR(INDEX(tblAccounts[Opening Balance],ROW()-1),0)) | F55: =IF($D55="","",SUMIFS(tblTransactions[Amount],tblTransactions[Transaction Type],"Income",tblTransactions[Transaction Status],"Completed",tblTransactions[Source Account],$D55)+SUMIFS(tblTransactions[Amount],tblTransactions[Transaction Type],"Income",tblTransactions[Transaction Status],"Reconciled",tblTransactions[Source Account],$D55)+SUMIFS(tblTransactions[Amount],tblTransactions[Transaction Type],"Transfer",tblTransactions[Transaction Status],"Completed",tblTransactions[Destination Type],"Account",tblTransactions[Destination Name],$D55)+SUMIFS(tblTransactions[Amount],tblTransactions[Transaction Type],"Transfer",tblTransactions[Transaction Status],"Reconciled",tblTransactions[Destination Type],"Account",tblTransactions[Destination Name],$D55)+SUMIFS(tblTransactions[Amount],tblTransactions[Transaction Type],"Adjustment",tblTransactions[Transaction Status],"Completed",tblTransactions[Source Account],$D55,tblTransactions[Amount],">0")+SUMIFS(tblTransactions[Amount],tblTransactions[Transaction Type],"Adjustment",tblTransactions[Transaction Status],"Reconciled",tblTransactions[Source Account],$D55,tblTransactions[Amount],">0")) | G55: =IF($D55="","",SUMIFS(tblTransactions[Amount],tblTransactions[Transaction Type],"Expense",tblTransactions[Transaction Status],"Completed",tblTransactions[Source Account],$D55)+SUMIFS(tblTransactions[Amount],tblTransactions[Transaction Type],"Expense",tblTransactions[Transaction Status],"Reconciled",tblTransactions[Source Account],$D55)+SUMIFS(tblTransactions[Amount],tblTransactions[Transaction Type],"Transfer",tblTransactions[Transaction Status],"Completed",tblTransactions[Source Account],$D55)+SUMIFS(tblTransactions[Amount],tblTransactions[Transaction Type],"Transfer",tblTransactions[Transaction Status],"Reconciled",tblTransactions[Source Account],$D55)-SUMIFS(tblTransactions[Amount],tblTransactions[Transaction Type],"Adjustment",tblTransactions[Transaction Status],"Completed",tblTransactions[Source Account],$D55,tblTransactions[Amount],"<0")-SUMIFS(tblTransactions[Amount],tblTransactions[Transaction Type],"Adjustment",tblTransactions[Transaction Status],"Reconciled",tblTransactions[Source Account],$D55,tblTransactions[Amount],"<0")) | H55: =IF($D55="","",$E55+$F55-$G55) | I55: =#N/A -> #N/A | J55: =IF($D55="","",IFERROR(INDEX(tblAccounts[Account Type],ROW()-1),"")) | K55: =IF($D55="","",IFERROR(INDEX(tblAccounts[Include in Dashboard],ROW()-1),"")) | L55: =IF($D55="","",IFERROR(INDEX(tblAccounts[Status],ROW()-1),""))
A56: Active Goal Count | B56: =COUNTIFS(tblGoals[Goal Status],"Active") -> 0 | D56: =IF(INDEX(tblAccounts[Account Name],ROW()-1)="","",INDEX(tblAccounts[Account Name],ROW()-1)) | E56: =IF($D56="","",IFERROR(INDEX(tblAccounts[Opening Balance],ROW()-1),0)) | F56: =IF($D56="","",SUMIFS(tblTransactions[Amount],tblTransactions[Transaction Type],"Income",tblTransactions[Transaction Status],"Completed",tblTransactions[Source Account],$D56)+SUMIFS(tblTransactions[Amount],tblTransactions[Transaction Type],"Income",tblTransactions[Transaction Status],"Reconciled",tblTransactions[Source Account],$D56)+SUMIFS(tblTransactions[Amount],tblTransactions[Transaction Type],"Transfer",tblTransactions[Transaction Status],"Completed",tblTransactions[Destination Type],"Account",tblTransactions[Destination Name],$D56)+SUMIFS(tblTransactions[Amount],tblTransactions[Transaction Type],"Transfer",tblTransactions[Transaction Status],"Reconciled",tblTransactions[Destination Type],"Account",tblTransactions[Destination Name],$D56)+SUMIFS(tblTransactions[Amount],tblTransactions[Transaction Type],"Adjustment",tblTransactions[Transaction Status],"Completed",tblTransactions[Source Account],$D56,tblTransactions[Amount],">0")+SUMIFS(tblTransactions[Amount],tblTransactions[Transaction Type],"Adjustment",tblTransactions[Transaction Status],"Reconciled",tblTransactions[Source Account],$D56,tblTransactions[Amount],">0")) | G56: =IF($D56="","",SUMIFS(tblTransactions[Amount],tblTransactions[Transaction Type],"Expense",tblTransactions[Transaction Status],"Completed",tblTransactions[Source Account],$D56)+SUMIFS(tblTransactions[Amount],tblTransactions[Transaction Type],"Expense",tblTransactions[Transaction Status],"Reconciled",tblTransactions[Source Account],$D56)+SUMIFS(tblTransactions[Amount],tblTransactions[Transaction Type],"Transfer",tblTransactions[Transaction Status],"Completed",tblTransactions[Source Account],$D56)+SUMIFS(tblTransactions[Amount],tblTransactions[Transaction Type],"Transfer",tblTransactions[Transaction Status],"Reconciled",tblTransactions[Source Account],$D56)-SUMIFS(tblTransactions[Amount],tblTransactions[Transaction Type],"Adjustment",tblTransactions[Transaction Status],"Completed",tblTransactions[Source Account],$D56,tblTransactions[Amount],"<0")-SUMIFS(tblTransactions[Amount],tblTransactions[Transaction Type],"Adjustment",tblTransactions[Transaction Status],"Reconciled",tblTransactions[Source Account],$D56,tblTransactions[Amount],"<0")) | H56: =IF($D56="","",$E56+$F56-$G56) | I56: =#N/A -> #N/A | J56: =IF($D56="","",IFERROR(INDEX(tblAccounts[Account Type],ROW()-1),"")) | K56: =IF($D56="","",IFERROR(INDEX(tblAccounts[Include in Dashboard],ROW()-1),"")) | L56: =IF($D56="","",IFERROR(INDEX(tblAccounts[Status],ROW()-1),""))
A57: Completed Goal Count | B57: =COUNTIFS(tblGoals[Goal Status],"Completed") -> 0 | D57: =IF(INDEX(tblAccounts[Account Name],ROW()-1)="","",INDEX(tblAccounts[Account Name],ROW()-1)) | E57: =IF($D57="","",IFERROR(INDEX(tblAccounts[Opening Balance],ROW()-1),0)) | F57: =IF($D57="","",SUMIFS(tblTransactions[Amount],tblTransactions[Transaction Type],"Income",tblTransactions[Transaction Status],"Completed",tblTransactions[Source Account],$D57)+SUMIFS(tblTransactions[Amount],tblTransactions[Transaction Type],"Income",tblTransactions[Transaction Status],"Reconciled",tblTransactions[Source Account],$D57)+SUMIFS(tblTransactions[Amount],tblTransactions[Transaction Type],"Transfer",tblTransactions[Transaction Status],"Completed",tblTransactions[Destination Type],"Account",tblTransactions[Destination Name],$D57)+SUMIFS(tblTransactions[Amount],tblTransactions[Transaction Type],"Transfer",tblTransactions[Transaction Status],"Reconciled",tblTransactions[Destination Type],"Account",tblTransactions[Destination Name],$D57)+SUMIFS(tblTransactions[Amount],tblTransactions[Transaction Type],"Adjustment",tblTransactions[Transaction Status],"Completed",tblTransactions[Source Account],$D57,tblTransactions[Amount],">0")+SUMIFS(tblTransactions[Amount],tblTransactions[Transaction Type],"Adjustment",tblTransactions[Transaction Status],"Reconciled",tblTransactions[Source Account],$D57,tblTransactions[Amount],">0")) | G57: =IF($D57="","",SUMIFS(tblTransactions[Amount],tblTransactions[Transaction Type],"Expense",tblTransactions[Transaction Status],"Completed",tblTransactions[Source Account],$D57)+SUMIFS(tblTransactions[Amount],tblTransactions[Transaction Type],"Expense",tblTransactions[Transaction Status],"Reconciled",tblTransactions[Source Account],$D57)+SUMIFS(tblTransactions[Amount],tblTransactions[Transaction Type],"Transfer",tblTransactions[Transaction Status],"Completed",tblTransactions[Source Account],$D57)+SUMIFS(tblTransactions[Amount],tblTransactions[Transaction Type],"Transfer",tblTransactions[Transaction Status],"Reconciled",tblTransactions[Source Account],$D57)-SUMIFS(tblTransactions[Amount],tblTransactions[Transaction Type],"Adjustment",tblTransactions[Transaction Status],"Completed",tblTransactions[Source Account],$D57,tblTransactions[Amount],"<0")-SUMIFS(tblTransactions[Amount],tblTransactions[Transaction Type],"Adjustment",tblTransactions[Transaction Status],"Reconciled",tblTransactions[Source Account],$D57,tblTransactions[Amount],"<0")) | H57: =IF($D57="","",$E57+$F57-$G57) | I57: =#N/A -> #N/A | J57: =IF($D57="","",IFERROR(INDEX(tblAccounts[Account Type],ROW()-1),"")) | K57: =IF($D57="","",IFERROR(INDEX(tblAccounts[Include in Dashboard],ROW()-1),"")) | L57: =IF($D57="","",IFERROR(INDEX(tblAccounts[Status],ROW()-1),""))
A58: Goal Completion % | B58: =IFERROR($B$54/$B$53,0) -> 0 | D58: =IF(INDEX(tblAccounts[Account Name],ROW()-1)="","",INDEX(tblAccounts[Account Name],ROW()-1)) | E58: =IF($D58="","",IFERROR(INDEX(tblAccounts[Opening Balance],ROW()-1),0)) | F58: =IF($D58="","",SUMIFS(tblTransactions[Amount],tblTransactions[Transaction Type],"Income",tblTransactions[Transaction Status],"Completed",tblTransactions[Source Account],$D58)+SUMIFS(tblTransactions[Amount],tblTransactions[Transaction Type],"Income",tblTransactions[Transaction Status],"Reconciled",tblTransactions[Source Account],$D58)+SUMIFS(tblTransactions[Amount],tblTransactions[Transaction Type],"Transfer",tblTransactions[Transaction Status],"Completed",tblTransactions[Destination Type],"Account",tblTransactions[Destination Name],$D58)+SUMIFS(tblTransactions[Amount],tblTransactions[Transaction Type],"Transfer",tblTransactions[Transaction Status],"Reconciled",tblTransactions[Destination Type],"Account",tblTransactions[Destination Name],$D58)+SUMIFS(tblTransactions[Amount],tblTransactions[Transaction Type],"Adjustment",tblTransactions[Transaction Status],"Completed",tblTransactions[Source Account],$D58,tblTransactions[Amount],">0")+SUMIFS(tblTransactions[Amount],tblTransactions[Transaction Type],"Adjustment",tblTransactions[Transaction Status],"Reconciled",tblTransactions[Source Account],$D58,tblTransactions[Amount],">0")) | G58: =IF($D58="","",SUMIFS(tblTransactions[Amount],tblTransactions[Transaction Type],"Expense",tblTransactions[Transaction Status],"Completed",tblTransactions[Source Account],$D58)+SUMIFS(tblTransactions[Amount],tblTransactions[Transaction Type],"Expense",tblTransactions[Transaction Status],"Reconciled",tblTransactions[Source Account],$D58)+SUMIFS(tblTransactions[Amount],tblTransactions[Transaction Type],"Transfer",tblTransactions[Transaction Status],"Completed",tblTransactions[Source Account],$D58)+SUMIFS(tblTransactions[Amount],tblTransactions[Transaction Type],"Transfer",tblTransactions[Transaction Status],"Reconciled",tblTransactions[Source Account],$D58)-SUMIFS(tblTransactions[Amount],tblTransactions[Transaction Type],"Adjustment",tblTransactions[Transaction Status],"Completed",tblTransactions[Source Account],$D58,tblTransactions[Amount],"<0")-SUMIFS(tblTransactions[Amount],tblTransactions[Transaction Type],"Adjustment",tblTransactions[Transaction Status],"Reconciled",tblTransactions[Source Account],$D58,tblTransactions[Amount],"<0")) | H58: =IF($D58="","",$E58+$F58-$G58) | I58: =#N/A -> #N/A | J58: =IF($D58="","",IFERROR(INDEX(tblAccounts[Account Type],ROW()-1),"")) | K58: =IF($D58="","",IFERROR(INDEX(tblAccounts[Include in Dashboard],ROW()-1),"")) | L58: =IF($D58="","",IFERROR(INDEX(tblAccounts[Status],ROW()-1),""))
D59: =IF(INDEX(tblAccounts[Account Name],ROW()-1)="","",INDEX(tblAccounts[Account Name],ROW()-1)) | E59: =IF($D59="","",IFERROR(INDEX(tblAccounts[Opening Balance],ROW()-1),0)) | F59: =IF($D59="","",SUMIFS(tblTransactions[Amount],tblTransactions[Transaction Type],"Income",tblTransactions[Transaction Status],"Completed",tblTransactions[Source Account],$D59)+SUMIFS(tblTransactions[Amount],tblTransactions[Transaction Type],"Income",tblTransactions[Transaction Status],"Reconciled",tblTransactions[Source Account],$D59)+SUMIFS(tblTransactions[Amount],tblTransactions[Transaction Type],"Transfer",tblTransactions[Transaction Status],"Completed",tblTransactions[Destination Type],"Account",tblTransactions[Destination Name],$D59)+SUMIFS(tblTransactions[Amount],tblTransactions[Transaction Type],"Transfer",tblTransactions[Transaction Status],"Reconciled",tblTransactions[Destination Type],"Account",tblTransactions[Destination Name],$D59)+SUMIFS(tblTransactions[Amount],tblTransactions[Transaction Type],"Adjustment",tblTransactions[Transaction Status],"Completed",tblTransactions[Source Account],$D59,tblTransactions[Amount],">0")+SUMIFS(tblTransactions[Amount],tblTransactions[Transaction Type],"Adjustment",tblTransactions[Transaction Status],"Reconciled",tblTransactions[Source Account],$D59,tblTransactions[Amount],">0")) | G59: =IF($D59="","",SUMIFS(tblTransactions[Amount],tblTransactions[Transaction Type],"Expense",tblTransactions[Transaction Status],"Completed",tblTransactions[Source Account],$D59)+SUMIFS(tblTransactions[Amount],tblTransactions[Transaction Type],"Expense",tblTransactions[Transaction Status],"Reconciled",tblTransactions[Source Account],$D59)+SUMIFS(tblTransactions[Amount],tblTransactions[Transaction Type],"Transfer",tblTransactions[Transaction Status],"Completed",tblTransactions[Source Account],$D59)+SUMIFS(tblTransactions[Amount],tblTransactions[Transaction Type],"Transfer",tblTransactions[Transaction Status],"Reconciled",tblTransactions[Source Account],$D59)-SUMIFS(tblTransactions[Amount],tblTransactions[Transaction Type],"Adjustment",tblTransactions[Transaction Status],"Completed",tblTransactions[Source Account],$D59,tblTransactions[Amount],"<0")-SUMIFS(tblTransactions[Amount],tblTransactions[Transaction Type],"Adjustment",tblTransactions[Transaction Status],"Reconciled",tblTransactions[Source Account],$D59,tblTransactions[Amount],"<0")) | H59: =IF($D59="","",$E59+$F59-$G59) | I59: =#N/A -> #N/A | J59: =IF($D59="","",IFERROR(INDEX(tblAccounts[Account Type],ROW()-1),"")) | K59: =IF($D59="","",IFERROR(INDEX(tblAccounts[Include in Dashboard],ROW()-1),"")) | L59: =IF($D59="","",IFERROR(INDEX(tblAccounts[Status],ROW()-1),""))
A60: SECTION 9 — Monthly Financial Health | D60: =IF(INDEX(tblAccounts[Account Name],ROW()-1)="","",INDEX(tblAccounts[Account Name],ROW()-1)) | E60: =IF($D60="","",IFERROR(INDEX(tblAccounts[Opening Balance],ROW()-1),0)) | F60: =IF($D60="","",SUMIFS(tblTransactions[Amount],tblTransactions[Transaction Type],"Income",tblTransactions[Transaction Status],"Completed",tblTransactions[Source Account],$D60)+SUMIFS(tblTransactions[Amount],tblTransactions[Transaction Type],"Income",tblTransactions[Transaction Status],"Reconciled",tblTransactions[Source Account],$D60)+SUMIFS(tblTransactions[Amount],tblTransactions[Transaction Type],"Transfer",tblTransactions[Transaction Status],"Completed",tblTransactions[Destination Type],"Account",tblTransactions[Destination Name],$D60)+SUMIFS(tblTransactions[Amount],tblTransactions[Transaction Type],"Transfer",tblTransactions[Transaction Status],"Reconciled",tblTransactions[Destination Type],"Account",tblTransactions[Destination Name],$D60)+SUMIFS(tblTransactions[Amount],tblTransactions[Transaction Type],"Adjustment",tblTransactions[Transaction Status],"Completed",tblTransactions[Source Account],$D60,tblTransactions[Amount],">0")+SUMIFS(tblTransactions[Amount],tblTransactions[Transaction Type],"Adjustment",tblTransactions[Transaction Status],"Reconciled",tblTransactions[Source Account],$D60,tblTransactions[Amount],">0")) | G60: =IF($D60="","",SUMIFS(tblTransactions[Amount],tblTransactions[Transaction Type],"Expense",tblTransactions[Transaction Status],"Completed",tblTransactions[Source Account],$D60)+SUMIFS(tblTransactions[Amount],tblTransactions[Transaction Type],"Expense",tblTransactions[Transaction Status],"Reconciled",tblTransactions[Source Account],$D60)+SUMIFS(tblTransactions[Amount],tblTransactions[Transaction Type],"Transfer",tblTransactions[Transaction Status],"Completed",tblTransactions[Source Account],$D60)+SUMIFS(tblTransactions[Amount],tblTransactions[Transaction Type],"Transfer",tblTransactions[Transaction Status],"Reconciled",tblTransactions[Source Account],$D60)-SUMIFS(tblTransactions[Amount],tblTransactions[Transaction Type],"Adjustment",tblTransactions[Transaction Status],"Completed",tblTransactions[Source Account],$D60,tblTransactions[Amount],"<0")-SUMIFS(tblTransactions[Amount],tblTransactions[Transaction Type],"Adjustment",tblTransactions[Transaction Status],"Reconciled",tblTransactions[Source Account],$D60,tblTransactions[Amount],"<0")) | H60: =IF($D60="","",$E60+$F60-$G60) | I60: =#N/A -> #N/A | J60: =IF($D60="","",IFERROR(INDEX(tblAccounts[Account Type],ROW()-1),"")) | K60: =IF($D60="","",IFERROR(INDEX(tblAccounts[Include in Dashboard],ROW()-1),"")) | L60: =IF($D60="","",IFERROR(INDEX(tblAccounts[Status],ROW()-1),""))
A61: Income | B61: =$B$16 -> 0 | D61: =IF(INDEX(tblAccounts[Account Name],ROW()-1)="","",INDEX(tblAccounts[Account Name],ROW()-1)) | E61: =IF($D61="","",IFERROR(INDEX(tblAccounts[Opening Balance],ROW()-1),0)) | F61: =IF($D61="","",SUMIFS(tblTransactions[Amount],tblTransactions[Transaction Type],"Income",tblTransactions[Transaction Status],"Completed",tblTransactions[Source Account],$D61)+SUMIFS(tblTransactions[Amount],tblTransactions[Transaction Type],"Income",tblTransactions[Transaction Status],"Reconciled",tblTransactions[Source Account],$D61)+SUMIFS(tblTransactions[Amount],tblTransactions[Transaction Type],"Transfer",tblTransactions[Transaction Status],"Completed",tblTransactions[Destination Type],"Account",tblTransactions[Destination Name],$D61)+SUMIFS(tblTransactions[Amount],tblTransactions[Transaction Type],"Transfer",tblTransactions[Transaction Status],"Reconciled",tblTransactions[Destination Type],"Account",tblTransactions[Destination Name],$D61)+SUMIFS(tblTransactions[Amount],tblTransactions[Transaction Type],"Adjustment",tblTransactions[Transaction Status],"Completed",tblTransactions[Source Account],$D61,tblTransactions[Amount],">0")+SUMIFS(tblTransactions[Amount],tblTransactions[Transaction Type],"Adjustment",tblTransactions[Transaction Status],"Reconciled",tblTransactions[Source Account],$D61,tblTransactions[Amount],">0")) | G61: =IF($D61="","",SUMIFS(tblTransactions[Amount],tblTransactions[Transaction Type],"Expense",tblTransactions[Transaction Status],"Completed",tblTransactions[Source Account],$D61)+SUMIFS(tblTransactions[Amount],tblTransactions[Transaction Type],"Expense",tblTransactions[Transaction Status],"Reconciled",tblTransactions[Source Account],$D61)+SUMIFS(tblTransactions[Amount],tblTransactions[Transaction Type],"Transfer",tblTransactions[Transaction Status],"Completed",tblTransactions[Source Account],$D61)+SUMIFS(tblTransactions[Amount],tblTransactions[Transaction Type],"Transfer",tblTransactions[Transaction Status],"Reconciled",tblTransactions[Source Account],$D61)-SUMIFS(tblTransactions[Amount],tblTransactions[Transaction Type],"Adjustment",tblTransactions[Transaction Status],"Completed",tblTransactions[Source Account],$D61,tblTransactions[Amount],"<0")-SUMIFS(tblTransactions[Amount],tblTransactions[Transaction Type],"Adjustment",tblTransactions[Transaction Status],"Reconciled",tblTransactions[Source Account],$D61,tblTransactions[Amount],"<0")) | H61: =IF($D61="","",$E61+$F61-$G61) | I61: =#N/A -> #N/A | J61: =IF($D61="","",IFERROR(INDEX(tblAccounts[Account Type],ROW()-1),"")) | K61: =IF($D61="","",IFERROR(INDEX(tblAccounts[Include in Dashboard],ROW()-1),"")) | L61: =IF($D61="","",IFERROR(INDEX(tblAccounts[Status],ROW()-1),""))
A62: Expenses | B62: =$B$22 -> 0 | D62: =IF(INDEX(tblAccounts[Account Name],ROW()-1)="","",INDEX(tblAccounts[Account Name],ROW()-1)) | E62: =IF($D62="","",IFERROR(INDEX(tblAccounts[Opening Balance],ROW()-1),0)) | F62: =IF($D62="","",SUMIFS(tblTransactions[Amount],tblTransactions[Transaction Type],"Income",tblTransactions[Transaction Status],"Completed",tblTransactions[Source Account],$D62)+SUMIFS(tblTransactions[Amount],tblTransactions[Transaction Type],"Income",tblTransactions[Transaction Status],"Reconciled",tblTransactions[Source Account],$D62)+SUMIFS(tblTransactions[Amount],tblTransactions[Transaction Type],"Transfer",tblTransactions[Transaction Status],"Completed",tblTransactions[Destination Type],"Account",tblTransactions[Destination Name],$D62)+SUMIFS(tblTransactions[Amount],tblTransactions[Transaction Type],"Transfer",tblTransactions[Transaction Status],"Reconciled",tblTransactions[Destination Type],"Account",tblTransactions[Destination Name],$D62)+SUMIFS(tblTransactions[Amount],tblTransactions[Transaction Type],"Adjustment",tblTransactions[Transaction Status],"Completed",tblTransactions[Source Account],$D62,tblTransactions[Amount],">0")+SUMIFS(tblTransactions[Amount],tblTransactions[Transaction Type],"Adjustment",tblTransactions[Transaction Status],"Reconciled",tblTransactions[Source Account],$D62,tblTransactions[Amount],">0")) | G62: =IF($D62="","",SUMIFS(tblTransactions[Amount],tblTransactions[Transaction Type],"Expense",tblTransactions[Transaction Status],"Completed",tblTransactions[Source Account],$D62)+SUMIFS(tblTransactions[Amount],tblTransactions[Transaction Type],"Expense",tblTransactions[Transaction Status],"Reconciled",tblTransactions[Source Account],$D62)+SUMIFS(tblTransactions[Amount],tblTransactions[Transaction Type],"Transfer",tblTransactions[Transaction Status],"Completed",tblTransactions[Source Account],$D62)+SUMIFS(tblTransactions[Amount],tblTransactions[Transaction Type],"Transfer",tblTransactions[Transaction Status],"Reconciled",tblTransactions[Source Account],$D62)-SUMIFS(tblTransactions[Amount],tblTransactions[Transaction Type],"Adjustment",tblTransactions[Transaction Status],"Completed",tblTransactions[Source Account],$D62,tblTransactions[Amount],"<0")-SUMIFS(tblTransactions[Amount],tblTransactions[Transaction Type],"Adjustment",tblTransactions[Transaction Status],"Reconciled",tblTransactions[Source Account],$D62,tblTransactions[Amount],"<0")) | H62: =IF($D62="","",$E62+$F62-$G62) | I62: =#N/A -> #N/A | J62: =IF($D62="","",IFERROR(INDEX(tblAccounts[Account Type],ROW()-1),"")) | K62: =IF($D62="","",IFERROR(INDEX(tblAccounts[Include in Dashboard],ROW()-1),"")) | L62: =IF($D62="","",IFERROR(INDEX(tblAccounts[Status],ROW()-1),""))
A63: Savings | B63: =$B$29 -> 0 | D63: =IF(INDEX(tblAccounts[Account Name],ROW()-1)="","",INDEX(tblAccounts[Account Name],ROW()-1)) | E63: =IF($D63="","",IFERROR(INDEX(tblAccounts[Opening Balance],ROW()-1),0)) | F63: =IF($D63="","",SUMIFS(tblTransactions[Amount],tblTransactions[Transaction Type],"Income",tblTransactions[Transaction Status],"Completed",tblTransactions[Source Account],$D63)+SUMIFS(tblTransactions[Amount],tblTransactions[Transaction Type],"Income",tblTransactions[Transaction Status],"Reconciled",tblTransactions[Source Account],$D63)+SUMIFS(tblTransactions[Amount],tblTransactions[Transaction Type],"Transfer",tblTransactions[Transaction Status],"Completed",tblTransactions[Destination Type],"Account",tblTransactions[Destination Name],$D63)+SUMIFS(tblTransactions[Amount],tblTransactions[Transaction Type],"Transfer",tblTransactions[Transaction Status],"Reconciled",tblTransactions[Destination Type],"Account",tblTransactions[Destination Name],$D63)+SUMIFS(tblTransactions[Amount],tblTransactions[Transaction Type],"Adjustment",tblTransactions[Transaction Status],"Completed",tblTransactions[Source Account],$D63,tblTransactions[Amount],">0")+SUMIFS(tblTransactions[Amount],tblTransactions[Transaction Type],"Adjustment",tblTransactions[Transaction Status],"Reconciled",tblTransactions[Source Account],$D63,tblTransactions[Amount],">0")) | G63: =IF($D63="","",SUMIFS(tblTransactions[Amount],tblTransactions[Transaction Type],"Expense",tblTransactions[Transaction Status],"Completed",tblTransactions[Source Account],$D63)+SUMIFS(tblTransactions[Amount],tblTransactions[Transaction Type],"Expense",tblTransactions[Transaction Status],"Reconciled",tblTransactions[Source Account],$D63)+SUMIFS(tblTransactions[Amount],tblTransactions[Transaction Type],"Transfer",tblTransactions[Transaction Status],"Completed",tblTransactions[Source Account],$D63)+SUMIFS(tblTransactions[Amount],tblTransactions[Transaction Type],"Transfer",tblTransactions[Transaction Status],"Reconciled",tblTransactions[Source Account],$D63)-SUMIFS(tblTransactions[Amount],tblTransactions[Transaction Type],"Adjustment",tblTransactions[Transaction Status],"Completed",tblTransactions[Source Account],$D63,tblTransactions[Amount],"<0")-SUMIFS(tblTransactions[Amount],tblTransactions[Transaction Type],"Adjustment",tblTransactions[Transaction Status],"Reconciled",tblTransactions[Source Account],$D63,tblTransactions[Amount],"<0")) | H63: =IF($D63="","",$E63+$F63-$G63) | I63: =#N/A -> #N/A | J63: =IF($D63="","",IFERROR(INDEX(tblAccounts[Account Type],ROW()-1),"")) | K63: =IF($D63="","",IFERROR(INDEX(tblAccounts[Include in Dashboard],ROW()-1),"")) | L63: =IF($D63="","",IFERROR(INDEX(tblAccounts[Status],ROW()-1),""))
